Workbook
Name TAX: #REF!

Sheet Header
D2: Batch | E2: 20251016
D3: Batch Desc | E3: Mastercard Invoices (November 2025)
D4: Reference | E4: MC-251116 | F4: `
D5: Document Date | E5: 45977
D6: Posting Date | E6: =E5 -> 45977
E13: LOG IN DETAILS
D15: User | E15: eTimesheet User
D16: Password | E16: gekko

Sheet S Baker
A1: Employee to code & narrate | J1: To be copied in to pronto
J2: Credit card Statement TOTAL
J3: Subtotal | K3: =SUM(M8:M143) -> 0
J4: Variance Check | K4: =K2-K3 -> 0
A5: Scott Baker
A6: Reference | B6: =CONCATENATE(Header!$E$4,"BAKER") -> MC-251116BAKER | J6: EMPLOYEES DO NOT CHANGE
A7: Document Date | B7: =Header!$E$5 -> 45977 | E7: Credit card holder to add details
A9: Date | B9: Narrative | C9: Debit Amount | D9: Credit Amount | E9: Description | F9: Project No | G9: Cost Category | H9: GL account | J9: Account | K9: Reference | L9: Tax | M9: Amount | N9: Tax CODE | O9: TAX Amount (leave blank) | P9: CBS - Only if required | R9: limit 56charaters
J10: =IF(F10>0,(_xlfn.CONCAT(F10,".",G10)),H10) -> 0 | K10: =_xlfn.CONCAT("S Baker-",B10,"-",E10) -> S Baker-- | L10: I | M10: =IF(C10>0,C10,-D10) -> 0 | N10: T | Q10: CBS - needs to be pasted seperately | R10: =LEN(K10) -> 9

Sheet S Barclay
A1: Employee to code & narrate | J1: To be copied in to pronto
J2: Credit card Statement TOTAL | K2: 237.48
J3: Subtotal | K3: =SUM(M8:M143) -> 237.48
J4: Variance Check | K4: =K2-K3 -> 0
A5: Simon Barclay
A6: Reference | B6: =CONCATENATE(Header!$E$4,"Barclay") -> MC-251116Barclay | J6: EMPLOYEES DO NOT CHANGE
A7: Document Date | B7: =Header!$E$5 -> 45977 | E7: Credit card holder to add details
A9: Date | B9: Narrative | C9: Debit Amount | D9: Credit Amount | E9: Description | F9: Project No | G9: Cost Category | H9: GL account | J9: Account | K9: Reference | L9: Tax | M9: Amount | N9: Tax CODE | O9: TAX Amount (leave blank) | P9: CBS - Only if required | R9: limit 56charaters
A10: 45968 | B10: Ink Station SYDNEY AUS | C10: 26.55 | D10: 0 | E10: Label roll | F10: 1053 | G10: cons | J10: =IF(F10>0,(_xlfn.CONCAT(F10,".",G10)),H10) -> 1053.cons | K10: =_xlfn.CONCAT("S Barclay-",E10,"-",B10) -> S Barclay-Label roll-Ink Station SYDNEY AUS | L10: I | M10: =IF(C10>0,C10,-D10) -> 26.55 | N10: T | Q10: CBS - needs to be pasted seperately | R10: =LEN(K10) -> 43
A11: 45975 | B11: OFFICEWORKS 0364 BALLARAT AUS | C11: 47.17 | D11: 0 | E11: stationary | F11: 1084 | G11: stat | J11: =IF(F11>0,(_xlfn.CONCAT(F11,".",G11)),H11) -> 1084.stat | K11: =_xlfn.CONCAT("S Barclay-",E11,"-",B11) -> S Barclay-stationary-OFFICEWORKS 0364 BALLARAT AUS | L11: I | M11: =IF(C11>0,C11,-D11) -> 47.17 | N11: T | Q11: CBS - needs to be pasted seperately | R11: =LEN(K11) -> 50
A12: 45958 | B12: BUNNINGS 329000 DELACOMBE AUS | C12: 49 | D12: 0 | E12: Tough Case | F12: 1073 | G12: tool | J12: =IF(F12>0,(_xlfn.CONCAT(F12,".",G12)),H12) -> 1073.tool | K12: =_xlfn.CONCAT("S Barclay-",E12,"-",B12) -> S Barclay-Tough Case-BUNNINGS 329000 DELACOMBE AUS | L12: I | M12: =IF(C12>0,C12,-D12) -> 49 | N12: T | Q12: CBS - needs to be pasted seperately | R12: =LEN(K12) -> 50
A13: 45961 | B13: WOOLWORTHS 3066 ALFREDTON AUS | C13: 114.76 | D13: 0 | E13: Pantry supplies | F13: 1084 | G13: cons | J13: =IF(F13>0,(_xlfn.CONCAT(F13,".",G13)),H13) -> 1084.cons | K13: =_xlfn.CONCAT("S Barclay-",E13,"-",B13) -> S Barclay-Pantry supplies-WOOLWORTHS 3066 ALFREDTON AUS | L13: I | M13: =IF(C13>0,C13,-D13) -> 114.76 | N13: T | Q13: CBS - needs to be pasted seperately | R13: =LEN(K13) -> 60

Sheet T Bell
A1: Employee to code & narrate | J1: To be copied in to pronto
J2: Credit card Statement TOTAL | K2: 1657.21
J3: Subtotal | K3: =SUM(M8:M143) -> 1657.21
J4: Variance Check | K4: =K2-K3 -> 0
A5: T Bell
A6: Reference | B6: =CONCATENATE(Header!$E$4,"Bell") -> MC-251116Bell | J6: EMPLOYEES DO NOT CHANGE
A7: Document Date | B7: =Header!$E$5 -> 45977 | E7: Credit card holder to add details
A9: Date | B9: Narrative | C9: Debit Amount | D9: Credit Amount | E9: Description | F9: Project No | G9: Cost Category | H9: GL account | J9: Account | K9: Reference | L9: Tax | M9: Amount | N9: Tax CODE | O9: TAX Amount (leave blank) | P9: CBS - Only if required | R9: limit 56charaters
A10: 16/11/2025 | B10: INTEREST CHARGES - CAS H | C10: 0.8 | D10: 0 | E10: Interest | F10: 1084 | G10: BFEE | J10: =IF(F10>0,(_xlfn.CONCAT(F10,".",G10)),H10) -> 1084.BFEE | K10: =_xlfn.CONCAT("T Bell-",E10,"-",B10) -> T Bell-Interest-INTEREST CHARGES - CAS H | L10: I | M10: =IF(C10>0,C10,-D10) -> 0.8 | N10: F | Q10: CBS - needs to be pasted seperately | R10: =LEN(K10) -> 40
A11: 16/10/2025 | B11: LEEDERVILLE MINI MAR LEEDERVILLE AUS | C11: 2.97 | D11: 0 | E11: Milk | F11: 1041 | G11: STAF | J11: =IF(F11>0,(_xlfn.CONCAT(F11,".",G11)),H11) -> 1041.STAF | K11: =_xlfn.CONCAT("T Bell-",E11,"-",B11) -> T Bell-Milk-LEEDERVILLE MINI MAR LEEDERVILLE AUS | L11: I | M11: =IF(C11>0,C11,-D11) -> 2.97 | N11: T | Q11: CBS - needs to be pasted seperately | R11: =LEN(K11) -> 48
A12: 10/11/2025 | B12: CASH ADVANCE FEE | C12: 5.93 | D12: 0 | E12: Fees | F12: 1084 | G12: BFEE | J12: =IF(F12>0,(_xlfn.CONCAT(F12,".",G12)),H12) -> 1084.BFEE | K12: =_xlfn.CONCAT("T Bell-",E12,"-",B12) -> T Bell-Fees-CASH ADVANCE FEE | L12: I | M12: =IF(C12>0,C12,-D12) -> 5.93 | N12: F | Q12: CBS - needs to be pasted seperately | R12: =LEN(K12) -> 28
A13: 9/11/2025 | B13: Panasonic Avionics Cor Irvine USA FRGN AMT: 3.99 U. S. DOLLAR | C13: 6.35 | D13: 0 | E13: Inflight Wifi on way to Turkey for IMCET | F13: G071 | G13: SALP | J13: =IF(F13>0,(_xlfn.CONCAT(F13,".",G13)),H13) -> G071.SALP | K13: =_xlfn.CONCAT("T Bell-",E13,"-",B13) -> T Bell-Inflight Wifi on way to Turkey for IMCET-Panasonic Avionics Cor Irvine USA FRGN AMT: 3.99 U. S. DOLLAR | L13: I | M13: =IF(C13>0,C13,-D13) -> 6.35 | N13: F | Q13: CBS - needs to be pasted seperately | R13: =LEN(K13) -> 110
A14: 9/11/2025 | B14: ZLR*WA Cellar Perth Airpo AUS | C14: 7 | D14: 0 | E14: Coffee at airport on way to Turkey for IMCET | F14: G071 | G14: SALP | J14: =IF(F14>0,(_xlfn.CONCAT(F14,".",G14)),H14) -> G071.SALP | K14: =_xlfn.CONCAT("T Bell-",E14,"-",B14) -> T Bell-Coffee at airport on way to Turkey for IMCET-ZLR*WA Cellar Perth Airpo AUS | L14: I | M14: =IF(C14>0,C14,-D14) -> 7 | N14: T | Q14: CBS - needs to be pasted seperately | R14: =LEN(K14) -> 81
A15: 7/11/2025 | B15: Holiday Inn Perth CBD Perth AUS | C15: 8.15 | D15: 0 | E15: Coffee/food at AGA Sukari meeting | F15: 1041 | G15: ENFE | J15: =IF(F15>0,(_xlfn.CONCAT(F15,".",G15)),H15) -> 1041.ENFE | K15: =_xlfn.CONCAT("T Bell-",E15,"-",B15) -> T Bell-Coffee/food at AGA Sukari meeting-Holiday Inn Perth CBD Perth AUS | L15: I | M15: =IF(C15>0,C15,-D15) -> 8.15 | N15: T | Q15: CBS - needs to be pasted seperately | R15: =LEN(K15) -> 72
A16: 4/11/2025 | B16: UBER* TRIP SYDNEY AUS | C16: 9 | D16: 0 | E16: Uber back from Northern Star Hemi meeting | F16: 1041 | G16: TRAV | J16: =IF(F16>0,(_xlfn.CONCAT(F16,".",G16)),H16) -> 1041.TRAV | K16: =_xlfn.CONCAT("T Bell-",E16,"-",B16) -> T Bell-Uber back from Northern Star Hemi meeting-UBER* TRIP SYDNEY AUS | L16: I | M16: =IF(C16>0,C16,-D16) -> 9 | N16: T | Q16: CBS - needs to be pasted seperately | R16: =LEN(K16) -> 70
A17: 5/11/2025 | B17: UBER *TRIP HELP.UBER.C 14518236738 AUS | C17: 9.39 | D17: 0 | E17: Uber to Northern Star Hemi meeting | F17: 1041 | G17: TRAV | J17: =IF(F17>0,(_xlfn.CONCAT(F17,".",G17)),H17) -> 1041.TRAV | K17: =_xlfn.CONCAT("T Bell-",E17,"-",B17) -> T Bell-Uber to Northern Star Hemi meeting-UBER *TRIP HELP.UBER.C 14518236738 AUS | L17: I | M17: =IF(C17>0,C17,-D17) -> 9.39 | N17: T | Q17: CBS - needs to be pasted seperately | R17: =LEN(K17) -> 80
A18: 23/10/2025 | B18: ZLR*BABYLON CAFE Leederville AUS | C18: 10.1 | D18: 0 | E18: Coffee with Bill S | F18: 1041 | G18: ENON | J18: =IF(F18>0,(_xlfn.CONCAT(F18,".",G18)),H18) -> 1041.ENON | K18: =_xlfn.CONCAT("T Bell-",E18,"-",B18) -> T Bell-Coffee with Bill S-ZLR*BABYLON CAFE Leederville AUS | L18: I | M18: =IF(C18>0,C18,-D18) -> 10.1 | N18: T | Q18: CBS - needs to be pasted seperately | R18: =LEN(K18) -> 58
A19: 30/10/2025 | B19: ZLR*BABYLON CAFE Leederville AUS | C19: 11.52 | D19: 0 | E19: Coffees for meeting | F19: 1041 | G19: ENON | J19: =IF(F19>0,(_xlfn.CONCAT(F19,".",G19)),H19) -> 1041.ENON | K19: =_xlfn.CONCAT("T Bell-",E19,"-",B19) -> T Bell-Coffees for meeting-ZLR*BABYLON CAFE Leederville AUS | L19: I | M19: =IF(C19>0,C19,-D19) -> 11.52 | N19: T | Q19: CBS - needs to be pasted seperately | R19: =LEN(K19) -> 59
A20: 9/11/2025 | B20: Hungry Jacks Perth AUS | C20: 11.7 | D20: 0 | E20: Food at airport on way to Turkey for IMCET | F20: G071 | G20: SALP | J20: =IF(F20>0,(_xlfn.CONCAT(F20,".",G20)),H20) -> G071.SALP | K20: =_xlfn.CONCAT("T Bell-",E20,"-",B20) -> T Bell-Food at airport on way to Turkey for IMCET-Hungry Jacks Perth AUS | L20: I | M20: =IF(C20>0,C20,-D20) -> 11.7 | N20: T | Q20: CBS - needs to be pasted seperately | R20: =LEN(K20) -> 72
A21: 28/10/2025 | B21: THE GOOD GROCER LEED LEEDERVILLE AUS | C21: 11.99 | D21: 0 | E21: Wednesday Lunch (Tim) | F21: 1084 | G21: ENON | J21: =IF(F21>0,(_xlfn.CONCAT(F21,".",G21)),H21) -> 1084.ENON | K21: =_xlfn.CONCAT("T Bell-",E21,"-",B21) -> T Bell-Wednesday Lunch (Tim)-THE GOOD GROCER LEED LEEDERVILLE AUS | L21: I | M21: =IF(C21>0,C21,-D21) -> 11.99 | N21: T | Q21: CBS - needs to be pasted seperately | R21: =LEN(K21) -> 65
A22: 9/11/2025 | B22: SPRINT-CASS PL T1 (E1) SINGAPORE SGP FRGN AMT: 9.90 SINGAPORE DOLLAR | C22: 12.11 | D22: 0 | E22: Travel adaptor for trip to Turkey, IMCET | F22: G071 | G22: SALP | J22: =IF(F22>0,(_xlfn.CONCAT(F22,".",G22)),H22) -> G071.SALP | K22: =_xlfn.CONCAT("T Bell-",E22,"-",B22) -> T Bell-Travel adaptor for trip to Turkey, IMCET-SPRINT-CASS PL T1 (E1) SINGAPORE SGP FRGN AMT: 9.90 SINGAPORE DOLLAR | L22: I | M22: =IF(C22>0,C22,-D22) -> 12.11 | N22: F | Q22: CBS - needs to be pasted seperately | R22: =LEN(K22) -> 117
A23: 26/10/2025 | B23: ROSSMOYNE IGA ROSSMOYNE AUS | C23: 13.35 | D23: 0 | E23: Milk / Coffee | F23: 1041 | G23: STAF | J23: =IF(F23>0,(_xlfn.CONCAT(F23,".",G23)),H23) -> 1041.STAF | K23: =_xlfn.CONCAT("T Bell-",E23,"-",B23) -> T Bell-Milk / Coffee-ROSSMOYNE IGA ROSSMOYNE AUS | L23: I | M23: =IF(C23>0,C23,-D23) -> 13.35 | N23: T | Q23: CBS - needs to be pasted seperately | R23: =LEN(K23) -> 48
A24: 16/10/2025 | B24: SQ *NOURISH KITCHEN & Leederville AUS | C24: 13.9 | D24: 0 | E24: Wednesday Lunch (Tim) | F24: 1084 | G24: ENON | J24: =IF(F24>0,(_xlfn.CONCAT(F24,".",G24)),H24) -> 1084.ENON | K24: =_xlfn.CONCAT("T Bell-",E24,"-",B24) -> T Bell-Wednesday Lunch (Tim)-SQ *NOURISH KITCHEN & Leederville AUS | L24: I | M24: =IF(C24>0,C24,-D24) -> 13.9 | N24: T | Q24: CBS - needs to be pasted seperately | R24: =LEN(K24) -> 66
A25: 31/10/2025 | B25: SQ *NOURISH KITCHEN & Leederville AUS | C25: 16.5 | D25: 0 | E25: Wednesday Lunch (Tim) | F25: 1084 | G25: ENON | J25: =IF(F25>0,(_xlfn.CONCAT(F25,".",G25)),H25) -> 1084.ENON | K25: =_xlfn.CONCAT("T Bell-",E25,"-",B25) -> T Bell-Wednesday Lunch (Tim)-SQ *NOURISH KITCHEN & Leederville AUS | L25: I | M25: =IF(C25>0,C25,-D25) -> 16.5 | N25: T | Q25: CBS - needs to be pasted seperately | R25: =LEN(K25) -> 66
A26: 10/11/2025 | B26: TT NET ANONIM STI ISTANBUL TUR FRGN AMT: 630.73 TURKISH LIRE | C26: 24.02 | D26: 0 | E26: Food/Drink on plane on way to Turkey for IMCET | F26: G071 | G26: SALP | J26: =IF(F26>0,(_xlfn.CONCAT(F26,".",G26)),H26) -> G071.SALP | K26: =_xlfn.CONCAT("T Bell-",E26,"-",B26) -> T Bell-Food/Drink on plane on way to Turkey for IMCET-TT NET ANONIM STI ISTANBUL TUR FRGN AMT: 630.73 TURKISH LIRE | L26: I | M26: =IF(C26>0,C26,-D26) -> 24.02 | N26: F | Q26: CBS - needs to be pasted seperately | R26: =LEN(K26) -> 115
A27: 7/11/2025 | B27: UBER *TRIP HELP.UBER.C 14518236738 AUS | C27: 28.56 | D27: 0 | E27: Uber to Sukari meeting | F27: 1041 | G27: TRAV | J27: =IF(F27>0,(_xlfn.CONCAT(F27,".",G27)),H27) -> 1041.TRAV | K27: =_xlfn.CONCAT("T Bell-",E27,"-",B27) -> T Bell-Uber to Sukari meeting-UBER *TRIP HELP.UBER.C 14518236738 AUS | L27: I | M27: =IF(C27>0,C27,-D27) -> 28.56 | N27: T | Q27: CBS - needs to be pasted seperately | R27: =LEN(K27) -> 68
A28: 24/10/2025 | B28: CELLARBRATIONS AT SHEL SHELLEY AUS | C28: 30 | D28: 0 | E28: Friday Drinks | F28: 1041 | G28: STAF | J28: =IF(F28>0,(_xlfn.CONCAT(F28,".",G28)),H28) -> 1041.STAF | K28: =_xlfn.CONCAT("T Bell-",E28,"-",B28) -> T Bell-Friday Drinks-CELLARBRATIONS AT SHEL SHELLEY AUS | L28: I | M28: =IF(C28>0,C28,-D28) -> 30 | N28: T | Q28: CBS - needs to be pasted seperately | R28: =LEN(K28) -> 55
A29: 8/11/2025 | B29: UBER *TRIP HELP.UBER.C 14518236738 AUS | C29: 30.74 | D29: 0 | E29: Uber home from Sukari meeting | F29: 1041 | G29: TRAV | J29: =IF(F29>0,(_xlfn.CONCAT(F29,".",G29)),H29) -> 1041.TRAV | K29: =_xlfn.CONCAT("T Bell-",E29,"-",B29) -> T Bell-Uber home from Sukari meeting-UBER *TRIP HELP.UBER.C 14518236738 AUS | L29: I | M29: =IF(C29>0,C29,-D29) -> 30.74 | N29: T | Q29: CBS - needs to be pasted seperately | R29: =LEN(K29) -> 75
A30: 4/11/2025 | B30: NIPPON FOOD ART PTY SUBIACO AUS | C30: 20.735 | D30: 0 | E30: Lunch with Marcus Locke - NSRL | F30: 1041 | G30: ENFE | J30: =IF(F30>0,(_xlfn.CONCAT(F30,".",G30)),H30) -> 1041.ENFE | K30: =_xlfn.CONCAT("T Bell-",E30,"-",B30) -> T Bell-Lunch with Marcus Locke - NSRL-NIPPON FOOD ART PTY SUBIACO AUS | L30: I | M30: =IF(C30>0,C30,-D30) -> 20.735 | N30: T | Q30: CBS - needs to be pasted seperately | R30: =LEN(K30) -> 69
A31: 4/11/2025 | B31: NIPPON FOOD ART PTY SUBIACO AUS | C31: 20.735 | D31: 0 | E31: Lunch with Marcus Locke - NSRL | F31: 1041 | G31: ENFN | J31: =IF(F31>0,(_xlfn.CONCAT(F31,".",G31)),H31) -> 1041.ENFN | K31: =_xlfn.CONCAT("T Bell-",E31,"-",B31) -> T Bell-Lunch with Marcus Locke - NSRL-NIPPON FOOD ART PTY SUBIACO AUS | L31: I | M31: =IF(C31>0,C31,-D31) -> 20.735 | N31: T | Q31: CBS - needs to be pasted seperately | R31: =LEN(K31) -> 69
A32: 10/11/2025 | B32: UBER *TRIP HELP.UBER.C 14518236738 AUS | C32: 42.25 | D32: 0 | E32: Uber to airport on way to Turkey for IMCET | F32: G071 | G32: SALP | J32: =IF(F32>0,(_xlfn.CONCAT(F32,".",G32)),H32) -> G071.SALP | K32: =_xlfn.CONCAT("T Bell-",E32,"-",B32) -> T Bell-Uber to airport on way to Turkey for IMCET-UBER *TRIP HELP.UBER.C 14518236738 AUS | L32: I | M32: =IF(C32>0,C32,-D32) -> 42.25 | N32: T | Q32: CBS - needs to be pasted seperately | R32: =LEN(K32) -> 88
A33: 9/11/2025 | B33: HEINEKEN WORLD BAR T1 SINGAPORE SGP FRGN AMT: 38.85 SINGAPORE DOLLAR | C33: 47.54 | D33: 0 | E33: Meal on way to Turkey for IMCET | F33: G071 | G33: SALP | J33: =IF(F33>0,(_xlfn.CONCAT(F33,".",G33)),H33) -> G071.SALP | K33: =_xlfn.CONCAT("T Bell-",E33,"-",B33) -> T Bell-Meal on way to Turkey for IMCET-HEINEKEN WORLD BAR T1 SINGAPORE SGP FRGN AMT: 38.85 SINGAPORE DOLLAR | L33: I | M33: =IF(C33>0,C33,-D33) -> 47.54 | N33: F | Q33: CBS - needs to be pasted seperately | R33: =LEN(K33) -> 108
A34: 27/10/2025 | B34: Hello Harry The Burge Leederville AUS | C34: 61 | D34: 0 | E34: Wednesday Lunch | F34: 1084 | G34: ENON | J34: =IF(F34>0,(_xlfn.CONCAT(F34,".",G34)),H34) -> 1084.ENON | K34: =_xlfn.CONCAT("T Bell-",E34,"-",B34) -> T Bell-Wednesday Lunch-Hello Harry The Burge Leederville AUS | L34: I | M34: =IF(C34>0,C34,-D34) -> 61 | N34: T | Q34: CBS - needs to be pasted seperately | R34: =LEN(K34) -> 60
A35: 20/10/2025 | B35: GYG Leederville Leederville AUS | C35: 65.5 | D35: 0 | E35: Wednesday Lunch | F35: 1084 | G35: ENON | J35: =IF(F35>0,(_xlfn.CONCAT(F35,".",G35)),H35) -> 1084.ENON | K35: =_xlfn.CONCAT("T Bell-",E35,"-",B35) -> T Bell-Wednesday Lunch-GYG Leederville Leederville AUS | L35: I | M35: =IF(C35>0,C35,-D35) -> 65.5 | N35: T | Q35: CBS - needs to be pasted seperately | R35: =LEN(K35) -> 54
A36: 18/10/2025 | B36: KATHMANDU PTY LTD SUCCESS AUS | C36: 83.99 | D36: 0 | E36: Personal issue with where credit card was stored which has now been resolved | F36: 1084 | G36: PERS | J36: =IF(F36>0,(_xlfn.CONCAT(F36,".",G36)),H36) -> 1084.PERS | K36: =_xlfn.CONCAT("T Bell-",E36,"-",B36) -> T Bell-Personal issue with where credit card was stored which has now been resolved-KATHMANDU PTY LTD SUCCESS AUS | L36: I | M36: =IF(C36>0,C36,-D36) -> 83.99 | N36: T | Q36: CBS - needs to be pasted seperately | R36: =LEN(K36) -> 113
A37: 22/10/2025 | B37: CELLARBRATIONS AT SHEL SHELLEY AUS | C37: 93 | D37: 0 | E37: Personal issue with where credit card was stored which has now been resolved | F37: 1084 | G37: PERS | J37: =IF(F37>0,(_xlfn.CONCAT(F37,".",G37)),H37) -> 1084.PERS | K37: =_xlfn.CONCAT("T Bell-",E37,"-",B37) -> T Bell-Personal issue with where credit card was stored which has now been resolved-CELLARBRATIONS AT SHEL SHELLEY AUS | L37: I | M37: =IF(C37>0,C37,-D37) -> 93 | N37: T | Q37: CBS - needs to be pasted seperately | R37: =LEN(K37) -> 118
A38: 19/10/2025 | B38: SOUTH SIDE POOL SERVIC CANNING VAL AUS | C38: 100 | D38: 0 | E38: Personal issue with where credit card was stored which has now been resolved | F38: 1084 | G38: PERS | J38: =IF(F38>0,(_xlfn.CONCAT(F38,".",G38)),H38) -> 1084.PERS | K38: =_xlfn.CONCAT("T Bell-",E38,"-",B38) -> T Bell-Personal issue with where credit card was stored which has now been resolved-SOUTH SIDE POOL SERVIC CANNING VAL AUS | L38: I | M38: =IF(C38>0,C38,-D38) -> 100 | N38: T | Q38: CBS - needs to be pasted seperately | R38: =LEN(K38) -> 122
A39: 24/10/2025 | B39: E-VISA TURKEY ANKARA TUR FRGN AMT: 67.95 U. S. DOLLAR | C39: 108.07 | D39: 0 | E39: Visa for Turkey - IMCET | F39: G071 | G39: SALP | J39: =IF(F39>0,(_xlfn.CONCAT(F39,".",G39)),H39) -> G071.SALP | K39: =_xlfn.CONCAT("T Bell-",E39,"-",B39) -> T Bell-Visa for Turkey - IMCET-E-VISA TURKEY ANKARA TUR FRGN AMT: 67.95 U. S. DOLLAR | L39: I | M39: =IF(C39>0,C39,-D39) -> 108.07 | N39: F | Q39: CBS - needs to be pasted seperately | R39: =LEN(K39) -> 85
A40: 3/11/2025 | B40: SQ *SEOUL HOPPERS Leederville AUS | C40: 137.9 | D40: 0 | E40: Wednesday Lunch | F40: 1084 | G40: ENON | J40: =IF(F40>0,(_xlfn.CONCAT(F40,".",G40)),H40) -> 1084.ENON | K40: =_xlfn.CONCAT("T Bell-",E40,"-",B40) -> T Bell-Wednesday Lunch-SQ *SEOUL HOPPERS Leederville AUS | L40: I | M40: =IF(C40>0,C40,-D40) -> 137.9 | N40: T | Q40: CBS - needs to be pasted seperately | R40: =LEN(K40) -> 56
A41: 13/11/2025 | B41: 7 MEHMET RESTAURANT ANTALYA TUR FRGN AMT: 3960.00 TURKISH LIRE | C41: 148.83 | D41: 0 | E41: Dinner in Turkey | F41: G071 | G41: SALP | J41: =IF(F41>0,(_xlfn.CONCAT(F41,".",G41)),H41) -> G071.SALP | K41: =_xlfn.CONCAT("T Bell-",E41,"-",B41) -> T Bell-Dinner in Turkey-7 MEHMET RESTAURANT ANTALYA TUR FRGN AMT: 3960.00 TURKISH LIRE | L41: I | M41: =IF(C41>0,C41,-D41) -> 148.83 | N41: F | Q41: CBS - needs to be pasted seperately | R41: =LEN(K41) -> 87
A42: 10/11/2025 | B42: CASH ADVANCE 010422312231127 NTALYA TUR | C42: 203.58 | D42: 0 | E42: Cash for taxi's, meals etc | F42: G071 | G42: SALP | J42: =IF(F42>0,(_xlfn.CONCAT(F42,".",G42)),H42) -> G071.SALP | K42: =_xlfn.CONCAT("T Bell-",E42,"-",B42) -> T Bell-Cash for taxi's, meals etc-CASH ADVANCE 010422312231127 NTALYA TUR | L42: I | M42: =IF(C42>0,C42,-D42) -> 203.58 | N42: F | Q42: CBS - needs to be pasted seperately | R42: =LEN(K42) -> 73
A43: 24/10/2025 | B43: MORLING COLLEGE MACQUARIE P AUS | C43: 260 | D43: 0 | E43: Mental Health First Aid Course - Debbie | F43: 1084 | G43: TRAI | J43: =IF(F43>0,(_xlfn.CONCAT(F43,".",G43)),H43) -> 1084.TRAI | K43: =_xlfn.CONCAT("T Bell-",E43,"-",B43) -> T Bell-Mental Health First Aid Course - Debbie-MORLING COLLEGE MACQUARIE P AUS | L43: I | M43: =IF(C43>0,C43,-D43) -> 260 | N43: T | Q43: CBS - needs to be pasted seperately | R43: =LEN(K43) -> 78

Sheet M Brown
A1: Employee to code & narrate | J1: To be copied in to pronto
J2: Credit card Statement TOTAL | K2: 1758.23
J3: Subtotal | K3: =SUM(M8:M143) -> 1758.23
J4: Variance Check | K4: =K2-K3 -> 0
A5: Michael Brown
A6: Reference | B6: =CONCATENATE(Header!$E$4,"Brown") -> MC-251116Brown | J6: EMPLOYEES DO NOT CHANGE
A7: Document Date | B7: =Header!$E$5 -> 45977 | E7: Credit card holder to add details
A9: Date | B9: Narrative | C9: Debit Amount | D9: Credit Amount | E9: Description | F9: Project No | G9: Cost Category | H9: GL account | J9: Account | K9: Reference | L9: Tax | M9: Amount | N9: Tax CODE | O9: TAX Amount (leave blank) | P9: CBS - Only if required | R9: limit 56charaters
A10: 45975 | B10: Ballarat Car Wash Pty Wendouree AUS | C10: 5.25 | D10: 0 | E10: Ute cleaning | F10: 1084 | G10: MVSR | J10: =IF(F10>0,(_xlfn.CONCAT(F10,".",G10)),H10) -> 1084.MVSR | K10: =_xlfn.CONCAT("M Brown-",E10,"-",B10) -> M Brown-Ute cleaning-Ballarat Car Wash Pty Wendouree AUS | L10: I | M10: =IF(C10>0,C10,-D10) -> 5.25 | N10: T | Q10: CBS - needs to be pasted seperately | R10: =LEN(K10) -> 56
A11: 45975 | B11: Ballarat Car Wash Pty Wendouree AUS | C11: 5.25 | D11: 0 | E11: Ute cleaning | F11: 1084 | G11: MVSR | J11: =IF(F11>0,(_xlfn.CONCAT(F11,".",G11)),H11) -> 1084.MVSR | K11: =_xlfn.CONCAT("M Brown-",E11,"-",B11) -> M Brown-Ute cleaning-Ballarat Car Wash Pty Wendouree AUS | L11: I | M11: =IF(C11>0,C11,-D11) -> 5.25 | N11: T | Q11: CBS - needs to be pasted seperately | R11: =LEN(K11) -> 56
A12: 45968 | B12: OFFICEWORKS 0364 BALLARAT AUS | C12: 9.98 | D12: 0 | E12: 2026 diary | F12: 1084 | G12: STAT | J12: =IF(F12>0,(_xlfn.CONCAT(F12,".",G12)),H12) -> 1084.STAT | K12: =_xlfn.CONCAT("M Brown-",E12,"-",B12) -> M Brown-2026 diary-OFFICEWORKS 0364 BALLARAT AUS | L12: I | M12: =IF(C12>0,C12,-D12) -> 9.98 | N12: T | Q12: CBS - needs to be pasted seperately | R12: =LEN(K12) -> 48
A13: 45957 | B13: Jaycar Ballarat Ballarat AUS | C13: 25 | D13: 0 | E13: Power lead for assay lab scales | F13: 1051 | G13: REPM | J13: =IF(F13>0,(_xlfn.CONCAT(F13,".",G13)),H13) -> 1051.REPM | K13: =_xlfn.CONCAT("M Brown-",E13,"-",B13) -> M Brown-Power lead for assay lab scales-Jaycar Ballarat Ballarat AUS | L13: I | M13: =IF(C13>0,C13,-D13) -> 25 | N13: T | Q13: CBS - needs to be pasted seperately | R13: =LEN(K13) -> 68
A14: 45946 | B14: RSEA PTY. LTD. BALLARAT CE AUS | C14: 29.99 | D14: 0 | E14: Hi Vis vests | F14: 1084 | G14: SPPE | J14: =IF(F14>0,(_xlfn.CONCAT(F14,".",G14)),H14) -> 1084.SPPE | K14: =_xlfn.CONCAT("M Brown-",E14,"-",B14) -> M Brown-Hi Vis vests-RSEA PTY. LTD. BALLARAT CE AUS | L14: I | M14: =IF(C14>0,C14,-D14) -> 29.99 | N14: T | Q14: CBS - needs to be pasted seperately | R14: =LEN(K14) -> 51
A15: 45973 | B15: BUNNINGS 329000 DELACOMBE AUS | C15: 36.6 | D15: 0 | E15: Masking tape and acetone | F15: 1084 | G15: REPM | J15: =IF(F15>0,(_xlfn.CONCAT(F15,".",G15)),H15) -> 1084.REPM | K15: =_xlfn.CONCAT("M Brown-",E15,"-",B15) -> M Brown-Masking tape and acetone-BUNNINGS 329000 DELACOMBE AUS | L15: I | M15: =IF(C15>0,C15,-D15) -> 36.6 | N15: T | Q15: CBS - needs to be pasted seperately | R15: =LEN(K15) -> 62
A16: 45960 | B16: BUNNINGS 730000 BALLARAT AUS | C16: 48.3 | D16: 0 | E16: masonite to repair ceiling B4 | F16: 1084 | G16: REPM | J16: =IF(F16>0,(_xlfn.CONCAT(F16,".",G16)),H16) -> 1084.REPM | K16: =_xlfn.CONCAT("M Brown-",E16,"-",B16) -> M Brown-masonite to repair ceiling B4-BUNNINGS 730000 BALLARAT AUS | L16: I | M16: =IF(C16>0,C16,-D16) -> 48.3 | N16: T | Q16: CBS - needs to be pasted seperately | R16: =LEN(K16) -> 66
A17: 45974 | B17: AWM WENDOUREE WENDOUREE AUS | C17: 49.88 | D17: 0 | E17: 15 amp lead for switch room | F17: 1084 | G17: REPM | J17: =IF(F17>0,(_xlfn.CONCAT(F17,".",G17)),H17) -> 1084.REPM | K17: =_xlfn.CONCAT("M Brown-",E17,"-",B17) -> M Brown-15 amp lead for switch room-AWM WENDOUREE WENDOUREE AUS | L17: I | M17: =IF(C17>0,C17,-D17) -> 49.88 | N17: T | Q17: CBS - needs to be pasted seperately | R17: =LEN(K17) -> 63
A18: 45957 | B18: BUNNINGS 329000 DELACOMBE AUS | C18: 67.86 | D18: 0 | E18: AAA and AA batteries | F18: 1084 | G18: REPM | J18: =IF(F18>0,(_xlfn.CONCAT(F18,".",G18)),H18) -> 1084.REPM | K18: =_xlfn.CONCAT("M Brown-",E18,"-",B18) -> M Brown-AAA and AA batteries-BUNNINGS 329000 DELACOMBE AUS | L18: I | M18: =IF(C18>0,C18,-D18) -> 67.86 | N18: T | Q18: CBS - needs to be pasted seperately | R18: =LEN(K18) -> 58
A19: 45972 | B19: AWM WENDOUREE WENDOUREE AUS | C19: 80.39 | D19: 0 | E19: Expanding foam B7 heater ducts | F19: 1084 | G19: REPM | J19: =IF(F19>0,(_xlfn.CONCAT(F19,".",G19)),H19) -> 1084.REPM | K19: =_xlfn.CONCAT("M Brown-",E19,"-",B19) -> M Brown-Expanding foam B7 heater ducts-AWM WENDOUREE WENDOUREE AUS | L19: I | M19: =IF(C19>0,C19,-D19) -> 80.39 | N19: T | Q19: CBS - needs to be pasted seperately | R19: =LEN(K19) -> 66
A20: 45947 | B20: BUNNINGS 730000 BALLARAT AUS | C20: 109.85 | D20: 0 | E20: Paint brush, stainless steal hooks | F20: 1084 | G20: REPM | J20: =IF(F20>0,(_xlfn.CONCAT(F20,".",G20)),H20) -> 1084.REPM | K20: =_xlfn.CONCAT("M Brown-",E20,"-",B20) -> M Brown-Paint brush, stainless steal hooks-BUNNINGS 730000 BALLARAT AUS | L20: I | M20: =IF(C20>0,C20,-D20) -> 109.85 | N20: T | Q20: CBS - needs to be pasted seperately | R20: =LEN(K20) -> 71
A21: 45952 | B21: Reddy Express 6744 Ballarat AUS | C21: 135.14 | D21: 0 | E21: Ute fuel | F21: 1084 | G21: MVPF | J21: =IF(F21>0,(_xlfn.CONCAT(F21,".",G21)),H21) -> 1084.MVPF | K21: =_xlfn.CONCAT("M Brown-",E21,"-",B21) -> M Brown-Ute fuel-Reddy Express 6744 Ballarat AUS | L21: I | M21: =IF(C21>0,C21,-D21) -> 135.14 | N21: T | Q21: CBS - needs to be pasted seperately | R21: =LEN(K21) -> 48
... A23: 45946 | B23: TOTAL TOOLS BALLARAT BALLARAT AUS | C23: 139 | D23: 0 | E23: Stud detector | F23: 1084 | G23: REPM | J23: =IF(F23>0,(_xlfn.CONCAT(F23,".",G23)),H23) -> 1084.REPM | K23: =_xlfn.CONCAT("M Brown-",E23,"-",B23) -> M Brown-Stud detector-TOTAL TOOLS BALLARAT BALLARAT AUS | L23: I | M23: =IF(C23>0,C23,-D23) -> 139 | N23: T | Q23: CBS - needs to be pasted seperately | R23: =LEN(K23) -> 55
A24: 45974 | B24: W J ROBSON AND SONS WENDOUREE AUS | C24: 149.63 | D24: 0 | E24: Window repair Mt Cog | F24: g125 | G24: misc | J24: =IF(F24>0,(_xlfn.CONCAT(F24,".",G24)),H24) -> g125.misc | K24: =_xlfn.CONCAT("M Brown-",E24,"-",B24) -> M Brown-Window repair Mt Cog-W J ROBSON AND SONS WENDOUREE AUS | L24: I | M24: =IF(C24>0,C24,-D24) -> 149.63 | N24: T | Q24: CBS - needs to be pasted seperately | R24: =LEN(K24) -> 62
A25: 45967 | B25: UNITED WENDOUREE WENDOUREE AUS | C25: 150.01 | D25: 0 | E25: Ute fuel | F25: 1084 | G25: MVPF | J25: =IF(F25>0,(_xlfn.CONCAT(F25,".",G25)),H25) -> 1084.MVPF | K25: =_xlfn.CONCAT("M Brown-",E25,"-",B25) -> M Brown-Ute fuel-UNITED WENDOUREE WENDOUREE AUS | L25: I | M25: =IF(C25>0,C25,-D25) -> 150.01 | N25: T | Q25: CBS - needs to be pasted seperately | R25: =LEN(K25) -> 47
A26: 45968 | B26: FIFTEEN NEEDLES GROUP WENDOUREE AUS | C26: 196 | D26: 0 | E26: Safety boots | F26: 1084 | G26: SPPE | J26: =IF(F26>0,(_xlfn.CONCAT(F26,".",G26)),H26) -> 1084.SPPE | K26: =_xlfn.CONCAT("M Brown-",E26,"-",B26) -> M Brown-Safety boots-FIFTEEN NEEDLES GROUP WENDOUREE AUS | L26: I | M26: =IF(C26>0,C26,-D26) -> 196 | N26: T | Q26: CBS - needs to be pasted seperately | R26: =LEN(K26) -> 56
A27: 45957 | B27: Industrial World BALLARAT AUS | C27: 381.1 | D27: 0 | E27: Assay Lab LM5 bearings | F27: 1051g | G27: REPM | J27: =IF(F27>0,(_xlfn.CONCAT(F27,".",G27)),H27) -> 1051g.REPM | K27: =_xlfn.CONCAT("M Brown-",E27,"-",B27) -> M Brown-Assay Lab LM5 bearings-Industrial World BALLARAT AUS | L27: I | M27: =IF(C27>0,C27,-D27) -> 381.1 | N27: T | Q27: CBS - needs to be pasted seperately | R27: =LEN(K27) -> 60

Sheet M Conroy
A1: Employee to code & narrate | J1: To be copied in to pronto
J2: Credit card Statement TOTAL | K2: 168.52
J3: Subtotal | K3: =SUM(M8:M143) -> 0
J4: Variance Check | K4: =K2-K3 -> 168.52
A5: Matthew Conroy
A6: Reference | B6: =CONCATENATE(Header!$E$4,"Conroy") -> MC-251116Conroy | J6: EMPLOYEES DO NOT CHANGE
A7: Document Date | B7: =Header!$E$5 -> 45977 | E7: Credit card holder to add details
A9: Date | B9: Narrative | C9: Debit Amount | D9: Credit Amount | E9: Description | F9: Project No | G9: Cost Category | H9: GL account | J9: Account | K9: Reference | L9: Tax | M9: Amount | N9: Tax CODE | O9: TAX Amount (leave blank) | P9: CBS - Only if required | R9: limit 56charaters
J10: =IF(F10>0,(_xlfn.CONCAT(F10,".",G10)),H10) -> 0 | K10: =_xlfn.CONCAT("M Conroy-",B10,"-",E10) -> M Conroy-- | L10: I | M10: =IF(C10>0,C10,-D10) -> 0 | N10: T | Q10: CBS - needs to be pasted seperately | R10: =LEN(K10) -> 10

Sheet G Delemontex
A1: Employee to code & narrate | J1: To be copied in to pronto
J2: Credit card Statement TOTAL | K2: 1280.11
J3: Subtotal | K3: =SUM(M8:M143) -> 1280.11
J4: Variance Check | K4: =K2-K3 -> 0
A5: Georges Delemontex
A6: Reference | B6: =CONCATENATE(Header!$E$4,"Delemontex") -> MC-251116Delemontex | J6: EMPLOYEES DO NOT CHANGE
A7: Document Date | B7: =Header!$E$5 -> 45977 | E7: Credit card holder to add details
A9: Date | B9: Narrative | C9: Debit Amount | D9: Credit Amount | E9: Description | F9: Project No | G9: Cost Category | H9: GL account | J9: Account | K9: Reference | L9: Tax | M9: Amount | N9: Tax CODE | O9: TAX Amount (leave blank) | P9: CBS - Only if required | R9: limit 56charaters
A10: 45960 | B10: BUNNINGS 730000 BALLARAT AUS | C10: 62.36 | D10: 0 | E10: R&D - Piping and fittings for trail of new lab digester pump | F10: 1060GE2 | G10: MISC | J10: =IF(F10>0,(_xlfn.CONCAT(F10,".",G10)),H10) -> 1060GE2.MISC | K10: =_xlfn.CONCAT("G Delemontex-",E10,"-",B10) -> G Delemontex-R&D - Piping and fittings for trail of new lab digester pump-BUNNINGS 730000 BALLARAT AUS | L10: I | M10: =IF(C10>0,C10,-D10) -> 62.36 | N10: T | Q10: CBS - needs to be pasted seperately | R10: =LEN(K10) -> 102
A11: 45954 | B11: Ballarat Plumbing Cen ALFREDTON AUS | C11: 87.75 | D11: 0 | E11: G24625 - AME - fittings for flowmeter installation to firm up total product flow | F11: 1060GE2 | G11: MISC | J11: =IF(F11>0,(_xlfn.CONCAT(F11,".",G11)),H11) -> 1060GE2.MISC | K11: =_xlfn.CONCAT("G Delemontex-",E11,"-",B11) -> G Delemontex-G24625 - AME - fittings for flowmeter installation to firm up total product flow-Ballarat Plumbing Cen ALFREDTON AUS | L11: I | M11: =IF(C11>0,C11,-D11) -> 87.75 | N11: T
A12: 45957 | B12: PUMPS AND PIPES SLACKS CREE AUS | C12: 1130 | D12: 0 | E12: R&D - PC Pump purchase for trail of new lab digester | F12: 1060GE2 | G12: MISC | J12: =IF(F12>0,(_xlfn.CONCAT(F12,".",G12)),H12) -> 1060GE2.MISC | K12: =_xlfn.CONCAT("G Delemontex-",E12,"-",B12) -> G Delemontex-R&D - PC Pump purchase for trail of new lab digester-PUMPS AND PIPES SLACKS CREE AUS | L12: I | M12: =IF(C12>0,C12,-D12) -> 1130 | N12: T

Sheet M Donadio
A1: Employee to code & narrate | J1: To be copied in to pronto
J2: Credit card Statement TOTAL | K2: 13283.13
J3: Subtotal | K3: =SUM(M8:M143) -> 13283.13
J4: Variance Check | K4: =K2-K3 -> 0
A5: Mark Donadio
A6: Reference | B6: =CONCATENATE(Header!$E$4,"Donadio") -> MC-251116Donadio | J6: EMPLOYEES DO NOT CHANGE
A7: Document Date | B7: =Header!$E$5 -> 45977 | E7: Credit card holder to add details
A9: Date | B9: Narrative | C9: Debit Amount | D9: Credit Amount | E9: Description | F9: Project No | G9: Cost Category | H9: GL account | J9: Account | K9: Reference | L9: Tax | M9: Amount | N9: Tax CODE | O9: TAX Amount (leave blank) | P9: CBS - Only if required | R9: limit 56charaters
A10: 45950 | B10: DNH*GODADDY#3927101700 SYDNEY AUS | C10: 30.45 | D10: 0 | E10: domain registration - www.Gaia-Evniro.com.au | F10: 1060GE2 | G10: MISC | J10: =IF(F10>0,(_xlfn.CONCAT(F10,".",G10)),H10) -> 1060GE2.MISC | K10: =_xlfn.CONCAT("M Donadio-",E10,"-",B10) -> M Donadio-domain registration - www.Gaia-Evniro.com.au-DNH*GODADDY#3927101700 SYDNEY AUS | L10: I | M10: =IF(C10>0,C10,-D10) -> 30.45 | N10: T | Q10: CBS - needs to be pasted seperately | R10: =LEN(K10) -> 88
A11: 45959 | B11: DNH*GODADDY#3934264793 SYDNEY AUS | C11: 40.9 | D11: 0 | E11: domain registration - gravityseparation | F11: 1084 | G11: WEBS | J11: =IF(F11>0,(_xlfn.CONCAT(F11,".",G11)),H11) -> 1084.WEBS | K11: =_xlfn.CONCAT("M Donadio-",E11,"-",B11) -> M Donadio-domain registration - gravityseparation-DNH*GODADDY#3934264793 SYDNEY AUS | L11: I | M11: =IF(C11>0,C11,-D11) -> 40.9 | N11: T | Q11: CBS - needs to be pasted seperately | R11: =LEN(K11) -> 83
A12: 45952 | B12: STARLINK INTERNET Sydney AUS | C12: 139 | D12: 0 | E12: Internet | F12: 1084 | G12: INTE | J12: =IF(F12>0,(_xlfn.CONCAT(F12,".",G12)),H12) -> 1084.INTE | K12: =_xlfn.CONCAT("M Donadio-",E12,"-",B12) -> M Donadio-Internet-STARLINK INTERNET Sydney AUS | L12: I | M12: =IF(C12>0,C12,-D12) -> 139 | N12: T | Q12: CBS - needs to be pasted seperately | R12: =LEN(K12) -> 47
A13: 45961 | B13: COLES 0628 BALLARAT AUS | C13: 215 | D13: 0 | E13: supplies | F13: 1084 | G13: STAF | J13: =IF(F13>0,(_xlfn.CONCAT(F13,".",G13)),H13) -> 1084.STAF | K13: =_xlfn.CONCAT("M Donadio-",E13,"-",B13) -> M Donadio-supplies-COLES 0628 BALLARAT AUS | L13: I | M13: =IF(C13>0,C13,-D13) -> 215 | N13: T | Q13: CBS - needs to be pasted seperately | R13: =LEN(K13) -> 42
A14: 45950 | B14: Hotel at Booking.com Sydney AUS | C14: 146.67 | D14: 0 | E14: accommodation for Cadell | F14: 1051 | G14: TRAI | J14: =IF(F14>0,(_xlfn.CONCAT(F14,".",G14)),H14) -> 1051.TRAI | K14: =_xlfn.CONCAT("M Donadio-",E14,"-",B14) -> M Donadio-accommodation for Cadell -Hotel at Booking.com Sydney AUS | L14: I | M14: =IF(C14>0,C14,-D14) -> 146.67 | N14: T | Q14: CBS - needs to be pasted seperately | R14: =LEN(K14) -> 67
A15: 46315 | B15: Hotel at Booking.com Sydney AUS | C15: 146.68 | D15: 0 | E15: accommodation for Oscar | F15: 1077 | G15: TRAI | J15: =IF(F15>0,(_xlfn.CONCAT(F15,".",G15)),H15) -> 1077.TRAI | K15: =_xlfn.CONCAT("M Donadio-",E15,"-",B15) -> M Donadio-accommodation for Oscar-Hotel at Booking.com Sydney AUS | L15: I | M15: =IF(C15>0,C15,-D15) -> 146.68 | N15: T | Q15: CBS - needs to be pasted seperately | R15: =LEN(K15) -> 65
A16: 45950 | B16: FlightCentre GiftCards South Brisb AUS | C16: 500 | D16: 0 | E16: farewell gift for Austell | F16: 1084 | G16: STAF | J16: =IF(F16>0,(_xlfn.CONCAT(F16,".",G16)),H16) -> 1084.STAF | K16: =_xlfn.CONCAT("M Donadio-",E16,"-",B16) -> M Donadio-farewell gift for Austell-FlightCentre GiftCards South Brisb AUS | L16: I | M16: =IF(C16>0,C16,-D16) -> 500 | N16: T | Q16: CBS - needs to be pasted seperately | R16: =LEN(K16) -> 74
A17: 45973 | B17: ANAESTHETIC GROUP BALLARAT AUS | C17: 685 | D17: 0 | E17: Loan to employee | F17: 1084 | G17: PERS | J17: =IF(F17>0,(_xlfn.CONCAT(F17,".",G17)),H17) -> 1084.PERS | K17: =_xlfn.CONCAT("M Donadio-",E17,"-",B17) -> M Donadio-Loan to employee-ANAESTHETIC GROUP BALLARAT AUS | L17: I | M17: =IF(C17>0,C17,-D17) -> 685 | N17: F | Q17: CBS - needs to be pasted seperately | R17: =LEN(K17) -> 57
A18: 45958 | B18: LinkedIn 10604917636 NORTH SYDNE AUS | C18: 1308.54 | D18: 0 | E18: LinkedIn recruiter | F18: 1084 | G18: RECR | J18: =IF(F18>0,(_xlfn.CONCAT(F18,".",G18)),H18) -> 1084.RECR | K18: =_xlfn.CONCAT("M Donadio-",E18,"-",B18) -> M Donadio-LinkedIn recruiter-LinkedIn 10604917636 NORTH SYDNE AUS | L18: I | M18: =IF(C18>0,C18,-D18) -> 1308.54 | N18: T | Q18: CBS - needs to be pasted seperately | R18: =LEN(K18) -> 65
A19: 45953 | B19: SMP*Major Roasts Ballarat No AUS | C19: 1607.59 | D19: 0 | E19: Wednesday lunch | F19: 1084 | G19: ENON | J19: =IF(F19>0,(_xlfn.CONCAT(F19,".",G19)),H19) -> 1084.ENON | K19: =_xlfn.CONCAT("M Donadio-",E19,"-",B19) -> M Donadio-Wednesday lunch-SMP*Major Roasts Ballarat No AUS | L19: I | M19: =IF(C19>0,C19,-D19) -> 1607.59 | N19: T | Q19: CBS - needs to be pasted seperately | R19: =LEN(K19) -> 58
A20: 45973 | B20: ST JOHN OF GOD BALLARA Perth AUS | C20: 2395 | D20: 0 | E20: Loan to employee | F20: 1084 | G20: PERS | J20: =IF(F20>0,(_xlfn.CONCAT(F20,".",G20)),H20) -> 1084.PERS | K20: =_xlfn.CONCAT("M Donadio-",E20,"-",B20) -> M Donadio-Loan to employee-ST JOHN OF GOD BALLARA Perth AUS | L20: I | M20: =IF(C20>0,C20,-D20) -> 2395 | N20: F | Q20: CBS - needs to be pasted seperately | R20: =LEN(K20) -> 59
A21: 45973 | B21: SP YETI CORPORATE SOUTH MELBO AUS | C21: 5450 | D21: 0 | E21: Gifst for staff celebrating OHS milestone | H21: 199999992320 | J21: =IF(F21>0,(_xlfn.CONCAT(F21,".",G21)),H21) -> 199999992320 | K21: =_xlfn.CONCAT("M Donadio-",E21,"-",B21) -> M Donadio-Gifst for staff celebrating OHS milestone-SP YETI CORPORATE SOUTH MELBO AUS | L21: I | M21: =IF(C21>0,C21,-D21) -> 5450 | N21: T | Q21: CBS - needs to be pasted seperately | R21: =LEN(K21) -> 85
A22: 45945 | B22: QANTAS | C22: 618.3 | D22: 0 | E22: QANTAS club membership for Wayne | F22: 1084 | G22: PREP | J22: =IF(F22>0,(_xlfn.CONCAT(F22,".",G22)),H22) -> 1084.PREP | K22: =_xlfn.CONCAT("M Donadio-",E22,"-",B22) -> M Donadio-QANTAS club membership for Wayne-QANTAS | L22: I | M22: =IF(C22>0,C22,-D22) -> 618.3 | N22: T | Q22: CBS - needs to be pasted seperately | R22: =LEN(K22) -> 49

Sheet L DUva
A1: Employee to code & narrate | J1: To be copied in to pronto
J2: Credit card Statement TOTAL | K2: 215.6
J3: Subtotal | K3: =SUM(M8:M143) -> 215.6
J4: Variance Check | K4: =K2-K3 -> 0
A5: Lisa Duva
A6: Reference | B6: =CONCATENATE(Header!$E$4,"DUVA") -> MC-251116DUVA | J6: EMPLOYEES DO NOT CHANGE
A7: Document Date | B7: =Header!$E$5 -> 45977 | E7: Credit card holder to add details
A9: Date | B9: Narrative | C9: Debit Amount | D9: Credit Amount | E9: Description | F9: Project No | G9: Cost Category | H9: GL account | J9: Account | K9: Reference | L9: Tax | M9: Amount | N9: Tax CODE | O9: TAX Amount (leave blank) | P9: CBS - Only if required | R9: limit 56charaters
A10: 45971 | B10: TSUKE BA LEEDERVILLE AUS | C10: 31 | D10: 0 | E10: Wednesday Lunch | F10: 1041 | G10: ENTON | J10: =IF(F10>0,(_xlfn.CONCAT(F10,".",G10)),H10) -> 1041.ENTON | K10: =_xlfn.CONCAT("L Duva-",E10,"-",B10) -> L Duva-Wednesday Lunch-TSUKE BA LEEDERVILLE AUS | L10: I | M10: =IF(C10>0,C10,-D10) -> 31 | N10: T | Q10: CBS - needs to be pasted seperately | R10: =LEN(K10) -> 47
A11: 45953 | B11: Live Payments Barangaroo AUS | C11: 92.3 | D11: 0 | E11: Taxi from Airport | F11: S17246 | G11: TRVT | J11: =IF(F11>0,(_xlfn.CONCAT(F11,".",G11)),H11) -> S17246.TRVT | K11: =_xlfn.CONCAT("L Duva-",E11,"-",B11) -> L Duva-Taxi from Airport-Live Payments Barangaroo AUS | L11: I | M11: =IF(C11>0,C11,-D11) -> 92.3 | N11: T | Q11: CBS - needs to be pasted seperately | R11: =LEN(K11) -> 53
A12: 45952 | B12: SPOTTO WA DARLINGHURS AUS | C12: 92.3 | D12: 0 | E12: Taxi to Airport | F12: S17246 | G12: TRVT | J12: =IF(F12>0,(_xlfn.CONCAT(F12,".",G12)),H12) -> S17246.TRVT | K12: =_xlfn.CONCAT("L Duva-",E12,"-",B12) -> L Duva- Taxi to Airport-SPOTTO WA DARLINGHURS AUS | L12: I | M12: =IF(C12>0,C12,-D12) -> 92.3 | N12: T | Q12: CBS - needs to be pasted seperately | R12: =LEN(K12) -> 49

Sheet A Edmondston
A1: Employee to code & narrate | J1: To be copied in to pronto
J2: Credit card Statement TOTAL | K2: 2897.18
J3: Subtotal | K3: =SUM(M10:M35) -> 2897.18
J4: Variance Check | K4: =K2-K3 -> 0
A5: Andrew Edmondston
A6: Reference | B6: =CONCATENATE(Header!$E$4,"Edmondston") -> MC-251116Edmondston | J6: EMPLOYEES DO NOT CHANGE
A7: Document Date | B7: =Header!$E$5 -> 45977 | E7: Credit card holder to add details
A9: Date | B9: Narrative | C9: Debit Amount | D9: Credit Amount | E9: Description | F9: Project No | G9: Cost Category | H9: GL account | J9: Account | K9: Reference | L9: Tax | M9: Amount | N9: Tax CODE | O9: TAX Amount (leave blank) | P9: CBS - Only if required | R9: limit 56charaters
A10: 45950 | B10: STATION REFRESHMEN BALLARAT AUS | C10: 5.95 | D10: 0 | E10: IMARC Food | F10: G081 | G10: SALP | J10: =IF(F10>0,(_xlfn.CONCAT(F10,".",G10)),H10) -> G081.SALP | K10: =_xlfn.CONCAT("A Edmondston-",E10,"-",B10) -> A Edmondston-IMARC Food-STATION REFRESHMEN BALLARAT AUS | L10: I | M10: =IF(C10>0,C10,-D10) -> 5.95 | N10: T | Q10: CBS - needs to be pasted seperately | R10: =LEN(K10) -> 55
A11: 45946 | B11: WOOLWORTHS 3309 WENDOUREE AUS | C11: 6 | D11: 0 | E11: Morning Tea - SDG Meeting | F11: 1084 | G11: ENON | J11: =IF(F11>0,(_xlfn.CONCAT(F11,".",G11)),H11) -> 1084.ENON | K11: =_xlfn.CONCAT("A Edmondston-",E11,"-",B11) -> A Edmondston-Morning Tea - SDG Meeting-WOOLWORTHS 3309 WENDOUREE AUS | L11: I | M11: =IF(C11>0,C11,-D11) -> 6 | N11: T | Q11: CBS - needs to be pasted seperately | R11: =LEN(K11) -> 73
A12: 45952 | B12: Brew Bros Cafe Sydney AUS | C12: 9.14 | D12: 0 | E12: IMARC Breakfast | F12: G081 | G12: SALP | J12: =IF(F12>0,(_xlfn.CONCAT(F12,".",G12)),H12) -> G081.SALP | K12: =_xlfn.CONCAT("A Edmondston-",E12,"-",B12) -> A Edmondston-IMARC Breakfast-Brew Bros Cafe Sydney AUS | L12: I | M12: =IF(C12>0,C12,-D12) -> 9.14 | N12: T | Q12: CBS - needs to be pasted seperately | R12: =LEN(K12) -> 54
A13: 45954 | B13: Ballarat City Council Ballarat Ce AUS | C13: 12 | D13: 0 | E13: Parking - Melbourne Mining Club | F13: 1084 | G13: MVPT | J13: =IF(F13>0,(_xlfn.CONCAT(F13,".",G13)),H13) -> 1084.MVPT | K13: =_xlfn.CONCAT("A Edmondston-",E13,"-",B13) -> A Edmondston-Parking - Melbourne Mining Club-Ballarat City Council Ballarat Ce AUS | L13: I | M13: =IF(C13>0,C13,-D13) -> 12 | N13: T | Q13: CBS - needs to be pasted seperately | R13: =LEN(K13) -> 82
A14: 45951 | B14: 347 KENT ST PTY LTD SYDNEY AUS | C14: 13.21 | D14: 0 | E14: IMARC Food | F14: G081 | G14: SALP | J14: =IF(F14>0,(_xlfn.CONCAT(F14,".",G14)),H14) -> G081.SALP | K14: =_xlfn.CONCAT("A Edmondston-",E14,"-",B14) -> A Edmondston-IMARC Food-347 KENT ST PTY LTD SYDNEY AUS | L14: I | M14: =IF(C14>0,C14,-D14) -> 13.21 | N14: T | Q14: CBS - needs to be pasted seperately | R14: =LEN(K14) -> 54
A15: 45950 | B15: UBER *TRIP HELP.UBER.C 14518236738 AUS | C15: 16.5 | D15: 0 | E15: IMARC - Taxi to station | F15: G081 | G15: SALP | J15: =IF(F15>0,(_xlfn.CONCAT(F15,".",G15)),H15) -> G081.SALP | K15: =_xlfn.CONCAT("A Edmondston-",E15,"-",B15) -> A Edmondston-IMARC - Taxi to station-UBER *TRIP HELP.UBER.C 14518236738 AUS | L15: I | M15: =IF(C15>0,C15,-D15) -> 16.5 | N15: T | Q15: CBS - needs to be pasted seperately | R15: =LEN(K15) -> 75
A16: 45946 | B16: BAKERS DELIGHT WENDOUR WENDOUREE AUS | C16: 19 | D16: 0 | E16: Morning Tea - SDG Meeting | F16: 1084 | G16: ENON | J16: =IF(F16>0,(_xlfn.CONCAT(F16,".",G16)),H16) -> 1084.ENON | K16: =_xlfn.CONCAT("A Edmondston-",E16,"-",B16) -> A Edmondston-Morning Tea - SDG Meeting-BAKERS DELIGHT WENDOUR WENDOUREE AUS | L16: I | M16: =IF(C16>0,C16,-D16) -> 19 | N16: T | Q16: CBS - needs to be pasted seperately | R16: =LEN(K16) -> 75
A17: 45953 | B17: TRANSPORTFORNSW TAP SYDNEY AUS | C17: 20.95 | D17: 0 | E17: IMARC - Train to Sydney City | F17: G081 | G17: SALP | J17: =IF(F17>0,(_xlfn.CONCAT(F17,".",G17)),H17) -> G081.SALP | K17: =_xlfn.CONCAT("A Edmondston-",E17,"-",B17) -> A Edmondston-IMARC - Train to Sydney City-TRANSPORTFORNSW TAP SYDNEY AUS | L17: I | M17: =IF(C17>0,C17,-D17) -> 20.95 | N17: T | Q17: CBS - needs to be pasted seperately | R17: =LEN(K17) -> 72
A18: 45952 | B18: ZLR*S2BISTR Mascot AUS | C18: 21.81 | D18: 0 | E18: IMARC Lunch | F18: G081 | G18: SALP | J18: =IF(F18>0,(_xlfn.CONCAT(F18,".",G18)),H18) -> G081.SALP | K18: =_xlfn.CONCAT("A Edmondston-",E18,"-",B18) -> A Edmondston-IMARC Lunch-ZLR*S2BISTR Mascot AUS | L18: I | M18: =IF(C18>0,C18,-D18) -> 21.81 | N18: T | Q18: CBS - needs to be pasted seperately | R18: =LEN(K18) -> 47
A19: 45951 | B19: TRANSPORTFORNSW TAP SYDNEY AUS | C19: 22.25 | D19: 0 | E19: IMARC - Train to Airport | F19: G081 | G19: SALP | J19: =IF(F19>0,(_xlfn.CONCAT(F19,".",G19)),H19) -> G081.SALP | K19: =_xlfn.CONCAT("A Edmondston-",E19,"-",B19) -> A Edmondston-IMARC - Train to Airport-TRANSPORTFORNSW TAP SYDNEY AUS | L19: I | M19: =IF(C19>0,C19,-D19) -> 22.25 | N19: T | Q19: CBS - needs to be pasted seperately | R19: =LEN(K19) -> 68
A20: 45950 | B20: Hotel CBD Sydney AUS | C20: 29.71 | D20: 0 | E20: IMARC - Food/Drinks | F20: G081 | G20: SALP | J20: =IF(F20>0,(_xlfn.CONCAT(F20,".",G20)),H20) -> G081.SALP | K20: =_xlfn.CONCAT("A Edmondston-",E20,"-",B20) -> A Edmondston-IMARC - Food/Drinks-Hotel CBD Sydney AUS | L20: I | M20: =IF(C20>0,C20,-D20) -> 29.71 | N20: T | Q20: CBS - needs to be pasted seperately | R20: =LEN(K20) -> 53
A21: 45950 | B21: Hotel CBD Sydney AUS | C21: 45.47 | D21: 0 | E21: IMARC Food/Drinks | F21: G081 | G21: SALP | J21: =IF(F21>0,(_xlfn.CONCAT(F21,".",G21)),H21) -> G081.SALP | K21: =_xlfn.CONCAT("A Edmondston-",E21,"-",B21) -> A Edmondston-IMARC Food/Drinks-Hotel CBD Sydney AUS | L21: I | M21: =IF(C21>0,C21,-D21) -> 45.47 | N21: T | Q21: CBS - needs to be pasted seperately | R21: =LEN(K21) -> 51
A22: 45951 | B22: Brew Bros Cafe Sydney AUS | C22: 45.68 | D22: 0 | E22: IMARC Food/Drinks | F22: G081 | G22: SALP | J22: =IF(F22>0,(_xlfn.CONCAT(F22,".",G22)),H22) -> G081.SALP | K22: =_xlfn.CONCAT("A Edmondston-",E22,"-",B22) -> A Edmondston-IMARC Food/Drinks-Brew Bros Cafe Sydney AUS | L22: I | M22: =IF(C22>0,C22,-D22) -> 45.68 | N22: T | Q22: CBS - needs to be pasted seperately | R22: =LEN(K22) -> 56
A23: 45970 | B23: SYMPOSIUM EVENTS PTY L MAIN BEACH AUS | C23: 50 | D23: 0 | E23: Australian Gold Conference Subscription | F23: 1084 | G23: CONF | J23: =IF(F23>0,(_xlfn.CONCAT(F23,".",G23)),H23) -> 1084.CONF | K23: =_xlfn.CONCAT("A Edmondston-",E23,"-",B23) -> A Edmondston-Australian Gold Conference Subscription-SYMPOSIUM EVENTS PTY L MAIN BEACH AUS | L23: I | M23: =IF(C23>0,C23,-D23) -> 50 | N23: T | Q23: CBS - needs to be pasted seperately | R23: =LEN(K23) -> 90
A24: 45952 | B24: ZLR*S2BISTR Mascot AUS | C24: 92.8 | D24: 0 | E24: IMARC Food | F24: G081 | G24: SALP | J24: =IF(F24>0,(_xlfn.CONCAT(F24,".",G24)),H24) -> G081.SALP | K24: =_xlfn.CONCAT("A Edmondston-",E24,"-",B24) -> A Edmondston-IMARC Food-ZLR*S2BISTR Mascot AUS | L24: I | M24: =IF(C24>0,C24,-D24) -> 92.8 | N24: T | Q24: CBS - needs to be pasted seperately | R24: =LEN(K24) -> 46
A25: 45952 | B25: Airport Shuttle Bus BAKERY HILL AUS | C25: 118 | D25: 0 | E25: IMARC Airport Shuttle Bus AE/NG | F25: G081 | G25: SALP | J25: =IF(F25>0,(_xlfn.CONCAT(F25,".",G25)),H25) -> G081.SALP | K25: =_xlfn.CONCAT("A Edmondston-",E25,"-",B25) -> A Edmondston-IMARC Airport Shuttle Bus AE/NG-Airport Shuttle Bus BAKERY HILL AUS | L25: I | M25: =IF(C25>0,C25,-D25) -> 118 | N25: T | Q25: CBS - needs to be pasted seperately | R25: =LEN(K25) -> 80
A26: 45947 | B26: THE LAKE VIEW Lake Wendou AUS | C26: 142.34 | D26: 0 | E26: Lunch AE, AL, MX, LC - Farewell lunch Austell | F26: 1084 | G26: ENFE | J26: =IF(F26>0,(_xlfn.CONCAT(F26,".",G26)),H26) -> 1084.ENFE | K26: =_xlfn.CONCAT("A Edmondston-",E26,"-",B26) -> A Edmondston-Lunch AE, AL, MX, LC - Farewell lunch Austell-THE LAKE VIEW Lake Wendou AUS | L26: I | M26: =IF(C26>0,C26,-D26) -> 142.34 | N26: T | Q26: CBS - needs to be pasted seperately | R26: =LEN(K26) -> 88
A27: 45973 | B27: 2 BLOKES COFFEE ROAST MOUNT HELEN AUS | C27: 185 | D27: 0 | E27: Coffee Beans | F27: 1084 | G27: STAF | J27: =IF(F27>0,(_xlfn.CONCAT(F27,".",G27)),H27) -> 1084.STAF | K27: =_xlfn.CONCAT("A Edmondston-",E27,"-",B27) -> A Edmondston-Coffee Beans-2 BLOKES COFFEE ROAST MOUNT HELEN AUS | L27: I | M27: =IF(C27>0,C27,-D27) -> 185 | N27: f | Q27: CBS - needs to be pasted seperately | R27: =LEN(K27) -> 64
A28: 45952 | B28: 2 BLOKES COFFEE ROAST MOUNT HELEN AUS | C28: 370 | D28: 0 | E28: Coffee Beans | F28: 1084 | G28: STAF | J28: =IF(F28>0,(_xlfn.CONCAT(F28,".",G28)),H28) -> 1084.STAF | K28: =_xlfn.CONCAT("A Edmondston-",E28,"-",B28) -> A Edmondston-Coffee Beans-2 BLOKES COFFEE ROAST MOUNT HELEN AUS | L28: I | M28: =IF(C28>0,C28,-D28) -> 370 | N28: f | Q28: CBS - needs to be pasted seperately | R28: =LEN(K28) -> 64
A29: 45951 | B29: JETSTARZT4MFK COLLINGWOOD AUS | C29: 1671.37 | D29: 0 | E29: IMARC - flights AE,NG | F29: G081 | G29: SALP | J29: =IF(F29>0,(_xlfn.CONCAT(F29,".",G29)),H29) -> G081.SALP | K29: =_xlfn.CONCAT("A Edmondston-",E29,"-",B29) -> A Edmondston-IMARC - flights AE,NG-JETSTARZT4MFK COLLINGWOOD AUS | L29: I | M29: =IF(C29>0,C29,-D29) -> 1671.37 | N29: T | Q29: CBS - needs to be pasted seperately | R29: =LEN(K29) -> 64

Sheet M Gort
A1: Employee to code & narrate | J1: To be copied in to pronto
J2: Credit card Statement TOTAL | K2: 138.59
J3: Subtotal | K3: =SUM(M8:M143) -> 138.59
J4: Variance Check | K4: =K2-K3 -> 0
A5: Marleen Gort
A6: Reference | B6: =CONCATENATE(Header!$E$4,"Gort") -> MC-251116Gort | J6: EMPLOYEES DO NOT CHANGE
A7: Document Date | B7: =Header!$E$5 -> 45977 | E7: Credit card holder to add details
A9: Date | B9: Narrative | C9: Debit Amount | D9: Credit Amount | E9: Description | F9: Project No | G9: Cost Category | H9: GL account | J9: Account | K9: Reference | L9: Tax | M9: Amount | N9: Tax CODE | O9: TAX Amount (leave blank) | P9: CBS - Only if required | R9: limit 56charaters
A10: 45968 | B10: Canva* 04693-7302731 Sydney AUS | C10: 41.6 | D10: 0 | E10: design software | F10: 1084 | G10: ITSW | J10: =IF(F10>0,(_xlfn.CONCAT(F10,".",G10)),H10) -> 1084.ITSW | K10: =_xlfn.CONCAT("M Gort-",E10,"-",B10) -> M Gort-design software-Canva* 04693-7302731 Sydney AUS | L10: I | M10: =IF(C10>0,C10,-D10) -> 41.6 | N10: T | Q10: CBS - needs to be pasted seperately | R10: =LEN(K10) -> 54
A11: 45956 | B11: Adobe Sydney AUS | C11: 96.99 | D11: 0 | E11: design software | F11: 1084 | G11: ITSW | J11: =IF(F11>0,(_xlfn.CONCAT(F11,".",G11)),H11) -> 1084.ITSW | K11: =_xlfn.CONCAT("M Gort-",E11,"-",B11) -> M Gort-design software-Adobe Sydney AUS | L11: I | M11: =IF(C11>0,C11,-D11) -> 96.99 | N11: T

Sheet N Grigg
A1: Employee to code & narrate | J1: To be copied in to pronto
J2: Credit card Statement TOTAL | K2: 4769.89
J3: Subtotal | K3: =SUM(M8:M143) -> 4769.89
J4: Variance Check | K4: =K2-K3 -> 0
A5: Nigel Grigg
A6: Reference | B6: =CONCATENATE(Header!$E$4,"Grigg") -> MC-251116Grigg | J6: EMPLOYEES DO NOT CHANGE
A7: Document Date | B7: =Header!$E$5 -> 45977 | E7: Credit card holder to add details
A9: Date | B9: Narrative | C9: Debit Amount | D9: Credit Amount | E9: Description | F9: Project No | G9: Cost Category | H9: GL account | J9: Account | K9: Reference | L9: Tax | M9: Amount | N9: Tax CODE | O9: TAX Amount (leave blank) | P9: CBS - Only if required | R9: limit 56charaters
A10: 45972 | B10: A N VENDING BALLARAT AUS | C10: 3.1 | D10: 0 | E10: food - cutting edge | F10: 1041 | G10: ENFE | J10: =IF(F10>0,(_xlfn.CONCAT(F10,".",G10)),H10) -> 1041.ENFE | K10: =_xlfn.CONCAT("N Grigg-",E10,"-",B10) -> N Grigg-food - cutting edge-A N VENDING BALLARAT AUS | L10: I | M10: =IF(C10>0,C10,-D10) -> 3.1 | N10: T | Q10: CBS - needs to be pasted seperately | R10: =LEN(K10) -> 53
A11: 45972 | B11: A N VENDING BALLARAT AUS | C11: 4.2 | D11: 0 | E11: food - cutting edge | F11: 1041 | G11: ENFE | J11: =IF(F11>0,(_xlfn.CONCAT(F11,".",G11)),H11) -> 1041.ENFE | K11: =_xlfn.CONCAT("N Grigg-",E11,"-",B11) -> N Grigg-food - cutting edge-A N VENDING BALLARAT AUS | L11: I | M11: =IF(C11>0,C11,-D11) -> 4.2 | N11: T | Q11: CBS - needs to be pasted seperately | R11: =LEN(K11) -> 53
A12: 45972 | B12: A N VENDING BALLARAT AUS | C12: 5.1 | D12: 0 | E12: food - cutting edge | F12: 1041 | G12: ENFE | J12: =IF(F12>0,(_xlfn.CONCAT(F12,".",G12)),H12) -> 1041.ENFE | K12: =_xlfn.CONCAT("N Grigg-",E12,"-",B12) -> N Grigg-food - cutting edge-A N VENDING BALLARAT AUS | L12: I | M12: =IF(C12>0,C12,-D12) -> 5.1 | N12: T | Q12: CBS - needs to be pasted seperately | R12: =LEN(K12) -> 53
A13: 45972 | B13: Hungry Jacks Melbourne ( AUS | C13: 14.75 | D13: 0 | E13: food - cutting edge | F13: 1041 | G13: ENFE | J13: =IF(F13>0,(_xlfn.CONCAT(F13,".",G13)),H13) -> 1041.ENFE | K13: =_xlfn.CONCAT("N Grigg-",E13,"-",B13) -> N Grigg-food - cutting edge-Hungry Jacks Melbourne ( AUS | L13: I | M13: =IF(C13>0,C13,-D13) -> 14.75 | N13: T | Q13: CBS - needs to be pasted seperately | R13: =LEN(K13) -> 57
A14: 45972 | B14: HI Melb Bourke SM ICP Melbourne AUS | C14: 14.99 | D14: 0 | E14: coffees -cutting edge | F14: 1041 | G14: ENFE | J14: =IF(F14>0,(_xlfn.CONCAT(F14,".",G14)),H14) -> 1041.ENFE | K14: =_xlfn.CONCAT("N Grigg-",E14,"-",B14) -> N Grigg-coffees -cutting edge-HI Melb Bourke SM ICP Melbourne AUS | L14: I | M14: =IF(C14>0,C14,-D14) -> 14.99 | N14: T | Q14: CBS - needs to be pasted seperately | R14: =LEN(K14) -> 65
A15: 45972 | B15: The Victoria Hotel ICP Melbourne AUS | C15: 20.3 | D15: 0 | E15: drinks -cutting edge - NG/BW | F15: 1041 | G15: ENFE | J15: =IF(F15>0,(_xlfn.CONCAT(F15,".",G15)),H15) -> 1041.ENFE | K15: =_xlfn.CONCAT("N Grigg-",E15,"-",B15) -> N Grigg-drinks -cutting edge - NG/BW-The Victoria Hotel ICP Melbourne AUS | L15: I | M15: =IF(C15>0,C15,-D15) -> 20.3 | N15: T | Q15: CBS - needs to be pasted seperately | R15: =LEN(K15) -> 73
A16: 45974 | B16: TICKETEK WEB Sydney AUS | C16: 268.5 | D16: 0 | E16: Ticket - AC | F16: 1041 | G16: ENFE | J16: =IF(F16>0,(_xlfn.CONCAT(F16,".",G16)),H16) -> 1041.ENFE | K16: =_xlfn.CONCAT("N Grigg-",E16,"-",B16) -> N Grigg-Ticket - AC-TICKETEK WEB Sydney AUS | L16: I | M16: =IF(C16>0,C16,-D16) -> 268.5 | N16: T | Q16: CBS - needs to be pasted seperately | R16: =LEN(K16) -> 43
A17: 45945 | B17: HO JIAK HAYMARKET | C17: 852.07 | D17: 0 | E17: Dinner | F17: G069 | G17: SALP | J17: =IF(F17>0,(_xlfn.CONCAT(F17,".",G17)),H17) -> G069.SALP | K17: =_xlfn.CONCAT("N Grigg-",E17,"-",B17) -> N Grigg-Dinner -HO JIAK HAYMARKET | L17: I | M17: =IF(C17>0,C17,-D17) -> 852.07 | N17: T | Q17: CBS - needs to be pasted seperately | R17: =LEN(K17) -> 34
A18: 45945 | B18: CROWN SYDNEY CIRQ BAR | C18: 71.22 | D18: 0 | E18: Drinks | F18: G069 | G18: SALP | J18: =IF(F18>0,(_xlfn.CONCAT(F18,".",G18)),H18) -> G069.SALP | K18: =_xlfn.CONCAT("N Grigg-",E18,"-",B18) -> N Grigg-Drinks-CROWN SYDNEY CIRQ BAR | L18: I | M18: =IF(C18>0,C18,-D18) -> 71.22 | N18: T | Q18: CBS - needs to be pasted seperately | R18: =LEN(K18) -> 36
A19: 45945 | B19: CROWN SYDNEY ICEBERGS | C19: 123.47 | D19: 0 | E19: Drinks/Lunch | F19: G069 | G19: SALP | J19: =IF(F19>0,(_xlfn.CONCAT(F19,".",G19)),H19) -> G069.SALP | K19: =_xlfn.CONCAT("N Grigg-",E19,"-",B19) -> N Grigg-Drinks/Lunch-CROWN SYDNEY ICEBERGS | L19: I | M19: =IF(C19>0,C19,-D19) -> 123.47 | N19: T | Q19: CBS - needs to be pasted seperately | R19: =LEN(K19) -> 42
A20: 45946 | B20: Crown Towers Sydney AUS | C20: 18.21 | D20: 0 | E20: drinks | F20: G069 | G20: SALP | J20: =IF(F20>0,(_xlfn.CONCAT(F20,".",G20)),H20) -> G069.SALP | K20: =_xlfn.CONCAT("N Grigg-",E20,"-",B20) -> N Grigg-drinks-Crown Towers Sydney AUS | L20: I | M20: =IF(C20>0,C20,-D20) -> 18.21 | N20: T | Q20: CBS - needs to be pasted seperately | R20: =LEN(K20) -> 38
A21: 45946 | B21: UBER *TRIP HELP.UBER.C 14518236738 AUS | C21: 23.8 | D21: 0 | E21: uber | F21: G069 | G21: SALP | J21: =IF(F21>0,(_xlfn.CONCAT(F21,".",G21)),H21) -> G069.SALP | K21: =_xlfn.CONCAT("N Grigg-",E21,"-",B21) -> N Grigg-uber-UBER *TRIP HELP.UBER.C 14518236738 AUS | L21: I | M21: =IF(C21>0,C21,-D21) -> 23.8 | N21: T | Q21: CBS - needs to be pasted seperately | R21: =LEN(K21) -> 51
A22: 45946 | B22: Crown Syd Icebergs Barangaroo AUS | C22: 72.32 | D22: 0 | E22: drinks/food | F22: G069 | G22: SALP | J22: =IF(F22>0,(_xlfn.CONCAT(F22,".",G22)),H22) -> G069.SALP | K22: =_xlfn.CONCAT("N Grigg-",E22,"-",B22) -> N Grigg-drinks/food-Crown Syd Icebergs Barangaroo AUS | L22: I | M22: =IF(C22>0,C22,-D22) -> 72.32 | N22: T | Q22: CBS - needs to be pasted seperately | R22: =LEN(K22) -> 53
A23: 45947 | B23: TRANSPORTFORNSW TAP SYDNEY AUS | C23: 22.25 | D23: 0 | E23: train airport | F23: G069 | G23: SALP | J23: =IF(F23>0,(_xlfn.CONCAT(F23,".",G23)),H23) -> G069.SALP | K23: =_xlfn.CONCAT("N Grigg-",E23,"-",B23) -> N Grigg-train airport-TRANSPORTFORNSW TAP SYDNEY AUS | L23: I | M23: =IF(C23>0,C23,-D23) -> 22.25 | N23: T | Q23: CBS - needs to be pasted seperately | R23: =LEN(K23) -> 52
A24: 45949 | B24: SGT*AppNibble Nicosia CYP FRGN AMT: 19.99 U. S. DOLLAR | C24: 31.97 | D24: 0 | E24: app cost | F24: 1084 | G24: ITSW | J24: =IF(F24>0,(_xlfn.CONCAT(F24,".",G24)),H24) -> 1084.ITSW | K24: =_xlfn.CONCAT("N Grigg-",E24,"-",B24) -> N Grigg-app cost-SGT*AppNibble Nicosia CYP FRGN AMT: 19.99 U. S. DOLLAR | L24: I | M24: =IF(C24>0,C24,-D24) -> 31.97 | N24: F | Q24: CBS - needs to be pasted seperately | R24: =LEN(K24) -> 72
A25: 45950 | B25: UBER *TRIP HELP.UBER.C 14518236738 AUS | C25: 16.36 | D25: 0 | E25: uber | F25: G069 | G25: SALP | J25: =IF(F25>0,(_xlfn.CONCAT(F25,".",G25)),H25) -> G069.SALP | K25: =_xlfn.CONCAT("N Grigg-",E25,"-",B25) -> N Grigg-uber -UBER *TRIP HELP.UBER.C 14518236738 AUS | L25: I | M25: =IF(C25>0,C25,-D25) -> 16.36 | N25: T | Q25: CBS - needs to be pasted seperately | R25: =LEN(K25) -> 52
A26: 45950 | B26: UBER *TRIP HELP.UBER.C 14518236738 AUS | C26: 28.31 | D26: 0 | E26: uber | F26: G069 | G26: SALP | J26: =IF(F26>0,(_xlfn.CONCAT(F26,".",G26)),H26) -> G069.SALP | K26: =_xlfn.CONCAT("N Grigg-",E26,"-",B26) -> N Grigg-uber-UBER *TRIP HELP.UBER.C 14518236738 AUS | L26: I | M26: =IF(C26>0,C26,-D26) -> 28.31 | N26: T | Q26: CBS - needs to be pasted seperately | R26: =LEN(K26) -> 51
A27: 45950 | B27: Hotel CBD Sydney AUS | C27: 65.89 | D27: 0 | E27: dinner AE/NG | F27: G081 | G27: SALP | J27: =IF(F27>0,(_xlfn.CONCAT(F27,".",G27)),H27) -> G081.SALP | K27: =_xlfn.CONCAT("N Grigg-",E27,"-",B27) -> N Grigg-dinner AE/NG-Hotel CBD Sydney AUS | L27: I | M27: =IF(C27>0,C27,-D27) -> 65.89 | N27: T | Q27: CBS - needs to be pasted seperately | R27: =LEN(K27) -> 41
A28: 45951 | B28: PLANAR RESTAURANT SYDNEY AUS | C28: 11.53 | D28: 0 | E28: drinks | F28: G081 | G28: SALP | J28: =IF(F28>0,(_xlfn.CONCAT(F28,".",G28)),H28) -> G081.SALP | K28: =_xlfn.CONCAT("N Grigg-",E28,"-",B28) -> N Grigg-drinks-PLANAR RESTAURANT SYDNEY AUS | L28: I | M28: =IF(C28>0,C28,-D28) -> 11.53 | N28: T | Q28: CBS - needs to be pasted seperately | R28: =LEN(K28) -> 43
A29: 45951 | B29: ICC Sydney Sydney AUS | C29: 16.8 | D29: 0 | E29: drinks | F29: G081 | G29: SALP | J29: =IF(F29>0,(_xlfn.CONCAT(F29,".",G29)),H29) -> G081.SALP | K29: =_xlfn.CONCAT("N Grigg-",E29,"-",B29) -> N Grigg-drinks-ICC Sydney Sydney AUS | L29: I | M29: =IF(C29>0,C29,-D29) -> 16.8 | N29: T | Q29: CBS - needs to be pasted seperately | R29: =LEN(K29) -> 36
A30: 45951 | B30: TRANSPORTFORNSW TAP SYDNEY AUS | C30: 22.25 | D30: 0 | E30: train | F30: G081 | G30: SALP | J30: =IF(F30>0,(_xlfn.CONCAT(F30,".",G30)),H30) -> G081.SALP | K30: =_xlfn.CONCAT("N Grigg-",E30,"-",B30) -> N Grigg-train -TRANSPORTFORNSW TAP SYDNEY AUS | L30: I | M30: =IF(C30>0,C30,-D30) -> 22.25 | N30: T | Q30: CBS - needs to be pasted seperately | R30: =LEN(K30) -> 45
A31: 45951 | B31: FratelliFreshDarling Sydney AUS | C31: 97.73 | D31: 0 | E31: dinner/drinks | F31: G081 | G31: SALP | J31: =IF(F31>0,(_xlfn.CONCAT(F31,".",G31)),H31) -> G081.SALP | K31: =_xlfn.CONCAT("N Grigg-",E31,"-",B31) -> N Grigg-dinner/drinks-FratelliFreshDarling Sydney AUS | L31: I | M31: =IF(C31>0,C31,-D31) -> 97.73 | N31: T | Q31: CBS - needs to be pasted seperately | R31: =LEN(K31) -> 53
A32: 45951 | B32: The Baxter Inn Sydney AUS | C32: 159.48 | D32: 0 | E32: dinner/drinks | F32: G081 | G32: SALP | J32: =IF(F32>0,(_xlfn.CONCAT(F32,".",G32)),H32) -> G081.SALP | K32: =_xlfn.CONCAT("N Grigg-",E32,"-",B32) -> N Grigg-dinner/drinks-The Baxter Inn Sydney AUS | L32: I | M32: =IF(C32>0,C32,-D32) -> 159.48 | N32: T | Q32: CBS - needs to be pasted seperately | R32: =LEN(K32) -> 47
A33: 45952 | B33: UBER *TRIP HELP.UBER.C 14518236738 AUS | C33: 20.35 | D33: 0 | E33: uber | F33: G081 | G33: SALP | J33: =IF(F33>0,(_xlfn.CONCAT(F33,".",G33)),H33) -> G081.SALP | K33: =_xlfn.CONCAT("N Grigg-",E33,"-",B33) -> N Grigg-uber-UBER *TRIP HELP.UBER.C 14518236738 AUS | L33: I | M33: =IF(C33>0,C33,-D33) -> 20.35 | N33: T | Q33: CBS - needs to be pasted seperately | R33: =LEN(K33) -> 51
A34: 45953 | B34: BENDIGO HOTEL FUND OP BENDIGO AUS | C34: 10.14 | D34: 0 | E34: drinks | F34: G119-05 | G34: SALP | J34: =IF(F34>0,(_xlfn.CONCAT(F34,".",G34)),H34) -> G119-05.SALP | K34: =_xlfn.CONCAT("N Grigg-",E34,"-",B34) -> N Grigg-drinks-BENDIGO HOTEL FUND OP BENDIGO AUS | L34: I | M34: =IF(C34>0,C34,-D34) -> 10.14 | N34: T | Q34: CBS - needs to be pasted seperately | R34: =LEN(K34) -> 48
A35: 45953 | B35: BENDIGO HOTEL FUND OP BENDIGO AUS | C35: 15.21 | D35: 0 | E35: drinks | F35: G119-05 | G35: SALP | J35: =IF(F35>0,(_xlfn.CONCAT(F35,".",G35)),H35) -> G119-05.SALP | K35: =_xlfn.CONCAT("N Grigg-",E35,"-",B35) -> N Grigg-drinks-BENDIGO HOTEL FUND OP BENDIGO AUS | L35: I | M35: =IF(C35>0,C35,-D35) -> 15.21 | N35: T | Q35: CBS - needs to be pasted seperately | R35: =LEN(K35) -> 48
A36: 45953 | B36: TRANSPORTFORNSW TAP SYDNEY AUS | C36: 20.95 | D36: 0 | E36: train to airport | F36: G081 | G36: SALP | J36: =IF(F36>0,(_xlfn.CONCAT(F36,".",G36)),H36) -> G081.SALP | K36: =_xlfn.CONCAT("N Grigg-",E36,"-",B36) -> N Grigg-train to airport-TRANSPORTFORNSW TAP SYDNEY AUS | L36: I | M36: =IF(C36>0,C36,-D36) -> 20.95 | N36: T | Q36: CBS - needs to be pasted seperately | R36: =LEN(K36) -> 55
... A45: 45954 | B45: Reddy Express 6821 Creswick AUS | C45: 151.98 | D45: 0 | E45: car/fuel | F45: G119-05 | G45: SALP | J45: =IF(F45>0,(_xlfn.CONCAT(F45,".",G45)),H45) -> G119-05.SALP | K45: =_xlfn.CONCAT("N Grigg-",E45,"-",B45) -> N Grigg-car/fuel-Reddy Express 6821 Creswick AUS | L45: I | M45: =IF(C45>0,C45,-D45) -> 151.98 | N45: T | Q45: CBS - needs to be pasted seperately | R45: =LEN(K45) -> 49
A46: 45955 | B46: IGA EXPRESS MURTOA MURTOA AUS | C46: 40.24 | D46: 0 | F46: 1084 | G46: pers | J46: =IF(F46>0,(_xlfn.CONCAT(F46,".",G46)),H46) -> 1084.pers | K46: =_xlfn.CONCAT("N Grigg-",E46,"-",B46) -> N Grigg--IGA EXPRESS MURTOA MURTOA AUS | L46: I | M46: =IF(C46>0,C46,-D46) -> 40.24 | N46: F | Q46: CBS - needs to be pasted seperately | R46: =LEN(K46) -> 38
A47: 45955 | B47: DROPBOX*KDDWM8XWDTJ4 D02FD79 IRL | C47: 190.2 | D47: 0 | E47: dropbox fees | F47: 1041 | G47: MEMB | J47: =IF(F47>0,(_xlfn.CONCAT(F47,".",G47)),H47) -> 1041.MEMB | K47: =_xlfn.CONCAT("N Grigg-",E47,"-",B47) -> N Grigg-dropbox fees-DROPBOX*KDDWM8XWDTJ4 D02FD79 IRL | L47: I | M47: =IF(C47>0,C47,-D47) -> 190.2 | N47: F | Q47: CBS - needs to be pasted seperately | R47: =LEN(K47) -> 53
A48: 45958 | B48: AusIMM 61396586100 AUS | C48: 572 | D48: 0 | E48: ausimm | F48: 1041 | G48: MEMB | J48: =IF(F48>0,(_xlfn.CONCAT(F48,".",G48)),H48) -> 1041.MEMB | K48: =_xlfn.CONCAT("N Grigg-",E48,"-",B48) -> N Grigg-ausimm-AusIMM 61396586100 AUS | L48: I | M48: =IF(C48>0,C48,-D48) -> 572 | N48: T | Q48: CBS - needs to be pasted seperately | R48: =LEN(K48) -> 37
A49: 45959 | B49: ALABC SYDNEY AUS | C49: 1100 | D49: 0 | E49: alabc | F49: 1041 | G49: MEMB | J49: =IF(F49>0,(_xlfn.CONCAT(F49,".",G49)),H49) -> 1041.MEMB | K49: =_xlfn.CONCAT("N Grigg-",E49,"-",B49) -> N Grigg-alabc-ALABC SYDNEY AUS | L49: I | M49: =IF(C49>0,C49,-D49) -> 1100 | N49: T | Q49: CBS - needs to be pasted seperately | R49: =LEN(K49) -> 30
A50: 45964 | B50: UBER *TRIP HELP.UBER.C 14518236738 AUS | C50: 15.63 | D50: 0 | E50: uber | F50: 1041 | G50: TRAV | J50: =IF(F50>0,(_xlfn.CONCAT(F50,".",G50)),H50) -> 1041.TRAV | K50: =_xlfn.CONCAT("N Grigg-",E50,"-",B50) -> N Grigg-uber-UBER *TRIP HELP.UBER.C 14518236738 AUS | L50: I | M50: =IF(C50>0,C50,-D50) -> 15.63 | N50: T | Q50: CBS - needs to be pasted seperately | R50: =LEN(K50) -> 51
A51: 45964 | B51: AUSIMM CARLTON AUS | C51: 20 | D51: 0 | E51: met fest | F51: G119-05 | G51: SALP | J51: =IF(F51>0,(_xlfn.CONCAT(F51,".",G51)),H51) -> G119-05.SALP | K51: =_xlfn.CONCAT("N Grigg-",E51,"-",B51) -> N Grigg-met fest -AUSIMM CARLTON AUS | L51: I | M51: =IF(C51>0,C51,-D51) -> 20 | N51: T | Q51: CBS - needs to be pasted seperately | R51: =LEN(K51) -> 36
A52: 45966 | B52: UBER *TRIP HELP.UBER.C 14518236738 AUS | C52: 12.2 | D52: 0 | E52: uber | F52: 1041 | G52: TRAV | J52: =IF(F52>0,(_xlfn.CONCAT(F52,".",G52)),H52) -> 1041.TRAV | K52: =_xlfn.CONCAT("N Grigg-",E52,"-",B52) -> N Grigg-uber -UBER *TRIP HELP.UBER.C 14518236738 AUS | L52: I | M52: =IF(C52>0,C52,-D52) -> 12.2 | N52: T | Q52: CBS - needs to be pasted seperately | R52: =LEN(K52) -> 52
A53: 45966 | B53: UBER *TRIP HELP.UBER.C 14518236738 AUS | C53: 17.84 | D53: 0 | E53: uber | F53: 1041 | G53: TRAV | J53: =IF(F53>0,(_xlfn.CONCAT(F53,".",G53)),H53) -> 1041.TRAV | K53: =_xlfn.CONCAT("N Grigg-",E53,"-",B53) -> N Grigg-uber-UBER *TRIP HELP.UBER.C 14518236738 AUS | L53: I | M53: =IF(C53>0,C53,-D53) -> 17.84 | N53: T | Q53: CBS - needs to be pasted seperately | R53: =LEN(K53) -> 51
A54: 45966 | B54: MYKI DISCCNTR SCS DSC MELBOURNE AUS | C54: 50 | D54: 0 | E54: train | F54: 1041 | G54: TRAV | J54: =IF(F54>0,(_xlfn.CONCAT(F54,".",G54)),H54) -> 1041.TRAV | K54: =_xlfn.CONCAT("N Grigg-",E54,"-",B54) -> N Grigg-train-MYKI DISCCNTR SCS DSC MELBOURNE AUS | L54: I | M54: =IF(C54>0,C54,-D54) -> 50 | N54: T | Q54: CBS - needs to be pasted seperately | R54: =LEN(K54) -> 49
A55: 45967 | B55: VIRGIN AU BRISBANE AUS | C55: 106.93 | D55: 0 | E55: change fee? | F55: 1041 | G55: TRAV | J55: =IF(F55>0,(_xlfn.CONCAT(F55,".",G55)),H55) -> 1041.TRAV | K55: =_xlfn.CONCAT("N Grigg-",E55,"-",B55) -> N Grigg-change fee?-VIRGIN AU BRISBANE AUS | L55: I | M55: =IF(C55>0,C55,-D55) -> 106.93 | N55: T | Q55: CBS - needs to be pasted seperately | R55: =LEN(K55) -> 42
A56: 45968 | B56: UBER *ONE Sydney AUS | C56: 9.99 | D56: 0 | E56: uber | F56: 1041 | G56: TRAV | J56: =IF(F56>0,(_xlfn.CONCAT(F56,".",G56)),H56) -> 1041.TRAV | K56: =_xlfn.CONCAT("N Grigg-",E56,"-",B56) -> N Grigg-uber-UBER *ONE Sydney AUS | L56: I | M56: =IF(C56>0,C56,-D56) -> 9.99 | N56: T | Q56: CBS - needs to be pasted seperately | R56: =LEN(K56) -> 35
A57: 45968 | B57: UBER *TRIP HELP.UBER.C 14518236738 AUS | C57: 15.07 | D57: 0 | E57: uber | F57: 1041 | G57: TRAV | J57: =IF(F57>0,(_xlfn.CONCAT(F57,".",G57)),H57) -> 1041.TRAV | K57: =_xlfn.CONCAT("N Grigg-",E57,"-",B57) -> N Grigg-uber-UBER *TRIP HELP.UBER.C 14518236738 AUS | L57: I | M57: =IF(C57>0,C57,-D57) -> 15.07 | N57: T | Q57: CBS - needs to be pasted seperately | R57: =LEN(K57) -> 51
A58: 45968 | B58: UBER *TRIP HELP.UBER.C 14518236738 AUS | C58: 18.89 | D58: 0 | E58: uber | F58: 1041 | G58: TRAV | J58: =IF(F58>0,(_xlfn.CONCAT(F58,".",G58)),H58) -> 1041.TRAV | K58: =_xlfn.CONCAT("N Grigg-",E58,"-",B58) -> N Grigg-uber-UBER *TRIP HELP.UBER.C 14518236738 AUS | L58: I | M58: =IF(C58>0,C58,-D58) -> 18.89 | N58: T | Q58: CBS - needs to be pasted seperately | R58: =LEN(K58) -> 51

Sheet T Hughes
A1: Employee to code & narrate | J1: To be copied in to pronto
J2: Credit card Statement TOTAL | K2: 261.91
J3: Subtotal | K3: =SUM(M8:M143) -> 261.91
J4: Variance Check | K4: =K2-K3 -> 0
A5: Tim Hughes
A6: Reference | B6: =CONCATENATE(Header!$E$4,"Hughes") -> MC-251116Hughes | J6: EMPLOYEES DO NOT CHANGE
A7: Document Date | B7: =Header!$E$5 -> 45977 | E7: Credit card holder to add details
A9: Date | B9: Narrative | C9: Debit Amount | D9: Credit Amount | E9: Description | F9: Project No | G9: Cost Category | H9: GL account | J9: Account | K9: Reference | L9: Tax | M9: Amount | N9: Tax CODE | O9: TAX Amount (leave blank) | P9: CBS - Only if required | R9: limit 56charaters
A10: 23/10/2025 | B10: BENDIGO HOTEL FUND OP BENDIGO AUS | C10: 7.7 | D10: 0 | E10: Coffee | F10: G119-05 | G10: SALP | J10: =IF(F10>0,(_xlfn.CONCAT(F10,".",G10)),H10) -> G119-05.SALP | K10: =_xlfn.CONCAT("T Hughes-",E10,"-",B10) -> T Hughes-Coffee-BENDIGO HOTEL FUND OP BENDIGO AUS | L10: I | M10: =IF(C10>0,C10,-D10) -> 7.7 | N10: T | Q10: CBS - needs to be pasted seperately | R10: =LEN(K10) -> 49
A11: 24/10/2025 | B11: EG GROUP 3873 LUCAS AUS | C11: 34.21 | D11: 0 | E11: Petrol to/from Bendigo | F11: G119-05 | G11: SALP | J11: =IF(F11>0,(_xlfn.CONCAT(F11,".",G11)),H11) -> G119-05.SALP | K11: =_xlfn.CONCAT("T Hughes-",E11,"-",B11) -> T Hughes-Petrol to/from Bendigo-EG GROUP 3873 LUCAS AUS | L11: I | M11: =IF(C11>0,C11,-D11) -> 34.21 | N11: T | Q11: CBS - needs to be pasted seperately | R11: =LEN(K11) -> 62
A12: 23/10/2025 | B12: GOLDEN REEF MOTOR INN STRATHDALE AUS | C12: 220 | D12: 0 | E12: Accom in Bendigo | F12: G119-05 | G12: SALP | J12: =IF(F12>0,(_xlfn.CONCAT(F12,".",G12)),H12) -> G119-05.SALP | K12: =_xlfn.CONCAT("T Hughes-",E12,"-",B12) -> T Hughes-Accom in Bendigo-GOLDEN REEF MOTOR INN STRATHDALE AUS | L12: I | M12: =IF(C12>0,C12,-D12) -> 220 | N12: T | Q12: CBS - needs to be pasted seperately | R12: =LEN(K12) -> 62

Sheet S Jenkins
A1: Employee to code & narrate | J1: To be copied in to pronto
J2: Credit card Statement TOTAL | K2: 445.07
J3: Subtotal | K3: =SUM(M8:M144) -> 445.07
J4: Variance Check | K4: =K2-K3 -> 0
A5: Shayne Jenkins
A6: Reference | B6: =CONCATENATE(Header!$E$4,"Jenkins") -> MC-251116Jenkins | J6: EMPLOYEES DO NOT CHANGE
A7: Document Date | B7: =Header!$E$5 -> 45977 | E7: Credit card holder to add details
A9: Date | B9: Narrative | C9: Debit Amount | D9: Credit Amount | E9: Description | F9: Project No | G9: Cost Category | H9: GL account | J9: Account | K9: Reference | L9: Tax | M9: Amount | N9: Tax CODE | O9: TAX Amount (leave blank) | P9: CBS - Only if required | R9: limit 56charaters
A10: 45969 | B10: UBER* TRIP SYDNEY AUS | C10: 25.54 | D10: 0 | E10: Personal charge | F10: 1084 | G10: PERS | J10: =IF(F10>0,(_xlfn.CONCAT(F10,".",G10)),H10) -> 1084.PERS | K10: =_xlfn.CONCAT("S Jenkins-",E10,"-",B10) -> S Jenkins-Personal charge-UBER* TRIP SYDNEY AUS | L10: I | M10: =IF(C10>0,C10,-D10) -> 25.54 | N10: F | Q10: CBS - needs to be pasted seperately | R10: =LEN(K10) -> 47
A11: 45974 | B11: TOTAL TOOLS BALLARAT BALLARAT AUS | C11: 78.25 | D11: 0 | E11: Tools for service kit | F11: 1054 | G11: TOOL | J11: =IF(F11>0,(_xlfn.CONCAT(F11,".",G11)),H11) -> 1054.TOOL | K11: =_xlfn.CONCAT("S Jenkins-",E11,"-",B11) -> S Jenkins-Tools for service kit-TOTAL TOOLS BALLARAT BALLARAT AUS | L11: I | M11: =IF(C11>0,C11,-D11) -> 78.25 | N11: T | Q11: CBS - needs to be pasted seperately | R11: =LEN(K11) -> 65
A12: 45952 | B12: Ballarat Plumbing Cen ALFREDTON AUS | C12: 100 | D12: 0 | E12: Denzo tape | F12: 1054 | G12: CONS | J12: =IF(F12>0,(_xlfn.CONCAT(F12,".",G12)),H12) -> 1054.CONS | K12: =_xlfn.CONCAT("S Jenkins-",E12,"-",B12) -> S Jenkins-Denzo tape-Ballarat Plumbing Cen ALFREDTON AUS | L12: I | M12: =IF(C12>0,C12,-D12) -> 100 | N12: T | Q12: CBS - needs to be pasted seperately | R12: =LEN(K12) -> 56
A13: 45948 | B13: APCO ALFREDTON ALFREDTON AUS | C13: 104.31 | D13: 0 | E13: Fuel | F13: 1054 | G13: MVPF | J13: =IF(F13>0,(_xlfn.CONCAT(F13,".",G13)),H13) -> 1054.MVPF | K13: =_xlfn.CONCAT("S Jenkins-",E13,"-",B13) -> S Jenkins-Fuel-APCO ALFREDTON ALFREDTON AUS | L13: I | M13: =IF(C13>0,C13,-D13) -> 104.31 | N13: T | Q13: CBS - needs to be pasted seperately | R13: =LEN(K13) -> 43
A14: 45956 | B14: APCO ALFREDTON ALFREDTON AUS | C14: 136.97 | D14: 0 | E14: Fuel | F14: 1054 | G14: MVPF | J14: =IF(F14>0,(_xlfn.CONCAT(F14,".",G14)),H14) -> 1054.MVPF | K14: =_xlfn.CONCAT("S Jenkins-",E14,"-",B14) -> S Jenkins-Fuel-APCO ALFREDTON ALFREDTON AUS | L14: I | M14: =IF(C14>0,C14,-D14) -> 136.97 | N14: T | Q14: CBS - needs to be pasted seperately | R14: =LEN(K14) -> 43
A15: 45950 | B15: Hotel at Booking.com Sydney AUS | C15: 369 | D15: 0 | E15: Accomodation | F15: CS004-D | J15: =IF(F15>0,(_xlfn.CONCAT(F15,".",G15)),H15) -> CS004-D. | K15: =_xlfn.CONCAT("S Jenkins-",E15,"-",B15) -> S Jenkins-Accomodation-Hotel at Booking.com Sydney AUS | L15: I | M15: =IF(C15>0,C15,-D15) -> 369 | N15: T | P15: 1.6 | Q15: CBS - needs to be pasted seperately | R15: =LEN(K15) -> 54
A16: 45975 | B16: CRED VOUCHER Hotel at Booking.com Sydney AUS | C16: 0 | D16: 369 | E16: Cancelled Accomodation | F16: CS004-D | J16: =IF(F16>0,(_xlfn.CONCAT(F16,".",G16)),H16) -> CS004-D. | K16: =_xlfn.CONCAT("S Jenkins-",E16,"-",B16) -> S Jenkins-Cancelled Accomodation-CRED VOUCHER Hotel at Booking.com Sydney AUS | L16: I | M16: =IF(C16>0,C16,-D16) -> -369 | N16: T | P16: 1.6 | Q16: CBS - needs to be pasted seperately | R16: =LEN(K16) -> 77

Sheet A Lanyon
A1: Employee to code & narrate | J1: To be copied in to pronto
J2: Credit card Statement TOTAL | K2: 89.76
J3: Subtotal | K3: =SUM(M8:M143) -> 0
J4: Variance Check | K4: =K2-K3 -> 89.76
A5: Austell Lanyon
A6: Reference | B6: =CONCATENATE(Header!$E$4,"Lanyon") -> MC-251116Lanyon | J6: EMPLOYEES DO NOT CHANGE
A7: Document Date | B7: =Header!$E$5 -> 45977 | E7: Credit card holder to add details
A9: Date | B9: Narrative | C9: Debit Amount | D9: Credit Amount | E9: Description | F9: Project No | G9: Cost Category | H9: GL account | J9: Account | K9: Reference | L9: Tax | M9: Amount | N9: Tax CODE | O9: TAX Amount (leave blank) | P9: CBS - Only if required | R9: limit 56charaters
J10: =IF(F10>0,(_xlfn.CONCAT(F10,".",G10)),H10) -> 0 | K10: =_xlfn.CONCAT("A Lanyon-",B10,"-",E10) -> A Lanyon-- | L10: I | M10: =IF(C10>0,C10,-D10) -> 0 | N10: T | Q10: CBS - needs to be pasted seperately | R10: =LEN(K10) -> 10

Sheet Z Lee
A1: Employee to code & narrate | J1: To be copied in to pronto
J2: Credit card Statement TOTAL | K2: =278.1+25 -> 303.1
J3: Subtotal | K3: =SUM(M8:M143) -> 0
J4: Variance Check | K4: =K2-K3 -> 303.1
A5: Zach Lee
A6: Reference | B6: =CONCATENATE(Header!$E$4,"Lee") -> MC-251116Lee | J6: EMPLOYEES DO NOT CHANGE
A7: Document Date | B7: =Header!$E$5 -> 45977 | E7: Credit card holder to add details
A9: Date | B9: Narrative | C9: Debit Amount | D9: Credit Amount | E9: Description | F9: Project No | G9: Cost Category | H9: GL account | J9: Account | K9: Reference | L9: Tax | M9: Amount | N9: Tax CODE | O9: TAX Amount (leave blank) | P9: CBS - Only if required | R9: limit 56charaters
J10: =IF(F10>0,(_xlfn.CONCAT(F10,".",G10)),H10) -> 0 | K10: =_xlfn.CONCAT("A Lee-",B10,"-",E10) -> A Lee-- | L10: I | M10: =IF(C10>0,C10,-D10) -> 0 | N10: F | Q10: CBS - needs to be pasted seperately | R10: =LEN(K10) -> 7

Sheet E Lewis-Gray
A1: Employee to code & narrate | J1: To be copied in to pronto
J2: Credit card Statement TOTAL | K2: 2925.14
J3: Subtotal | K3: =SUM(M8:M143) -> 2925.14
J4: Variance Check | K4: =K2-K3 -> 0
A5: Elizabeth Lewis-Gray
A6: Reference | B6: =CONCATENATE(Header!$E$4,"ELG") -> MC-251116ELG | J6: EMPLOYEES DO NOT CHANGE
A7: Document Date | B7: =Header!$E$5 -> 45977 | E7: Credit card holder to add details
A9: Date | B9: Narrative | C9: Debit Amount | D9: Credit Amount | E9: Description | F9: Project No | G9: Cost Category | H9: GL account | J9: Account | K9: Reference | L9: Tax | M9: Amount | N9: Tax CODE | O9: TAX Amount (leave blank) | P9: CBS - Only if required | R9: limit 56charaters
A10: 45955 | B10: QANTAS0812378083449 NSW AUS | C10: 1462.57 | D10: 0 | E10: Flights for Sandy/Lewie to travel to Perth to meet with customers. | F10: 1084 | G10: TRAV | J10: =IF(F10>0,(_xlfn.CONCAT(F10,".",G10)),H10) -> 1084.TRAV | K10: =_xlfn.CONCAT("ELewisGray-",E10,"-",B10) -> ELewisGray-Flights for Sandy/Lewie to travel to Perth to meet with customers.-QANTAS0812378083449 NSW AUS | L10: I | M10: =IF(C10>0,C10,-D10) -> 1462.57 | N10: T | Q10: CBS - needs to be pasted seperately | R10: =LEN(K10) -> 105
A11: 45955 | B11: QANTAS0812378083448 NSW AUS | C11: 1462.57 | D11: 0 | E11: Flights for Sandy/Lewie to travel to Perth to meet with customers. | F11: 1084 | G11: TRAV | J11: =IF(F11>0,(_xlfn.CONCAT(F11,".",G11)),H11) -> 1084.TRAV | K11: =_xlfn.CONCAT("ELewisGray-",E11,"-",B11) -> ELewisGray-Flights for Sandy/Lewie to travel to Perth to meet with customers.-QANTAS0812378083448 NSW AUS | L11: I | M11: =IF(C11>0,C11,-D11) -> 1462.57 | N11: T

Sheet S Lewis-Gray
A1: Employee to code & narrate | J1: To be copied in to pronto
J2: Credit card Statement TOTAL | K2: 2045.16
J3: Subtotal | K3: =SUM(M8:M143) -> 2045.16
J4: Variance Check | K4: =K2-K3 -> 0
A5: Sandy Gray
A6: Reference | B6: =CONCATENATE(Header!$E$4,"ALG") -> MC-251116ALG | J6: EMPLOYEES DO NOT CHANGE
A7: Document Date | B7: =Header!$E$5 -> 45977 | E7: Credit card holder to add details
A9: Date | B9: Narrative | C9: Debit Amount | D9: Credit Amount | E9: Description | F9: Project No | G9: Cost Category | H9: GL account | J9: Account | K9: Reference | L9: Tax | M9: Amount | N9: Tax CODE | O9: TAX Amount (leave blank) | P9: CBS - Only if required | R9: limit 56charaters
A10: 45950 | B10: SPOLETO PATIO SAVASSI BELO HORIZO BRA FRGN AMT: 77.00 BRAZILIAN REAL | C10: 22.74 | D10: 0 | E10: Intulo | F10: G185 | G10: MISC | J10: =IF(F10>0,(_xlfn.CONCAT(F10,".",G10)),H10) -> G185.MISC | K10: =_xlfn.CONCAT("S Gray-",E10,"-",B10) -> S Gray-Intulo-SPOLETO PATIO SAVASSI BELO HORIZO BRA FRGN AMT: 77.00 BRAZILIAN REAL | L10: I | M10: =IF(C10>0,C10,-D10) -> 22.74 | N10: F | Q10: CBS - needs to be pasted seperately | R10: =LEN(K10) -> 83
A11: 45953 | B11: RADISSON BLU BELO HORI BELO HORIZO BRA FRGN AMT: 117.90 BRAZILIAN REAL | C11: 34.9 | D11: 0 | E11: Intulo | F11: G185 | G11: MISC | J11: =IF(F11>0,(_xlfn.CONCAT(F11,".",G11)),H11) -> G185.MISC | K11: =_xlfn.CONCAT("S Gray-",E11,"-",B11) -> S Gray-Intulo-RADISSON BLU BELO HORI BELO HORIZO BRA FRGN AMT: 117.90 BRAZILIAN REAL | L11: I | M11: =IF(C11>0,C11,-D11) -> 34.9 | N11: F | Q11: CBS - needs to be pasted seperately | R11: =LEN(K11) -> 85
A12: 45953 | B12: ESTHER DE FIGUEIREDO Belo Horizo BRA FRGN AMT: 185.86 BRAZILIAN REAL | C12: 55.02 | D12: 0 | E12: Intulo | F12: G185 | G12: MISC | J12: =IF(F12>0,(_xlfn.CONCAT(F12,".",G12)),H12) -> G185.MISC | K12: =_xlfn.CONCAT("S Gray-",E12,"-",B12) -> S Gray-Intulo-ESTHER DE FIGUEIREDO Belo Horizo BRA FRGN AMT: 185.86 BRAZILIAN REAL | L12: I | M12: =IF(C12>0,C12,-D12) -> 55.02 | N12: F | Q12: CBS - needs to be pasted seperately | R12: =LEN(K12) -> 83
A13: 45949 | B13: ESTHER DE FIGUEIREDO Belo Horizo BRA FRGN AMT: 227.16 BRAZILIAN REAL | C13: 67.1 | D13: 0 | E13: Intulo | F13: G185 | G13: MISC | J13: =IF(F13>0,(_xlfn.CONCAT(F13,".",G13)),H13) -> G185.MISC | K13: =_xlfn.CONCAT("S Gray-",E13,"-",B13) -> S Gray-Intulo-ESTHER DE FIGUEIREDO Belo Horizo BRA FRGN AMT: 227.16 BRAZILIAN REAL | L13: I | M13: =IF(C13>0,C13,-D13) -> 67.1 | N13: F | Q13: CBS - needs to be pasted seperately | R13: =LEN(K13) -> 83
A14: 45974 | B14: Post Perth AUS | C14: 184.69 | D14: 0 | E14: Post Perth | F14: 1084 | G14: POST | J14: =IF(F14>0,(_xlfn.CONCAT(F14,".",G14)),H14) -> 1084.POST | K14: =_xlfn.CONCAT("S Gray-",E14,"-",B14) -> S Gray-Post Perth-Post Perth AUS | L14: I | M14: =IF(C14>0,C14,-D14) -> 184.69 | N14: T | Q14: CBS - needs to be pasted seperately | R14: =LEN(K14) -> 32
A15: 45951 | B15: T9WEB SISTEMAS E INFOR BELO HORIZO BRA FRGN AMT: 5665.93 BRAZILIAN REAL | C15: 1680.71 | D15: 0 | E15: Intulo | F15: G185 | G15: MISC | J15: =IF(F15>0,(_xlfn.CONCAT(F15,".",G15)),H15) -> G185.MISC | K15: =_xlfn.CONCAT("S Gray-",E15,"-",B15) -> S Gray-Intulo-T9WEB SISTEMAS E INFOR BELO HORIZO BRA FRGN AMT: 5665.93 BRAZILIAN REAL | L15: I | M15: =IF(C15>0,C15,-D15) -> 1680.71 | N15: F | Q15: CBS - needs to be pasted seperately | R15: =LEN(K15) -> 86

Sheet H Lodge
A1: Employee to code & narrate | J1: To be copied in to pronto
J2: Credit card Statement TOTAL | K2: 1076.26
J3: Subtotal | K3: =SUM(M8:M143) -> 1076.26
J4: Variance Check | K4: =K2-K3 -> 0
A5: Harry Lodge
A6: Reference | B6: =CONCATENATE(Header!$E$4,"HLodge") -> MC-251116HLodge | J6: EMPLOYEES DO NOT CHANGE
A7: Document Date | B7: =Header!$E$5 -> 45977 | E7: Credit card holder to add details
A9: Date | B9: Narrative | C9: Debit Amount | D9: Credit Amount | E9: Description | F9: Project No | G9: Cost Category | H9: GL account | J9: Account | K9: Reference | L9: Tax | M9: Amount | N9: Tax CODE | O9: TAX Amount (leave blank) | P9: CBS - Only if required | R9: limit 56charaters
A10: 24/10/2025 | B10: ANACONDA LAKE GARDEN AUS | C10: 33.98 | D10: 0 | E10: Mosquito repelent | F10: 16138 | G10: TRVP | J10: =IF(F10>0,(_xlfn.CONCAT(F10,".",G10)),H10) -> 16138.TRVP | K10: =_xlfn.CONCAT("H Lodge-",E10,"-",B10) -> H Lodge-Mosquito repelent-ANACONDA LAKE GARDEN AUS | L10: I | M10: =IF(C10>0,C10,-D10) -> 33.98 | N10: T | Q10: CBS - needs to be pasted seperately | R10: =LEN(K10) -> 50
A11: 5/11/2025 | B11: AIRALO SINGAPORE SGP | C11: 38.13 | D11: 0 | E11: E-sim Guinea Orange network | F11: 16138 | G11: TRVP | J11: =IF(F11>0,(_xlfn.CONCAT(F11,".",G11)),H11) -> 16138.TRVP | K11: =_xlfn.CONCAT("H Lodge-",E11,"-",B11) -> H Lodge-E-sim Guinea Orange network-AIRALO SINGAPORE SGP | L11: I | M11: =IF(C11>0,C11,-D11) -> 38.13 | N11: F | Q11: CBS - needs to be pasted seperately | R11: =LEN(K11) -> 56
A12: 27/10/2025 | B12: AIRALO SINGAPORE SGP | C12: 40.68 | D12: 0 | E12: E-sim Guinea Orange network | F12: 16138 | G12: TRVP | J12: =IF(F12>0,(_xlfn.CONCAT(F12,".",G12)),H12) -> 16138.TRVP | K12: =_xlfn.CONCAT("H Lodge-",E12,"-",B12) -> H Lodge-E-sim Guinea Orange network-AIRALO SINGAPORE SGP | L12: I | M12: =IF(C12>0,C12,-D12) -> 40.68 | N12: F | Q12: CBS - needs to be pasted seperately | R12: =LEN(K12) -> 56
A13: 24/10/2025 | B13: SydneyToolsDelacombe Delacombe AUS | C13: 54.95 | D13: 0 | E13: Hydration powder packets | F13: 16138 | G13: TRVP | J13: =IF(F13>0,(_xlfn.CONCAT(F13,".",G13)),H13) -> 16138.TRVP | K13: =_xlfn.CONCAT("H Lodge-",E13,"-",B13) -> H Lodge-Hydration powder packets-SydneyToolsDelacombe Delacombe AUS | L13: I | M13: =IF(C13>0,C13,-D13) -> 54.95 | N13: T | Q13: CBS - needs to be pasted seperately | R13: =LEN(K13) -> 67
A14: 27/10/2025 | B14: Airport Shuttle Bus BAKERY HILL AUS | C14: 90 | D14: 0 | E14: Airport shuttle to and from melbourne airport | F14: 16138 | G14: TRVP | J14: =IF(F14>0,(_xlfn.CONCAT(F14,".",G14)),H14) -> 16138.TRVP | K14: =_xlfn.CONCAT("H Lodge-",E14,"-",B14) -> H Lodge-Airport shuttle to and from melbourne airport-Airport Shuttle Bus BAKERY HILL AUS | L14: I | M14: =IF(C14>0,C14,-D14) -> 90 | N14: T | Q14: CBS - needs to be pasted seperately | R14: =LEN(K14) -> 89
A15: 24/10/2025 | B15: UFS HEALTHCARE LTD DELACOMBE AUS | C15: 157.5 | D15: 0 | E15: Anti-malaria tablets 1 box (24 tabs) | F15: 16138 | G15: TRVP | J15: =IF(F15>0,(_xlfn.CONCAT(F15,".",G15)),H15) -> 16138.TRVP | K15: =_xlfn.CONCAT("H Lodge-",E15,"-",B15) -> H Lodge-Anti-malaria tablets 1 box (24 tabs)-UFS HEALTHCARE LTD DELACOMBE AUS | L15: I | M15: =IF(C15>0,C15,-D15) -> 157.5 | N15: F | Q15: CBS - needs to be pasted seperately | R15: =LEN(K15) -> 77
A16: 21/10/2025 | B16: ONESIMCARD.COM BELMONT USA FRGN AMT: 103.90 U. S. DOLLAR | C16: 165.15 | D16: 0 | E16: One sim, international sim cards data | F16: CS005-G | G16: TRVP | J16: =IF(F16>0,(_xlfn.CONCAT(F16,".",G16)),H16) -> CS005-G.TRVP | K16: =_xlfn.CONCAT("H Lodge-",E16,"-",B16) -> H Lodge-One sim, international sim cards data-ONESIMCARD.COM BELMONT USA FRGN AMT: 103.90 U. S. DOLLAR | L16: I | M16: =IF(C16>0,C16,-D16) -> 165.15 | N16: F | Q16: CBS - needs to be pasted seperately | R16: =LEN(K16) -> 103
A17: 10/11/2025 | B17: ONESIMCARD.COM BELMONT USA FRGN AMT: 103.90 U. S. DOLLAR | C17: 165.58 | D17: 0 | E17: One sim, international sim cards data | F17: S14735 | G17: TRVP | J17: =IF(F17>0,(_xlfn.CONCAT(F17,".",G17)),H17) -> S14735.TRVP | K17: =_xlfn.CONCAT("H Lodge-",E17,"-",B17) -> H Lodge-One sim, international sim cards data-ONESIMCARD.COM BELMONT USA FRGN AMT: 103.90 U. S. DOLLAR | L17: I | M17: =IF(C17>0,C17,-D17) -> 165.58 | N17: F | Q17: CBS - needs to be pasted seperately | R17: =LEN(K17) -> 103
A18: 21/10/2025 | B18: ONESIMCARD.COM BELMONT USA FRGN AMT: 207.80 U. S. DOLLAR | C18: 330.29 | D18: 0 | E18: One sim, international sim cards data | F18: CS007-D | G18: TRVP | J18: =IF(F18>0,(_xlfn.CONCAT(F18,".",G18)),H18) -> CS007-D.TRVP | K18: =_xlfn.CONCAT("H Lodge-",E18,"-",B18) -> H Lodge-One sim, international sim cards data-ONESIMCARD.COM BELMONT USA FRGN AMT: 207.80 U. S. DOLLAR | L18: I | M18: =IF(C18>0,C18,-D18) -> 330.29 | N18: F | Q18: CBS - needs to be pasted seperately | R18: =LEN(K18) -> 103

Sheet W Lodge
A1: Employee to code & narrate | J1: To be copied in to pronto
J2: Credit card Statement TOTAL | K2: 2156.94
J3: Subtotal | K3: =SUM(M8:M143) -> 2156.94
J4: Variance Check | K4: =K2-K3 -> 0
A5: Wayne Lodge
A6: Reference | B6: =CONCATENATE(Header!$E$4,"Lodge") -> MC-251116Lodge | J6: EMPLOYEES DO NOT CHANGE
A7: Document Date | B7: =Header!$E$5 -> 45977 | E7: Credit card holder to add details
A9: Date | B9: Narrative | C9: Debit Amount | D9: Credit Amount | E9: Description | F9: Project No | G9: Cost Category | H9: GL account | J9: Account | K9: Reference | L9: Tax | M9: Amount | N9: Tax CODE | O9: TAX Amount (leave blank) | P9: CBS - Only if required | R9: limit 56charaters
A10: 45955 | B10: WD QUICK SHOP SALVADOR BRA FRGN AMT: 7.00 BRAZILIAN REAL | C10: 2.07 | D10: 0 | E10: Food/drink | F10: G185 | G10: MISC | J10: =IF(F10>0,(_xlfn.CONCAT(F10,".",G10)),H10) -> G185.MISC | K10: =_xlfn.CONCAT("W Lodge-",E10,"-",B10) -> W Lodge-Food/drink-WD QUICK SHOP SALVADOR BRA FRGN AMT: 7.00 BRAZILIAN REAL | L10: I | M10: =IF(C10>0,C10,-D10) -> 2.07 | N10: F | Q10: CBS - needs to be pasted seperately | R10: =LEN(K10) -> 76
A11: 45953 | B11: OLEGARIO BELO HORIZO BRA FRGN AMT: 9.00 BRAZILIAN REAL | C11: 2.66 | D11: 0 | E11: Food/drink | F11: G185 | G11: MISC | J11: =IF(F11>0,(_xlfn.CONCAT(F11,".",G11)),H11) -> G185.MISC | K11: =_xlfn.CONCAT("W Lodge-",E11,"-",B11) -> W Lodge-Food/drink-OLEGARIO BELO HORIZO BRA FRGN AMT: 9.00 BRAZILIAN REAL | L11: I | M11: =IF(C11>0,C11,-D11) -> 2.66 | N11: F | Q11: CBS - needs to be pasted seperately | R11: =LEN(K11) -> 74
A12: 45948 | B12: CCEP NORTH SYDNE AUS | C12: 4.3 | D12: 0 | E12: Food/drink | F12: G185 | G12: MISC | J12: =IF(F12>0,(_xlfn.CONCAT(F12,".",G12)),H12) -> G185.MISC | K12: =_xlfn.CONCAT("W Lodge-",E12,"-",B12) -> W Lodge-Food/drink-CCEP NORTH SYDNE AUS | L12: I | M12: =IF(C12>0,C12,-D12) -> 4.3 | N12: T | Q12: CBS - needs to be pasted seperately | R12: =LEN(K12) -> 39
A13: 45955 | B13: CNF AEROPORTO DE COFIN CONFINS BRA FRGN AMT: 14.90 BRAZILIAN REAL | C13: 4.41 | D13: 0 | E13: Food/drink | F13: G185 | G13: MISC | J13: =IF(F13>0,(_xlfn.CONCAT(F13,".",G13)),H13) -> G185.MISC | K13: =_xlfn.CONCAT("W Lodge-",E13,"-",B13) -> W Lodge-Food/drink-CNF AEROPORTO DE COFIN CONFINS BRA FRGN AMT: 14.90 BRAZILIAN REAL | L13: I | M13: =IF(C13>0,C13,-D13) -> 4.41 | N13: F | Q13: CBS - needs to be pasted seperately | R13: =LEN(K13) -> 85
A14: 45948 | B14: CCEP NORTH SYDNE AUS | C14: 5 | D14: 0 | E14: Food/drink | F14: G185 | G14: MISC | J14: =IF(F14>0,(_xlfn.CONCAT(F14,".",G14)),H14) -> G185.MISC | K14: =_xlfn.CONCAT("W Lodge-",E14,"-",B14) -> W Lodge-Food/drink-CCEP NORTH SYDNE AUS | L14: I | M14: =IF(C14>0,C14,-D14) -> 5 | N14: T | Q14: CBS - needs to be pasted seperately | R14: =LEN(K14) -> 39
A15: 45948 | B15: CCEP NORTH SYDNE AUS | C15: 5.2 | D15: 0 | E15: Food/drink | F15: G185 | G15: MISC | J15: =IF(F15>0,(_xlfn.CONCAT(F15,".",G15)),H15) -> G185.MISC | K15: =_xlfn.CONCAT("W Lodge-",E15,"-",B15) -> W Lodge-Food/drink-CCEP NORTH SYDNE AUS | L15: I | M15: =IF(C15>0,C15,-D15) -> 5.2 | N15: T | Q15: CBS - needs to be pasted seperately | R15: =LEN(K15) -> 39
A16: 45948 | B16: CCEP NORTH SYDNE AUS | C16: 5.9 | D16: 0 | E16: Food/drink | F16: G185 | G16: MISC | J16: =IF(F16>0,(_xlfn.CONCAT(F16,".",G16)),H16) -> G185.MISC | K16: =_xlfn.CONCAT("W Lodge-",E16,"-",B16) -> W Lodge-Food/drink-CCEP NORTH SYDNE AUS | L16: I | M16: =IF(C16>0,C16,-D16) -> 5.9 | N16: T | Q16: CBS - needs to be pasted seperately | R16: =LEN(K16) -> 39
A17: 45955 | B17: JUICE*VCP*POA*TERRA CONFINS BRA FRGN AMT: 38.00 BRAZILIAN REAL | C17: 11.24 | D17: 0 | E17: Food/drink | F17: G185 | G17: MISC | J17: =IF(F17>0,(_xlfn.CONCAT(F17,".",G17)),H17) -> G185.MISC | K17: =_xlfn.CONCAT("W Lodge-",E17,"-",B17) -> W Lodge-Food/drink-JUICE*VCP*POA*TERRA CONFINS BRA FRGN AMT: 38.00 BRAZILIAN REAL | L17: I | M17: =IF(C17>0,C17,-D17) -> 11.24 | N17: F | Q17: CBS - needs to be pasted seperately | R17: =LEN(K17) -> 82
A18: 45952 | B18: OLEGARIO BELO HORIZO BRA FRGN AMT: 40.00 BRAZILIAN REAL | C18: 11.84 | D18: 0 | E18: Food/drink | F18: G185 | G18: MISC | J18: =IF(F18>0,(_xlfn.CONCAT(F18,".",G18)),H18) -> G185.MISC | K18: =_xlfn.CONCAT("W Lodge-",E18,"-",B18) -> W Lodge-Food/drink-OLEGARIO BELO HORIZO BRA FRGN AMT: 40.00 BRAZILIAN REAL | L18: I | M18: =IF(C18>0,C18,-D18) -> 11.84 | N18: F | Q18: CBS - needs to be pasted seperately | R18: =LEN(K18) -> 75
A19: 45953 | B19: SUPERMERCADO E PADARIA BELO HORIZO BRA FRGN AMT: 47.52 BRAZILIAN REAL | C19: 14.06 | D19: 0 | E19: Food/drink | F19: G185 | G19: MISC | J19: =IF(F19>0,(_xlfn.CONCAT(F19,".",G19)),H19) -> G185.MISC | K19: =_xlfn.CONCAT("W Lodge-",E19,"-",B19) -> W Lodge-Food/drink-SUPERMERCADO E PADARIA BELO HORIZO BRA FRGN AMT: 47.52 BRAZILIAN REAL | L19: I | M19: =IF(C19>0,C19,-D19) -> 14.06 | N19: F | Q19: CBS - needs to be pasted seperately | R19: =LEN(K19) -> 89
A20: 45950 | B20: EDDIE FINE BURGUERS BELO HORIZO BRA FRGN AMT: 56.00 BRAZILIAN REAL | C20: 16.54 | D20: 0 | E20: Food/drink | F20: G185 | G20: MISC | J20: =IF(F20>0,(_xlfn.CONCAT(F20,".",G20)),H20) -> G185.MISC | K20: =_xlfn.CONCAT("W Lodge-",E20,"-",B20) -> W Lodge-Food/drink-EDDIE FINE BURGUERS BELO HORIZO BRA FRGN AMT: 56.00 BRAZILIAN REAL | L20: I | M20: =IF(C20>0,C20,-D20) -> 16.54 | N20: F | Q20: CBS - needs to be pasted seperately | R20: =LEN(K20) -> 86
A21: 45949 | B21: Intelsat Inflight LLC Mclean USA FRGN AMT: 11.25 U. S. DOLLAR | C21: 17.99 | D21: 0 | E21: Internet | F21: G185 | G21: MISC | J21: =IF(F21>0,(_xlfn.CONCAT(F21,".",G21)),H21) -> G185.MISC | K21: =_xlfn.CONCAT("W Lodge-",E21,"-",B21) -> W Lodge-Internet-Intelsat Inflight LLC Mclean USA FRGN AMT: 11.25 U. S. DOLLAR | L21: I | M21: =IF(C21>0,C21,-D21) -> 17.99 | N21: F | Q21: CBS - needs to be pasted seperately | R21: =LEN(K21) -> 79
A22: 45951 | B22: OLEGARIO BELO HORIZO BRA FRGN AMT: 72.09 BRAZILIAN REAL | C22: 21.38 | D22: 0 | E22: Food/drink | F22: G185 | G22: MISC | J22: =IF(F22>0,(_xlfn.CONCAT(F22,".",G22)),H22) -> G185.MISC | K22: =_xlfn.CONCAT("W Lodge-",E22,"-",B22) -> W Lodge-Food/drink-OLEGARIO BELO HORIZO BRA FRGN AMT: 72.09 BRAZILIAN REAL | L22: I | M22: =IF(C22>0,C22,-D22) -> 21.38 | N22: F | Q22: CBS - needs to be pasted seperately | R22: =LEN(K22) -> 75
A23: 45949 | B23: JB HI FI MELBOURNE D MELBOURNE A AUS | C23: 29.95 | D23: 0 | E23: Cable phone head set | F23: 1053 | G23: CONS | J23: =IF(F23>0,(_xlfn.CONCAT(F23,".",G23)),H23) -> 1053.CONS | K23: =_xlfn.CONCAT("W Lodge-",E23,"-",B23) -> W Lodge-Cable phone head set-JB HI FI MELBOURNE D MELBOURNE A AUS | L23: I | M23: =IF(C23>0,C23,-D23) -> 29.95 | N23: T | Q23: CBS - needs to be pasted seperately | R23: =LEN(K23) -> 65
A24: 45954 | B24: HAVANNA BH SHOPPING BELO HORIZO BRA FRGN AMT: 104.30 BRAZILIAN REAL | C24: 30.84 | D24: 0 | E24: Food/drink | F24: G185 | G24: MISC | J24: =IF(F24>0,(_xlfn.CONCAT(F24,".",G24)),H24) -> G185.MISC | K24: =_xlfn.CONCAT("W Lodge-",E24,"-",B24) -> W Lodge-Food/drink-HAVANNA BH SHOPPING BELO HORIZO BRA FRGN AMT: 104.30 BRAZILIAN REAL | L24: I | M24: =IF(C24>0,C24,-D24) -> 30.84 | N24: F | Q24: CBS - needs to be pasted seperately | R24: =LEN(K24) -> 87
A25: 45950 | B25: OLEGARIO BELO HORIZO BRA FRGN AMT: 122.49 BRAZILIAN REAL | C25: 36.28 | D25: 0 | E25: Food/drink | F25: G185 | G25: MISC | J25: =IF(F25>0,(_xlfn.CONCAT(F25,".",G25)),H25) -> G185.MISC | K25: =_xlfn.CONCAT("W Lodge-",E25,"-",B25) -> W Lodge-Food/drink-OLEGARIO BELO HORIZO BRA FRGN AMT: 122.49 BRAZILIAN REAL | L25: I | M25: =IF(C25>0,C25,-D25) -> 36.28 | N25: F | Q25: CBS - needs to be pasted seperately | R25: =LEN(K25) -> 76
A26: 45955 | B26: ESTHER DE FIGUEIREDO Belo Horizo BRA FRGN AMT: 185.86 BRAZILIAN REAL | C26: 55.02 | D26: 0 | E26: Food/drink | F26: G185 | G26: MISC | J26: =IF(F26>0,(_xlfn.CONCAT(F26,".",G26)),H26) -> G185.MISC | K26: =_xlfn.CONCAT("W Lodge-",E26,"-",B26) -> W Lodge-Food/drink-ESTHER DE FIGUEIREDO Belo Horizo BRA FRGN AMT: 185.86 BRAZILIAN REAL | L26: I | M26: =IF(C26>0,C26,-D26) -> 55.02 | N26: F | Q26: CBS - needs to be pasted seperately | R26: =LEN(K26) -> 88
A27: 45953 | B27: EDDIE FINE BURGUERS BELO HORIZO BRA FRGN AMT: 195.80 BRAZILIAN REAL | C27: 57.97 | D27: 0 | E27: Food/drink | F27: G185 | G27: MISC | J27: =IF(F27>0,(_xlfn.CONCAT(F27,".",G27)),H27) -> G185.MISC | K27: =_xlfn.CONCAT("W Lodge-",E27,"-",B27) -> W Lodge-Food/drink-EDDIE FINE BURGUERS BELO HORIZO BRA FRGN AMT: 195.80 BRAZILIAN REAL | L27: I | M27: =IF(C27>0,C27,-D27) -> 57.97 | N27: F | Q27: CBS - needs to be pasted seperately | R27: =LEN(K27) -> 87
A28: 45953 | B28: OLEGARIO BELO HORIZO BRA FRGN AMT: 314.81 BRAZILIAN REAL | C28: 93.1 | D28: 0 | E28: Food/drink | F28: G185 | G28: MISC | J28: =IF(F28>0,(_xlfn.CONCAT(F28,".",G28)),H28) -> G185.MISC | K28: =_xlfn.CONCAT("W Lodge-",E28,"-",B28) -> W Lodge-Food/drink-OLEGARIO BELO HORIZO BRA FRGN AMT: 314.81 BRAZILIAN REAL | L28: I | M28: =IF(C28>0,C28,-D28) -> 93.1 | N28: F | Q28: CBS - needs to be pasted seperately | R28: =LEN(K28) -> 76
A29: 45954 | B29: OLEGARIO BELO HORIZO BRA | C29: 107 | D29: 0 | E29: Food/drink | F29: G185 | G29: MISC | J29: =IF(F29>0,(_xlfn.CONCAT(F29,".",G29)),H29) -> G185.MISC | K29: =_xlfn.CONCAT("W Lodge-",E29,"-",B29) -> W Lodge-Food/drink-OLEGARIO BELO HORIZO BRA | L29: I | M29: =IF(C29>0,C29,-D29) -> 107 | N29: F | Q29: CBS - needs to be pasted seperately | R29: =LEN(K29) -> 43
A30: 45949 | B30: OLEGARIO BELO HORIZO BRA | C30: 111.25 | D30: 0 | E30: Food/drink | F30: G185 | G30: MISC | J30: =IF(F30>0,(_xlfn.CONCAT(F30,".",G30)),H30) -> G185.MISC | K30: =_xlfn.CONCAT("W Lodge-",E30,"-",B30) -> W Lodge-Food/drink-OLEGARIO BELO HORIZO BRA | L30: I | M30: =IF(C30>0,C30,-D30) -> 111.25 | N30: F | Q30: CBS - needs to be pasted seperately | R30: =LEN(K30) -> 43
A31: 45955 | B31: RADISSON BLU BELO HORI BELO HORIZO BRA | C31: 126 | D31: 0 | E31: Food/drink | F31: G185 | G31: MISC | J31: =IF(F31>0,(_xlfn.CONCAT(F31,".",G31)),H31) -> G185.MISC | K31: =_xlfn.CONCAT("W Lodge-",E31,"-",B31) -> W Lodge-Food/drink-RADISSON BLU BELO HORI BELO HORIZO BRA | L31: I | M31: =IF(C31>0,C31,-D31) -> 126 | N31: F | Q31: CBS - needs to be pasted seperately | R31: =LEN(K31) -> 57
A32: 45950 | B32: MD COM DE ALIMENT LTDA BELO HORIZO BRA | C32: 175.49 | D32: 0 | E32: Food/drink | F32: G185 | G32: MISC | J32: =IF(F32>0,(_xlfn.CONCAT(F32,".",G32)),H32) -> G185.MISC | K32: =_xlfn.CONCAT("W Lodge-",E32,"-",B32) -> W Lodge-Food/drink-MD COM DE ALIMENT LTDA BELO HORIZO BRA | L32: I | M32: =IF(C32>0,C32,-D32) -> 175.49 | N32: F | Q32: CBS - needs to be pasted seperately | R32: =LEN(K32) -> 57
A33: 45952 | B33: OLEGARIO BELO HORIZO BRA FRGN AMT: 920.27 BRAZILIAN REAL | C33: 272.45 | D33: 0 | E33: Food/drink | F33: G185 | G33: MISC | J33: =IF(F33>0,(_xlfn.CONCAT(F33,".",G33)),H33) -> G185.MISC | K33: =_xlfn.CONCAT("W Lodge-",E33,"-",B33) -> W Lodge-Food/drink-OLEGARIO BELO HORIZO BRA FRGN AMT: 920.27 BRAZILIAN REAL | L33: I | M33: =IF(C33>0,C33,-D33) -> 272.45 | N33: F | Q33: CBS - needs to be pasted seperately | R33: =LEN(K33) -> 76
A34: 45973 | B34: SPECIALIST CENTRE BALLARAT CE AUS | C34: 939 | D34: 0 | E34: Employee Loan | F34: 1084 | G34: PERS | J34: =IF(F34>0,(_xlfn.CONCAT(F34,".",G34)),H34) -> 1084.PERS | K34: =_xlfn.CONCAT("W Lodge-",E34,"-",B34) -> W Lodge-Employee Loan-SPECIALIST CENTRE BALLARAT CE AUS | L34: I | M34: =IF(C34>0,C34,-D34) -> 939 | N34: F | Q34: CBS - needs to be pasted seperately | R34: =LEN(K34) -> 55

Sheet S McLaughlin
A1: Employee to code & narrate | J1: To be copied in to pronto
J2: Credit card Statement TOTAL | K2: 1417.03
J3: Subtotal | K3: =SUM(M8:M143) -> 1417.03
J4: Variance Check | K4: =K2-K3 -> 0
A5: Shane McLaughlin
A6: Reference | B6: =CONCATENATE(Header!$E$4,"McLaughlin") -> MC-251116McLaughlin | J6: EMPLOYEES DO NOT CHANGE
A7: Document Date | B7: =Header!$E$5 -> 45977 | E7: Credit card holder to add details
A9: Date | B9: Narrative | C9: Debit Amount | D9: Credit Amount | E9: Description | F9: Project No | G9: Cost Category | H9: GL account | J9: Account | K9: Reference | L9: Tax | M9: Amount | N9: Tax CODE | O9: TAX Amount (leave blank) | P9: CBS - Only if required | R9: limit 56charaters
A10: 45952 | B10: WOOLWORTHS 3280 BALLARAT AUS | C10: 7.95 | D10: 0 | E10: Wednesday lunch soft drinks | F10: 1051 | G10: ENON | J10: =IF(F10>0,(_xlfn.CONCAT(F10,".",G10)),H10) -> 1051.ENON | K10: =_xlfn.CONCAT("S McLaughlin-",E10,"-",B10) -> S McLaughlin-Wednesday lunch soft drinks-WOOLWORTHS 3280 BALLARAT AUS | L10: I | M10: =IF(C10>0,C10,-D10) -> 7.95 | N10: T | Q10: CBS - needs to be pasted seperately | R10: =LEN(K10) -> 74
A11: 45954 | B11: METRO PETROLEUM GOLDEN Golden Poin AUS | C11: 17.78 | D11: 0 | E11: Cyanide pump petrol | F11: 1051 | G11: MVPF | J11: =IF(F11>0,(_xlfn.CONCAT(F11,".",G11)),H11) -> 1051.MVPF | K11: =_xlfn.CONCAT("S McLaughlin-",E11,"-",B11) -> S McLaughlin-Cyanide pump petrol-METRO PETROLEUM GOLDEN Golden Poin AUS | L11: I | M11: =IF(C11>0,C11,-D11) -> 17.78 | N11: T | Q11: CBS - needs to be pasted seperately | R11: =LEN(K11) -> 71
A12: 45954 | B12: WOOLWORTHS 3280 BALLARAT AUS | C12: 35.5 | D12: 0 | E12: Dishwasher tabs, soft drinks | F12: 1051 | G12: CONS | J12: =IF(F12>0,(_xlfn.CONCAT(F12,".",G12)),H12) -> 1051.CONS | K12: =_xlfn.CONCAT("S McLaughlin-",E12,"-",B12) -> S McLaughlin-Dishwasher tabs, soft drinks-WOOLWORTHS 3280 BALLARAT AUS | L12: I | M12: =IF(C12>0,C12,-D12) -> 35.5 | N12: T | Q12: CBS - needs to be pasted seperately | R12: =LEN(K12) -> 75
A13: 45957 | B13: Woolworths Online BellaVista AUS | C13: 64 | D13: 0 | E13: Man down phone case | F13: 1051 | G13: SPPE | J13: =IF(F13>0,(_xlfn.CONCAT(F13,".",G13)),H13) -> 1051.SPPE | K13: =_xlfn.CONCAT("S McLaughlin-",E13,"-",B13) -> S McLaughlin-Man down phone case-Woolworths Online BellaVista AUS | L13: I | M13: =IF(C13>0,C13,-D13) -> 64 | N13: T | Q13: CBS - needs to be pasted seperately | R13: =LEN(K13) -> 65
A14: 45957 | B14: APCO MAIN RD BALLARA BALLARAT AUS | C14: 69.99 | D14: 0 | E14: Fuel personal car use | F14: 1051 | G14: MVPF | J14: =IF(F14>0,(_xlfn.CONCAT(F14,".",G14)),H14) -> 1051.MVPF | K14: =_xlfn.CONCAT("S McLaughlin-",E14,"-",B14) -> S McLaughlin-Fuel personal car use-APCO MAIN RD BALLARA BALLARAT AUS | L14: I | M14: =IF(C14>0,C14,-D14) -> 69.99 | N14: T | Q14: CBS - needs to be pasted seperately | R14: =LEN(K14) -> 68
A15: 45953 | B15: OFFICEWORKS 0364 BALLARAT AUS | C15: 89.96 | D15: 0 | E15: address labels | F15: 1051 | G15: CONS | J15: =IF(F15>0,(_xlfn.CONCAT(F15,".",G15)),H15) -> 1051.CONS | K15: =_xlfn.CONCAT("S McLaughlin-",E15,"-",B15) -> S McLaughlin-address labels-OFFICEWORKS 0364 BALLARAT AUS | L15: I | M15: =IF(C15>0,C15,-D15) -> 89.96 | N15: T | Q15: CBS - needs to be pasted seperately | R15: =LEN(K15) -> 57
A16: 45959 | B16: SQ *ANUKRIT DISMIN Geelong AUS | C16: 160.55 | D16: 0 | E16: Wednesday lunch thai | F16: 1051 | G16: ENON | J16: =IF(F16>0,(_xlfn.CONCAT(F16,".",G16)),H16) -> 1051.ENON | K16: =_xlfn.CONCAT("S McLaughlin-",E16,"-",B16) -> S McLaughlin-Wednesday lunch thai-SQ *ANUKRIT DISMIN Geelong AUS | L16: I | M16: =IF(C16>0,C16,-D16) -> 160.55 | N16: T | Q16: CBS - needs to be pasted seperately | R16: =LEN(K16) -> 64
A17: 45961 | B17: CERTAGS PTY LTD KNOXFIELD AUS | C17: 971.3 | D17: 0 | E17: Leachwell bottle labels | F17: 1051 | G17: CONS | J17: =IF(F17>0,(_xlfn.CONCAT(F17,".",G17)),H17) -> 1051.CONS | K17: =_xlfn.CONCAT("S McLaughlin-",E17,"-",B17) -> S McLaughlin-Leachwell bottle labels-CERTAGS PTY LTD KNOXFIELD AUS | L17: I | M17: =IF(C17>0,C17,-D17) -> 971.3 | N17: T | Q17: CBS - needs to be pasted seperately | R17: =LEN(K17) -> 66

Sheet M Ntombela
A1: Employee to code & narrate | J1: To be copied in to pronto
J2: Credit card Statement TOTAL | K2: 300.19
J3: Subtotal | K3: =SUM(M8:M143) -> 300.19
J4: Variance Check | K4: =K2-K3 -> 0
A5: Mx Ntombela
A6: Reference | B6: =CONCATENATE(Header!$E$4,"Ntombela") -> MC-251116Ntombela | J6: EMPLOYEES DO NOT CHANGE
A7: Document Date | B7: =Header!$E$5 -> 45977 | E7: Credit card holder to add details
A9: Date | B9: Narrative | C9: Debit Amount | D9: Credit Amount | E9: Description | F9: Project No | G9: Cost Category | H9: GL account | J9: Account | K9: Reference | L9: Tax | M9: Amount | N9: Tax CODE | O9: TAX Amount (leave blank) | P9: CBS - Only if required | R9: limit 56charaters
A10: 45954 | B10: BENDIGO HOTEL FUND OP BENDIGO AUS | C10: 65.19 | D10: 0 | E10: Meals, Breakfast, M Ntombela and T Hughes | F10: G119-05 | G10: SALP | J10: =IF(F10>0,(_xlfn.CONCAT(F10,".",G10)),H10) -> G119-05.SALP | K10: =_xlfn.CONCAT("M Ntombela-",E10,"-",B10) -> M Ntombela-Meals, Breakfast, M Ntombela and T Hughes-BENDIGO HOTEL FUND OP BENDIGO AUS | L10: I | M10: =IF(C10>0,C10,-D10) -> 65.19 | N10: T | Q10: CBS - needs to be pasted seperately | R10: =LEN(K10) -> 86
A11: 45953 | B11: BENDIGO HOTEL FUND OP BENDIGO AUS | C11: 235 | D11: 0 | E11: Accommodation, MetFest Victoria 2025 | F11: G119-05 | G11: SALP | J11: =IF(F11>0,(_xlfn.CONCAT(F11,".",G11)),H11) -> G119-05.SALP | K11: =_xlfn.CONCAT("M Ntombela-",E11,"-",B11) -> M Ntombela-Accommodation, MetFest Victoria 2025-BENDIGO HOTEL FUND OP BENDIGO AUS | L11: I | M11: =IF(C11>0,C11,-D11) -> 235 | N11: T | Q11: CBS - needs to be pasted seperately | R11: =LEN(K11) -> 81

Sheet D OHalloran
A1: Employee to code & narrate | J1: To be copied in to pronto
J2: Credit card Statement TOTAL | K2: 157.54
J3: Subtotal | K3: =SUM(M8:M143) -> 157.54
J4: Variance Check | K4: =K2-K3 -> 0
A5: Dan O'Halloran
A6: Reference | B6: =CONCATENATE(Header!$E$4,"O'Halloran") -> MC-251116O'Halloran | J6: EMPLOYEES DO NOT CHANGE
A7: Document Date | B7: =Header!$E$5 -> 45977 | E7: Credit card holder to add details
A9: Date | B9: Narrative | C9: Debit Amount | D9: Credit Amount | E9: Description | F9: Project No | G9: Cost Category | H9: GL account | J9: Account | K9: Reference | L9: Tax | M9: Amount | N9: Tax CODE | O9: TAX Amount (leave blank) | P9: CBS - Only if required | R9: limit 56charaters
A10: 45964 | B10: Civil Ballarat Delacombe AUS | C10: 157.54 | D10: 0 | E10: FAT fittings workshop | F10: 1073 | G10: cons | J10: =IF(F10>0,(_xlfn.CONCAT(F10,".",G10)),H10) -> 1073.cons | K10: =_xlfn.CONCAT("D O'Halloran-",E10,"-",B10) -> D O'Halloran-FAT fittings workshop-Civil Ballarat Delacombe AUS | L10: I | M10: =IF(C10>0,C10,-D10) -> 157.54 | N10: T | Q10: CBS - needs to be pasted seperately | R10: =LEN(K10) -> 63

Sheet M Prendergast
A1: Employee to code & narrate | J1: To be copied in to pronto
J2: Credit card Statement TOTAL | K2: 152.8
J3: Subtotal | K3: =SUM(M8:M142) -> 152.8
J4: Variance Check | K4: =K2-K3 -> 0
A5: Melinda Pendergast
A6: Reference | B6: =CONCATENATE(Header!$E$4,"Pendergast") -> MC-251116Pendergast | J6: EMPLOYEES DO NOT CHANGE
A7: Document Date | B7: =Header!$E$5 -> 45977 | E7: Credit card holder to add details
A9: Date | B9: Narrative | C9: Debit Amount | D9: Credit Amount | E9: Description | F9: Project No | G9: Cost Category | H9: GL account | J9: Account | K9: Reference | L9: Tax | M9: Amount | N9: Tax CODE | O9: TAX Amount (leave blank) | P9: CBS - Only if required | R9: limit 56charaters
A10: 45973 | B10: FEDEX EXPRESS AUSTRALI MASCOT AUS | C10: 97.25 | D10: 0 | E10: Freight for Spectrometer back from Amptek | F10: X129.04 | G10: ASPU | J10: =IF(F10>0,(_xlfn.CONCAT(F10,".",G10)),H10) -> X129.04.ASPU | K10: =_xlfn.CONCAT("M Pendergast-",E10,"-",B10) -> M Pendergast-Freight for Spectrometer back from Amptek-FEDEX EXPRESS AUSTRALI MASCOT AUS | L10: I | M10: =IF(C10>0,C10,-D10) -> 97.25 | N10: T | Q10: CBS - needs to be pasted seperately | R10: =LEN(K10) -> 88
A11: 45957 | B11: WWW.ALIEXPRESS.COM LONDON GBR | C11: 14.85 | D11: 0 | E11: angled USB adaptors | F11: X195 | G11: ASPU | J11: =IF(F11>0,(_xlfn.CONCAT(F11,".",G11)),H11) -> X195.ASPU | K11: =_xlfn.CONCAT("M Pendergast-",E11,"-",B11) -> M Pendergast-angled USB adaptors-WWW.ALIEXPRESS.COM LONDON GBR | L11: I | M11: =IF(C11>0,C11,-D11) -> 14.85 | N11: F | Q11: CBS - needs to be pasted seperately | R11: =LEN(K11) -> 62
A12: 45967 | B12: eBay O*27-13772-68098 Sydney AUS | C12: 33.9 | D12: 0 | E12: Receipted via PO 77301 | J12: =IF(F12>0,(_xlfn.CONCAT(F12,".",G12)),H12) -> 0 | K12: =_xlfn.CONCAT("M Pendergast-",E12,"-",B12) -> M Pendergast-Receipted via PO 77301-eBay O*27-13772-68098 Sydney AUS | L12: I | M12: =IF(C12>0,C12,-D12) -> 33.9 | N12: F | Q12: CBS - needs to be pasted seperately | R12: =LEN(K12) -> 68
A13: 45967 | B13: eBay O*27-13772-68099 Sydney AUS | C13: 6.8 | D13: 0 | E13: Receipted via PO 77301 | J13: =IF(F13>0,(_xlfn.CONCAT(F13,".",G13)),H13) -> 0 | K13: =_xlfn.CONCAT("M Pendergast-",E13,"-",B13) -> M Pendergast-Receipted via PO 77301-eBay O*27-13772-68099 Sydney AUS | L13: I | M13: =IF(C13>0,C13,-D13) -> 6.8 | N13: F | Q13: CBS - needs to be pasted seperately | R13: =LEN(K13) -> 68

Sheet A Randell
A1: Employee to code & narrate | J1: To be copied in to pronto
J2: Credit card Statement TOTAL | K2: 1067.34
J3: Subtotal | K3: =SUM(M8:M143) -> 1067.34
J4: Variance Check | K4: =K2-K3 -> 0
A5: Adrian Randell
A6: Reference | B6: =CONCATENATE(Header!$E$4,"Randell") -> MC-251116Randell | J6: EMPLOYEES DO NOT CHANGE
A7: Document Date | B7: =Header!$E$5 -> 45977 | E7: Credit card holder to add details
A9: Date | B9: Narrative | C9: Debit Amount | D9: Credit Amount | E9: Description | F9: Project No | G9: Cost Category | H9: GL account | J9: Account | K9: Reference | L9: Tax | M9: Amount | N9: Tax CODE | O9: TAX Amount (leave blank) | P9: CBS - Only if required | R9: limit 56charaters
A10: 45958 | B10: Perth Airport Pty Ltd Perth Airpo AUS | C10: 27.39 | D10: 0 | E10: parking for site visit tropicana | F10: CS003-C | G10: trvp | J10: =IF(F10>0,(_xlfn.CONCAT(F10,".",G10)),H10) -> CS003-C.trvp | K10: =_xlfn.CONCAT("ARandell-",E10,"-",B10) -> ARandell-parking for site visit tropicana-Perth Airport Pty Ltd Perth Airpo AUS | L10: I | M10: =IF(C10>0,C10,-D10) -> 27.39 | N10: T | Q10: CBS - needs to be pasted seperately | R10: =LEN(K10) -> 79
A11: 45965 | B11: THE GOOD GROCER LEED LEEDERVILLE AUS | C11: 33.49 | D11: 0 | E11: office supoolies perth office | F11: 1084 | G11: staf | J11: =IF(F11>0,(_xlfn.CONCAT(F11,".",G11)),H11) -> 1084.staf | K11: =_xlfn.CONCAT("ARandell-",E11,"-",B11) -> ARandell-office supoolies perth office-THE GOOD GROCER LEED LEEDERVILLE AUS | L11: I | M11: =IF(C11>0,C11,-D11) -> 33.49 | N11: T | Q11: CBS - needs to be pasted seperately | R11: =LEN(K11) -> 75
A12: 45961 | B12: CIBT AUSTRALIA MELBOURNE AUS | C12: 206.66 | D12: 0 | E12: visa for haile visit | F12: CS007-D | G12: TRVT | J12: =IF(F12>0,(_xlfn.CONCAT(F12,".",G12)),H12) -> CS007-D.TRVT | K12: =_xlfn.CONCAT("ARandell-",E12,"-",B12) -> ARandell-visa for haile visit-CIBT AUSTRALIA MELBOURNE AUS | L12: I | M12: =IF(C12>0,C12,-D12) -> 206.66 | N12: T | Q12: CBS - needs to be pasted seperately | R12: =LEN(K12) -> 58
A13: 45966 | B13: TOTAL TOOLS CANNING CANNING VAL AUS | C13: 267.5 | D13: 0 | E13: tools | F13: 1054 | G13: TOOL | J13: =IF(F13>0,(_xlfn.CONCAT(F13,".",G13)),H13) -> 1054.TOOL | K13: =_xlfn.CONCAT("ARandell-",E13,"-",B13) -> ARandell-tools-TOTAL TOOLS CANNING CANNING VAL AUS | L13: I | M13: =IF(C13>0,C13,-D13) -> 267.5 | N13: T | Q13: CBS - needs to be pasted seperately | R13: =LEN(K13) -> 50
A14: 45952 | B14: TOTAL TOOLS OCONNOR O'CONNOR AUS | C14: 532.3 | D14: 0 | E14: tools | F14: 1054 | G14: TOOL | J14: =IF(F14>0,(_xlfn.CONCAT(F14,".",G14)),H14) -> 1054.TOOL | K14: =_xlfn.CONCAT("ARandell-",E14,"-",B14) -> ARandell-tools-TOTAL TOOLS OCONNOR O'CONNOR AUS | L14: I | M14: =IF(C14>0,C14,-D14) -> 532.3 | N14: T | Q14: CBS - needs to be pasted seperately | R14: =LEN(K14) -> 47

Sheet A Riley
A1: Employee to code & narrate | J1: To be copied in to pronto
J2: Credit card Statement TOTAL | K2: 1712.76
J3: Subtotal | K3: =SUM(M8:M143) -> 1712.76
J4: Variance Check | K4: =K2-K3 -> 0
A5: Aimee Riley
A6: Reference | B6: =CONCATENATE(Header!$E$4,"Riley") -> MC-251116Riley | J6: EMPLOYEES DO NOT CHANGE
A7: Document Date | B7: =Header!$E$5 -> 45977 | E7: Credit card holder to add details
A9: Date | B9: Narrative | C9: Debit Amount | D9: Credit Amount | E9: Description | F9: Project No | G9: Cost Category | H9: GL account | J9: Account | K9: Reference | L9: Tax | M9: Amount | N9: Tax CODE | O9: TAX Amount (leave blank) | P9: CBS - Only if required | R9: limit 56charaters
A10: 45964 | B10: AUSIMM CARLTON AUS | C10: 20 | D10: 0 | E10: Conference | F10: 1084 | G10: CONF | J10: =IF(F10>0,(_xlfn.CONCAT(F10,".",G10)),H10) -> 1084.CONF | K10: =_xlfn.CONCAT("ARiley-",E10,"-",B10) -> ARiley-Conference -AUSIMM CARLTON AUS | L10: I | M10: =IF(C10>0,C10,-D10) -> 20 | N10: T | Q10: CBS - needs to be pasted seperately | R10: =LEN(K10) -> 37
A11: 45973 | B11: OFFICEWORKS 0302 STH MELBOUR AUS | C11: 51.89 | D11: 0 | E11: Gaia Open Day | F11: 1060GE2 | G11: MISC | J11: =IF(F11>0,(_xlfn.CONCAT(F11,".",G11)),H11) -> 1060GE2.MISC | K11: =_xlfn.CONCAT("ARiley-",E11,"-",B11) -> ARiley-Gaia Open Day -OFFICEWORKS 0302 STH MELBOUR AUS | L11: I | M11: =IF(C11>0,C11,-D11) -> 51.89 | N11: T
A12: 45946 | B12: OFFICEWORKS 0364 BALLARAT AUS | C12: 59.73 | D12: 0 | E12: Intulo | F12: G185 | G12: MISC | J12: =IF(F12>0,(_xlfn.CONCAT(F12,".",G12)),H12) -> G185.MISC | K12: =_xlfn.CONCAT("ARiley-",E12,"-",B12) -> ARiley-Intulo-OFFICEWORKS 0364 BALLARAT AUS | L12: I | M12: =IF(C12>0,C12,-D12) -> 59.73 | N12: T
A13: 45946 | B13: OFFICEWORKS 0364 BALLARAT AUS | C13: 88.79 | D13: 0 | E13: Gaia Open Day | F13: 1060GE2 | G13: MISC | J13: =IF(F13>0,(_xlfn.CONCAT(F13,".",G13)),H13) -> 1060GE2.MISC | K13: =_xlfn.CONCAT("ARiley-",E13,"-",B13) -> ARiley-Gaia Open Day-OFFICEWORKS 0364 BALLARAT AUS | L13: I | M13: =IF(C13>0,C13,-D13) -> 88.79 | N13: T
A14: 45974 | B14: KMART Mulgrave AUS | C14: 94.5 | D14: 0 | E14: Gaia Open Day | F14: 1060GE2 | G14: MISC | J14: =IF(F14>0,(_xlfn.CONCAT(F14,".",G14)),H14) -> 1060GE2.MISC | K14: =_xlfn.CONCAT("ARiley-",E14,"-",B14) -> ARiley-Gaia Open Day -KMART Mulgrave AUS | L14: I | M14: =IF(C14>0,C14,-D14) -> 94.5 | N14: T
A15: 45974 | B15: OFFICEWORKS Bentleigh E AUS | C15: 95.76 | D15: 0 | E15: Gaia Open Day | F15: 1060GE2 | G15: MISC | J15: =IF(F15>0,(_xlfn.CONCAT(F15,".",G15)),H15) -> 1060GE2.MISC | K15: =_xlfn.CONCAT("ARiley-",E15,"-",B15) -> ARiley-Gaia Open Day -OFFICEWORKS Bentleigh E AUS | L15: I | M15: =IF(C15>0,C15,-D15) -> 95.76 | N15: T
A16: 45960 | B16: Eclectic Tastes Lake Wendou AUS | C16: 116.5 | D16: 0 | E16: Marketing Team lunch with Marleen | F16: 1084 | G16: ENFE | J16: =IF(F16>0,(_xlfn.CONCAT(F16,".",G16)),H16) -> 1084.ENFE | K16: =_xlfn.CONCAT("ARiley-",E16,"-",B16) -> ARiley-Marketing Team lunch with Marleen-Eclectic Tastes Lake Wendou AUS | L16: I | M16: =IF(C16>0,C16,-D16) -> 116.5 | N16: T
A17: 45963 | B17: LinkedIn P649925436 Singapore SGP FRGN AMT: 109.69 U. S. DOLLAR | C17: 172.98 | D17: 0 | F17: 1084 | G17: ADVT | J17: =IF(F17>0,(_xlfn.CONCAT(F17,".",G17)),H17) -> 1084.ADVT | K17: =_xlfn.CONCAT("ARiley-",E17,"-",B17) -> ARiley--LinkedIn P649925436 Singapore SGP FRGN AMT: 109.69 U. S. DOLLAR | L17: I | M17: =IF(C17>0,C17,-D17) -> 172.98 | N17: f
A18: 45971 | B18: LinkedIn P661161166 Singapore SGP FRGN AMT: 122.01 U. S. DOLLAR | C18: 194.44 | D18: 0 | F18: 1084 | G18: ADVT | J18: =IF(F18>0,(_xlfn.CONCAT(F18,".",G18)),H18) -> 1084.ADVT | K18: =_xlfn.CONCAT("ARiley-",E18,"-",B18) -> ARiley--LinkedIn P661161166 Singapore SGP FRGN AMT: 122.01 U. S. DOLLAR | L18: I | M18: =IF(C18>0,C18,-D18) -> 194.44 | N18: f
A19: 45974 | B19: LinkedIn P665494506 Singapore SGP FRGN AMT: 126.91 U. S. DOLLAR | C19: 200.7 | D19: 0 | F19: 1084 | G19: ADVT | J19: =IF(F19>0,(_xlfn.CONCAT(F19,".",G19)),H19) -> 1084.ADVT | K19: =_xlfn.CONCAT("ARiley-",E19,"-",B19) -> ARiley--LinkedIn P665494506 Singapore SGP FRGN AMT: 126.91 U. S. DOLLAR | L19: I | M19: =IF(C19>0,C19,-D19) -> 200.7 | N19: f
A20: 45975 | B20: SQ *LE PECHE GOURMAND Creswick AUS | C20: 577.47 | D20: 0 | E20: Gaia Open Day Lunch | F20: 1060GE2 | G20: MISC | J20: =IF(F20>0,(_xlfn.CONCAT(F20,".",G20)),H20) -> 1060GE2.MISC | K20: =_xlfn.CONCAT("ARiley-",E20,"-",B20) -> ARiley-Gaia Open Day Lunch -SQ *LE PECHE GOURMAND Creswick AUS | L20: I | M20: =IF(C20>0,C20,-D20) -> 577.47 | N20: t
A21: 45945 | B21: AUSIMM CARLTON AUS | C21: 40 | D21: 0 | E21: Conference | F21: 1084 | G21: CONF | J21: =IF(F21>0,(_xlfn.CONCAT(F21,".",G21)),H21) -> 1084.CONF | K21: =_xlfn.CONCAT("ARiley-",E21,"-",B21) -> ARiley-Conference-AUSIMM CARLTON AUS | L21: I | M21: =IF(C21>0,C21,-D21) -> 40 | N21: T

Sheet K Rouhan
A1: Employee to code & narrate | J1: To be copied in to pronto
J2: Credit card Statement TOTAL | K2: 2697.99
J3: Subtotal | K3: =SUM(M8:M143) -> 2697.99
J4: Variance Check | K4: =K2-K3 -> 0
A5: Kate Rouhan
A6: Reference | B6: =CONCATENATE(Header!$E$4,"Rouhan") -> MC-251116Rouhan | J6: EMPLOYEES DO NOT CHANGE
A7: Document Date | B7: =Header!$E$5 -> 45977 | E7: Credit card holder to add details
A9: Date | B9: Narrative | C9: Debit Amount | D9: Credit Amount | E9: Description | F9: Project No | G9: Cost Category | H9: GL account | J9: Account | K9: Reference | L9: Tax | M9: Amount | N9: Tax CODE | O9: TAX Amount (leave blank) | P9: CBS - Only if required | R9: limit 56charaters
A10: 45977 | B10: INTEREST CHARGES - CAS H | C10: 0.17 | D10: 0 | E10: Interest charged on credit card | F10: 1084 | G10: BFEE | J10: =IF(F10>0,(_xlfn.CONCAT(F10,".",G10)),H10) -> 1084.BFEE | K10: =_xlfn.CONCAT("K Rouhan-",E10,"-",B10) -> K Rouhan-Interest charged on credit card-INTEREST CHARGES - CAS H | L10: I | M10: =IF(C10>0,C10,-D10) -> 0.17 | N10: F | Q10: CBS - needs to be pasted seperately | R10: =LEN(K10) -> 65
A11: 45975 | B11: CASH ADVANCE FEE | C11: 3 | D11: 0 | E11: Withdrawal for work experience student | F11: 1084 | G11: BFEE | J11: =IF(F11>0,(_xlfn.CONCAT(F11,".",G11)),H11) -> 1084.BFEE | K11: =_xlfn.CONCAT("K Rouhan-",E11,"-",B11) -> K Rouhan-Withdrawal for work experience student-CASH ADVANCE FEE | L11: I | M11: =IF(C11>0,C11,-D11) -> 3 | N11: F | Q11: CBS - needs to be pasted seperately | R11: =LEN(K11) -> 64
A12: 45960 | B12: POST WENDOUREE POST SH WENDOUREE AUS | C12: 3.4 | D12: 0 | E12: Large letter envelop purchased | F12: 1084 | G12: POST | J12: =IF(F12>0,(_xlfn.CONCAT(F12,".",G12)),H12) -> 1084.POST | K12: =_xlfn.CONCAT("K Rouhan-",E12,"-",B12) -> K Rouhan-Large letter envelop purchased-POST WENDOUREE POST SH WENDOUREE AUS | L12: I | M12: =IF(C12>0,C12,-D12) -> 3.4 | N12: T | Q12: CBS - needs to be pasted seperately | R12: =LEN(K12) -> 76
A13: 45972 | B13: POST WENDOUREE VILLAGE WENDOUREE AUS | C13: 11.15 | D13: 0 | E13: Posting radiation monitors | F13: 1084 | G13: POST | J13: =IF(F13>0,(_xlfn.CONCAT(F13,".",G13)),H13) -> 1084.POST | K13: =_xlfn.CONCAT("K Rouhan-",E13,"-",B13) -> K Rouhan-Posting radiation monitors-POST WENDOUREE VILLAGE WENDOUREE AUS | L13: I | M13: =IF(C13>0,C13,-D13) -> 11.15 | N13: T | Q13: CBS - needs to be pasted seperately | R13: =LEN(K13) -> 72
A14: 45947 | B14: ALDI STORES WENDOUREE AUS | C14: 14.01 | D14: 0 | E14: Milk | F14: 1084 | G14: STAF | J14: =IF(F14>0,(_xlfn.CONCAT(F14,".",G14)),H14) -> 1084.STAF | K14: =_xlfn.CONCAT("K Rouhan-",E14,"-",B14) -> K Rouhan-Milk-ALDI STORES WENDOUREE AUS | L14: I | M14: =IF(C14>0,C14,-D14) -> 14.01 | N14: F | Q14: CBS - needs to be pasted seperately | R14: =LEN(K14) -> 39
A15: 45947 | B15: Nextra Wendouree Wendouree AUS | C15: 15.12 | D15: 0 | E15: Farwell card for staff member | F15: 1084 | G15: STAF | J15: =IF(F15>0,(_xlfn.CONCAT(F15,".",G15)),H15) -> 1084.STAF | K15: =_xlfn.CONCAT("K Rouhan-",E15,"-",B15) -> K Rouhan-Farwell card for staff member-Nextra Wendouree Wendouree AUS | L15: I | M15: =IF(C15>0,C15,-D15) -> 15.12 | N15: T | Q15: CBS - needs to be pasted seperately | R15: =LEN(K15) -> 69
A16: 45950 | B16: Bakers Delight Ballarat AUS | C16: 19 | D16: 0 | E16: Farwell morning tea for AL | F16: 1084 | G16: STAF | J16: =IF(F16>0,(_xlfn.CONCAT(F16,".",G16)),H16) -> 1084.STAF | K16: =_xlfn.CONCAT("K Rouhan-",E16,"-",B16) -> K Rouhan-Farwell morning tea for AL-Bakers Delight Ballarat AUS | L16: I | M16: =IF(C16>0,C16,-D16) -> 19 | N16: T | Q16: CBS - needs to be pasted seperately | R16: =LEN(K16) -> 63
A17: 45959 | B17: KMART 1037 WENDOUREE AUS | C17: 20 | D17: 0 | E17: Purchase of knives for lunch hut | F17: 1084 | G17: STAF | J17: =IF(F17>0,(_xlfn.CONCAT(F17,".",G17)),H17) -> 1084.STAF | K17: =_xlfn.CONCAT("K Rouhan-",E17,"-",B17) -> K Rouhan-Purchase of knives for lunch hut-KMART 1037 WENDOUREE AUS | L17: I | M17: =IF(C17>0,C17,-D17) -> 20 | N17: T | Q17: CBS - needs to be pasted seperately | R17: =LEN(K17) -> 66
A18: 45954 | B18: CapCut SINGAPORE SGP | C18: 30.88 | D18: 0 | E18: Marketing prepaid software | F18: 1084 | G18: MEMB | J18: =IF(F18>0,(_xlfn.CONCAT(F18,".",G18)),H18) -> 1084.MEMB | K18: =_xlfn.CONCAT("K Rouhan-",E18,"-",B18) -> K Rouhan-Marketing prepaid software-CapCut SINGAPORE SGP | L18: I | M18: =IF(C18>0,C18,-D18) -> 30.88 | N18: T | Q18: CBS - needs to be pasted seperately | R18: =LEN(K18) -> 56
A19: 45975 | B19: CASH ADVANCE BANK OF BENDIGO WENDOUREE AUS | C19: 100 | D19: 0 | E19: Money for work experience student - Delivery | H19: 110739997830 | J19: =IF(F19>0,(_xlfn.CONCAT(F19,".",G19)),H19) -> 110739997830 | K19: =_xlfn.CONCAT("K Rouhan-",E19,"-",B19) -> K Rouhan-Money for work experience student - Delivery-CASH ADVANCE BANK OF BENDIGO WENDOUREE AUS | L19: I | M19: =IF(C19>0,C19,-D19) -> 100 | N19: F | Q19: CBS - needs to be pasted seperately | R19: =LEN(K19) -> 96
A20: 45950 | B20: WOOLWORTHS 3066 ALFREDTON AUS | C20: 115.25 | D20: 0 | E20: Farwell morning tea and dessert for wed lunch | F20: 1084 | G20: STAF | J20: =IF(F20>0,(_xlfn.CONCAT(F20,".",G20)),H20) -> 1084.STAF | K20: =_xlfn.CONCAT("K Rouhan-",E20,"-",B20) -> K Rouhan-Farwell morning tea and dessert for wed lunch-WOOLWORTHS 3066 ALFREDTON AUS | L20: I | M20: =IF(C20>0,C20,-D20) -> 115.25 | N20: T | Q20: CBS - needs to be pasted seperately | R20: =LEN(K20) -> 89
A21: 45959 | B21: ALDI STORES WENDOUREE AUS | C21: 173.67 | D21: 0 | E21: Purchase for wed lunch | F21: 1084 | G21: ENON | J21: =IF(F21>0,(_xlfn.CONCAT(F21,".",G21)),H21) -> 1084.ENON | K21: =_xlfn.CONCAT("K Rouhan-",E21,"-",B21) -> K Rouhan-Purchase for wed lunch-ALDI STORES WENDOUREE AUS | L21: I | M21: =IF(C21>0,C21,-D21) -> 173.67 | N21: T | Q21: CBS - needs to be pasted seperately | R21: =LEN(K21) -> 57
A22: 45959 | B22: WOOLWORTHS 3603 WENDOUREE AUS | C22: 221.05 | D22: 0 | E22: Wednesday lunch/Baked potatoes | F22: 1084 | G22: ENON | J22: =IF(F22>0,(_xlfn.CONCAT(F22,".",G22)),H22) -> 1084.ENON | K22: =_xlfn.CONCAT("K Rouhan-",E22,"-",B22) -> K Rouhan-Wednesday lunch/Baked potatoes-WOOLWORTHS 3603 WENDOUREE AUS | L22: I | M22: =IF(C22>0,C22,-D22) -> 221.05 | N22: T | Q22: CBS - needs to be pasted seperately | R22: =LEN(K22) -> 74
A23: 45947 | B23: Subway Wendouree Lake Wendou AUS | C23: 240 | D23: 0 | E23: lunch for training | F23: 1084 | G23: ENON | J23: =IF(F23>0,(_xlfn.CONCAT(F23,".",G23)),H23) -> 1084.ENON | K23: =_xlfn.CONCAT("K Rouhan-",E23,"-",B23) -> K Rouhan-lunch for training-Subway Wendouree Lake Wendou AUS | L23: I | M23: =IF(C23>0,C23,-D23) -> 240 | N23: T | Q23: CBS - needs to be pasted seperately | R23: =LEN(K23) -> 60
A24: 45951 | B24: Woolworths Online BellaVista AUS | C24: 268 | D24: 0 | E24: Groceries | F24: 1084 | G24: STAF | J24: =IF(F24>0,(_xlfn.CONCAT(F24,".",G24)),H24) -> 1084.STAF | K24: =_xlfn.CONCAT("K Rouhan-",E24,"-",B24) -> K Rouhan-Groceries-Woolworths Online BellaVista AUS | L24: I | M24: =IF(C24>0,C24,-D24) -> 268 | N24: T | Q24: CBS - needs to be pasted seperately | R24: =LEN(K24) -> 51
A25: 45973 | B25: HTTPS://SCRIBE.HOW/B SAN FRANCIS USA FRGN AMT: 171.06 U. S. DOLLAR | C25: 270.51 | D25: 0 | E25: Scribe prepaid software | F25: 1084 | G25: PREP | J25: =IF(F25>0,(_xlfn.CONCAT(F25,".",G25)),H25) -> 1084.PREP | K25: =_xlfn.CONCAT("K Rouhan-",E25,"-",B25) -> K Rouhan-Scribe prepaid software-HTTPS://SCRIBE.HOW/B SAN FRANCIS USA FRGN AMT: 171.06 U. S. DOLLAR | L25: I | M25: =IF(C25>0,C25,-D25) -> 270.51 | N25: F | Q25: CBS - needs to be pasted seperately | R25: =LEN(K25) -> 100
A26: 45946 | B26: DAN MURPHY'S 3905 DELACOMBE AUS | C26: 280.78 | D26: 0 | E26: drinks for lunch hut fridge | F26: 1084 | G26: STAF | J26: =IF(F26>0,(_xlfn.CONCAT(F26,".",G26)),H26) -> 1084.STAF | K26: =_xlfn.CONCAT("K Rouhan-",E26,"-",B26) -> K Rouhan-drinks for lunch hut fridge-DAN MURPHY'S 3905 DELACOMBE AUS | L26: I | M26: =IF(C26>0,C26,-D26) -> 280.78 | N26: T | Q26: CBS - needs to be pasted seperately | R26: =LEN(K26) -> 71
A27: 45960 | B27: CRUST - BALLARAT ROBINA AUS | C27: 912 | D27: 0 | E27: Wednesday lunch | F27: 1084 | G27: ENON | J27: =IF(F27>0,(_xlfn.CONCAT(F27,".",G27)),H27) -> 1084.ENON | K27: =_xlfn.CONCAT("K Rouhan-",E27,"-",B27) -> K Rouhan-Wednesday lunch-CRUST - BALLARAT ROBINA AUS | L27: I | M27: =IF(C27>0,C27,-D27) -> 912 | N27: T | Q27: CBS - needs to be pasted seperately | R27: =LEN(K27) -> 52

Sheet C Torney
A1: Employee to code & narrate | J1: To be copied in to pronto
J2: Credit card Statement TOTAL | K2: 185.14
J3: Subtotal | K3: =SUM(M8:M143) -> 185.14
J4: Variance Check | K4: =K2-K3 -> 0
A5: Clint Torney
A6: Reference | B6: =CONCATENATE(Header!$E$4,"Torney") -> MC-251116Torney | J6: EMPLOYEES DO NOT CHANGE
A7: Document Date | B7: =Header!$E$5 -> 45977 | E7: Credit card holder to add details
A9: Date | B9: Narrative | C9: Debit Amount | D9: Credit Amount | E9: Description | F9: Project No | G9: Cost Category | H9: GL account | J9: Account | K9: Reference | L9: Tax | M9: Amount | N9: Tax CODE | O9: TAX Amount (leave blank) | P9: CBS - Only if required | R9: limit 56charaters
A10: 13/11/2025 | B10: BUNNINGS 329000 DELACOMBE AUS | C10: 27.4 | D10: 0 | E10: paint brush | F10: 1073 | G10: CONS | J10: =IF(F10>0,(_xlfn.CONCAT(F10,".",G10)),H10) -> 1073.CONS | K10: =_xlfn.CONCAT("C Torney-",E10,"-",B10) -> C Torney-paint brush-BUNNINGS 329000 DELACOMBE AUS | L10: I | M10: =IF(C10>0,C10,-D10) -> 27.4 | N10: T | Q10: CBS - needs to be pasted seperately | R10: =LEN(K10) -> 50
A11: 20/10/2025 | B11: Mid City Hotel Ballar BALLARAT CE AUS | C11: 30.49 | D11: 0 | E11: welding test supervisor accomadation | F11: x212 | G11: ASPU | J11: =IF(F11>0,(_xlfn.CONCAT(F11,".",G11)),H11) -> x212.ASPU | K11: =_xlfn.CONCAT("C Torney-",E11,"-",B11) -> C Torney-welding test supervisor accomadation-Mid City Hotel Ballar BALLARAT CE AUS | L11: I | M11: =IF(C11>0,C11,-D11) -> 30.49 | N11: T
A12: 19/10/2025 | B12: Mid City Hotel Ballar BALLARAT CE AUS | C12: 127.25 | D12: 0 | E12: welding test supervisor accomadation | F12: x212 | G12: ASPU | J12: =IF(F12>0,(_xlfn.CONCAT(F12,".",G12)),H12) -> x212.ASPU | K12: =_xlfn.CONCAT("C Torney-",E12,"-",B12) -> C Torney-welding test supervisor accomadation-Mid City Hotel Ballar BALLARAT CE AUS | L12: I | M12: =IF(C12>0,C12,-D12) -> 127.25 | N12: T

Sheet M Trenorden
A1: Employee to code & narrate | J1: To be copied in to pronto
J2: Credit card Statement TOTAL | K2: 1339.8
J3: Subtotal | K3: =SUM(M8:M143) -> 0
J4: Variance Check | K4: =K2-K3 -> 1339.8
A5: Michael Trenorden
A6: Reference | B6: =CONCATENATE(Header!$E$4,"Trenorden") -> MC-251116Trenorden | J6: EMPLOYEES DO NOT CHANGE
A7: Document Date | B7: =Header!$E$5 -> 45977 | E7: Credit card holder to add details
A9: Date | B9: Narrative | C9: Debit Amount | D9: Credit Amount | E9: Description | F9: Project No | G9: Cost Category | H9: GL account | J9: Account | K9: Reference | L9: Tax | M9: Amount | N9: Tax CODE | O9: TAX Amount (leave blank) | P9: CBS - Only if required | R9: limit 56charaters
J10: =IF(F10>0,(_xlfn.CONCAT(F10,".",G10)),H10) -> 0 | K10: =_xlfn.CONCAT("MTrenorden-",B10,"-",E10) -> MTrenorden-- | L10: I | M10: =IF(C10>0,C10,-D10) -> 0 | N10: T | Q10: CBS - needs to be pasted seperately | R10: =LEN(K10) -> 12

Sheet B Tuncks
A1: Employee to code & narrate | J1: To be copied in to pronto
J2: Credit card Statement TOTAL | K2: 1833.51
J3: Subtotal | K3: =SUM(M8:M143) -> 1833.51
J4: Variance Check | K4: =K2-K3 -> 0
A5: Barry Tuncks
A6: Reference | B6: =CONCATENATE(Header!$E$4,"Tuncks") -> MC-251116Tuncks | J6: EMPLOYEES DO NOT CHANGE
A7: Document Date | B7: =Header!$E$5 -> 45977 | E7: Credit card holder to add details
A9: Date | B9: Narrative | C9: Debit Amount | D9: Credit Amount | E9: Description | F9: Project No | G9: Cost Category | H9: GL account | J9: Account | K9: Reference | L9: Tax | M9: Amount | N9: Tax CODE | O9: TAX Amount (leave blank) | P9: CBS - Only if required | R9: limit 56charaters
A10: 45971 | B10: FLUENTPRO SOFTWARE REDMOND USA FRGN AMT: 5.48 U. S. DOLLAR | C10: 8.7 | D10: 0 | E10: Asana Backup subscription | F10: 1084 | G10: ITSW | J10: =IF(F10>0,(_xlfn.CONCAT(F10,".",G10)),H10) -> 1084.ITSW | K10: =_xlfn.CONCAT("B Tuncks-",E10,"-",B10) -> B Tuncks-Asana Backup subscription-FLUENTPRO SOFTWARE REDMOND USA FRGN AMT: 5.48 U. S. DOLLAR | L10: I | M10: =IF(C10>0,C10,-D10) -> 8.7 | N10: F | Q10: CBS - needs to be pasted seperately | R10: =LEN(K10) -> 94
A11: 45957 | B11: MSFT * E0400XKMI1 Sydney AUS | C11: 13.2 | D11: 0 | E11: Gaia M365 subscriptions | F11: 1060GE2 | G11: MISC | J11: =IF(F11>0,(_xlfn.CONCAT(F11,".",G11)),H11) -> 1060GE2.MISC | K11: =_xlfn.CONCAT("B Tuncks-",E11,"-",B11) -> B Tuncks-Gaia M365 subscriptions-MSFT * E0400XKMI1 Sydney AUS | L11: I | M11: =IF(C11>0,C11,-D11) -> 13.2 | N11: T | Q11: CBS - needs to be pasted seperately | R11: =LEN(K11) -> 61
A12: 45957 | B12: MSFT+*+E0400XKMI0 Sydney AUS | C12: 14.85 | D12: 0 | E12: Gaia M365 subscriptions | F12: 1060GE2 | G12: MISC | J12: =IF(F12>0,(_xlfn.CONCAT(F12,".",G12)),H12) -> 1060GE2.MISC | K12: =_xlfn.CONCAT("B Tuncks-",E12,"-",B12) -> B Tuncks-Gaia M365 subscriptions-MSFT+*+E0400XKMI0 Sydney AUS | L12: I | M12: =IF(C12>0,C12,-D12) -> 14.85 | N12: T | Q12: CBS - needs to be pasted seperately | R12: =LEN(K12) -> 61
A13: 45957 | B13: SMTP2GO, I* SMTP2GO EM KELLER USA FRGN AMT: 15.00 U. S. DOLLAR | C13: 23.73 | D13: 0 | E13: Email Relay service. | F13: 1084 | G13: ITSW | J13: =IF(F13>0,(_xlfn.CONCAT(F13,".",G13)),H13) -> 1084.ITSW | K13: =_xlfn.CONCAT("B Tuncks-",E13,"-",B13) -> B Tuncks-Email Relay service.-SMTP2GO, I* SMTP2GO EM KELLER USA FRGN AMT: 15.00 U. S. DOLLAR | L13: I | M13: =IF(C13>0,C13,-D13) -> 23.73 | N13: F | Q13: CBS - needs to be pasted seperately | R13: =LEN(K13) -> 93
A14: 45952 | B14: 1PASSWORD TORONTO CAN FRGN AMT: 21.95 U. S. DOLLAR | C14: 34.89 | D14: 0 | E14: Password manager subscription | F14: 1084 | G14: ITSW | J14: =IF(F14>0,(_xlfn.CONCAT(F14,".",G14)),H14) -> 1084.ITSW | K14: =_xlfn.CONCAT("B Tuncks-",E14,"-",B14) -> B Tuncks-Password manager subscription-1PASSWORD TORONTO CAN FRGN AMT: 21.95 U. S. DOLLAR | L14: I | M14: =IF(C14>0,C14,-D14) -> 34.89 | N14: F | Q14: CBS - needs to be pasted seperately | R14: =LEN(K14) -> 90
A15: 45957 | B15: MSFT * E0400XKTVZ Sydney AUS | C15: 46.2 | D15: 0 | E15: Gaia M365 subscriptions | F15: 1060GE2 | G15: MISC | J15: =IF(F15>0,(_xlfn.CONCAT(F15,".",G15)),H15) -> 1060GE2.MISC | K15: =_xlfn.CONCAT("B Tuncks-",E15,"-",B15) -> B Tuncks-Gaia M365 subscriptions-MSFT * E0400XKTVZ Sydney AUS | L15: I | M15: =IF(C15>0,C15,-D15) -> 46.2 | N15: T | Q15: CBS - needs to be pasted seperately | R15: =LEN(K15) -> 61
A16: 45957 | B16: MSFT * E0400XKSKZ Sydney AUS | C16: 69.3 | D16: 0 | E16: Gaia M365 subscriptions | F16: 1060GE2 | G16: MISC | J16: =IF(F16>0,(_xlfn.CONCAT(F16,".",G16)),H16) -> 1060GE2.MISC | K16: =_xlfn.CONCAT("B Tuncks-",E16,"-",B16) -> B Tuncks-Gaia M365 subscriptions-MSFT * E0400XKSKZ Sydney AUS | L16: I | M16: =IF(C16>0,C16,-D16) -> 69.3 | N16: T | Q16: CBS - needs to be pasted seperately | R16: =LEN(K16) -> 61
A17: 45956 | B17: PAYPAL *ADOBESYSTEM 4029357733 AUS | C17: 75.99 | D17: 0 | E17: Adobe Acrobat PDF Editor x2 | F17: 1084 | G17: ITSW | J17: =IF(F17>0,(_xlfn.CONCAT(F17,".",G17)),H17) -> 1084.ITSW | K17: =_xlfn.CONCAT("B Tuncks-",E17,"-",B17) -> B Tuncks-Adobe Acrobat PDF Editor x2-PAYPAL *ADOBESYSTEM 4029357733 AUS | L17: I | M17: =IF(C17>0,C17,-D17) -> 75.99 | N17: T | Q17: CBS - needs to be pasted seperately | R17: =LEN(K17) -> 71
A18: 45972 | B18: PAYPAL *CLOUDFLARE 4029357733 USA | C18: 82.75 | D18: 0 | E18: Website Domain and security | F18: 1084 | G18: ITSW | J18: =IF(F18>0,(_xlfn.CONCAT(F18,".",G18)),H18) -> 1084.ITSW | K18: =_xlfn.CONCAT("B Tuncks-",E18,"-",B18) -> B Tuncks-Website Domain and security-PAYPAL *CLOUDFLARE 4029357733 USA | L18: I | M18: =IF(C18>0,C18,-D18) -> 82.75 | N18: T | Q18: CBS - needs to be pasted seperately | R18: =LEN(K18) -> 70
A19: 45957 | B19: MSFT * E0400XKKR8 Sydney AUS | C19: 99 | D19: 0 | E19: Gaia M365 subscriptions | F19: 1060GE2 | G19: MISC | J19: =IF(F19>0,(_xlfn.CONCAT(F19,".",G19)),H19) -> 1060GE2.MISC | K19: =_xlfn.CONCAT("B Tuncks-",E19,"-",B19) -> B Tuncks-Gaia M365 subscriptions-MSFT * E0400XKKR8 Sydney AUS | L19: I | M19: =IF(C19>0,C19,-D19) -> 99 | N19: T | Q19: CBS - needs to be pasted seperately | R19: =LEN(K19) -> 61
A20: 45971 | B20: DATACHANT HIGHLAND PA USA FRGN AMT: 100.00 U. S. DOLLAR | C20: 158.8 | D20: 0 | E20: Projects Tools | F20: 1084 | G20: ITSW | J20: =IF(F20>0,(_xlfn.CONCAT(F20,".",G20)),H20) -> 1084.ITSW | K20: =_xlfn.CONCAT("B Tuncks-",E20,"-",B20) -> B Tuncks-Projects Tools-DATACHANT HIGHLAND PA USA FRGN AMT: 100.00 U. S. DOLLAR | L20: I | M20: =IF(C20>0,C20,-D20) -> 158.8 | N20: F | Q20: CBS - needs to be pasted seperately | R20: =LEN(K20) -> 80
A21: 45972 | B21: INTRUDER.IO PRO LONDON GBR FRGN AMT: 263.67 U. S. DOLLAR | C21: 417.04 | D21: 0 | E21: Cyber Security scanner | F21: 1084 | G21: ITSW | J21: =IF(F21>0,(_xlfn.CONCAT(F21,".",G21)),H21) -> 1084.ITSW | K21: =_xlfn.CONCAT("B Tuncks-",E21,"-",B21) -> B Tuncks-Cyber Security scanner-INTRUDER.IO PRO LONDON GBR FRGN AMT: 263.67 U. S. DOLLAR | L21: I | M21: =IF(C21>0,C21,-D21) -> 417.04 | N21: F | Q21: CBS - needs to be pasted seperately | R21: =LEN(K21) -> 89
A22: 45957 | B22: MSFT * E0400XKTW0 Sydney AUS | C22: 542.85 | D22: 0 | E22: Gaia M365 subscriptions | F22: 1060GE2 | G22: MISC | J22: =IF(F22>0,(_xlfn.CONCAT(F22,".",G22)),H22) -> 1060GE2.MISC | K22: =_xlfn.CONCAT("B Tuncks-",E22,"-",B22) -> B Tuncks-Gaia M365 subscriptions-MSFT * E0400XKTW0 Sydney AUS | L22: I | M22: =IF(C22>0,C22,-D22) -> 542.85 | N22: T | Q22: CBS - needs to be pasted seperately | R22: =LEN(K22) -> 61
A23: 45944 | B23: fluentpro software redmond usa US 50.00 | C23: 79.98 | D23: 0 | E23: Asana Backup subscription | F23: 1084 | G23: ITSW | J23: =IF(F23>0,(_xlfn.CONCAT(F23,".",G23)),H23) -> 1084.ITSW | K23: =_xlfn.CONCAT("B Tuncks-",E23,"-",B23) -> B Tuncks-Asana Backup subscription-fluentpro software redmond usa US 50.00 | L23: I | M23: =IF(C23>0,C23,-D23) -> 79.98 | N23: F | Q23: CBS - needs to be pasted seperately | R23: =LEN(K23) -> 74
A24: 45945 | B24: onesimcard.com belomnt usa US 103.90 | C24: 166.23 | D24: 0 | E24: Machine Data Ops Macraes | F24: CS007-D | G24: REMS | J24: =IF(F24>0,(_xlfn.CONCAT(F24,".",G24)),H24) -> CS007-D.REMS | K24: =_xlfn.CONCAT("B Tuncks-",E24,"-",B24) -> B Tuncks-Machine Data Ops Macraes-onesimcard.com belomnt usa US 103.90 | L24: I | M24: =IF(C24>0,C24,-D24) -> 166.23 | N24: F | Q24: CBS - needs to be pasted seperately | R24: =LEN(K24) -> 70

Sheet L VanKollenburg
A1: Employee to code & narrate | J1: To be copied in to pronto
J2: Credit card Statement TOTAL | K2: 801.18
J3: Subtotal | K3: =SUM(M8:M143) -> 801.18
J4: Variance Check | K4: =K2-K3 -> 0
A5: Leon VanKollenburg
A6: Reference | B6: =CONCATENATE(Header!$E$4,"VanKollenburg") -> MC-251116VanKollenburg | J6: EMPLOYEES DO NOT CHANGE
A7: Document Date | B7: =Header!$E$5 -> 45977 | E7: Credit card holder to add details
A9: Date | B9: Narrative | C9: Debit Amount | D9: Credit Amount | E9: Description | F9: Project No | G9: Cost Category | H9: GL account | J9: Account | K9: Reference | L9: Tax | M9: Amount | N9: Tax CODE | O9: TAX Amount (leave blank) | P9: CBS - Only if required | R9: limit 56charaters
A10: 45963 | B10: BP IDALIA 5707 TOWNSVILLE AUS | C10: 6 | D10: 0 | E10: drinking water | F10: S16717 | G10: TRVP | J10: =IF(F10>0,(_xlfn.CONCAT(F10,".",G10)),H10) -> S16717.TRVP | K10: =_xlfn.CONCAT("L VanKollenburg-",E10,"-",B10) -> L VanKollenburg-drinking water-BP IDALIA 5707 TOWNSVILLE AUS | L10: I | M10: =IF(C10>0,C10,-D10) -> 6 | N10: T | Q10: CBS - needs to be pasted seperately | R10: =LEN(K10) -> 60
A11: 45965 | B11: Relay Garbutt AUS | C11: 6.38 | D11: 0 | E11: drinking water | F11: S16717 | G11: TRAV | J11: =IF(F11>0,(_xlfn.CONCAT(F11,".",G11)),H11) -> S16717.TRAV | K11: =_xlfn.CONCAT("L VanKollenburg-",E11,"-",B11) -> L VanKollenburg-drinking water-Relay Garbutt AUS | L11: I | M11: =IF(C11>0,C11,-D11) -> 6.38 | N11: T | Q11: CBS - needs to be pasted seperately | R11: =LEN(K11) -> 48
A12: 45963 | B12: MCDONALDS NORTH WARD TOWNSVILLE AUS | C12: 9.95 | D12: 0 | E12: breakfast | F12: S16718 | G12: TRAV | J12: =IF(F12>0,(_xlfn.CONCAT(F12,".",G12)),H12) -> S16718.TRAV | K12: =_xlfn.CONCAT("L VanKollenburg-",E12,"-",B12) -> L VanKollenburg-breakfast-MCDONALDS NORTH WARD TOWNSVILLE AUS | L12: I | M12: =IF(C12>0,C12,-D12) -> 9.95 | N12: T | Q12: CBS - needs to be pasted seperately | R12: =LEN(K12) -> 61
A13: 45965 | B13: ZLR*BDNEWST Brisbane Ai AUS | C13: 10.04 | D13: 0 | E13: Lunch at airport | F13: S16718 | G13: TRAV | J13: =IF(F13>0,(_xlfn.CONCAT(F13,".",G13)),H13) -> S16718.TRAV | K13: =_xlfn.CONCAT("L VanKollenburg-",E13,"-",B13) -> L VanKollenburg-Lunch at airport-ZLR*BDNEWST Brisbane Ai AUS | L13: I | M13: =IF(C13>0,C13,-D13) -> 10.04 | N13: T | Q13: CBS - needs to be pasted seperately | R13: =LEN(K13) -> 60
A14: 45964 | B14: Quest Townsville on North Ward AUS | C14: 10.13 | D14: 0 | E14: parking at hotel | F14: S16718 | G14: TRAV | J14: =IF(F14>0,(_xlfn.CONCAT(F14,".",G14)),H14) -> S16718.TRAV | K14: =_xlfn.CONCAT("L VanKollenburg-",E14,"-",B14) -> L VanKollenburg-parking at hotel-Quest Townsville on North Ward AUS | L14: I | M14: =IF(C14>0,C14,-D14) -> 10.13 | N14: T | Q14: CBS - needs to be pasted seperately | R14: =LEN(K14) -> 67
A15: 45962 | B15: SO OPERATIONS AUST PTY BRISBANE AI AUS | C15: 12.5 | D15: 0 | E15: Lunch at airport | F15: S16718 | G15: TRAV | J15: =IF(F15>0,(_xlfn.CONCAT(F15,".",G15)),H15) -> S16718.TRAV | K15: =_xlfn.CONCAT("L VanKollenburg-",E15,"-",B15) -> L VanKollenburg-Lunch at airport-SO OPERATIONS AUST PTY BRISBANE AI AUS | L15: I | M15: =IF(C15>0,C15,-D15) -> 12.5 | N15: T | Q15: CBS - needs to be pasted seperately | R15: =LEN(K15) -> 71
A16: 45964 | B16: SQ *RAVENSWOOD PO STOR Ravenswood AUS | C16: 13.7 | D16: 0 | E16: Drink and Snack leaving site | F16: S16718 | G16: TRAV | J16: =IF(F16>0,(_xlfn.CONCAT(F16,".",G16)),H16) -> S16718.TRAV | K16: =_xlfn.CONCAT("L VanKollenburg-",E16,"-",B16) -> L VanKollenburg-Drink and Snack leaving site-SQ *RAVENSWOOD PO STOR Ravenswood AUS | L16: I | M16: =IF(C16>0,C16,-D16) -> 13.7 | N16: T | Q16: CBS - needs to be pasted seperately | R16: =LEN(K16) -> 82
A17: 45965 | B17: ZLR*THE LOCAL Brisbane Ai AUS | C17: 17.5 | D17: 0 | E17: Lunch at airport | F17: S16718 | G17: TRAV | J17: =IF(F17>0,(_xlfn.CONCAT(F17,".",G17)),H17) -> S16718.TRAV | K17: =_xlfn.CONCAT("L VanKollenburg-",E17,"-",B17) -> L VanKollenburg-Lunch at airport-ZLR*THE LOCAL Brisbane Ai AUS | L17: I | M17: =IF(C17>0,C17,-D17) -> 17.5 | N17: T | Q17: CBS - needs to be pasted seperately | R17: =LEN(K17) -> 62
A18: 45962 | B18: Icons Melbourne A AUS | C18: 21.11 | D18: 0 | E18: Coffee and Lunch at airport | F18: S16718 | G18: TRAV | J18: =IF(F18>0,(_xlfn.CONCAT(F18,".",G18)),H18) -> S16718.TRAV | K18: =_xlfn.CONCAT("L VanKollenburg-",E18,"-",B18) -> L VanKollenburg-Coffee and Lunch at airport-Icons Melbourne A AUS | L18: I | M18: =IF(C18>0,C18,-D18) -> 21.11 | N18: T | Q18: CBS - needs to be pasted seperately | R18: =LEN(K18) -> 65
A19: 45963 | B19: TOWNSVILLE 132227 HYDE PARK C AUS | C19: 25.41 | D19: 0 | E19: Taxi to airport | F19: S16718 | G19: TRAV | J19: =IF(F19>0,(_xlfn.CONCAT(F19,".",G19)),H19) -> S16718.TRAV | K19: =_xlfn.CONCAT("L VanKollenburg-",E19,"-",B19) -> L VanKollenburg-Taxi to airport-TOWNSVILLE 132227 HYDE PARK C AUS | L19: I | M19: =IF(C19>0,C19,-D19) -> 25.41 | N19: T | Q19: CBS - needs to be pasted seperately | R19: =LEN(K19) -> 65
A20: 45965 | B20: JULIETTE'S L0184 NORTH WARD AUS | C20: 25.78 | D20: 0 | E20: Breakfast | F20: S16718 | G20: TRAV | J20: =IF(F20>0,(_xlfn.CONCAT(F20,".",G20)),H20) -> S16718.TRAV | K20: =_xlfn.CONCAT("L VanKollenburg-",E20,"-",B20) -> L VanKollenburg-Breakfast-JULIETTE'S L0184 NORTH WARD AUS | L20: I | M20: =IF(C20>0,C20,-D20) -> 25.78 | N20: T | Q20: CBS - needs to be pasted seperately | R20: =LEN(K20) -> 61
A21: 45964 | B21: SQ *HAROLD SEAFOOD ON North Ward AUS | C21: 26.31 | D21: 0 | E21: Dinner | F21: S16718 | G21: TRAV | J21: =IF(F21>0,(_xlfn.CONCAT(F21,".",G21)),H21) -> S16718.TRAV | K21: =_xlfn.CONCAT("L VanKollenburg-",E21,"-",B21) -> L VanKollenburg-Dinner-SQ *HAROLD SEAFOOD ON North Ward AUS | L21: I | M21: =IF(C21>0,C21,-D21) -> 26.31 | N21: T | Q21: CBS - needs to be pasted seperately | R21: =LEN(K21) -> 59
... A29: 45950 | B29: BOC GAS AND GEAR BALLARAT WE AUS | C29: 85.56 | D29: 0 | E29: dry ice | F29: x165-07 | G29: aspu | J29: =IF(F29>0,(_xlfn.CONCAT(F29,".",G29)),H29) -> x165-07.aspu | K29: =_xlfn.CONCAT("L VanKollenburg-",E29,"-",B29) -> L VanKollenburg-dry ice-BOC GAS AND GEAR BALLARAT WE AUS | L29: I | M29: =IF(C29>0,C29,-D29) -> 85.56 | N29: T | Q29: CBS - needs to be pasted seperately | R29: =LEN(K29) -> 56
A30: 45952 | B30: FIFTEEN NEEDLES GROUP WENDOUREE AUS | C30: 123.2 | D30: 0 | E30: work pants | F30: 1073 | G30: unif | J30: =IF(F30>0,(_xlfn.CONCAT(F30,".",G30)),H30) -> 1073.unif | K30: =_xlfn.CONCAT("L VanKollenburg-",E30,"-",B30) -> L VanKollenburg-work pants-FIFTEEN NEEDLES GROUP WENDOUREE AUS | L30: I | M30: =IF(C30>0,C30,-D30) -> 123.2 | N30: T | Q30: CBS - needs to be pasted seperately | R30: =LEN(K30) -> 62
A31: 45952 | B31: FIFTEEN NEEDLES GROUP SMYTHES CRE AUS | C31: 123.2 | D31: 0 | E31: work pants | F31: 1073 | G31: unif | J31: =IF(F31>0,(_xlfn.CONCAT(F31,".",G31)),H31) -> 1073.unif | K31: =_xlfn.CONCAT("L VanKollenburg-",E31,"-",B31) -> L VanKollenburg-work pants-FIFTEEN NEEDLES GROUP SMYTHES CRE AUS | L31: I | M31: =IF(C31>0,C31,-D31) -> 123.2 | N31: T | Q31: CBS - needs to be pasted seperately | R31: =LEN(K31) -> 64

Sheet B Wraith
A1: Employee to code & narrate | J1: To be copied in to pronto
J2: Credit card Statement TOTAL | K2: 466.08
J3: Subtotal | K3: =SUM(M8:M143) -> 466.08
J4: Variance Check | K4: =K2-K3 -> 0
A5: Ben Wraith
A6: Reference | B6: =CONCATENATE(Header!$E$4,"Wraith") -> MC-251116Wraith | J6: EMPLOYEES DO NOT CHANGE
A7: Document Date | B7: =Header!$E$5 -> 45977 | E7: Credit card holder to add details
A9: Date | B9: Narrative | C9: Debit Amount | D9: Credit Amount | E9: Description | F9: Project No | G9: Cost Category | H9: GL account | J9: Account | K9: Reference | L9: Tax | M9: Amount | N9: Tax CODE | O9: TAX Amount (leave blank) | P9: CBS - Only if required | R9: limit 56charaters
A10: 45950 | B10: AUSIMM CARLTON AUS | C10: 20 | D10: 0 | E10: Attendance for MetFest Victoria | F10: G119-05 | G10: SALP | J10: =IF(F10>0,(_xlfn.CONCAT(F10,".",G10)),H10) -> G119-05.SALP | K10: =_xlfn.CONCAT("B Wraith-",E10,"-",B10) -> B Wraith-Attendance for MetFest Victoria-AUSIMM CARLTON AUS | L10: I | M10: =IF(C10>0,C10,-D10) -> 20 | N10: T | Q10: CBS - needs to be pasted seperately | R10: =LEN(K10) -> 59
A11: 45953 | B11: BENDIGO HOTEL FUND OP BENDIGO AUS | C11: 23.85 | D11: 0 | E11: Meals and Entertainment with non Gekko employees | F11: G119-05 | G11: SALP | J11: =IF(F11>0,(_xlfn.CONCAT(F11,".",G11)),H11) -> G119-05.SALP | K11: =_xlfn.CONCAT("B Wraith-",E11,"-",B11) -> B Wraith-Meals and Entertainment with non Gekko employees-BENDIGO HOTEL FUND OP BENDIGO AUS | L11: I | M11: =IF(C11>0,C11,-D11) -> 23.85 | N11: T | Q11: CBS - needs to be pasted seperately | R11: =LEN(K11) -> 91
A12: 45954 | B12: THE DECK BENDIGO BENDIGO AUS | C12: 36.54 | D12: 0 | E12: Meals and Entertainment with non Gekko employees | F12: G119-05 | G12: SALP | J12: =IF(F12>0,(_xlfn.CONCAT(F12,".",G12)),H12) -> G119-05.SALP | K12: =_xlfn.CONCAT("B Wraith-",E12,"-",B12) -> B Wraith-Meals and Entertainment with non Gekko employees-THE DECK BENDIGO BENDIGO AUS | L12: I | M12: =IF(C12>0,C12,-D12) -> 36.54 | N12: T | Q12: CBS - needs to be pasted seperately | R12: =LEN(K12) -> 86
A13: 45950 | B13: AUSIMM CARLTON AUS | C13: 40 | D13: 0 | E13: Attendance for MetFest Victoria | F13: G119-05 | G13: SALP | J13: =IF(F13>0,(_xlfn.CONCAT(F13,".",G13)),H13) -> G119-05.SALP | K13: =_xlfn.CONCAT("B Wraith-",E13,"-",B13) -> B Wraith-Attendance for MetFest Victoria-AUSIMM CARLTON AUS | L13: I | M13: =IF(C13>0,C13,-D13) -> 40 | N13: T | Q13: CBS - needs to be pasted seperately | R13: =LEN(K13) -> 59
A14: 45954 | B14: BENDIGO HOTEL FUND OP BENDIGO AUS | C14: 42.68 | D14: 0 | E14: Meals and Entertainment with NG and non Gekko employees | F14: G119-05 | G14: SALP | J14: =IF(F14>0,(_xlfn.CONCAT(F14,".",G14)),H14) -> G119-05.SALP | K14: =_xlfn.CONCAT("B Wraith-",E14,"-",B14) -> B Wraith-Meals and Entertainment with NG and non Gekko employees-BENDIGO HOTEL FUND OP BENDIGO AUS | L14: I | M14: =IF(C14>0,C14,-D14) -> 42.68 | N14: T | Q14: CBS - needs to be pasted seperately | R14: =LEN(K14) -> 98
A15: 45953 | B15: THE DECK BENDIGO BENDIGO AUS | C15: 68.01 | D15: 0 | E15: Meals and Entertainment with non Gekko employees | F15: G119-05 | G15: SALP | J15: =IF(F15>0,(_xlfn.CONCAT(F15,".",G15)),H15) -> G119-05.SALP | K15: =_xlfn.CONCAT("B Wraith-",E15,"-",B15) -> B Wraith-Meals and Entertainment with non Gekko employees-THE DECK BENDIGO BENDIGO AUS | L15: I | M15: =IF(C15>0,C15,-D15) -> 68.01 | N15: T | Q15: CBS - needs to be pasted seperately | R15: =LEN(K15) -> 86
A16: 45953 | B16: BENDIGO HOTEL FUND OP BENDIGO AUS | C16: 235 | D16: 0 | E16: Accomodation for MetFest Victoria | F16: G119-05 | G16: SALP | J16: =IF(F16>0,(_xlfn.CONCAT(F16,".",G16)),H16) -> G119-05.SALP | K16: =_xlfn.CONCAT("B Wraith-",E16,"-",B16) -> B Wraith-Accomodation for MetFest Victoria-BENDIGO HOTEL FUND OP BENDIGO AUS | L16: I | M16: =IF(C16>0,C16,-D16) -> 235 | N16: T | Q16: CBS - needs to be pasted seperately | R16: =LEN(K16) -> 76

Sheet N Zhang
A1: Employee to code & narrate | J1: To be copied in to pronto
J2: Credit card Statement TOTAL | K2: 275
J3: Subtotal | K3: =SUM(M8:M147) -> 275
J4: Variance Check | K4: =K2-K3 -> 0
A5: Nick Zhang
A6: Reference | B6: =CONCATENATE(Header!$E$4,"Zhang") -> MC-251116Zhang | J6: EMPLOYEES DO NOT CHANGE
A7: Document Date | B7: =Header!$E$5 -> 45977 | E7: Credit card holder to add details
A9: Date | B9: Narrative | C9: Debit Amount | D9: Credit Amount | E9: Description | F9: Project No | G9: Cost Category | H9: GL account | J9: Account | K9: Reference | L9: Tax | M9: Amount | N9: Tax CODE | O9: TAX Amount (leave blank) | P9: CBS - Only if required | R9: limit 56charaters
A10: 45952 | B10: RISK MANAGEMENT TECHNO WEST PERTH AUS | C10: 275 | D10: 0 | E10: SDS Creation | F10: 1053 | G10: OTHE | J10: =IF(F10>0,(_xlfn.CONCAT(F10,".",G10)),H10) -> 1053.OTHE | K10: =_xlfn.CONCAT("N Zhang-",E10,"-",B10) -> N Zhang-SDS Creation-RISK MANAGEMENT TECHNO WEST PERTH AUS | L10: I | M10: =IF(C10>0,C10,-D10) -> 275 | N10: T | Q10: CBS - needs to be pasted seperately | R10: =LEN(K10) -> 58

Sheet Full Data
B1: Bank Account | C1: Date | D1: Narrative | E1: Debit Amount | F1: Credit Amount | J1: Card Number | K1: Name
A2: =VLOOKUP(B2,$J$2:$K$33,2,FALSE) -> Barclay | B2: 6341 | C2: 45958 | D2: BUNNINGS 329000 DELACOMBE AUS | E2: 49 | J2: 6547 | K2: Baker
A3: =VLOOKUP(B3,$J$2:$K$33,2,FALSE) -> Barclay | B3: 6341 | C3: 45961 | D3: WOOLWORTHS 3066 ALFREDTON AUS | E3: 114.76 | J3: 6341 | K3: Barclay
A4: =VLOOKUP(B4,$J$2:$K$33,2,FALSE) -> Barclay | B4: 6341 | C4: 45968 | D4: Ink Station SYDNEY AUS | E4: 26.55 | J4: 4137 | K4: Bell
A5: =VLOOKUP(B5,$J$2:$K$33,2,FALSE) -> Barclay | B5: 6341 | C5: 45975 | D5: OFFICEWORKS 0364 BALLARAT AUS | E5: 47.17 | J5: 7173 | K5: Brown
A6: =VLOOKUP(B6,$J$2:$K$33,2,FALSE) -> Bell | B6: 4137 | C6: 45946 | D6: LEEDERVILLE MINI MAR LEEDERVILLE AUS | E6: 2.97 | J6: 4265 | K6: Conroy
A7: =VLOOKUP(B7,$J$2:$K$33,2,FALSE) -> Bell | B7: 4137 | C7: 45946 | D7: SQ *NOURISH KITCHEN & Leederville AUS | E7: 13.9 | J7: 7718 | K7: Delemontex
A8: =VLOOKUP(B8,$J$2:$K$33,2,FALSE) -> Bell | B8: 4137 | C8: 45948 | D8: KATHMANDU PTY LTD SUCCESS AUS | E8: 83.99 | J8: 2571 | K8: Donadio
A9: =VLOOKUP(B9,$J$2:$K$33,2,FALSE) -> Bell | B9: 4137 | C9: 45949 | D9: SOUTH SIDE POOL SERVIC CANNING VAL AUS | E9: 100 | J9: 3601 | K9: DUva
A10: =VLOOKUP(B10,$J$2:$K$33,2,FALSE) -> Bell | B10: 4137 | C10: 45950 | D10: GYG Leederville Leederville AUS | E10: 65.5 | J10: 1694 | K10: Edmondston
A11: =VLOOKUP(B11,$J$2:$K$33,2,FALSE) -> Bell | B11: 4137 | C11: 45952 | D11: CELLARBRATIONS AT SHEL SHELLEY AUS | E11: 93 | J11: 3540 | K11: Gort
A12: =VLOOKUP(B12,$J$2:$K$33,2,FALSE) -> Bell | B12: 4137 | C12: 45953 | D12: ZLR*BABYLON CAFE Leederville AUS | E12: 10.1 | J12: 8338 | K12: Grigg
A13: =VLOOKUP(B13,$J$2:$K$33,2,FALSE) -> Bell | B13: 4137 | C13: 45954 | D13: CELLARBRATIONS AT SHEL SHELLEY AUS | E13: 30 | J13: 7601 | K13: Hughes
... A33: =VLOOKUP(B33,$J$2:$K$33,2,FALSE) -> Bell | B33: 4137 | C33: 45971 | D33: CASH ADVANCE FEE | E33: 5.93 | J33: 9087 | K33: Randell
A34: =VLOOKUP(B34,$J$2:$K$33,2,FALSE) -> Bell | B34: 4137 | C34: 45971 | D34: TT NET ANONIM STI ISTANBUL TUR FRGN AMT: 630.73 TURKISH LIRE | E34: 24.02
A35: =VLOOKUP(B35,$J$2:$K$33,2,FALSE) -> Bell | B35: 4137 | C35: 45971 | D35: UBER *TRIP HELP.UBER.C 14518236738 AUS | E35: 42.25
A36: =VLOOKUP(B36,$J$2:$K$33,2,FALSE) -> Bell | B36: 4137 | C36: 45971 | D36: CASH ADVANCE 010422312231127 NTALYA TUR | E36: 203.58
A37: =VLOOKUP(B37,$J$2:$K$33,2,FALSE) -> Bell | B37: 4137 | C37: 45974 | D37: 7 MEHMET RESTAURANT ANTALYA TUR FRGN AMT: 3960.00 TURKISH LIRE | E37: 148.83
A38: =VLOOKUP(B38,$J$2:$K$33,2,FALSE) -> Bell | B38: 4137 | C38: 45977 | D38: INTEREST CHARGES - CAS H | E38: 0.8
A39: =VLOOKUP(B39,$J$2:$K$33,2,FALSE) -> Brown | B39: 7173 | C39: 45946 | D39: RSEA PTY. LTD. BALLARAT CE AUS | E39: 29.99
A40: =VLOOKUP(B40,$J$2:$K$33,2,FALSE) -> Brown | B40: 7173 | C40: 45946 | D40: TOTAL TOOLS BALLARAT BALLARAT AUS | E40: 139
A41: =VLOOKUP(B41,$J$2:$K$33,2,FALSE) -> Brown | B41: 7173 | C41: 45947 | D41: BUNNINGS 730000 BALLARAT AUS | E41: 109.85
A42: =VLOOKUP(B42,$J$2:$K$33,2,FALSE) -> Brown | B42: 7173 | C42: 45952 | D42: Reddy Express 6744 Ballarat AUS | E42: 135.14
A43: =VLOOKUP(B43,$J$2:$K$33,2,FALSE) -> Brown | B43: 7173 | C43: 45957 | D43: Jaycar Ballarat Ballarat AUS | E43: 25
A44: =VLOOKUP(B44,$J$2:$K$33,2,FALSE) -> Brown | B44: 7173 | C44: 45957 | D44: BUNNINGS 329000 DELACOMBE AUS | E44: 67.86
A45: =VLOOKUP(B45,$J$2:$K$33,2,FALSE) -> Brown | B45: 7173 | C45: 45957 | D45: Industrial World BALLARAT AUS | E45: 381.1
... A154: =VLOOKUP(B154,$J$2:$K$33,2,FALSE) -> Jenkins | B154: 9020 | C154: 45974 | D154: TOTAL TOOLS BALLARAT BALLARAT AUS | E154: 78.25
A155: =VLOOKUP(B155,$J$2:$K$33,2,FALSE) -> Jenkins | B155: 9020 | C155: 45975 | D155: CRED VOUCHER Hotel at Booking.com Sydney AUS | F155: -369
A156: =VLOOKUP(B156,$J$2:$K$33,2,FALSE) -> Lewis Gray E | B156: 3599 | C156: 45955 | D156: QANTAS0812378083449 NSW AUS | E156: 1462.57
A157: =VLOOKUP(B157,$J$2:$K$33,2,FALSE) -> Lewis Gray E | B157: 3599 | C157: 45955 | D157: QANTAS0812378083448 NSW AUS | E157: 1462.57
A158: =VLOOKUP(B158,$J$2:$K$33,2,FALSE) -> Lewis Gray S | B158: 1929 | C158: 45949 | D158: ESTHER DE FIGUEIREDO Belo Horizo BRA FRGN AMT: 227.16 BRAZILIAN REAL | E158: 67.1
A159: =VLOOKUP(B159,$J$2:$K$33,2,FALSE) -> Lewis Gray S | B159: 1929 | C159: 45950 | D159: SPOLETO PATIO SAVASSI BELO HORIZO BRA FRGN AMT: 77.00 BRAZILIAN REAL | E159: 22.74
A160: =VLOOKUP(B160,$J$2:$K$33,2,FALSE) -> Lewis Gray S | B160: 1929 | C160: 45951 | D160: T9WEB SISTEMAS E INFOR BELO HORIZO BRA FRGN AMT: 5665.93 BRAZILIAN REAL | E160: 1680.71
A161: =VLOOKUP(B161,$J$2:$K$33,2,FALSE) -> Lewis Gray S | B161: 1929 | C161: 45953 | D161: RADISSON BLU BELO HORI BELO HORIZO BRA FRGN AMT: 117.90 BRAZILIAN REAL | E161: 34.9
A162: =VLOOKUP(B162,$J$2:$K$33,2,FALSE) -> Lewis Gray S | B162: 1929 | C162: 45953 | D162: ESTHER DE FIGUEIREDO Belo Horizo BRA FRGN AMT: 185.86 BRAZILIAN REAL | E162: 55.02
A163: =VLOOKUP(B163,$J$2:$K$33,2,FALSE) -> Lewis Gray S | B163: 1929 | C163: 45974 | D163: Post Perth AUS | E163: 184.69
A164: =VLOOKUP(B164,$J$2:$K$33,2,FALSE) -> Lodge H | B164: 5474 | C164: 45951 | D164: ONESIMCARD.COM BELMONT USA FRGN AMT: 103.90 U. S. DOLLAR | E164: 165.15
A165: =VLOOKUP(B165,$J$2:$K$33,2,FALSE) -> Lodge H | B165: 5474 | C165: 45951 | D165: ONESIMCARD.COM BELMONT USA FRGN AMT: 207.80 U. S. DOLLAR | E165: 330.29
A166: =VLOOKUP(B166,$J$2:$K$33,2,FALSE) -> Lodge H | B166: 5474 | C166: 45954 | D166: ANACONDA LAKE GARDEN AUS | E166: 33.98
A167: =VLOOKUP(B167,$J$2:$K$33,2,FALSE) -> Lodge H | B167: 5474 | C167: 45954 | D167: SydneyToolsDelacombe Delacombe AUS | E167: 54.95
... A295: =VLOOKUP(B295,$J$2:$K$33,2,FALSE) -> Zhang | B295: 6594 | C295: 45952 | D295: RISK MANAGEMENT TECHNO WEST PERTH AUS | E295: 275
B296: 1929 | C296: 45949 | D296: FOREIGN FEE AUD 1.95 FRGN AMT: 227.16 BRAZILIAN REAL | E296: 0
B297: 4138 | C297: 45949 | D297: FOREIGN FEE AUD 3.24 | E297: 0
B298: 4138 | C298: 45949 | D298: FOREIGN FEE AUD 0.52 FRGN AMT: 11.25 U. S. DOLLAR | E298: 0
B299: 8338 | C299: 45949 | D299: FOREIGN FEE AUD 0.93 FRGN AMT: 19.99 U. S. DOLLAR | E299: 0
B300: 1929 | C300: 45950 | D300: FOREIGN FEE AUD 0.66 FRGN AMT: 77.00 BRAZILIAN REAL | E300: 0
B301: 4138 | C301: 45950 | D301: FOREIGN FEE AUD 0.48 FRGN AMT: 56.00 BRAZILIAN REAL | E301: 0
B302: 4138 | C302: 45950 | D302: FOREIGN FEE AUD 1.05 FRGN AMT: 122.49 BRAZILIAN REAL | E302: 0
B303: 4138 | C303: 45950 | D303: FOREIGN FEE AUD 5.11 | E303: 0
B304: 1929 | C304: 45951 | D304: FOREIGN FEE AUD 48.95 FRGN AMT: 5665.93 BRAZILIAN REAL | E304: 0
B305: 4138 | C305: 45951 | D305: FOREIGN FEE AUD 0.62 FRGN AMT: 72.09 BRAZILIAN REAL | E305: 0
B306: 5474 | C306: 45951 | D306: FOREIGN FEE AUD 9.61 FRGN AMT: 207.80 U. S. DOLLAR | E306: 0
B307: 5474 | C307: 45951 | D307: FOREIGN FEE AUD 4.81 FRGN AMT: 103.90 U. S. DOLLAR | E307: 0
... B331: 5474 | C331: 45966 | D331: FOREIGN FEE AUD 1.11 | E331: 0
B332: 7173 | C332: 45967 | D332: C34626 TFR FROM Westpa c Busines | F332: 5000
B333: 2571 | C333: 45968 | D333: C02265 TFR FROM Westpa c Busines | F333: 5500
B334: 4137 | C334: 45970 | D334: FOREIGN FEE AUD 0.35 FRGN AMT: 9.90 SINGAPORE DOLLAR | E334: 0
B335: 4137 | C335: 45970 | D335: FOREIGN FEE AUD 1.38 FRGN AMT: 38.85 SINGAPORE DOLLAR | E335: 0
B336: 4137 | C336: 45970 | D336: FOREIGN FEE AUD 0.18 FRGN AMT: 3.99 U. S. DOLLAR | E336: 0
B337: 1431 | C337: 45971 | D337: FOREIGN FEE AUD 0.25 FRGN AMT: 5.48 U. S. DOLLAR | E337: 0
B338: 1431 | C338: 45971 | D338: FOREIGN FEE AUD 4.62 FRGN AMT: 100.00 U. S. DOLLAR | E338: 0
B339: 4137 | C339: 45971 | D339: FOREIGN FEE AUD 0.70 FRGN AMT: 630.73 TURKISH LIRE | E339: 0
B340: 4137 | C340: 45971 | D340: FOREIGN FEE AUD 5.92 | E340: 0
B341: 5474 | C341: 45971 | D341: FOREIGN FEE AUD 4.82 FRGN AMT: 103.90 U. S. DOLLAR | E341: 0
B342: 8761 | C342: 45971 | D342: FOREIGN FEE AUD 5.66 FRGN AMT: 122.01 U. S. DOLLAR | E342: 0
B343: 9020 | C343: 45971 | D343: C78349 TFR FROM Westpa c Busines | F343: 700
B344: 1431 | C344: 45972 | D344: FOREIGN FEE AUD 2.41 | E344: 0
B345: 1431 | C345: 45972 | D345: FOREIGN FEE AUD 12.14 FRGN AMT: 263.67 U. S. DOLLAR | E345: 0
B346: 6087 | C346: 45973 | D346: FOREIGN FEE AUD 7.87 FRGN AMT: 171.06 U. S. DOLLAR | E346: 0
B347: 2571 | C347: 45973 | D347: C91631 TFR FROM Westpa c Busines | F347: 3000
B348: 4137 | C348: 45974 | D348: FOREIGN FEE AUD 4.33 FRGN AMT: 3960.00 TURKISH LIRE | E348: 0
B349: 8761 | C349: 45974 | D349: FOREIGN FEE AUD 5.84 FRGN AMT: 126.91 U. S. DOLLAR | E349: 0
B350: 9087 | C350: 45975 | D350: C89454 TFR FROM Westpa c Busines | F350: 300
B351: 3599 | C351: 45977 | D351: PRINCIPAL CREDIT | F351: 2925.14
B352: 1929 | C352: 45977 | D352: PRINCIPAL CREDIT | F352: 2045.16
B353: 7601 | C353: 45977 | D353: PRINCIPAL CREDIT | F353: 261.91
B354: 2571 | C354: 45977 | D354: PRINCIPAL CREDIT | F354: 4783.13
B355: 4138 | C355: 45977 | D355: PRINCIPAL CREDIT | F355: 2156.94
B356: 3540 | C356: 45977 | D356: PRINCIPAL CREDIT | F356: 138.59
B357: 5635 | C357: 45977 | D357: PRINCIPAL CREDIT | F357: 300.19
B358: 1431 | C358: 45977 | D358: PRINCIPAL CREDIT | F358: 1833.51
B359: 8624 | C359: 45977 | D359: PRINCIPAL CREDIT | F359: 157.54
B360: 4137 | C360: 45977 | D360: SERVICE CHARGE CREDIT | F360: 5.93
B361: 4137 | C361: 45977 | D361: FINANCE CHARGE CREDIT | F361: 0.8
... B381: 8761 | C381: 45977 | D381: PRINCIPAL CREDIT | F381: 1712.76

Sheet Pronto layout
A1: Format for copy & paste of invoice
A3: Account | B3: Reference | C3: Tax | D3: Amount | E3: Tax CODE | F3: TAX Amount (leave blank) | G3: CBS
A4: 1051.CONS | B4: credit card import test | C4: I | D4: 900 | E4: T | G4: 1.3 | H4: CBS - needs to be pasted seperately
A5: 1084.PHON | B5: credit card import test | C5: I | D5: 450 | E5: F
A6: 110849995900 | B6: credit card import test | C6: I | D6: 600 | E6: T
A7: 199999991140 | B7: credit card import test | C7: I | D7: 50 | E7: F
A38: To find your job number & cost code category
A40: Log in to Pronto
A41: Select Reporting Portal
A42: Select Gekko Reporting
A43: Select GEK_Credit Card Code Lookup
A44: Find the relevant project code
A45: Select OK at the bottom of the screen
A46: Enter the Project number & the Cost Category into the relevant cells.
A47: If you cannot find the information you are after then leave it blank & let me know.
