Workbook
Name TAX: #REF!

Sheet Header
D2: Batch | E2: 20250816
D3: Batch Desc | E3: Mastercard Invoices (August 2025)
D4: Reference | E4: MC-250816
D5: Document Date | E5: 45885
D6: Posting Date | E6: =E5 -> 45885
E13: LOG IN DETAILS
D15: User | E15: eTimesheet User
D16: Password | E16: gekko

Sheet T Bell
A1: Employee to code & narrate | J1: To be copied in to pronto
J2: Credit card Statement TOTAL | K2: 3402.27
J3: Subtotal | K3: =SUM(M9:M144) -> 3402.27
A4: T Bell | J4: Variance Check | K4: =K2-K3 -> 0
A5: Reference | B5: =CONCATENATE(Header!$E$4,"Bell") -> MC-250816Bell | J5: EMPLOYEES DO NOT CHANGE
A6: Document Date | B6: =Header!$E$5 -> 45885 | E6: Credit card holder to add details
A8: Date | B8: Narrative | C8: Debit Amount | D8: Credit Amount | E8: Description | F8: Project No | G8: Cost Category | H8: GL account | J8: Account | K8: Reference | L8: Tax | M8: Amount | N8: Tax CODE | O8: TAX Amount (leave blank) | P8: CBS - Only if required | R8: limit 56charaters
A9: 45877 | B9: BELMONTS CAFE BELMONT AUS | C9: 108 | E9: Food for Lunch and Learn with GR Engineering | F9: 1084 | G9: ENFN | J9: =IF(F9>0,(_xlfn.CONCAT(F9,".",G9)),H9) -> 1084.ENFN | K9: =_xlfn.CONCAT("T Bell-",(LEFT(B9,15)),"-",E9) -> T Bell-BELMONTS CAFE B-Food for Lunch and Learn with GR Engineering | L9: I | M9: =IF(C9>0,C9,-D9) -> 108 | N9: T | Q9: CBS - needs to be pasted seperately | R9: =LEN(K9) -> 67
A10: 45876 | B10: BP GOLDEN GATE 1896 KALGOORLIE AUS | C10: 105.26 | E10: Diggers and Dealers - Petrol | F10: G077 | G10: SALP | J10: =IF(F10>0,(_xlfn.CONCAT(F10,".",G10)),H10) -> G077.SALP | K10: =_xlfn.CONCAT("T Bell-",(LEFT(B10,15)),"-",E10) -> T Bell-BP GOLDEN GATE -Diggers and Dealers - Petrol | L10: I | M10: =IF(C10>0,C10,-D10) -> 105.26 | N10: T | R10: =LEN(K10) -> 52
A11: 45876 | B11: BP STHERN CROS1932 SOUTHERN CR AUS | C11: 17.9 | E11: Diggers and Dealers - Food / Amenities | F11: G077 | G11: SALP | J11: =IF(F11>0,(_xlfn.CONCAT(F11,".",G11)),H11) -> G077.SALP | K11: =_xlfn.CONCAT("T Bell-",(LEFT(B11,15)),"-",E11) -> T Bell-BP STHERN CROS1-Diggers and Dealers - Food / Amenities | L11: I | M11: =IF(C11>0,C11,-D11) -> 17.9 | N11: T | R11: =LEN(K11) -> 61
A12: 45869 | B12: CHILDRENS MEDICAL RESE WESTMEAD AUS | C12: 27.81 | E12: Lycopodium Jeans for Genes - Extra Seat Charity Dinner | F12: 1041 | G12: CONF | J12: =IF(F12>0,(_xlfn.CONCAT(F12,".",G12)),H12) -> 1041.CONF | K12: =_xlfn.CONCAT("T Bell-",(LEFT(B12,15)),"-",E12) -> T Bell-CHILDRENS MEDIC-Lycopodium Jeans for Genes - Extra Seat Charity Dinner | L12: I | M12: =IF(C12>0,C12,-D12) -> 27.81 | N12: T | R12: =LEN(K12) -> 77
A13: 45879 | B13: DELAWARE NORTH RETAQPS REDCLIFFE AUS | C13: 6.9 | E13: Ballarat Sales Conference - Food / Amenities | F13: G068 | G13: SALP | J13: =IF(F13>0,(_xlfn.CONCAT(F13,".",G13)),H13) -> G068.SALP | K13: =_xlfn.CONCAT("T Bell-",(LEFT(B13,15)),"-",E13) -> T Bell-DELAWARE NORTH -Ballarat Sales Conference - Food / Amenities | L13: I | M13: =IF(C13>0,C13,-D13) -> 6.9 | N13: T | R13: =LEN(K13) -> 67
A14: 45873 | B14: Exchange Hotel Kalgoorlie AUS | C14: 211.63 | E14: Diggers and Dealers - Food / Amenities | F14: G077 | G14: SALP | J14: =IF(F14>0,(_xlfn.CONCAT(F14,".",G14)),H14) -> G077.SALP | K14: =_xlfn.CONCAT("T Bell-",(LEFT(B14,15)),"-",E14) -> T Bell-Exchange Hotel -Diggers and Dealers - Food / Amenities | L14: I | M14: =IF(C14>0,C14,-D14) -> 211.63 | N14: T | R14: =LEN(K14) -> 61
A15: 45855 | B15: FIBBER MCGEE 'S LEEDERVILLE AUS | C15: =26/2 -> 13 | E15: Catch up with Steffen, re testwork | F15: 1084 | G15: ENFE | J15: =IF(F15>0,(_xlfn.CONCAT(F15,".",G15)),H15) -> 1084.ENFE | K15: =_xlfn.CONCAT("T Bell-",(LEFT(B15,15)),"-",E15) -> T Bell-FIBBER MCGEE 'S-Catch up with Steffen, re testwork | L15: I | M15: =IF(C15>0,C15,-D15) -> 13 | N15: T | R15: =LEN(K15) -> 57
A16: 45855 | B16: FIBBER MCGEE 'S LEEDERVILLE AUS | C16: =26/2 -> 13 | E16: Catch up with Steffen, re testwork | F16: 1084 | G16: ENFN | J16: =IF(F16>0,(_xlfn.CONCAT(F16,".",G16)),H16) -> 1084.ENFN | K16: =_xlfn.CONCAT("T Bell-",(LEFT(B16,15)),"-",E16) -> T Bell-FIBBER MCGEE 'S-Catch up with Steffen, re testwork | L16: I | M16: =IF(C16>0,C16,-D16) -> 13 | N16: T | R16: =LEN(K16) -> 57
A17: 45854 | B17: GASTECH AUSTRALIA WANGARA AUS | C17: 907.5 | E17: 1 x HCN Detctor Service and 1 x new HCN Detector | F17: 1041 | G17: SPPE | J17: =IF(F17>0,(_xlfn.CONCAT(F17,".",G17)),H17) -> 1041.SPPE | K17: =_xlfn.CONCAT("T Bell-",(LEFT(B17,15)),"-",E17) -> T Bell-GASTECH AUSTRAL-1 x HCN Detctor Service and 1 x new HCN Detector | L17: I | M17: =IF(C17>0,C17,-D17) -> 907.5 | N17: T | R17: =LEN(K17) -> 71
A18: 45867 | B18: GOOD GROCER L0030 LEEDERVILLE AUS | C18: 19.48 | E18: Wednesday Lunch | F18: 1084 | G18: ENON | J18: =IF(F18>0,(_xlfn.CONCAT(F18,".",G18)),H18) -> 1084.ENON | K18: =_xlfn.CONCAT("T Bell-",(LEFT(B18,15)),"-",E18) -> T Bell-GOOD GROCER -Wednesday Lunch | L18: I | M18: =IF(C18>0,C18,-D18) -> 19.48 | N18: T | R18: =LEN(K18) -> 38
A19: 45859 | B19: GOOD GROCER L0030 LEEDERVILLE AUS | C19: 16.89 | E19: Coffee / Sugar | F19: 1084 | G19: STAF | J19: =IF(F19>0,(_xlfn.CONCAT(F19,".",G19)),H19) -> 1084.STAF | K19: =_xlfn.CONCAT("T Bell-",(LEFT(B19,15)),"-",E19) -> T Bell-GOOD GROCER -Coffee / Sugar | L19: I | M19: =IF(C19>0,C19,-D19) -> 16.89 | N19: T | R19: =LEN(K19) -> 37
A20: 45879 | B20: GRILL'D BALLARAT BALLARAT AUS | C20: 51.7 | E20: Ballarat Sales Conference - Food / Amenities | F20: G068 | G20: SALP | J20: =IF(F20>0,(_xlfn.CONCAT(F20,".",G20)),H20) -> G068.SALP | K20: =_xlfn.CONCAT("T Bell-",(LEFT(B20,15)),"-",E20) -> T Bell-GRILL'D BALLARA-Ballarat Sales Conference - Food / Amenities | L20: I | M20: =IF(C20>0,C20,-D20) -> 51.7 | N20: T | R20: =LEN(K20) -> 67
A21: 45860 | B21: GRILLD PTY LTD - LEEDE LEEDERVILLE AUS | C21: 89 | E21: Wednesday Lunch | F21: 1041 | G21: ENON | J21: =IF(F21>0,(_xlfn.CONCAT(F21,".",G21)),H21) -> 1041.ENON | K21: =_xlfn.CONCAT("T Bell-",(LEFT(B21,15)),"-",E21) -> T Bell-GRILLD PTY LTD -Wednesday Lunch | L21: I | M21: =IF(C21>0,C21,-D21) -> 89 | N21: T | R21: =LEN(K21) -> 38
A22: 45869 | B22: Kwik Kopy Canning Vale Canning Val AUS | C22: 165.33 | E22: Diggers and Dealers - Modular Plant Brochures | F22: G077 | G22: SALP | J22: =IF(F22>0,(_xlfn.CONCAT(F22,".",G22)),H22) -> G077.SALP | K22: =_xlfn.CONCAT("T Bell-",(LEFT(B22,15)),"-",E22) -> T Bell-Kwik Kopy Canni-Diggers and Dealers - Modular Plant Brochures | L22: I | M22: =IF(C22>0,C22,-D22) -> 165.33 | N22: T | R22: =LEN(K22) -> 68
A23: 45861 | B23: Kwik Kopy Canning Vale Canning Val AUS | C23: 807.83 | E23: Diggers and Dealers - Flyers for Stachels | F23: G077 | G23: SALP | J23: =IF(F23>0,(_xlfn.CONCAT(F23,".",G23)),H23) -> G077.SALP | K23: =_xlfn.CONCAT("T Bell-",(LEFT(B23,15)),"-",E23) -> T Bell-Kwik Kopy Canni-Diggers and Dealers - Flyers for Stachels | L23: I | M23: =IF(C23>0,C23,-D23) -> 807.83 | N23: T | R23: =LEN(K23) -> 64
A24: 45856 | B24: LEEDERVILLE MINI MAR LEEDERVILLE AUS | C24: 3.98 | E24: Milk | F24: 1084 | G24: STAF | J24: =IF(F24>0,(_xlfn.CONCAT(F24,".",G24)),H24) -> 1084.STAF | K24: =_xlfn.CONCAT("T Bell-",(LEFT(B24,15)),"-",E24) -> T Bell-LEEDERVILLE MIN-Milk | L24: I | M24: =IF(C24>0,C24,-D24) -> 3.98 | N24: T | R24: =LEN(K24) -> 27
A25: 45869 | B25: LENA'S BAR Perth AUS | C25: =64.96/2 -> 32.48 | E25: Lunch with Emily at Woodside | F25: 1084 | G25: ENFE | J25: =IF(F25>0,(_xlfn.CONCAT(F25,".",G25)),H25) -> 1084.ENFE | K25: =_xlfn.CONCAT("T Bell-",(LEFT(B25,15)),"-",E25) -> T Bell-LENA'S BAR Pert-Lunch with Emily at Woodside | L25: I | M25: =IF(C25>0,C25,-D25) -> 32.48 | N25: T | R25: =LEN(K25) -> 51
A26: 45869 | B26: LENA'S BAR Perth AUS | C26: =64.96/2 -> 32.48 | E26: Lunch with Emily at Woodside | F26: 1084 | G26: ENFN | J26: =IF(F26>0,(_xlfn.CONCAT(F26,".",G26)),H26) -> 1084.ENFN | K26: =_xlfn.CONCAT("T Bell-",(LEFT(B26,15)),"-",E26) -> T Bell-LENA'S BAR Pert-Lunch with Emily at Woodside | M26: =IF(C26>0,C26,-D26) -> 32.48 | N26: T | R26: =LEN(K26) -> 51
A27: 45867 | B27: LOUVE PERTH AUS | C27: =10.5/2 -> 5.25 | E27: Coffee with Darren Athies - Ramelius | F27: 1084 | G27: ENFE | J27: =IF(F27>0,(_xlfn.CONCAT(F27,".",G27)),H27) -> 1084.ENFE | K27: =_xlfn.CONCAT("T Bell-",(LEFT(B27,15)),"-",E27) -> T Bell-LOUVE PERTH AUS-Coffee with Darren Athies - Ramelius | L27: I | M27: =IF(C27>0,C27,-D27) -> 5.25 | N27: T | R27: =LEN(K27) -> 59
A28: 45867 | B28: LOUVE PERTH AUS | C28: =10.5/2 -> 5.25 | E28: Coffee with Darren Athies - Ramelius | F28: 1084 | G28: ENFN | J28: =IF(F28>0,(_xlfn.CONCAT(F28,".",G28)),H28) -> 1084.ENFN | K28: =_xlfn.CONCAT("T Bell-",(LEFT(B28,15)),"-",E28) -> T Bell-LOUVE PERTH AUS-Coffee with Darren Athies - Ramelius | M28: =IF(C28>0,C28,-D28) -> 5.25 | N28: T | R28: =LEN(K28) -> 59
A29: 45883 | B29: MCDONALDS WENDOUREE WENDOUREE AUS | C29: 9.7 | E29: Ballarat Sales Conference - Food / Amenities | F29: G068 | G29: SALP | J29: =IF(F29>0,(_xlfn.CONCAT(F29,".",G29)),H29) -> G068.SALP | K29: =_xlfn.CONCAT("T Bell-",(LEFT(B29,15)),"-",E29) -> T Bell-MCDONALDS WENDO-Ballarat Sales Conference - Food / Amenities | L29: I | M29: =IF(C29>0,C29,-D29) -> 9.7 | N29: T | R29: =LEN(K29) -> 67
A30: 45882 | B30: MCDONALDS WENDOUREE WENDOUREE AUS | C30: 9.7 | E30: Ballarat Sales Conference - Food / Amenities | F30: G068 | G30: SALP | J30: =IF(F30>0,(_xlfn.CONCAT(F30,".",G30)),H30) -> G068.SALP | K30: =_xlfn.CONCAT("T Bell-",(LEFT(B30,15)),"-",E30) -> T Bell-MCDONALDS WENDO-Ballarat Sales Conference - Food / Amenities | L30: I | M30: =IF(C30>0,C30,-D30) -> 9.7 | N30: T | R30: =LEN(K30) -> 67
A31: 45881 | B31: MCDONALDS WENDOUREE WENDOUREE AUS | C31: 15.8 | E31: Ballarat Sales Conference - Food / Amenities | F31: G068 | G31: SALP | J31: =IF(F31>0,(_xlfn.CONCAT(F31,".",G31)),H31) -> G068.SALP | K31: =_xlfn.CONCAT("T Bell-",(LEFT(B31,15)),"-",E31) -> T Bell-MCDONALDS WENDO-Ballarat Sales Conference - Food / Amenities | L31: I | M31: =IF(C31>0,C31,-D31) -> 15.8 | N31: T | R31: =LEN(K31) -> 67
A32: 45880 | B32: MCDONALDS WENDOUREE WENDOUREE AUS | C32: 9.7 | E32: Ballarat Sales Conference - Food / Amenities | F32: G068 | G32: SALP | J32: =IF(F32>0,(_xlfn.CONCAT(F32,".",G32)),H32) -> G068.SALP | K32: =_xlfn.CONCAT("T Bell-",(LEFT(B32,15)),"-",E32) -> T Bell-MCDONALDS WENDO-Ballarat Sales Conference - Food / Amenities | L32: I | M32: =IF(C32>0,C32,-D32) -> 9.7 | N32: T | R32: =LEN(K32) -> 67
A33: 45881 | B33: North Star Hotel SOLDIERS HI AUS | C33: 156.88 | E33: Ballarat Sales Conference - Food / Amenities | F33: G068 | G33: SALP | J33: =IF(F33>0,(_xlfn.CONCAT(F33,".",G33)),H33) -> G068.SALP | K33: =_xlfn.CONCAT("T Bell-",(LEFT(B33,15)),"-",E33) -> T Bell-North Star Hote-Ballarat Sales Conference - Food / Amenities | L33: I | M33: =IF(C33>0,C33,-D33) -> 156.88 | N33: T | R33: =LEN(K33) -> 67
A34: 45874 | B34: PALACE HOTEL KALGOORL Kalgoorlie AUS | C34: 13.95 | E34: Diggers and Dealers - Food / Amenities | F34: G077 | G34: SALP | J34: =IF(F34>0,(_xlfn.CONCAT(F34,".",G34)),H34) -> G077.SALP | K34: =_xlfn.CONCAT("T Bell-",(LEFT(B34,15)),"-",E34) -> T Bell-PALACE HOTEL KA-Diggers and Dealers - Food / Amenities | L34: I | M34: =IF(C34>0,C34,-D34) -> 13.95 | N34: T | R34: =LEN(K34) -> 61
A35: 45874 | B35: PALACE HOTEL KALGOORL Kalgoorlie AUS | C35: 51.16 | E35: Diggers and Dealers - Food / Amenities | F35: G077 | G35: SALP | J35: =IF(F35>0,(_xlfn.CONCAT(F35,".",G35)),H35) -> G077.SALP | K35: =_xlfn.CONCAT("T Bell-",(LEFT(B35,15)),"-",E35) -> T Bell-PALACE HOTEL KA-Diggers and Dealers - Food / Amenities | L35: I | M35: =IF(C35>0,C35,-D35) -> 51.16 | N35: T | R35: =LEN(K35) -> 61
A36: 45866 | B36: ROSSMOYNE IGA ROSSMOYNE AUS | C36: 6.49 | E36: Coffee | F36: 1084 | G36: STAF | J36: =IF(F36>0,(_xlfn.CONCAT(F36,".",G36)),H36) -> 1084.STAF | K36: =_xlfn.CONCAT("T Bell-",(LEFT(B36,15)),"-",E36) -> T Bell-ROSSMOYNE IGA R-Coffee | L36: I | M36: =IF(C36>0,C36,-D36) -> 6.49 | N36: T | R36: =LEN(K36) -> 31
A37: 45877 | B37: SQ *NOURISH KITCHEN & Leederville AUS | C37: 15.9 | E37: Wednesday Lunch | F37: 1084 | G37: ENON | J37: =IF(F37>0,(_xlfn.CONCAT(F37,".",G37)),H37) -> 1084.ENON | K37: =_xlfn.CONCAT("T Bell-",(LEFT(B37,15)),"-",E37) -> T Bell-SQ *NOURISH KIT-Wednesday Lunch | L37: I | M37: =IF(C37>0,C37,-D37) -> 15.9 | N37: T | R37: =LEN(K37) -> 38
A38: 45880 | B38: THE CITY OVAL HOTEL BA BALLARAT CE AUS | C38: 25.07 | E38: Ballarat Sales Conference - Food / Amenities | F38: G068 | G38: SALP | J38: =IF(F38>0,(_xlfn.CONCAT(F38,".",G38)),H38) -> G068.SALP | K38: =_xlfn.CONCAT("T Bell-",(LEFT(B38,15)),"-",E38) -> T Bell-THE CITY OVAL H-Ballarat Sales Conference - Food / Amenities | L38: I | M38: =IF(C38>0,C38,-D38) -> 25.07 | N38: T | R38: =LEN(K38) -> 67
A39: 45884 | B39: UBER *TRIP HELP.UBER.C 14518236738 AUS | C39: 33.67 | E39: Ballarat Sales Conference - Uber | F39: G077 | G39: SALP | J39: =IF(F39>0,(_xlfn.CONCAT(F39,".",G39)),H39) -> G077.SALP | K39: =_xlfn.CONCAT("T Bell-",(LEFT(B39,15)),"-",E39) -> T Bell-UBER *TRIP HELP-Ballarat Sales Conference - Uber | L39: I | M39: =IF(C39>0,C39,-D39) -> 33.67 | N39: T | R39: =LEN(K39) -> 55
A40: 45879 | B40: UBER *TRIP HELP.UBER.C 14518236738 AUS | C40: 38 | E40: Ballarat Sales Conference - Uber | F40: G068 | G40: SALP | J40: =IF(F40>0,(_xlfn.CONCAT(F40,".",G40)),H40) -> G068.SALP | K40: =_xlfn.CONCAT("T Bell-",(LEFT(B40,15)),"-",E40) -> T Bell-UBER *TRIP HELP-Ballarat Sales Conference - Uber | L40: I | M40: =IF(C40>0,C40,-D40) -> 38 | N40: T | R40: =LEN(K40) -> 55
... A55: 45879 | B55: ZLR*M1FLATC Melbourne A AUS | C55: 22.9 | E55: Ballarat Sales Conference - Food / Amenities | F55: G068 | G55: SALP | J55: =IF(F55>0,(_xlfn.CONCAT(F55,".",G55)),H55) -> G068.SALP | K55: =_xlfn.CONCAT("T Bell-",(LEFT(B55,15)),"-",E55) -> T Bell-ZLR*M1FLATC Mel-Ballarat Sales Conference - Food / Amenities | L55: I | M55: =IF(C55>0,C55,-D55) -> 22.9 | N55: T | R55: =LEN(K55) -> 67

Sheet S Baker
A1: Employee to code & narrate | J1: To be copied in to pronto
J2: Credit card Statement TOTAL | K2: 98.96
J3: Subtotal | K3: =SUM(M9:M144) -> 98.96
A4: Scott Baker | J4: Variance Check | K4: =K2-K3 -> 0
A5: Reference | B5: =CONCATENATE(Header!$E$4,"BAKER") -> MC-250816BAKER | J5: EMPLOYEES DO NOT CHANGE
A6: Document Date | B6: =Header!$E$5 -> 45885 | E6: Credit card holder to add details
A8: Date | B8: Narrative | C8: Debit Amount | D8: Credit Amount | E8: Description | F8: Project No | G8: Cost Category | H8: GL account | J8: Account | K8: Reference | L8: Tax | M8: Amount | N8: Tax CODE | O8: TAX Amount (leave blank) | P8: CBS - Only if required | R8: limit 56charaters
A9: 45862 | B9: BUNNINGS 329000 DELACOMBE AUS | C9: 98.96 | E9: Delivery team tools - fire blanket | F9: 1073 | G9: TOOL | J9: =IF(F9>0,(_xlfn.CONCAT(F9,".",G9)),H9) -> 1073.TOOL | K9: =_xlfn.CONCAT("S Baker-",(LEFT(B9,15)),"-",E9) -> S Baker-BUNNINGS 329000-Delivery team tools - fire blanket | L9: I | M9: =IF(C9>0,C9,-D9) -> 98.96 | N9: T | Q9: CBS - needs to be pasted seperately | R9: =LEN(K9) -> 58
R10: =LEN(K10) -> 0
R11: =LEN(K11) -> 0
R12: =LEN(K12) -> 0
R13: =LEN(K13) -> 0
R14: =LEN(K14) -> 0
R15: =LEN(K15) -> 0
R16: =LEN(K16) -> 0
R17: =LEN(K17) -> 0
R18: =LEN(K18) -> 0
R19: =LEN(K19) -> 0
R20: =LEN(K20) -> 0
R21: =LEN(K21) -> 0
... R35: =LEN(K35) -> 0

Sheet S Barclay
A1: Employee to code & narrate | J1: To be copied in to pronto
J2: Credit card Statement TOTAL | K2: 532.97
J3: Subtotal | K3: =SUM(M9:M144) -> 532.97
A4: Simon Barclay | J4: Variance Check | K4: =K2-K3 -> 0
A5: Reference | B5: =CONCATENATE(Header!$E$4,"Barclay") -> MC-250816Barclay | J5: EMPLOYEES DO NOT CHANGE
A6: Document Date | B6: =Header!$E$5 -> 45885 | E6: Credit card holder to add details
A8: Date | B8: Narrative | C8: Debit Amount | D8: Credit Amount | E8: Description | F8: Project No | G8: Cost Category | H8: GL account | J8: Account | K8: Reference | L8: Tax | M8: Amount | N8: Tax CODE | O8: TAX Amount (leave blank) | P8: CBS - Only if required | R8: limit 56charaters
A9: 45884 | B9: WOOLWORTHS 3066 ALFREDTON AUS | C9: 216.27 | E9: Pantry supplies | F9: 1084 | G9: STAF | J9: =IF(F9>0,(_xlfn.CONCAT(F9,".",G9)),H9) -> 1084.STAF | K9: =_xlfn.CONCAT("S Barclay-",(LEFT(B9,15)),"-",E9) -> S Barclay-WOOLWORTHS -Pantry supplies | L9: I | M9: =IF(C9>0,C9,-D9) -> 216.27 | N9: T | Q9: CBS - needs to be pasted seperately | R9: =LEN(K9) -> 41
A10: 45876 | B10: WOOLWORTHS 3066 ALFREDTON AUS | C10: 93.93 | E10: Pantry Supplies | F10: 1084 | G10: STAF | J10: =IF(F10>0,(_xlfn.CONCAT(F10,".",G10)),H10) -> 1084.STAF | K10: =_xlfn.CONCAT("S Barclay-",(LEFT(B10,15)),"-",E10) -> S Barclay-WOOLWORTHS -Pantry Supplies | L10: I | M10: =IF(C10>0,C10,-D10) -> 93.93 | N10: T | R10: =LEN(K10) -> 41
A11: 45871 | B11: LINKT MELBOURNE MELBOURNE AUS | C11: 33.92 | E11: Toll | F11: 1073 | G11: MVPT | J11: =IF(F11>0,(_xlfn.CONCAT(F11,".",G11)),H11) -> 1073.MVPT | K11: =_xlfn.CONCAT("S Barclay-",(LEFT(B11,15)),"-",E11) -> S Barclay-LINKT MELBOURNE-Toll | L11: I | M11: =IF(C11>0,C11,-D11) -> 33.92 | N11: T | R11: =LEN(K11) -> 30
A12: 45869 | B12: OFFICEWORKS 0364OFFICE BALLARAT AUS | C12: 58 | E12: Stationary | F12: 1084 | G12: STAT | J12: =IF(F12>0,(_xlfn.CONCAT(F12,".",G12)),H12) -> 1084.STAT | K12: =_xlfn.CONCAT("S Barclay-",(LEFT(B12,15)),"-",E12) -> S Barclay-OFFICEWORKS 036-Stationary | L12: I | M12: =IF(C12>0,C12,-D12) -> 58 | N12: T | R12: =LEN(K12) -> 36
A13: 45868 | B13: J AND M CATERING SERVI WENDOUREE AUS | C13: 77.5 | E13: Stocktake catering | F13: 1077 | G13: ENON | J13: =IF(F13>0,(_xlfn.CONCAT(F13,".",G13)),H13) -> 1077.ENON | K13: =_xlfn.CONCAT("S Barclay-",(LEFT(B13,15)),"-",E13) -> S Barclay-J AND M CATERIN-Stocktake catering | L13: I | M13: =IF(C13>0,C13,-D13) -> 77.5 | N13: T | R13: =LEN(K13) -> 44
A14: 45866 | B14: BUNNINGS 329000 DELACOMBE AUS | C14: 53.35 | F14: 1073 | G14: TOOL | J14: =IF(F14>0,(_xlfn.CONCAT(F14,".",G14)),H14) -> 1073.TOOL | K14: =_xlfn.CONCAT("S Barclay-",(LEFT(B14,15)),"-",E14) -> S Barclay-BUNNINGS 329000- | L14: I | M14: =IF(C14>0,C14,-D14) -> 53.35 | N14: T | R14: =LEN(K14) -> 26
R15: =LEN(K15) -> 0
R16: =LEN(K16) -> 0
R17: =LEN(K17) -> 0
R18: =LEN(K18) -> 0
R19: =LEN(K19) -> 0
R20: =LEN(K20) -> 0
R21: =LEN(K21) -> 0
R22: =LEN(K22) -> 0
R23: =LEN(K23) -> 0
R24: =LEN(K24) -> 0
R25: =LEN(K25) -> 0
R26: =LEN(K26) -> 0
... R35: =LEN(K35) -> 0

Sheet M Brown
A1: Employee to code & narrate | J1: To be copied in to pronto
J2: Credit card Statement TOTAL | K2: 2525.33
J3: Subtotal | K3: =SUM(M9:M144) -> 2525.33
A4: Michael Brown | J4: Variance Check | K4: =K2-K3 -> 0
A5: Reference | B5: =CONCATENATE(Header!$E$4,"Brown") -> MC-250816Brown | J5: EMPLOYEES DO NOT CHANGE
A6: Document Date | B6: =Header!$E$5 -> 45885 | E6: Credit card holder to add details
A8: Date | B8: Narrative | C8: Debit Amount | D8: Credit Amount | E8: Description | F8: Project No | G8: Cost Category | H8: GL account | J8: Account | K8: Reference | L8: Tax | M8: Amount | N8: Tax CODE | O8: TAX Amount (leave blank) | P8: CBS - Only if required | R8: limit 56charaters
A9: 45881 | B9: BUNNINGS 329000 DELACOMBE AUS | C9: 44.94 | E9: Powerboards | F9: 1084 | G9: repm | J9: =IF(F9>0,(_xlfn.CONCAT(F9,".",G9)),H9) -> 1084.repm | K9: =_xlfn.CONCAT("M Brown-",(LEFT(B9,15)),"-",E9) -> M Brown-BUNNINGS 329000-Powerboards | L9: I | M9: =IF(C9>0,C9,-D9) -> 44.94 | N9: T | Q9: CBS - needs to be pasted seperately | R9: =LEN(K9) -> 35
A10: 45881 | B10: BALLARAT SAFETY PTY L BALLARAT AUS | C10: 17.6 | E10: Safety boot insole | F10: 1084 | G10: sppe | J10: =IF(F10>0,(_xlfn.CONCAT(F10,".",G10)),H10) -> 1084.sppe | K10: =_xlfn.CONCAT("M Brown-",(LEFT(B10,15)),"-",E10) -> M Brown-BALLARAT SAFETY-Safety boot insole | L10: I | M10: =IF(C10>0,C10,-D10) -> 17.6 | N10: T | R10: =LEN(K10) -> 42
A11: 45881 | B11: Industrial World BALLARAT AUS | C11: 25.61 | E11: PV5 drive belts | F11: 1051g | G11: repm | J11: =IF(F11>0,(_xlfn.CONCAT(F11,".",G11)),H11) -> 1051g.repm | K11: =_xlfn.CONCAT("M Brown-",(LEFT(B11,15)),"-",E11) -> M Brown-Industrial Worl-PV5 drive belts | L11: I | M11: =IF(C11>0,C11,-D11) -> 25.61 | N11: T | R11: =LEN(K11) -> 39
A12: 45877 | B12: TOTAL TOOLS BALLARAT BALLARAT AUS | C12: 114.2 | E12: Gas burner for weed removal | F12: 1084 | G12: repm | J12: =IF(F12>0,(_xlfn.CONCAT(F12,".",G12)),H12) -> 1084.repm | K12: =_xlfn.CONCAT("M Brown-",(LEFT(B12,15)),"-",E12) -> M Brown-TOTAL TOOLS BAL-Gas burner for weed removal | L12: I | M12: =IF(C12>0,C12,-D12) -> 114.2 | N12: T | R12: =LEN(K12) -> 51
A13: 45876 | B13: STARLINK INTERNET Sydney AUS | C13: 139 | E13: Mt Coghill inernet | F13: 1084 | G13: inte | J13: =IF(F13>0,(_xlfn.CONCAT(F13,".",G13)),H13) -> 1084.inte | K13: =_xlfn.CONCAT("M Brown-",(LEFT(B13,15)),"-",E13) -> M Brown-STARLINK INTERN-Mt Coghill inernet | L13: I | M13: =IF(C13>0,C13,-D13) -> 139 | N13: T | R13: =LEN(K13) -> 42
A14: 45875 | B14: BUNNINGS 329000 DELACOMBE AUS | C14: 44.7 | E14: 15 amp Switch lead | F14: 1084 | G14: repm | J14: =IF(F14>0,(_xlfn.CONCAT(F14,".",G14)),H14) -> 1084.repm | K14: =_xlfn.CONCAT("M Brown-",(LEFT(B14,15)),"-",E14) -> M Brown-BUNNINGS 329000-15 amp Switch lead | L14: I | M14: =IF(C14>0,C14,-D14) -> 44.7 | N14: T | R14: =LEN(K14) -> 42
A15: 45875 | B15: UNITED BALLARAT EURE WENDOUREE AUS | C15: 122.62 | E15: Ute fuel | F15: 1084 | G15: mvpf | J15: =IF(F15>0,(_xlfn.CONCAT(F15,".",G15)),H15) -> 1084.mvpf | K15: =_xlfn.CONCAT("M Brown-",(LEFT(B15,15)),"-",E15) -> M Brown-UNITED BALLARAT-Ute fuel | L15: I | M15: =IF(C15>0,C15,-D15) -> 122.62 | N15: T | R15: =LEN(K15) -> 32
A16: 45874 | B16: AWM WENDOUREE WENDOUREE AUS | C16: 184.67 | E16: B1 airconditioners | F16: 1084 | G16: repm | J16: =IF(F16>0,(_xlfn.CONCAT(F16,".",G16)),H16) -> 1084.repm | K16: =_xlfn.CONCAT("M Brown-",(LEFT(B16,15)),"-",E16) -> M Brown-AWM WENDOUREE W-B1 airconditioners | L16: I | M16: =IF(C16>0,C16,-D16) -> 184.67 | N16: T | R16: =LEN(K16) -> 42
A17: 45874 | B17: CRED VOUCHER AWM WENDOUREE WENDOUREE AUS | D17: 71.98 | E17: Overcharge credit | F17: 1084 | G17: repm | J17: =IF(F17>0,(_xlfn.CONCAT(F17,".",G17)),H17) -> 1084.repm | K17: =_xlfn.CONCAT("M Brown-",(LEFT(B17,15)),"-",E17) -> M Brown-CRED VOUCHER AW-Overcharge credit | L17: I | M17: =IF(C17>0,C17,-D17) -> -71.98 | N17: T | R17: =LEN(K17) -> 41
A18: 45874 | B18: L&H WENDOUREE WENDOUREE AUS | C18: 241.66 | E18: B1 airconditioners | F18: 1084 | G18: repm | J18: =IF(F18>0,(_xlfn.CONCAT(F18,".",G18)),H18) -> 1084.repm | K18: =_xlfn.CONCAT("M Brown-",(LEFT(B18,15)),"-",E18) -> M Brown-L&H WENDOUREE W-B1 airconditioners | L18: I | M18: =IF(C18>0,C18,-D18) -> 241.66 | N18: T | R18: =LEN(K18) -> 42
A19: 45869 | B19: Ballarat Materials Ha MITCHELL PA AUS | C19: 250.97 | E19: Pallet rack load limit signs | F19: 1084 | G19: sppe | J19: =IF(F19>0,(_xlfn.CONCAT(F19,".",G19)),H19) -> 1084.sppe | K19: =_xlfn.CONCAT("M Brown-",(LEFT(B19,15)),"-",E19) -> M Brown-Ballarat Materi-Pallet rack load limit signs | L19: I | M19: =IF(C19>0,C19,-D19) -> 250.97 | N19: T | R19: =LEN(K19) -> 52
A20: 45868 | B20: AVENUTUM BALLARAT BALLARAT AUS | C20: 486.57 | E20: PV5 safety switck | F20: 1051g | G20: repm | J20: =IF(F20>0,(_xlfn.CONCAT(F20,".",G20)),H20) -> 1051g.repm | K20: =_xlfn.CONCAT("M Brown-",(LEFT(B20,15)),"-",E20) -> M Brown-AVENUTUM BALLAR-PV5 safety switck | L20: I | M20: =IF(C20>0,C20,-D20) -> 486.57 | N20: T | R20: =LEN(K20) -> 41
A21: 45868 | B21: UNITED BALLARAT EURE WENDOUREE AUS | C21: 118.34 | E21: Ute fuel | F21: 1084 | G21: mvpf | J21: =IF(F21>0,(_xlfn.CONCAT(F21,".",G21)),H21) -> 1084.mvpf | K21: =_xlfn.CONCAT("M Brown-",(LEFT(B21,15)),"-",E21) -> M Brown-UNITED BALLARAT-Ute fuel | L21: I | M21: =IF(C21>0,C21,-D21) -> 118.34 | N21: T | R21: =LEN(K21) -> 32
A22: 45866 | B22: Ballarat Bolts & Fast DELACOMBE AUS | C22: 4.06 | E22: PV5 bolts | F22: 1051g | G22: repm | J22: =IF(F22>0,(_xlfn.CONCAT(F22,".",G22)),H22) -> 1051g.repm | K22: =_xlfn.CONCAT("M Brown-",(LEFT(B22,15)),"-",E22) -> M Brown-Ballarat Bolts -PV5 bolts | L22: I | M22: =IF(C22>0,C22,-D22) -> 4.06 | N22: T | R22: =LEN(K22) -> 33
A23: 45863 | B23: BUNNINGS 329000 DELACOMBE AUS | C23: 33 | E23: Coach bolts | F23: 1084 | G23: repm | J23: =IF(F23>0,(_xlfn.CONCAT(F23,".",G23)),H23) -> 1084.repm | K23: =_xlfn.CONCAT("M Brown-",(LEFT(B23,15)),"-",E23) -> M Brown-BUNNINGS 329000-Coach bolts | L23: I | M23: =IF(C23>0,C23,-D23) -> 33 | N23: T | R23: =LEN(K23) -> 35
A24: 45860 | B24: STERIDIUM PTY LTD CLEAR ISLAN AUS | C24: 483.87 | E24: Assay oven controler | F24: 1051g | G24: repm | J24: =IF(F24>0,(_xlfn.CONCAT(F24,".",G24)),H24) -> 1051g.repm | K24: =_xlfn.CONCAT("M Brown-",(LEFT(B24,15)),"-",E24) -> M Brown-STERIDIUM PTY L-Assay oven controler | L24: I | M24: =IF(C24>0,C24,-D24) -> 483.87 | N24: T | R24: =LEN(K24) -> 44
A25: 45859 | B25: BUNNINGS 329000 DELACOMBE AUS | C25: 59.45 | E25: LM5 cables | F25: 1051g | G25: repm | J25: =IF(F25>0,(_xlfn.CONCAT(F25,".",G25)),H25) -> 1051g.repm | K25: =_xlfn.CONCAT("M Brown-",(LEFT(B25,15)),"-",E25) -> M Brown-BUNNINGS 329000-LM5 cables | L25: I | M25: =IF(C25>0,C25,-D25) -> 59.45 | N25: T | R25: =LEN(K25) -> 34
A26: 45859 | B26: UNITED BALLARAT EURE WENDOUREE AUS | C26: 118.45 | E26: Ute fuel | F26: 1084 | G26: mvpf | J26: =IF(F26>0,(_xlfn.CONCAT(F26,".",G26)),H26) -> 1084.mvpf | K26: =_xlfn.CONCAT("M Brown-",(LEFT(B26,15)),"-",E26) -> M Brown-UNITED BALLARAT-Ute fuel | L26: I | M26: =IF(C26>0,C26,-D26) -> 118.45 | N26: T | R26: =LEN(K26) -> 32
A27: 45856 | B27: L&H WENDOUREE WENDOUREE AUS | C27: 73.61 | E27: Assay oven fan motors | F27: 1051g | G27: repm | J27: =IF(F27>0,(_xlfn.CONCAT(F27,".",G27)),H27) -> 1051g.repm | K27: =_xlfn.CONCAT("M Brown-",(LEFT(B27,15)),"-",E27) -> M Brown-L&H WENDOUREE W-Assay oven fan motors | L27: I | M27: =IF(C27>0,C27,-D27) -> 73.61 | N27: T | R27: =LEN(K27) -> 45
A28: 45855 | B28: COLES 0628COLES 0628 BALLARAT AUS | C28: 12 | E28: B2 kitchen supplies | F28: 1084 | G28: repm | J28: =IF(F28>0,(_xlfn.CONCAT(F28,".",G28)),H28) -> 1084.repm | K28: =_xlfn.CONCAT("M Brown-",(LEFT(B28,15)),"-",E28) -> M Brown-COLES 0628COLES-B2 kitchen supplies | L28: I | M28: =IF(C28>0,C28,-D28) -> 12 | N28: T | R28: =LEN(K28) -> 43
A29: 45854 | B29: BUNNINGS 329000 DELACOMBE AUS | C29: 21.99 | E29: B2 rubbish bin | F29: 1084 | G29: repm | J29: =IF(F29>0,(_xlfn.CONCAT(F29,".",G29)),H29) -> 1084.repm | K29: =_xlfn.CONCAT("M Brown-",(LEFT(B29,15)),"-",E29) -> M Brown-BUNNINGS 329000-B2 rubbish bin | L29: I | M29: =IF(C29>0,C29,-D29) -> 21.99 | N29: T | R29: =LEN(K29) -> 38
R30: =LEN(K30) -> 0
R31: =LEN(K31) -> 0
R32: =LEN(K32) -> 0
R33: =LEN(K33) -> 0
R34: =LEN(K34) -> 0
R35: =LEN(K35) -> 0

Sheet M Donadio
A1: Employee to code & narrate | J1: To be copied in to pronto
J2: Credit card Statement TOTAL | K2: 5018.74
J3: Subtotal | K3: =SUM(M9:M144) -> 5018.74
A4: Mark Donadio | J4: Variance Check | K4: =K2-K3 -> 0
A5: Reference | B5: =CONCATENATE(Header!$E$4,"Donadio") -> MC-250816Donadio | J5: EMPLOYEES DO NOT CHANGE
A6: Document Date | B6: =Header!$E$5 -> 45885 | E6: Credit card holder to add details
A8: Date | B8: Narrative | C8: Debit Amount | D8: Credit Amount | E8: Description | F8: Project No | G8: Cost Category | H8: GL account | J8: Account | K8: Reference | L8: Tax | M8: Amount | N8: Tax CODE | O8: TAX Amount (leave blank) | P8: CBS - Only if required | R8: limit 56charaters
A9: 45881 | B9: SP XNOTE DOVER USA | C9: 1135.57 | E9: trial of Ai writing tools x 3 | F9: 1084 | G9: ITHA | J9: =IF(F9>0,(_xlfn.CONCAT(F9,".",G9)),H9) -> 1084.ITHA | K9: =_xlfn.CONCAT("M Donadio-",(LEFT(B9,15)),"-",E9) -> M Donadio-SP XNOTE DOVER -trial of Ai writing tools x 3 | L9: I | M9: =IF(C9>0,C9,-D9) -> 1135.57 | N9: T | Q9: CBS - needs to be pasted seperately | R9: =LEN(K9) -> 55
A10: 45879 | B10: SP RED DRAGON NUTRIT WOONONA AUS | C10: 169.95 | E10: Personal Exp | F10: 1084 | G10: PERS | J10: =IF(F10>0,(_xlfn.CONCAT(F10,".",G10)),H10) -> 1084.PERS | K10: =_xlfn.CONCAT("M Donadio-",(LEFT(B10,15)),"-",E10) -> M Donadio-SP RED DRAGON N-Personal Exp | L10: I | M10: =IF(C10>0,C10,-D10) -> 169.95 | N10: F | R10: =LEN(K10) -> 38
A11: 45877 | B11: CRUST - BALLARAT ROBINA AUS | C11: 963 | E11: Wednesday lunch | F11: 1084 | G11: ENON | J11: =IF(F11>0,(_xlfn.CONCAT(F11,".",G11)),H11) -> 1084.ENON | K11: =_xlfn.CONCAT("M Donadio-",(LEFT(B11,15)),"-",E11) -> M Donadio-CRUST - BALLARA-Wednesday lunch | L11: I | M11: =IF(C11>0,C11,-D11) -> 963 | N11: T | R11: =LEN(K11) -> 41
A12: 45875 | B12: SP RUNAWAYTHELABEL.COM MARRICKVILL AUS | C12: 353.6 | E12: Personal Exp | F12: 1084 | G12: PERS | J12: =IF(F12>0,(_xlfn.CONCAT(F12,".",G12)),H12) -> 1084.PERS | K12: =_xlfn.CONCAT("M Donadio-",(LEFT(B12,15)),"-",E12) -> M Donadio-SP RUNAWAYTHELA-Personal Exp | L12: I | M12: =IF(C12>0,C12,-D12) -> 353.6 | N12: F | R12: =LEN(K12) -> 38
A13: 45873 | B13: DNH*GODADDY#3840902371 SYDNEY AUS | C13: 111.31 | E13: Domain registrations | F13: 1084 | G13: WEBS | J13: =IF(F13>0,(_xlfn.CONCAT(F13,".",G13)),H13) -> 1084.WEBS | K13: =_xlfn.CONCAT("M Donadio-",(LEFT(B13,15)),"-",E13) -> M Donadio-DNH*GODADDY#384-Domain registrations | L13: I | M13: =IF(C13>0,C13,-D13) -> 111.31 | N13: T | R13: =LEN(K13) -> 46
A14: 45871 | B14: CRUST - BALLARAT ROBINA AUS | C14: 137 | E14: Lunch on Go Live weekend | F14: 1084 | G14: ENON | J14: =IF(F14>0,(_xlfn.CONCAT(F14,".",G14)),H14) -> 1084.ENON | K14: =_xlfn.CONCAT("M Donadio-",(LEFT(B14,15)),"-",E14) -> M Donadio-CRUST - BALLARA-Lunch on Go Live weekend | L14: I | M14: =IF(C14>0,C14,-D14) -> 137 | N14: T | R14: =LEN(K14) -> 50
A15: 45868 | B15: SQ *NAOMI & I Soldiers Hi AUS | C15: 54.86 | E15: Morning tea | F15: 1084 | G15: ENON | J15: =IF(F15>0,(_xlfn.CONCAT(F15,".",G15)),H15) -> 1084.ENON | K15: =_xlfn.CONCAT("M Donadio-",(LEFT(B15,15)),"-",E15) -> M Donadio-SQ *NAOMI & I S-Morning tea | L15: I | M15: =IF(C15>0,C15,-D15) -> 54.86 | N15: T | R15: =LEN(K15) -> 37
A16: 45868 | B16: BWS LIQUOR 3834 WENDOUREE AUS | C16: 78 | E16: Gift for Daniel V (Staff costs and Amenities) | F16: 1084 | G16: STAF | J16: =IF(F16>0,(_xlfn.CONCAT(F16,".",G16)),H16) -> 1084.STAF | K16: =_xlfn.CONCAT("M Donadio-",(LEFT(B16,15)),"-",E16) -> M Donadio-BWS LIQUOR -Gift for Daniel V (Staff costs and Amenities) | L16: I | M16: =IF(C16>0,C16,-D16) -> 78 | N16: T | R16: =LEN(K16) -> 71
A17: 45868 | B17: WOOLWORTHS 3309 WENDOUREE AUS | C17: 77.5 | E17: Morning tea | F17: 1084 | G17: ENON | J17: =IF(F17>0,(_xlfn.CONCAT(F17,".",G17)),H17) -> 1084.ENON | K17: =_xlfn.CONCAT("M Donadio-",(LEFT(B17,15)),"-",E17) -> M Donadio-WOOLWORTHS -Morning tea | L17: I | M17: =IF(C17>0,C17,-D17) -> 77.5 | N17: T | R17: =LEN(K17) -> 37
A18: 45868 | B18: BAKERS DELIGHT WENDOUR WENDOUREE AUS | C18: 52.1 | E18: Morning tea | F18: 1084 | G18: ENON | J18: =IF(F18>0,(_xlfn.CONCAT(F18,".",G18)),H18) -> 1084.ENON | K18: =_xlfn.CONCAT("M Donadio-",(LEFT(B18,15)),"-",E18) -> M Donadio-BAKERS DELIGHT -Morning tea | L18: I | M18: =IF(C18>0,C18,-D18) -> 52.1 | N18: T | R18: =LEN(K18) -> 37
A19: 45867 | B19: LinkedIn 10459237796 NORTH SYDNE AUS | C19: 1308.54 | E19: LinkedIn Recruiter | F19: 1084 | G19: RECR | J19: =IF(F19>0,(_xlfn.CONCAT(F19,".",G19)),H19) -> 1084.RECR | K19: =_xlfn.CONCAT("M Donadio-",(LEFT(B19,15)),"-",E19) -> M Donadio-LinkedIn 104592-LinkedIn Recruiter | L19: I | M19: =IF(C19>0,C19,-D19) -> 1308.54 | N19: T | R19: =LEN(K19) -> 44
A20: 45860 | B20: STARLINK INTERNET Sydney AUS | C20: 278 | E20: Internet | F20: 1084 | G20: INTE | J20: =IF(F20>0,(_xlfn.CONCAT(F20,".",G20)),H20) -> 1084.INTE | K20: =_xlfn.CONCAT("M Donadio-",(LEFT(B20,15)),"-",E20) -> M Donadio-STARLINK INTERN-Internet | L20: I | M20: =IF(C20>0,C20,-D20) -> 278 | N20: T | R20: =LEN(K20) -> 34
A21: 45860 | B21: WOOLWORTHS 3309 WENDOUREE AUS | C21: 89.48 | E21: Morning tea | F21: 1084 | G21: ENON | J21: =IF(F21>0,(_xlfn.CONCAT(F21,".",G21)),H21) -> 1084.ENON | K21: =_xlfn.CONCAT("M Donadio-",(LEFT(B21,15)),"-",E21) -> M Donadio-WOOLWORTHS -Morning tea | L21: I | M21: =IF(C21>0,C21,-D21) -> 89.48 | N21: T | R21: =LEN(K21) -> 37
... A25: 45854 | B25: WOOLWORTHS 3309 WENDOUREE AUS | C25: 27 | E25: Morning tea | F25: 1084 | G25: ENON | J25: =IF(F25>0,(_xlfn.CONCAT(F25,".",G25)),H25) -> 1084.ENON | K25: =_xlfn.CONCAT("M Donadio-",(LEFT(B25,15)),"-",E25) -> M Donadio-WOOLWORTHS -Morning tea | L25: I | M25: =IF(C25>0,C25,-D25) -> 27 | N25: T | R25: =LEN(K25) -> 37
A26: 45853 | B26: DNH*GODADDY#3840902371 SYDNEY AUS | C26: 70.2 | E26: Domain registrations | F26: 1084 | G26: WEBS | J26: =IF(F26>0,(_xlfn.CONCAT(F26,".",G26)),H26) -> 1084.WEBS | K26: =_xlfn.CONCAT("M Donadio-",(LEFT(B26,15)),"-",E26) -> M Donadio-DNH*GODADDY#384-Domain registrations | M26: =IF(C26>0,C26,-D26) -> 70.2 | N26: T | R26: =LEN(K26) -> 46
R27: =LEN(K27) -> 0
R28: =LEN(K28) -> 0
R29: =LEN(K29) -> 0
R30: =LEN(K30) -> 0
R31: =LEN(K31) -> 0
R32: =LEN(K32) -> 0
R33: =LEN(K33) -> 0
R34: =LEN(K34) -> 0
R35: =LEN(K35) -> 0

Sheet L DUva
A1: Employee to code & narrate | J1: To be copied in to pronto
J2: Credit card Statement TOTAL | K2: 366.53
J3: Subtotal | K3: =SUM(M9:M144) -> 366.53
A4: Lisa Duva | J4: Variance Check | K4: =K2-K3 -> 0
A5: Reference | B5: =CONCATENATE(Header!$E$4,"DUVA") -> MC-250816DUVA | J5: EMPLOYEES DO NOT CHANGE
A6: Document Date | B6: =Header!$E$5 -> 45885 | E6: Credit card holder to add details
A8: Date | B8: Narrative | C8: Debit Amount | D8: Credit Amount | E8: Description | F8: Project No | G8: Cost Category | H8: GL account | J8: Account | K8: Reference | L8: Tax | M8: Amount | N8: Tax CODE | O8: TAX Amount (leave blank) | P8: CBS - Only if required | R8: limit 56charaters
A9: 45881 | B9: SQ *NOURISH KITCHEN & Leederville AUS | C9: 16.9 | E9: Weekly work lunch | F9: 1041 | G9: ENON | J9: =IF(F9>0,(_xlfn.CONCAT(F9,".",G9)),H9) -> 1041.ENON | K9: =_xlfn.CONCAT("L Duva-",(LEFT(B9,15)),"-",E9) -> L Duva-SQ *NOURISH KIT-Weekly work lunch | L9: I | M9: =IF(C9>0,C9,-D9) -> 16.9 | N9: T | Q9: CBS - needs to be pasted seperately | R9: =LEN(K9) -> 40
A10: 45873 | B10: TSUKE BA LEEDERVILLE AUS | C10: 32.5 | E10: Weekly work lunch | F10: 1041 | G10: ENON | J10: =IF(F10>0,(_xlfn.CONCAT(F10,".",G10)),H10) -> 1041.ENON | K10: =_xlfn.CONCAT("L Duva-",(LEFT(B10,15)),"-",E10) -> L Duva-TSUKE BA LEEDER-Weekly work lunch | L10: I | M10: =IF(C10>0,C10,-D10) -> 32.5 | N10: T | R10: =LEN(K10) -> 40
A11: 45871 | B11: UBER *TRIP HELP.UBER.C 14518236738 AUS | C11: 34.98 | E11: Travel - Networking Event: Jeans for Genes fundraiser | F11: 1041 | G11: TRAV | J11: =IF(F11>0,(_xlfn.CONCAT(F11,".",G11)),H11) -> 1041.TRAV | K11: =_xlfn.CONCAT("L Duva-",(LEFT(B11,15)),"-",E11) -> L Duva-UBER *TRIP HELP-Travel - Networking Event: Jeans for Genes fundraiser | L11: I | M11: =IF(C11>0,C11,-D11) -> 34.98 | N11: T | R11: =LEN(K11) -> 76
A12: 45871 | B12: UBER *TRIP HELP.UBER.C 14518236738 AUS | C12: 36.07 | E12: Travel - Networking Event: Jeans for Genes fundraiser | F12: 1041 | G12: TRAV | J12: =IF(F12>0,(_xlfn.CONCAT(F12,".",G12)),H12) -> 1041.TRAV | K12: =_xlfn.CONCAT("L Duva-",(LEFT(B12,15)),"-",E12) -> L Duva-UBER *TRIP HELP-Travel - Networking Event: Jeans for Genes fundraiser | L12: I | M12: =IF(C12>0,C12,-D12) -> 36.07 | N12: T | R12: =LEN(K12) -> 76
A13: 45867 | B13: GYG Leederville Leederville AUS | C13: 26.8 | E13: Weekly work lunch | F13: 1041 | G13: ENON | J13: =IF(F13>0,(_xlfn.CONCAT(F13,".",G13)),H13) -> 1041.ENON | K13: =_xlfn.CONCAT("L Duva-",(LEFT(B13,15)),"-",E13) -> L Duva-GYG Leederville-Weekly work lunch | L13: I | M13: =IF(C13>0,C13,-D13) -> 26.8 | N13: T | R13: =LEN(K13) -> 40
A14: 45855 | B14: AUZICAB 0478 045 250 SOUTHERN RI AUS | C14: 93.24 | E14: Gruyere - Travel to airport | F14: S17144 | G14: TRVP | J14: =IF(F14>0,(_xlfn.CONCAT(F14,".",G14)),H14) -> S17144.TRVP | K14: =_xlfn.CONCAT("L Duva-",(LEFT(B14,15)),"-",E14) -> L Duva-AUZICAB 0478 04-Gruyere - Travel to airport | L14: I | M14: =IF(C14>0,C14,-D14) -> 93.24 | N14: T | P14: 1.6.01 | R14: =LEN(K14) -> 50
A15: 45854 | B15: COMPASS GOLDRDGRUYERE LAVERTON AUS | C15: 13 | E15: Gruyere - Site Networking Drinks | F15: S17144 | G15: TRVP | J15: =IF(F15>0,(_xlfn.CONCAT(F15,".",G15)),H15) -> S17144.TRVP | K15: =_xlfn.CONCAT("L Duva-",(LEFT(B15,15)),"-",E15) -> L Duva-COMPASS GOLDRDG-Gruyere - Site Networking Drinks | L15: I | M15: =IF(C15>0,C15,-D15) -> 13 | N15: T | P15: 1.6.03 | R15: =LEN(K15) -> 55
A16: 45854 | B16: COMPASS GOLDRDGRUYERE LAVERTON AUS | C16: 18.7 | E16: Gruyere - Site Networking Drinks | F16: S17144 | G16: TRVP | J16: =IF(F16>0,(_xlfn.CONCAT(F16,".",G16)),H16) -> S17144.TRVP | K16: =_xlfn.CONCAT("L Duva-",(LEFT(B16,15)),"-",E16) -> L Duva-COMPASS GOLDRDG-Gruyere - Site Networking Drinks | L16: I | M16: =IF(C16>0,C16,-D16) -> 18.7 | N16: T | P16: 1.6.03 | R16: =LEN(K16) -> 55
A17: 45854 | B17: COMPASS GOLDRDGRUYERE LAVERTON AUS | C17: 17.9 | E17: Gruyere - Site Networking Drinks | F17: S17144 | G17: TRVP | J17: =IF(F17>0,(_xlfn.CONCAT(F17,".",G17)),H17) -> S17144.TRVP | K17: =_xlfn.CONCAT("L Duva-",(LEFT(B17,15)),"-",E17) -> L Duva-COMPASS GOLDRDG-Gruyere - Site Networking Drinks | L17: I | M17: =IF(C17>0,C17,-D17) -> 17.9 | N17: T | P17: 1.6.03 | R17: =LEN(K17) -> 55
A18: 45854 | B18: SWAN TAXIS PTY LTD VICTORIA PA AUS | C18: 76.44 | E18: Gruyere - Travel from airport | F18: S17144 | G18: TRVP | J18: =IF(F18>0,(_xlfn.CONCAT(F18,".",G18)),H18) -> S17144.TRVP | K18: =_xlfn.CONCAT("L Duva-",(LEFT(B18,15)),"-",E18) -> L Duva-SWAN TAXIS PTY -Gruyere - Travel from airport | L18: I | M18: =IF(C18>0,C18,-D18) -> 76.44 | N18: T | P18: 1.6.01 | R18: =LEN(K18) -> 52
R19: =LEN(K19) -> 0
R20: =LEN(K20) -> 0
R21: =LEN(K21) -> 0
R22: =LEN(K22) -> 0
R23: =LEN(K23) -> 0
R24: =LEN(K24) -> 0
R25: =LEN(K25) -> 0
R26: =LEN(K26) -> 0
R27: =LEN(K27) -> 0
R28: =LEN(K28) -> 0
R29: =LEN(K29) -> 0
R30: =LEN(K30) -> 0
... R35: =LEN(K35) -> 0

Sheet A Edmondston
A1: Employee to code & narrate | J1: To be copied in to pronto
J2: Credit card Statement TOTAL | K2: 3357.86
J3: Subtotal | K3: =SUM(M9:M146) -> 3357.86
A4: Andrew Edmondston | J4: Variance Check | K4: =K2-K3 -> 0
A5: Reference | B5: =CONCATENATE(Header!$E$4,"Edmondston") -> MC-250816Edmondston | J5: EMPLOYEES DO NOT CHANGE
A6: Document Date | B6: =Header!$E$5 -> 45885 | E6: Credit card holder to add details
A8: Date | B8: Narrative | C8: Debit Amount | D8: Credit Amount | E8: Description | F8: Project No | G8: Cost Category | H8: GL account | J8: Account | K8: Reference | L8: Tax | M8: Amount | N8: Tax CODE | O8: TAX Amount (leave blank) | P8: CBS - Only if required | R8: limit 56charaters
A9: 45883 | B9: Bakers Delight Ballarat Ci AUS | C9: 28.5 | E9: Catering Sales Conference | F9: G068 | G9: SALP | J9: =IF(F9>0,(_xlfn.CONCAT(F9,".",G9)),H9) -> G068.SALP | K9: =_xlfn.CONCAT("A Edmondston-",(LEFT(B9,15)),"-",E9) -> A Edmondston-Bakers Delight -Catering Sales Conference | L9: I | M9: =IF(C9>0,C9,-D9) -> 28.5 | N9: T | Q9: CBS - needs to be pasted seperately | R9: =LEN(K9) -> 54
A10: 45883 | B10: GOLDEN NUGGET BAKERY Wendouree AUS | C10: 75.62 | E10: Catering Sales Conference | F10: G068 | G10: SALP | J10: =IF(F10>0,(_xlfn.CONCAT(F10,".",G10)),H10) -> G068.SALP | K10: =_xlfn.CONCAT("A Edmondston-",(LEFT(B10,15)),"-",E10) -> A Edmondston-GOLDEN NUGGET B-Catering Sales Conference | L10: I | M10: =IF(C10>0,C10,-D10) -> 75.62 | N10: T | R10: =LEN(K10) -> 54
A11: 45882 | B11: Bakers Delight Ballarat Ci AUS | C11: 27 | E11: Catering Sales Conference | F11: G068 | G11: SALP | J11: =IF(F11>0,(_xlfn.CONCAT(F11,".",G11)),H11) -> G068.SALP | K11: =_xlfn.CONCAT("A Edmondston-",(LEFT(B11,15)),"-",E11) -> A Edmondston-Bakers Delight -Catering Sales Conference | L11: I | M11: =IF(C11>0,C11,-D11) -> 27 | N11: T | R11: =LEN(K11) -> 54
A12: 45881 | B12: RYANS IGA MIDVALE MOUNT CLEAR AUS | C12: 16.39 | E12: Catering Sales Conference | F12: G068 | G12: SALP | J12: =IF(F12>0,(_xlfn.CONCAT(F12,".",G12)),H12) -> G068.SALP | K12: =_xlfn.CONCAT("A Edmondston-",(LEFT(B12,15)),"-",E12) -> A Edmondston-RYANS IGA MIDVA-Catering Sales Conference | L12: I | M12: =IF(C12>0,C12,-D12) -> 16.39 | N12: T | R12: =LEN(K12) -> 54
A13: 45880 | B13: RYANS IGA MIDVALE MOUNT CLEAR AUS | C13: 48.23 | E13: Catering Sales Conference | F13: G068 | G13: SALP | J13: =IF(F13>0,(_xlfn.CONCAT(F13,".",G13)),H13) -> G068.SALP | K13: =_xlfn.CONCAT("A Edmondston-",(LEFT(B13,15)),"-",E13) -> A Edmondston-RYANS IGA MIDVA-Catering Sales Conference | L13: I | M13: =IF(C13>0,C13,-D13) -> 48.23 | N13: T | R13: =LEN(K13) -> 54
A14: 45880 | B14: Subway Wendouree Lake Wendou AUS | C14: 128 | E14: Catering Sales Conference | F14: G068 | G14: SALP | J14: =IF(F14>0,(_xlfn.CONCAT(F14,".",G14)),H14) -> G068.SALP | K14: =_xlfn.CONCAT("A Edmondston-",(LEFT(B14,15)),"-",E14) -> A Edmondston-Subway Wendoure-Catering Sales Conference | L14: I | M14: =IF(C14>0,C14,-D14) -> 128 | N14: T | R14: =LEN(K14) -> 54
A15: 45880 | B15: CITYOVA | C15: =527.9*0.2 -> 105.58 | E15: MealAE,TB,NG,WL,SG,ELG,BW,NZ,SM, AL | F15: G068 | G15: SALP | J15: =IF(F15>0,(_xlfn.CONCAT(F15,".",G15)),H15) -> G068.SALP | K15: =_xlfn.CONCAT("A Edmondston-",(LEFT(B15,15)),"-",E15) -> A Edmondston-CITYOVA-MealAE,TB,NG,WL,SG,ELG,BW,NZ,SM, AL | L15: I | M15: =IF(C15>0,C15,-D15) -> 105.58 | N15: T | R15: =LEN(K15) -> 56
A16: 45880 | B16: CITYOva | C16: =527.9*0.8 -> 422.32 | E16: MealAE,TB,NG,WL,SG,ELG,BW,NZ,SM, AL | F16: 1084 | G16: ENFE | J16: =IF(F16>0,(_xlfn.CONCAT(F16,".",G16)),H16) -> 1084.ENFE | K16: =_xlfn.CONCAT("A Edmondston-",(LEFT(B16,15)),"-",E16) -> A Edmondston-CITYOva-MealAE,TB,NG,WL,SG,ELG,BW,NZ,SM, AL | M16: =IF(C16>0,C16,-D16) -> 422.32 | N16: T | R16: =LEN(K16) -> 56
A17: 45877 | B17: POST WENDOUREE VILLAGE WENDOUREE AUS | C17: 19.65 | E17: Post bank guarantees | F17: 1084 | G17: POST | J17: =IF(F17>0,(_xlfn.CONCAT(F17,".",G17)),H17) -> 1084.POST | K17: =_xlfn.CONCAT("A Edmondston-",(LEFT(B17,15)),"-",E17) -> A Edmondston-POST WENDOUREE -Post bank guarantees | L17: I | M17: =IF(C17>0,C17,-D17) -> 19.65 | N17: T | R17: =LEN(K17) -> 49
A18: 45876 | B18: MYKI BALLARAT RS BAT BALLARAT CE AUS | C18: 30 | E18: Train - Melbourne Mining Club | F18: 1084 | G18: TRAV | J18: =IF(F18>0,(_xlfn.CONCAT(F18,".",G18)),H18) -> 1084.TRAV | K18: =_xlfn.CONCAT("A Edmondston-",(LEFT(B18,10)),"-",E18) -> A Edmondston-MYKI BALLA-Train - Melbourne Mining Club | L18: I | M18: =IF(C18>0,C18,-D18) -> 30 | N18: T | R18: =LEN(K18) -> 53
A19: 45876 | B19: SQ *SHOWTIME EVENT GRO Melbourne AUS | C19: =128.52*0.3 -> 38.556 | E19: Wine for table - Melbourne Mining Club AE, MX, SM | F19: 1084 | G19: ENFE | J19: =IF(F19>0,(_xlfn.CONCAT(F19,".",G19)),H19) -> 1084.ENFE | K19: =_xlfn.CONCAT("A Edmondston-",(LEFT(B19,10)),"-",E19) -> A Edmondston-SQ *SHOWTI-Wine for table - Melbourne Mining Club AE, MX, SM | L19: I | M19: =IF(C19>0,C19,-D19) -> 38.556 | N19: T | R19: =LEN(K19) -> 73
A20: 45876 | B20: SQ *SHOWTIME EVENT GRO Melbourne AUS | C20: =128.52*0.7 -> 89.964 | E20: Wine for table - Melbourne Mining Club 7 - Non employees | F20: 1084 | G20: ENFN | J20: =IF(F20>0,(_xlfn.CONCAT(F20,".",G20)),H20) -> 1084.ENFN | K20: =_xlfn.CONCAT("A Edmondston-",(LEFT(B20,10)),"-",E20) -> A Edmondston-SQ *SHOWTI-Wine for table - Melbourne Mining Club 7 - Non employees | L20: I | M20: =IF(C20>0,C20,-D20) -> 89.964 | N20: T | R20: =LEN(K20) -> 80
A21: 45874 | B21: CA ANZ SYDNEY AUS | C21: 899 | E21: Chartered Accountants Aust & NZ Annual Membership | F21: 1084 | G21: MEMB | J21: =IF(F21>0,(_xlfn.CONCAT(F21,".",G21)),H21) -> 1084.MEMB | K21: =_xlfn.CONCAT("A Edmondston-",(LEFT(B21,10)),"-",E21) -> A Edmondston-CA ANZ SYD-Chartered Accountants Aust & NZ Annual Membership | L21: I | M21: =IF(C21>0,C21,-D21) -> 899 | N21: T | R21: =LEN(K21) -> 73
A22: 45870 | B22: GOLDEN NUGGET BAKERY Wendouree AUS | C22: 41.05 | E22: Food for Pronto Team | F22: 1084 | G22: ENON | J22: =IF(F22>0,(_xlfn.CONCAT(F22,".",G22)),H22) -> 1084.ENON | K22: =_xlfn.CONCAT("A Edmondston-",(LEFT(B22,10)),"-",E22) -> A Edmondston-GOLDEN NUG-Food for Pronto Team | L22: I | M22: =IF(C22>0,C22,-D22) -> 41.05 | N22: T | R22: =LEN(K22) -> 44
A23: 45869 | B23: 2 BLOKES COFFEE ROAST MOUNT HELEN AUS | C23: 370 | E23: Coffee Beans | F23: 1084 | G23: STAF | J23: =IF(F23>0,(_xlfn.CONCAT(F23,".",G23)),H23) -> 1084.STAF | K23: =_xlfn.CONCAT("A Edmondston-",(LEFT(B23,10)),"-",E23) -> A Edmondston-2 BLOKES -Coffee Beans | L23: I | M23: =IF(C23>0,C23,-D23) -> 370 | N23: F | R23: =LEN(K23) -> 36
A24: 45865 | B24: ZLR*Liv Eat Western Jun AUS | C24: 15.11 | E24: Food while in Burnie - Elphinstone Group Function | F24: 1084 | G24: TRAV | J24: =IF(F24>0,(_xlfn.CONCAT(F24,".",G24)),H24) -> 1084.TRAV | K24: =_xlfn.CONCAT("A Edmondston-",(LEFT(B24,10)),"-",E24) -> A Edmondston-ZLR*Liv Ea-Food while in Burnie - Elphinstone Group Function | L24: I | M24: =IF(C24>0,C24,-D24) -> 15.11 | N24: T | R24: =LEN(K24) -> 73
A25: 45864 | B25: THE FORESHORE TASMANIA BURNIE AUS | C25: 9.1 | E25: Food while in Burnie - Elphinstone Group Function | F25: 1084 | G25: TRAV | J25: =IF(F25>0,(_xlfn.CONCAT(F25,".",G25)),H25) -> 1084.TRAV | K25: =_xlfn.CONCAT("A Edmondston-",(LEFT(B25,10)),"-",E25) -> A Edmondston-THE FORESH-Food while in Burnie - Elphinstone Group Function | L25: I | M25: =IF(C25>0,C25,-D25) -> 9.1 | N25: T | R25: =LEN(K25) -> 73
A26: 45864 | B26: BELINDA SHEREE DUDFIEL BURNIE AUS | C26: 28 | E26: Food while in Burnie - Elphinstone Group Function | F26: 1084 | G26: TRAV | J26: =IF(F26>0,(_xlfn.CONCAT(F26,".",G26)),H26) -> 1084.TRAV | K26: =_xlfn.CONCAT("A Edmondston-",(LEFT(B26,10)),"-",E26) -> A Edmondston-BELINDA SH-Food while in Burnie - Elphinstone Group Function | L26: I | M26: =IF(C26>0,C26,-D26) -> 28 | N26: T | R26: =LEN(K26) -> 73
A27: 45864 | B27: One North Terrace Burnie AUS | C27: 604.76 | E27: Accom Burnie - Elphinstone Group Function | F27: 1084 | G27: TRAV | J27: =IF(F27>0,(_xlfn.CONCAT(F27,".",G27)),H27) -> 1084.TRAV | K27: =_xlfn.CONCAT("A Edmondston-",(LEFT(B27,10)),"-",E27) -> A Edmondston-One North -Accom Burnie - Elphinstone Group Function | L27: I | M27: =IF(C27>0,C27,-D27) -> 604.76 | N27: T | R27: =LEN(K27) -> 65
A28: 45864 | B28: Penguin Country Bakeh Penguin AUS | C28: 11.1 | E28: Meals Burnie - Elphinstone Group Function | F28: 1084 | G28: TRAV | J28: =IF(F28>0,(_xlfn.CONCAT(F28,".",G28)),H28) -> 1084.TRAV | K28: =_xlfn.CONCAT("A Edmondston-",(LEFT(B28,10)),"-",E28) -> A Edmondston-Penguin Co-Meals Burnie - Elphinstone Group Function | L28: I | M28: =IF(C28>0,C28,-D28) -> 11.1 | N28: T | R28: =LEN(K28) -> 65
A29: 45863 | B29: SQ *EMBER & VINES Burnie, Tas AUS | C29: 135.5 | E29: MealsBurnie -AE &V De Santis | F29: 1084 | G29: TRAV | J29: =IF(F29>0,(_xlfn.CONCAT(F29,".",G29)),H29) -> 1084.TRAV | K29: =_xlfn.CONCAT("A Edmondston-",(LEFT(B29,10)),"-",E29) -> A Edmondston-SQ *EMBER -MealsBurnie -AE &V De Santis | L29: I | M29: =IF(C29>0,C29,-D29) -> 135.5 | N29: T | R29: =LEN(K29) -> 52
A30: 45863 | B30: BELINDA SHEREE DUDFIEL BURNIE AUS | C30: 15.5 | E30: Food while in Burnie - Elphinstone Group Function | F30: 1084 | G30: TRAV | J30: =IF(F30>0,(_xlfn.CONCAT(F30,".",G30)),H30) -> 1084.TRAV | K30: =_xlfn.CONCAT("A Edmondston-",(LEFT(B30,10)),"-",E30) -> A Edmondston-BELINDA SH-Food while in Burnie - Elphinstone Group Function | L30: I | M30: =IF(C30>0,C30,-D30) -> 15.5 | N30: T | R30: =LEN(K30) -> 73
A31: 45863 | B31: UBER *TRIP HELP.UBER.C 14518236738 AUS | C31: 19.87 | E31: Taxi to station for Burnie trip-Elphinstone Group Function | F31: 1084 | G31: TRAV | J31: =IF(F31>0,(_xlfn.CONCAT(F31,".",G31)),H31) -> 1084.TRAV | K31: =_xlfn.CONCAT("A Edmondston-",(LEFT(B31,10)),"-",E31) -> A Edmondston-UBER *TRIP-Taxi to station for Burnie trip-Elphinstone Group Function | L31: I | M31: =IF(C31>0,C31,-D31) -> 19.87 | N31: T | R31: =LEN(K31) -> 82
A32: 45862 | B32: KFC BURNIE BURNIE AUS | C32: 15.45 | E32: Food while in Burnie - Elphinstone Group Function | F32: 1084 | G32: TRAV | J32: =IF(F32>0,(_xlfn.CONCAT(F32,".",G32)),H32) -> 1084.TRAV | K32: =_xlfn.CONCAT("A Edmondston-",(LEFT(B32,10)),"-",E32) -> A Edmondston-KFC BURNIE-Food while in Burnie - Elphinstone Group Function | L32: I | M32: =IF(C32>0,C32,-D32) -> 15.45 | N32: T | R32: =LEN(K32) -> 73
... A35: 45861 | B35: Airport Shuttle Bus BAKERY HILL AUS | C35: 90 | E35: Shuttle bus - Elphinstone Group Function | F35: 1084 | G35: TRAV | J35: =IF(F35>0,(_xlfn.CONCAT(F35,".",G35)),H35) -> 1084.TRAV | K35: =_xlfn.CONCAT("A Edmondston-",(LEFT(B35,10)),"-",E35) -> A Edmondston-Airport Sh-Shuttle bus - Elphinstone Group Function | L35: I | M35: =IF(C35>0,C35,-D35) -> 90 | N35: T | R35: =LEN(K35) -> 64
R36: =LEN(K36) -> 0
R37: =LEN(K37) -> 0

Sheet M Gort
A1: Employee to code & narrate | J1: To be copied in to pronto
J2: Credit card Statement TOTAL | K2: 622.79
J3: Subtotal | K3: =SUM(M9:M144) -> 622.79
A4: Marleen Gort | J4: Variance Check | K4: =K2-K3 -> 0
A5: Reference | B5: =CONCATENATE(Header!$E$4,"Gort") -> MC-250816Gort | J5: EMPLOYEES DO NOT CHANGE
A6: Document Date | B6: =Header!$E$5 -> 45885 | E6: Credit card holder to add details
A8: Date | B8: Narrative | C8: Debit Amount | D8: Credit Amount | E8: Description | F8: Project No | G8: Cost Category | H8: GL account | J8: Account | K8: Reference | L8: Tax | M8: Amount | N8: Tax CODE | O8: TAX Amount (leave blank) | P8: CBS - Only if required | R8: limit 56charaters
A9: 45867 | B9: Yoast B.V. merchantRef Wijchen NLD FRGN AMT: 267.30 U. S. DOLLAR | C9: 422.72 | E9: Website SEO plugin yearly fee | F9: 1084 | G9: ITSW | J9: =IF(F9>0,(_xlfn.CONCAT(F9,".",G9)),H9) -> 1084.ITSW | K9: =_xlfn.CONCAT("M Gort-",(LEFT(B9,15)),"-",E9) -> M Gort-Yoast B.V. merc-Website SEO plugin yearly fee | L9: I | M9: =IF(C9>0,C9,-D9) -> 422.72 | N9: F | Q9: CBS - needs to be pasted seperately | R9: =LEN(K9) -> 53
A10: 45863 | B10: Adobe Sydney AUS | C10: 96.99 | E10: Adobe Creative Cloud monthly fee | F10: 1084 | G10: ITSW | J10: =IF(F10>0,(_xlfn.CONCAT(F10,".",G10)),H10) -> 1084.ITSW | K10: =_xlfn.CONCAT("M Gort-",(LEFT(B10,15)),"-",E10) -> M Gort-Adobe Sydney AU-Adobe Creative Cloud monthly fee | L10: I | M10: =IF(C10>0,C10,-D10) -> 96.99 | N10: T | R10: =LEN(K10) -> 56
A11: 45856 | B11: CODETWO JELENIA GOR POL FRGN AMT: 64.58 U. S. DOLLAR | C11: 103.08 | E11: Signature software extra licenses | F11: 1060GE2 | G11: MISC | J11: =IF(F11>0,(_xlfn.CONCAT(F11,".",G11)),H11) -> 1060GE2.MISC | K11: =_xlfn.CONCAT("M Gort-",(LEFT(B11,15)),"-",E11) -> M Gort-CODETWO JELENIA-Signature software extra licenses | L11: I | M11: =IF(C11>0,C11,-D11) -> 103.08 | N11: F | R11: =LEN(K11) -> 57
R12: =LEN(K12) -> 0
R13: =LEN(K13) -> 0
R14: =LEN(K14) -> 0
R15: =LEN(K15) -> 0
R16: =LEN(K16) -> 0
R17: =LEN(K17) -> 0
R18: =LEN(K18) -> 0
R19: =LEN(K19) -> 0
R20: =LEN(K20) -> 0
R21: =LEN(K21) -> 0
R22: =LEN(K22) -> 0
R23: =LEN(K23) -> 0
... R35: =LEN(K35) -> 0

Sheet N Grigg
A1: Employee to code & narrate | J1: To be copied in to pronto
J2: Credit card Statement TOTAL | K2: 4667.18
J3: Subtotal | K3: =SUM(M9:M144) -> 4667.18
A4: Nigel Grigg | J4: Variance Check | K4: =K2-K3 -> 0
A5: Reference | B5: =CONCATENATE(Header!$E$4,"Grigg") -> MC-250816Grigg | J5: EMPLOYEES DO NOT CHANGE
A6: Document Date | B6: =Header!$E$5 -> 45885 | E6: Credit card holder to add details
A8: Date | B8: Narrative | C8: Debit Amount | D8: Credit Amount | E8: Description | F8: Project No | G8: Cost Category | H8: GL account | J8: Account | K8: Reference | L8: Tax | M8: Amount | N8: Tax CODE | O8: TAX Amount (leave blank) | P8: CBS - Only if required | R8: limit 56charaters
A9: 45882 | B9: WHSMITH SYD PIERC SAT MASCOT AUS | C9: 10.13 | E9: airport - Drinks | F9: G077 | G9: SALP | J9: =IF(F9>0,(_xlfn.CONCAT(F9,".",G9)),H9) -> G077.SALP | K9: =_xlfn.CONCAT("N Grigg-",(LEFT(B9,15)),"-",E9) -> N Grigg-WHSMITH SYD PIE-airport - Drinks | L9: I | M9: =IF(C9>0,C9,-D9) -> 10.13 | N9: T | Q9: CBS - needs to be pasted seperately | R9: =LEN(K9) -> 40
A10: 45882 | B10: TRANSPORTFORNSW TAP SYDNEY AUS | C10: 8.03 | E10: Travel NC | F10: G077 | G10: SALP | J10: =IF(F10>0,(_xlfn.CONCAT(F10,".",G10)),H10) -> G077.SALP | K10: =_xlfn.CONCAT("N Grigg-",(LEFT(B10,15)),"-",E10) -> N Grigg-TRANSPORTFORNSW-Travel NC | L10: I | M10: =IF(C10>0,C10,-D10) -> 8.03 | N10: T | R10: =LEN(K10) -> 33
A11: 45882 | B11: ZLR*S1TOBYA Mascot AUS | C11: 6.59 | E11: Travel NC | F11: G077 | G11: SALP | J11: =IF(F11>0,(_xlfn.CONCAT(F11,".",G11)),H11) -> G077.SALP | K11: =_xlfn.CONCAT("N Grigg-",(LEFT(B11,15)),"-",E11) -> N Grigg-ZLR*S1TOBYA Mas-Travel NC | L11: I | M11: =IF(C11>0,C11,-D11) -> 6.59 | N11: T | R11: =LEN(K11) -> 33
A12: 45881 | B12: UFS HEALTHCARE LTD BALLARAT AUS | C12: 27.18 | E12: Persoanl Cost | F12: 1084 | G12: PERS | J12: =IF(F12>0,(_xlfn.CONCAT(F12,".",G12)),H12) -> 1084.PERS | K12: =_xlfn.CONCAT("N Grigg-",(LEFT(B12,15)),"-",E12) -> N Grigg-UFS HEALTHCARE -Persoanl Cost | L12: I | M12: =IF(C12>0,C12,-D12) -> 27.18 | N12: F | R12: =LEN(K12) -> 37
A13: 45881 | B13: APCO ALFREDTON ALFREDTON AUS | C13: 112.79 | E13: Travel NC - Fuel - | F13: G077 | G13: SALP | J13: =IF(F13>0,(_xlfn.CONCAT(F13,".",G13)),H13) -> G077.SALP | K13: =_xlfn.CONCAT("N Grigg-",(LEFT(B13,15)),"-",E13) -> N Grigg-APCO ALFREDTON -Travel NC - Fuel - | L13: I | M13: =IF(C13>0,C13,-D13) -> 112.79 | N13: T | R13: =LEN(K13) -> 43
A14: 45881 | B14: THINK ASIA T4 MELBOURNE A AUS | C14: 31.82 | E14: Airport Dinner | F14: G077 | G14: SALP | J14: =IF(F14>0,(_xlfn.CONCAT(F14,".",G14)),H14) -> G077.SALP | K14: =_xlfn.CONCAT("N Grigg-",(LEFT(B14,15)),"-",E14) -> N Grigg-THINK ASIA T4 M-Airport Dinner | L14: I | M14: =IF(C14>0,C14,-D14) -> 31.82 | N14: T | R14: =LEN(K14) -> 38
A15: 45881 | B15: MELBOURNE AIRPORT TULLAMARINE AUS | C15: 111 | E15: Travel NC | F15: G077 | G15: SALP | J15: =IF(F15>0,(_xlfn.CONCAT(F15,".",G15)),H15) -> G077.SALP | K15: =_xlfn.CONCAT("N Grigg-",(LEFT(B15,15)),"-",E15) -> N Grigg-MELBOURNE AIRPO-Travel NC | L15: I | M15: =IF(C15>0,C15,-D15) -> 111 | N15: T | R15: =LEN(K15) -> 33
A16: 45880 | B16: UBER *TRIP HELP.UBER.C 14518236738 AUS | C16: 12.05 | E16: Travel NC | F16: G077 | G16: SALP | J16: =IF(F16>0,(_xlfn.CONCAT(F16,".",G16)),H16) -> G077.SALP | K16: =_xlfn.CONCAT("N Grigg-",(LEFT(B16,15)),"-",E16) -> N Grigg-UBER *TRIP HELP-Travel NC | L16: I | M16: =IF(C16>0,C16,-D16) -> 12.05 | N16: T | R16: =LEN(K16) -> 33
A17: 45879 | B17: VIRGIN AU7954422641797 BRISBANE AUS | C17: 263.31 | E17: Flight Kal- Diggers | F17: G077 | G17: SALP | J17: =IF(F17>0,(_xlfn.CONCAT(F17,".",G17)),H17) -> G077.SALP | K17: =_xlfn.CONCAT("N Grigg-",(LEFT(B17,15)),"-",E17) -> N Grigg-VIRGIN AU795442-Flight Kal- Diggers | L17: I | M17: =IF(C17>0,C17,-D17) -> 263.31 | N17: T | R17: =LEN(K17) -> 43
A18: 45879 | B18: QANTAS0812374500543 NSW AUS | C18: 385.79 | E18: Flight perth - Diggers | F18: G077 | G18: SALP | J18: =IF(F18>0,(_xlfn.CONCAT(F18,".",G18)),H18) -> G077.SALP | K18: =_xlfn.CONCAT("N Grigg-",(LEFT(B18,15)),"-",E18) -> N Grigg-QANTAS081237450-Flight perth - Diggers | L18: I | M18: =IF(C18>0,C18,-D18) -> 385.79 | N18: T | R18: =LEN(K18) -> 46
A19: 45877 | B19: UBER *TRIP HELP.UBER.C 14518236738 AUS | C19: 8.94 | E19: Travel NC | F19: G077 | G19: SALP | J19: =IF(F19>0,(_xlfn.CONCAT(F19,".",G19)),H19) -> G077.SALP | K19: =_xlfn.CONCAT("N Grigg-",(LEFT(B19,15)),"-",E19) -> N Grigg-UBER *TRIP HELP-Travel NC | L19: I | M19: =IF(C19>0,C19,-D19) -> 8.94 | N19: T | R19: =LEN(K19) -> 33
A20: 45877 | B20: UBER *TRIP HELP.UBER.C 14518236738 AUS | C20: 173.35 | E20: Travel NC | F20: G077 | G20: SALP | J20: =IF(F20>0,(_xlfn.CONCAT(F20,".",G20)),H20) -> G077.SALP | K20: =_xlfn.CONCAT("N Grigg-",(LEFT(B20,15)),"-",E20) -> N Grigg-UBER *TRIP HELP-Travel NC | L20: I | M20: =IF(C20>0,C20,-D20) -> 173.35 | N20: T | R20: =LEN(K20) -> 33
A21: 45877 | B21: UBER *TRIP HELP.UBER.C 14518236738 AUS | C21: 31.53 | E21: Travel NC | F21: G077 | G21: SALP | J21: =IF(F21>0,(_xlfn.CONCAT(F21,".",G21)),H21) -> G077.SALP | K21: =_xlfn.CONCAT("N Grigg-",(LEFT(B21,15)),"-",E21) -> N Grigg-UBER *TRIP HELP-Travel NC | L21: I | M21: =IF(C21>0,C21,-D21) -> 31.53 | N21: T | R21: =LEN(K21) -> 33
A22: 45877 | B22: MondoMenu Long Neck Do MELBOURNE AUS | C22: 35.61 | E22: Food Airport | F22: G077 | G22: SALP | J22: =IF(F22>0,(_xlfn.CONCAT(F22,".",G22)),H22) -> G077.SALP | K22: =_xlfn.CONCAT("N Grigg-",(LEFT(B22,15)),"-",E22) -> N Grigg-MondoMenu Long -Food Airport | L22: I | M22: =IF(C22>0,C22,-D22) -> 35.61 | N22: T | R22: =LEN(K22) -> 36
A23: 45876 | B23: H.I. West Perth OPI West Perth AUS | C23: 282.67 | E23: Accom - Diggers NG | F23: G077 | G23: SALP | J23: =IF(F23>0,(_xlfn.CONCAT(F23,".",G23)),H23) -> G077.SALP | K23: =_xlfn.CONCAT("N Grigg-",(LEFT(B23,15)),"-",E23) -> N Grigg-H.I. West Perth-Accom - Diggers NG | L23: I | M23: =IF(C23>0,C23,-D23) -> 282.67 | N23: T | R23: =LEN(K23) -> 42
A24: 45876 | B24: BP KAMBALDA 6233 KAMBALDA EA AUS | C24: 64.1 | E24: Travel NC | F24: G077 | G24: SALP | J24: =IF(F24>0,(_xlfn.CONCAT(F24,".",G24)),H24) -> G077.SALP | K24: =_xlfn.CONCAT("N Grigg-",(LEFT(B24,15)),"-",E24) -> N Grigg-BP KAMBALDA 623-Travel NC | L24: I | M24: =IF(C24>0,C24,-D24) -> 64.1 | N24: T | R24: =LEN(K24) -> 33
... A68: 45860 | B68: UBER *TRIP Sydney AUS | C68: 13.52 | E68: Travel NC | F68: G077 | G68: SALP | J68: =IF(F68>0,(_xlfn.CONCAT(F68,".",G68)),H68) -> G077.SALP | K68: =_xlfn.CONCAT("N Grigg-",(LEFT(B68,15)),"-",E68) -> N Grigg-UBER *TRIP Sy-Travel NC | L68: I | M68: =IF(C68>0,C68,-D68) -> 13.52 | N68: T | R68: =LEN(K68) -> 33
A69: 45860 | B69: The Victoria Hotel ICP Melbourne AUS | C69: 8.12 | E69: Travel NC | F69: 1041 | G69: ENFE | J69: =IF(F69>0,(_xlfn.CONCAT(F69,".",G69)),H69) -> 1041.ENFE | K69: =_xlfn.CONCAT("N Grigg-",(LEFT(B69,15)),"-",E69) -> N Grigg-The Victoria Ho-Travel NC | L69: I | M69: =IF(C69>0,C69,-D69) -> 8.12 | N69: T | R69: =LEN(K69) -> 33
A70: 45860 | B70: The Victoria Hotel ICP Melbourne AUS | C70: 16.24 | E70: Cutting edge | F70: 1041 | G70: ENFE | J70: =IF(F70>0,(_xlfn.CONCAT(F70,".",G70)),H70) -> 1041.ENFE | K70: =_xlfn.CONCAT("N Grigg-",(LEFT(B70,15)),"-",E70) -> N Grigg-The Victoria Ho-Cutting edge | L70: I | M70: =IF(C70>0,C70,-D70) -> 16.24 | N70: T | R70: =LEN(K70) -> 37
A71: 45860 | B71: BALLARAT TAXI 131008 BALLARAT NO AUS | C71: 18.01 | E71: Travel NC | F71: G077 | G71: SALP | J71: =IF(F71>0,(_xlfn.CONCAT(F71,".",G71)),H71) -> G077.SALP | K71: =_xlfn.CONCAT("N Grigg-",(LEFT(B71,15)),"-",E71) -> N Grigg-BALLARAT TAXI 1-Travel NC | L71: I | M71: =IF(C71>0,C71,-D71) -> 18.01 | N71: T | R71: =LEN(K71) -> 33
A72: 45857 | B72: UBER *TRIP HELP.UBER.C 14518236738 AUS | C72: 11.39 | E72: Travel NC | F72: G077 | G72: SALP | J72: =IF(F72>0,(_xlfn.CONCAT(F72,".",G72)),H72) -> G077.SALP | K72: =_xlfn.CONCAT("N Grigg-",(LEFT(B72,15)),"-",E72) -> N Grigg-UBER *TRIP HELP-Travel NC | L72: I | M72: =IF(C72>0,C72,-D72) -> 11.39 | N72: T | R72: =LEN(K72) -> 33

Sheet S Jenkins
A1: Employee to code & narrate | J1: To be copied in to pronto
J2: Credit card Statement TOTAL | K2: 1682.17
J3: Subtotal | K3: =SUM(M9:M144) -> 1682.17
A4: Shayne Jenkins | J4: Variance Check | K4: =K2-K3 -> 0
A5: Reference | B5: =CONCATENATE(Header!$E$4,"Jenkins") -> MC-250816Jenkins | J5: EMPLOYEES DO NOT CHANGE
A6: Document Date | B6: =Header!$E$5 -> 45885 | E6: Credit card holder to add details
A8: Date | B8: Narrative | C8: Debit Amount | D8: Credit Amount | E8: Description | F8: Project No | G8: Cost Category | H8: GL account | J8: Account | K8: Reference | L8: Tax | M8: Amount | N8: Tax CODE | O8: TAX Amount (leave blank) | P8: CBS - Only if required | R8: limit 56charaters
A9: 45884 | B9: CASH ADVANCE FEE | C9: 6 | E9: Bank charge | F9: 1084 | G9: BFEE | J9: =IF(F9>0,(_xlfn.CONCAT(F9,".",G9)),H9) -> 1084.BFEE | K9: =_xlfn.CONCAT("S Jenkins-",(LEFT(B9,15)),"-",E9) -> S Jenkins-CASH ADVANCE FE-Bank charge | L9: I | M9: =IF(C9>0,C9,-D9) -> 6 | N9: F | Q9: CBS - needs to be pasted seperately | R9: =LEN(K9) -> 37
A10: 45884 | B10: ATM WDRL FEE BANK OF BENDIGO Alfredton Lu AUS | C10: 3.2 | E10: Bank charge | F10: 1084 | G10: BFEE | J10: =IF(F10>0,(_xlfn.CONCAT(F10,".",G10)),H10) -> 1084.BFEE | K10: =_xlfn.CONCAT("S Jenkins-",(LEFT(B10,15)),"-",E10) -> S Jenkins-ATM WDRL FEE BA-Bank charge | L10: I | M10: =IF(C10>0,C10,-D10) -> 3.2 | N10: F | R10: =LEN(K10) -> 37
A11: 45884 | B11: CASH ADVANCE BANK OF BENDIGO Alfredton Lu AUS | C11: 200 | E11: Change to filippino currency | F11: S14734 | G11: TRVP | J11: =IF(F11>0,(_xlfn.CONCAT(F11,".",G11)),H11) -> S14734.TRVP | K11: =_xlfn.CONCAT("S Jenkins-",(LEFT(B11,15)),"-",E11) -> S Jenkins-CASH ADVANCE BA-Change to filippino currency | L11: I | M11: =IF(C11>0,C11,-D11) -> 200 | N11: F | R11: =LEN(K11) -> 54
A12: 45882 | B12: APCO ALFREDTON ALFREDTON AUS | C12: 102.52 | E12: Fuel | F12: 1054 | G12: MVPF | J12: =IF(F12>0,(_xlfn.CONCAT(F12,".",G12)),H12) -> 1054.MVPF | K12: =_xlfn.CONCAT("S Jenkins-",(LEFT(B12,15)),"-",E12) -> S Jenkins-APCO ALFREDTON -Fuel | L12: I | M12: =IF(C12>0,C12,-D12) -> 102.52 | N12: T | R12: =LEN(K12) -> 30
A13: 45881 | B13: RSEA PTY. LTD. BALLARAT CE AUS | C13: 170.97 | E13: Hi-vis work clothing | F13: 1054 | G13: UNIF | J13: =IF(F13>0,(_xlfn.CONCAT(F13,".",G13)),H13) -> 1054.UNIF | K13: =_xlfn.CONCAT("S Jenkins-",(LEFT(B13,15)),"-",E13) -> S Jenkins-RSEA PTY. LTD. -Hi-vis work clothing | L13: I | M13: =IF(C13>0,C13,-D13) -> 170.97 | N13: T | R13: =LEN(K13) -> 46
A14: 45881 | B14: N. KIMPTON PTY. LTD. Ballarat AUS | C14: 99 | E14: Travel doctor | F14: S14734 | G14: TRVP | J14: =IF(F14>0,(_xlfn.CONCAT(F14,".",G14)),H14) -> S14734.TRVP | K14: =_xlfn.CONCAT("S Jenkins-",(LEFT(B14,15)),"-",E14) -> S Jenkins-N. KIMPTON PTY.-Travel doctor | L14: I | M14: =IF(C14>0,C14,-D14) -> 99 | N14: T | R14: =LEN(K14) -> 39
A15: 45880 | B15: Airport Shuttle Bus BAKERY HILL AUS | C15: 49 | E15: Airport shuttle | F15: S14734 | G15: TRVP | J15: =IF(F15>0,(_xlfn.CONCAT(F15,".",G15)),H15) -> S14734.TRVP | K15: =_xlfn.CONCAT("S Jenkins-",(LEFT(B15,15)),"-",E15) -> S Jenkins-Airport Shuttle-Airport shuttle | L15: I | M15: =IF(C15>0,C15,-D15) -> 49 | N15: T | R15: =LEN(K15) -> 41
A16: 45880 | B16: TOTAL TOOLS BALLARAT BALLARAT AUS | C16: 96.8 | E16: Tools for service visits | F16: 1054 | G16: TOOL | J16: =IF(F16>0,(_xlfn.CONCAT(F16,".",G16)),H16) -> 1054.TOOL | K16: =_xlfn.CONCAT("S Jenkins-",(LEFT(B16,15)),"-",E16) -> S Jenkins-TOTAL TOOLS BAL-Tools for service visits | L16: I | M16: =IF(C16>0,C16,-D16) -> 96.8 | N16: T | R16: =LEN(K16) -> 50
A17: 45873 | B17: APCO SKIPTON ST BALL BALLARAT AUS | C17: 128.03 | E17: Fuel | F17: 1054 | G17: MVPF | J17: =IF(F17>0,(_xlfn.CONCAT(F17,".",G17)),H17) -> 1054.MVPF | K17: =_xlfn.CONCAT("S Jenkins-",(LEFT(B17,15)),"-",E17) -> S Jenkins-APCO SKIPTON ST-Fuel | L17: I | M17: =IF(C17>0,C17,-D17) -> 128.03 | N17: T | R17: =LEN(K17) -> 30
A18: 45873 | B18: OFFICEWORKS 0364OFFICE BALLARAT AUS | C18: 55 | E18: Country travel adaptor | F18: S14734 | G18: TRVP | J18: =IF(F18>0,(_xlfn.CONCAT(F18,".",G18)),H18) -> S14734.TRVP | K18: =_xlfn.CONCAT("S Jenkins-",(LEFT(B18,15)),"-",E18) -> S Jenkins-OFFICEWORKS 036-Country travel adaptor | L18: I | M18: =IF(C18>0,C18,-D18) -> 55 | N18: T | R18: =LEN(K18) -> 48
A19: 45864 | B19: BUNNINGS 329000 DELACOMBE AUS | C19: 116.95 | E19: Cleaning supplies for B2 | F19: 1054 | G19: REPM | J19: =IF(F19>0,(_xlfn.CONCAT(F19,".",G19)),H19) -> 1054.REPM | K19: =_xlfn.CONCAT("S Jenkins-",(LEFT(B19,15)),"-",E19) -> S Jenkins-BUNNINGS 329000-Cleaning supplies for B2 | L19: I | M19: =IF(C19>0,C19,-D19) -> 116.95 | N19: T | R19: =LEN(K19) -> 50
A20: 45860 | B20: N. KIMPTON PTY. LTD. Ballarat AUS | C20: 218 | E20: Travel doctor | F20: S14734 | G20: TRVP | J20: =IF(F20>0,(_xlfn.CONCAT(F20,".",G20)),H20) -> S14734.TRVP | K20: =_xlfn.CONCAT("S Jenkins-",(LEFT(B20,15)),"-",E20) -> S Jenkins-N. KIMPTON PTY.-Travel doctor | L20: I | M20: =IF(C20>0,C20,-D20) -> 218 | N20: T | R20: =LEN(K20) -> 39
A21: 45860 | B21: Ballarat Medical Cent Ballarat AUS | C21: 436.7 | E21: Travel doctor | F21: S14734 | G21: TRVP | J21: =IF(F21>0,(_xlfn.CONCAT(F21,".",G21)),H21) -> S14734.TRVP | K21: =_xlfn.CONCAT("S Jenkins-",(LEFT(B21,15)),"-",E21) -> S Jenkins-Ballarat Medica-Travel doctor | L21: I | M21: =IF(C21>0,C21,-D21) -> 436.7 | N21: T | R21: =LEN(K21) -> 39
R22: =LEN(K22) -> 0
R23: =LEN(K23) -> 0
R24: =LEN(K24) -> 0
R25: =LEN(K25) -> 0
R26: =LEN(K26) -> 0
R27: =LEN(K27) -> 0
R28: =LEN(K28) -> 0
R29: =LEN(K29) -> 0
R30: =LEN(K30) -> 0
R31: =LEN(K31) -> 0
R32: =LEN(K32) -> 0
R33: =LEN(K33) -> 0
... R35: =LEN(K35) -> 0

Sheet A Lanyon
A1: Employee to code & narrate | J1: To be copied in to pronto
J2: Credit card Statement TOTAL | K2: 462.25
J3: Subtotal | K3: =SUM(M9:M144) -> 462.25
A4: Austell Lanyon | J4: Variance Check | K4: =K2-K3 -> 0
A5: Reference | B5: =CONCATENATE(Header!$E$4,"Lanyon") -> MC-250816Lanyon | J5: EMPLOYEES DO NOT CHANGE
A6: Document Date | B6: =Header!$E$5 -> 45885 | E6: Credit card holder to add details
A8: Date | B8: Narrative | C8: Debit Amount | D8: Credit Amount | E8: Description | F8: Project No | G8: Cost Category | H8: GL account | J8: Account | K8: Reference | L8: Tax | M8: Amount | N8: Tax CODE | O8: TAX Amount (leave blank) | P8: CBS - Only if required | R8: limit 56charaters
A9: 45874 | B9: OFFICEWORKS 0364OFFICE BALLARAT AUS | C9: 27.46 | F9: 1054 | G9: cons | J9: =IF(F9>0,(_xlfn.CONCAT(F9,".",G9)),H9) -> 1054.cons | K9: =_xlfn.CONCAT("A Lanyon-",(LEFT(B9,15)),"-",E9) -> A Lanyon-OFFICEWORKS 036- | L9: I | M9: =IF(C9>0,C9,-D9) -> 27.46 | N9: T | Q9: CBS - needs to be pasted seperately | R9: =LEN(K9) -> 25
A10: 45863 | B10: UBER *TRIP HELP.UBER.C 14518236738 AUS | C10: 11.21 | E10: Blackjack Trip | F10: S16858 | G10: TRVP | J10: =IF(F10>0,(_xlfn.CONCAT(F10,".",G10)),H10) -> S16858.TRVP | K10: =_xlfn.CONCAT("A Lanyon-",(LEFT(B10,15)),"-",E10) -> A Lanyon-UBER *TRIP HELP-Blackjack Trip | L10: I | M10: =IF(C10>0,C10,-D10) -> 11.21 | N10: T | R10: =LEN(K10) -> 39
A11: 45862 | B11: CALTEX CLUDEN CLUDEN AUS | C11: 44.74 | E11: Blackjack Trip | F11: S16858 | G11: TRVP | J11: =IF(F11>0,(_xlfn.CONCAT(F11,".",G11)),H11) -> S16858.TRVP | K11: =_xlfn.CONCAT("A Lanyon-",(LEFT(B11,15)),"-",E11) -> A Lanyon-CALTEX CLUDEN C-Blackjack Trip | L11: I | M11: =IF(C11>0,C11,-D11) -> 44.74 | N11: T | R11: =LEN(K11) -> 39
A12: 45862 | B12: HANNAS - MELB AIRPORT FITZROY NOR AUS | C12: 20.74 | E12: Blackjack Trip | F12: S16858 | G12: TRVP | J12: =IF(F12>0,(_xlfn.CONCAT(F12,".",G12)),H12) -> S16858.TRVP | K12: =_xlfn.CONCAT("A Lanyon-",(LEFT(B12,15)),"-",E12) -> A Lanyon-HANNAS - MELB A-Blackjack Trip | L12: I | M12: =IF(C12>0,C12,-D12) -> 20.74 | N12: T | R12: =LEN(K12) -> 39
A13: 45860 | B13: WOOLWORTHS 2682 CHARTERS TW AUS | C13: 23.4 | E13: Blackjack Trip | F13: S16858 | G13: TRVP | J13: =IF(F13>0,(_xlfn.CONCAT(F13,".",G13)),H13) -> S16858.TRVP | K13: =_xlfn.CONCAT("A Lanyon-",(LEFT(B13,15)),"-",E13) -> A Lanyon-WOOLWORTHS -Blackjack Trip | L13: I | M13: =IF(C13>0,C13,-D13) -> 23.4 | N13: T | R13: =LEN(K13) -> 39
A14: 45859 | B14: SOVEREIGN TAVERN CHARTERS TO AUS | C14: 46.8 | E14: Blackjack Trip | F14: S16858 | G14: TRVP | J14: =IF(F14>0,(_xlfn.CONCAT(F14,".",G14)),H14) -> S16858.TRVP | K14: =_xlfn.CONCAT("A Lanyon-",(LEFT(B14,15)),"-",E14) -> A Lanyon-SOVEREIGN TAVER-Blackjack Trip | L14: I | M14: =IF(C14>0,C14,-D14) -> 46.8 | N14: T | R14: =LEN(K14) -> 39
A15: 45859 | B15: SOVEREIGN TAVERN CHARTERS TO AUS | C15: 14.9 | E15: Blackjack Trip | F15: S16858 | G15: TRVP | J15: =IF(F15>0,(_xlfn.CONCAT(F15,".",G15)),H15) -> S16858.TRVP | K15: =_xlfn.CONCAT("A Lanyon-",(LEFT(B15,15)),"-",E15) -> A Lanyon-SOVEREIGN TAVER-Blackjack Trip | L15: I | M15: =IF(C15>0,C15,-D15) -> 14.9 | N15: T | R15: =LEN(K15) -> 39
A16: 45858 | B16: C-TOWERS PTY LTD CHARTERS TO AUS | C16: 22.74 | E16: Blackjack Trip | F16: S16858 | G16: TRVP | J16: =IF(F16>0,(_xlfn.CONCAT(F16,".",G16)),H16) -> S16858.TRVP | K16: =_xlfn.CONCAT("A Lanyon-",(LEFT(B16,15)),"-",E16) -> A Lanyon-C-TOWERS PTY LT-Blackjack Trip | L16: I | M16: =IF(C16>0,C16,-D16) -> 22.74 | N16: T | R16: =LEN(K16) -> 39
A17: 45858 | B17: Star Charters IGA Charters To AUS | C17: 29 | E17: Blackjack Trip | F17: S16858 | G17: TRVP | J17: =IF(F17>0,(_xlfn.CONCAT(F17,".",G17)),H17) -> S16858.TRVP | K17: =_xlfn.CONCAT("A Lanyon-",(LEFT(B17,15)),"-",E17) -> A Lanyon-Star Charters I-Blackjack Trip | L17: I | M17: =IF(C17>0,C17,-D17) -> 29 | N17: T | R17: =LEN(K17) -> 39
A18: 45857 | B18: RED ROOSTER CHARTER TO CHARTERS TO AUS | C18: 17.5 | E18: Blackjack Trip | F18: S16858 | G18: TRVP | J18: =IF(F18>0,(_xlfn.CONCAT(F18,".",G18)),H18) -> S16858.TRVP | K18: =_xlfn.CONCAT("A Lanyon-",(LEFT(B18,15)),"-",E18) -> A Lanyon-RED ROOSTER CHA-Blackjack Trip | L18: I | M18: =IF(C18>0,C18,-D18) -> 17.5 | N18: T | R18: =LEN(K18) -> 39
A19: 45856 | B19: MCDONALDS FAIRFIELD IDALIA AUS | C19: 18.3 | E19: Blackjack Trip | F19: S16858 | G19: TRVP | J19: =IF(F19>0,(_xlfn.CONCAT(F19,".",G19)),H19) -> S16858.TRVP | K19: =_xlfn.CONCAT("A Lanyon-",(LEFT(B19,15)),"-",E19) -> A Lanyon-MCDONALDS FAIRF-Blackjack Trip | L19: I | M19: =IF(C19>0,C19,-D19) -> 18.3 | N19: T | R19: =LEN(K19) -> 39
A20: 45856 | B20: DELAWARE NORTH RETAQPS MELBOURNE A AUS | C20: 23 | E20: Blackjack Trip | F20: S16858 | G20: TRVP | J20: =IF(F20>0,(_xlfn.CONCAT(F20,".",G20)),H20) -> S16858.TRVP | K20: =_xlfn.CONCAT("A Lanyon-",(LEFT(B20,15)),"-",E20) -> A Lanyon-DELAWARE NORTH -Blackjack Trip | L20: I | M20: =IF(C20>0,C20,-D20) -> 23 | N20: T | R20: =LEN(K20) -> 39
A21: 45856 | B21: WOOLWORTHS 2682 CHARTERS TW AUS | C21: 32.64 | E21: Blackjack Trip | F21: S16858 | G21: TRVP | J21: =IF(F21>0,(_xlfn.CONCAT(F21,".",G21)),H21) -> S16858.TRVP | K21: =_xlfn.CONCAT("A Lanyon-",(LEFT(B21,15)),"-",E21) -> A Lanyon-WOOLWORTHS -Blackjack Trip | L21: I | M21: =IF(C21>0,C21,-D21) -> 32.64 | N21: T | R21: =LEN(K21) -> 39
... A24: 45855 | B24: Airport Shuttle Bus BAKERY HILL AUS | C24: 90 | E24: Blackjack Trip | F24: S16858 | G24: TRVP | J24: =IF(F24>0,(_xlfn.CONCAT(F24,".",G24)),H24) -> S16858.TRVP | K24: =_xlfn.CONCAT("A Lanyon-",(LEFT(B24,15)),"-",E24) -> A Lanyon-Airport Shuttle-Blackjack Trip | L24: I | M24: =IF(C24>0,C24,-D24) -> 90 | N24: T | R24: =LEN(K24) -> 39
R25: =LEN(K25) -> 0
R26: =LEN(K26) -> 0
R27: =LEN(K27) -> 0
R28: =LEN(K28) -> 0
R29: =LEN(K29) -> 0
R30: =LEN(K30) -> 0
R31: =LEN(K31) -> 0
R32: =LEN(K32) -> 0
R33: =LEN(K33) -> 0
R34: =LEN(K34) -> 0
R35: =LEN(K35) -> 0

Sheet E Lewis-Gray
A1: Employee to code & narrate | J1: To be copied in to pronto
J2: Credit card Statement TOTAL | K2: 253.42
J3: Subtotal | K3: =SUM(M9:M144) -> 253.42
A4: Elizabeth Lewis-Gray | J4: Variance Check | K4: =K2-K3 -> 0
A5: Reference | B5: =CONCATENATE(Header!$E$4,"ELG") -> MC-250816ELG | J5: EMPLOYEES DO NOT CHANGE
A6: Document Date | B6: =Header!$E$5 -> 45885 | E6: Credit card holder to add details
A8: Date | B8: Narrative | C8: Debit Amount | D8: Credit Amount | E8: Description | F8: Project No | G8: Cost Category | H8: GL account | J8: Account | K8: Reference | L8: Tax | M8: Amount | N8: Tax CODE | O8: TAX Amount (leave blank) | P8: CBS - Only if required | R8: limit 56charaters
A9: 45861 | B9: FLOWERSGILB 0364262877 AUS | C9: 175 | E9: Flowers for M Gort | F9: 1084 | G9: STAF | J9: =IF(F9>0,(_xlfn.CONCAT(F9,".",G9)),H9) -> 1084.STAF | K9: =_xlfn.CONCAT("ELewisGray-",(LEFT(B9,15)),"-",E9) -> ELewisGray-FLOWERSGILB 036-Flowers for M Gort | L9: I | M9: =IF(C9>0,C9,-D9) -> 175 | N9: T | Q9: CBS - needs to be pasted seperately | R9: =LEN(K9) -> 45
A10: 45859 | B10: AVIS AUSTRALIA MASCOT AUS | C10: 78.42 | E10: Personal Use | F10: 1084 | G10: pers | J10: =IF(F10>0,(_xlfn.CONCAT(F10,".",G10)),H10) -> 1084.pers | K10: =_xlfn.CONCAT("ELewisGray-",(LEFT(B10,15)),"-",E10) -> ELewisGray-AVIS AUSTRALIA -Personal Use | L10: I | M10: =IF(C10>0,C10,-D10) -> 78.42 | N10: F | R10: =LEN(K10) -> 39
R11: =LEN(K11) -> 0
R12: =LEN(K12) -> 0
R13: =LEN(K13) -> 0
R14: =LEN(K14) -> 0
R15: =LEN(K15) -> 0
R16: =LEN(K16) -> 0
R17: =LEN(K17) -> 0
R18: =LEN(K18) -> 0
R19: =LEN(K19) -> 0
R20: =LEN(K20) -> 0
R21: =LEN(K21) -> 0
R22: =LEN(K22) -> 0
... R35: =LEN(K35) -> 0

Sheet S Lewis-Gray
A1: Employee to code & narrate | J1: To be copied in to pronto
J2: Credit card Statement TOTAL | K2: 3937
J3: Subtotal | K3: =SUM(M9:M144) -> 3937
A4: Sandy Gray | J4: Variance Check | K4: =K2-K3 -> 0
A5: Reference | B5: =CONCATENATE(Header!$E$4,"ALG") -> MC-250816ALG | J5: EMPLOYEES DO NOT CHANGE
A6: Document Date | B6: =Header!$E$5 -> 45885 | E6: Credit card holder to add details
A8: Date | B8: Narrative | C8: Debit Amount | D8: Credit Amount | E8: Description | F8: Project No | G8: Cost Category | H8: GL account | J8: Account | K8: Reference | L8: Tax | M8: Amount | N8: Tax CODE | O8: TAX Amount (leave blank) | P8: CBS - Only if required | R8: limit 56charaters
A9: 45877 | B9: BUDGET RENT A CAR MASCOT AUS | C9: =295.96/2 -> 147.98 | E9: Peninsula Downs Trip / WA Gekko Sales Trip | F9: 1084 | G9: TRAV | J9: =IF(F9>0,(_xlfn.CONCAT(F9,".",G9)),H9) -> 1084.TRAV | K9: =_xlfn.CONCAT("S Gray-",(LEFT(B9,15)),"-",E9) -> S Gray-BUDGET RENT A C-Peninsula Downs Trip / WA Gekko Sales Trip | L9: I | M9: =IF(C9>0,C9,-D9) -> 147.98 | N9: T | R9: =LEN(K9) -> 66
A10: 45877 | B10: BUDGET RENT A CAR MASCOT AUS | C10: =295.96/2 -> 147.98 | E10: G1145-Peninsula Downs Trip | F10: 1060GE2 | G10: MISC | J10: =IF(F10>0,(_xlfn.CONCAT(F10,".",G10)),H10) -> 1060GE2.MISC | K10: =_xlfn.CONCAT("S Gray-",(LEFT(B10,15)),"-",E10) -> S Gray-BUDGET RENT A C-G1145-Peninsula Downs Trip | L10: I | M10: =IF(C10>0,C10,-D10) -> 147.98 | N10: T | R10: =LEN(K10) -> 49
A11: 45877 | B11: QT PERTH OPI Perth AUS | C11: =28.42/2 -> 14.21 | E11: Peninsula Downs Trip / WA Gekko Sales Trip | F11: 1084 | G11: TRAV | J11: =IF(F11>0,(_xlfn.CONCAT(F11,".",G11)),H11) -> 1084.TRAV | K11: =_xlfn.CONCAT("S Gray-",(LEFT(B11,15)),"-",E11) -> S Gray-QT PERTH OPI Pe-Peninsula Downs Trip / WA Gekko Sales Trip | L11: I | M11: =IF(C11>0,C11,-D11) -> 14.21 | N11: T | R11: =LEN(K11) -> 66
A12: 45877 | B12: QT PERTH OPI Perth AUS | C12: =28.42/2 -> 14.21 | E12: G1145-Peninsula Downs Trip | F12: 1060GE2 | G12: MISC | J12: =IF(F12>0,(_xlfn.CONCAT(F12,".",G12)),H12) -> 1060GE2.MISC | K12: =_xlfn.CONCAT("S Gray-",(LEFT(B12,15)),"-",E12) -> S Gray-QT PERTH OPI Pe-G1145-Peninsula Downs Trip | L12: I | M12: =IF(C12>0,C12,-D12) -> 14.21 | N12: T | R12: =LEN(K12) -> 49
A13: 45877 | B13: QT PERTH OPI Perth AUS | C13: =156.82/2 -> 78.41 | E13: Peninsula Downs Trip / WA Gekko Sales Trip | F13: 1084 | G13: TRAV | J13: =IF(F13>0,(_xlfn.CONCAT(F13,".",G13)),H13) -> 1084.TRAV | K13: =_xlfn.CONCAT("S Gray-",(LEFT(B13,15)),"-",E13) -> S Gray-QT PERTH OPI Pe-Peninsula Downs Trip / WA Gekko Sales Trip | L13: I | M13: =IF(C13>0,C13,-D13) -> 78.41 | N13: T | R13: =LEN(K13) -> 66
A14: 45877 | B14: QT PERTH OPI Perth AUS | C14: =156.82/2 -> 78.41 | E14: G1145-Peninsula Downs Trip | F14: 1060GE2 | G14: MISC | J14: =IF(F14>0,(_xlfn.CONCAT(F14,".",G14)),H14) -> 1060GE2.MISC | K14: =_xlfn.CONCAT("S Gray-",(LEFT(B14,15)),"-",E14) -> S Gray-QT PERTH OPI Pe-G1145-Peninsula Downs Trip | L14: I | M14: =IF(C14>0,C14,-D14) -> 78.41 | N14: T | R14: =LEN(K14) -> 49
A15: 45877 | B15: 7 ELEVEN 3045 ASCOT AUS | C15: =78.88/2 -> 39.44 | E15: Peninsula Downs Trip / WA Gekko Sales Trip | F15: 1084 | G15: TRAV | J15: =IF(F15>0,(_xlfn.CONCAT(F15,".",G15)),H15) -> 1084.TRAV | K15: =_xlfn.CONCAT("S Gray-",(LEFT(B15,15)),"-",E15) -> S Gray-7 ELEVEN 3045 A-Peninsula Downs Trip / WA Gekko Sales Trip | L15: I | M15: =IF(C15>0,C15,-D15) -> 39.44 | N15: T | R15: =LEN(K15) -> 66
A16: 45877 | B16: 7 ELEVEN 3045 ASCOT AUS | C16: =78.88/2 -> 39.44 | E16: G1145-Peninsula Downs Trip | F16: 1060GE2 | G16: MISC | J16: =IF(F16>0,(_xlfn.CONCAT(F16,".",G16)),H16) -> 1060GE2.MISC | K16: =_xlfn.CONCAT("S Gray-",(LEFT(B16,15)),"-",E16) -> S Gray-7 ELEVEN 3045 A-G1145-Peninsula Downs Trip | L16: I | M16: =IF(C16>0,C16,-D16) -> 39.44 | N16: T | R16: =LEN(K16) -> 49
A17: 45877 | B17: QANTAS VALET Fitzroy AUS | C17: =312/2 -> 156 | E17: Peninsula Downs Trip / WA Gekko Sales Trip | F17: 1084 | G17: TRAV | J17: =IF(F17>0,(_xlfn.CONCAT(F17,".",G17)),H17) -> 1084.TRAV | K17: =_xlfn.CONCAT("S Gray-",(LEFT(B17,15)),"-",E17) -> S Gray-QANTAS VALET Fi-Peninsula Downs Trip / WA Gekko Sales Trip | L17: I | M17: =IF(C17>0,C17,-D17) -> 156 | N17: T | R17: =LEN(K17) -> 66
A18: 45877 | B18: QANTAS VALET Fitzroy AUS | C18: =312/2 -> 156 | E18: G1145-Peninsula Downs Trip | F18: 1060GE2 | G18: MISC | J18: =IF(F18>0,(_xlfn.CONCAT(F18,".",G18)),H18) -> 1060GE2.MISC | K18: =_xlfn.CONCAT("S Gray-",(LEFT(B18,15)),"-",E18) -> S Gray-QANTAS VALET Fi-G1145-Peninsula Downs Trip | L18: I | M18: =IF(C18>0,C18,-D18) -> 156 | N18: T | R18: =LEN(K18) -> 49
A19: 45875 | B19: QANTAS0812374309572 NSW AUS | C19: =455.07/2 -> 227.535 | E19: Peninsula Downs Trip / WA Gekko Sales Trip | F19: 1084 | G19: TRAV | J19: =IF(F19>0,(_xlfn.CONCAT(F19,".",G19)),H19) -> 1084.TRAV | K19: =_xlfn.CONCAT("S Gray-",(LEFT(B19,15)),"-",E19) -> S Gray-QANTAS081237430-Peninsula Downs Trip / WA Gekko Sales Trip | L19: I | M19: =IF(C19>0,C19,-D19) -> 227.535 | N19: T | R19: =LEN(K19) -> 66
A20: 45875 | B20: QANTAS0812374309572 NSW AUS | C20: =455.07/2 -> 227.535 | E20: G1145-Peninsula Downs Trip | F20: 1060GE2 | G20: MISC | J20: =IF(F20>0,(_xlfn.CONCAT(F20,".",G20)),H20) -> 1060GE2.MISC | K20: =_xlfn.CONCAT("S Gray-",(LEFT(B20,15)),"-",E20) -> S Gray-QANTAS081237430-G1145-Peninsula Downs Trip | L20: I | M20: =IF(C20>0,C20,-D20) -> 227.535 | N20: T | R20: =LEN(K20) -> 49
A21: 45875 | B21: MARY STREET BAKERY ALL Perth AUS | C21: =41.49/2 -> 20.745 | E21: Peninsula Downs Trip / WA Gekko Sales Trip | F21: 1084 | G21: TRAV | J21: =IF(F21>0,(_xlfn.CONCAT(F21,".",G21)),H21) -> 1084.TRAV | K21: =_xlfn.CONCAT("S Gray-",(LEFT(B21,15)),"-",E21) -> S Gray-MARY STREET BAK-Peninsula Downs Trip / WA Gekko Sales Trip | L21: I | M21: =IF(C21>0,C21,-D21) -> 20.745 | N21: T | R21: =LEN(K21) -> 66
A22: 45875 | B22: MARY STREET BAKERY ALL Perth AUS | C22: =41.49/2 -> 20.745 | E22: G1145-Peninsula Downs Trip | F22: 1060GE2 | G22: MISC | J22: =IF(F22>0,(_xlfn.CONCAT(F22,".",G22)),H22) -> 1060GE2.MISC | K22: =_xlfn.CONCAT("S Gray-",(LEFT(B22,15)),"-",E22) -> S Gray-MARY STREET BAK-G1145-Peninsula Downs Trip | L22: I | M22: =IF(C22>0,C22,-D22) -> 20.745 | N22: T | R22: =LEN(K22) -> 49
A23: 45875 | B23: SWAN TAXIS PTY LTD VICTORIA PA AUS | C23: =22.79/2 -> 11.395 | E23: Peninsula Downs Trip / WA Gekko Sales Trip | F23: 1084 | G23: TRAV | J23: =IF(F23>0,(_xlfn.CONCAT(F23,".",G23)),H23) -> 1084.TRAV | K23: =_xlfn.CONCAT("S Gray-",(LEFT(B23,15)),"-",E23) -> S Gray-SWAN TAXIS PTY -Peninsula Downs Trip / WA Gekko Sales Trip | L23: I | M23: =IF(C23>0,C23,-D23) -> 11.395 | N23: T | R23: =LEN(K23) -> 66
A24: 45875 | B24: SWAN TAXIS PTY LTD VICTORIA PA AUS | C24: =22.79/2 -> 11.395 | E24: G1145-Peninsula Downs Trip | F24: 1060GE2 | G24: MISC | J24: =IF(F24>0,(_xlfn.CONCAT(F24,".",G24)),H24) -> 1060GE2.MISC | K24: =_xlfn.CONCAT("S Gray-",(LEFT(B24,15)),"-",E24) -> S Gray-SWAN TAXIS PTY -G1145-Peninsula Downs Trip | L24: I | M24: =IF(C24>0,C24,-D24) -> 11.395 | N24: T | R24: =LEN(K24) -> 49
A25: 45875 | B25: Hotel at Booking.com Sydney AUS | C25: =165/2 -> 82.5 | E25: Peninsula Downs Trip / WA Gekko Sales Trip | F25: 1084 | G25: TRAV | J25: =IF(F25>0,(_xlfn.CONCAT(F25,".",G25)),H25) -> 1084.TRAV | K25: =_xlfn.CONCAT("S Gray-",(LEFT(B25,15)),"-",E25) -> S Gray-Hotel at Bookin-Peninsula Downs Trip / WA Gekko Sales Trip | L25: I | M25: =IF(C25>0,C25,-D25) -> 82.5 | N25: T | R25: =LEN(K25) -> 66
A26: 45875 | B26: Hotel at Booking.com Sydney AUS | C26: =165/2 -> 82.5 | E26: G1145-Peninsula Downs Trip | F26: 1060GE2 | G26: MISC | J26: =IF(F26>0,(_xlfn.CONCAT(F26,".",G26)),H26) -> 1060GE2.MISC | K26: =_xlfn.CONCAT("S Gray-",(LEFT(B26,15)),"-",E26) -> S Gray-Hotel at Bookin-G1145-Peninsula Downs Trip | L26: I | M26: =IF(C26>0,C26,-D26) -> 82.5 | N26: T | R26: =LEN(K26) -> 49
A27: 45868 | B27: QANTAS081HQA3H4VM6A MASCOT AUS | C27: =885/2 -> 442.5 | E27: Peninsula Downs Trip / WA Gekko Sales Trip | F27: 1084 | G27: TRAV | J27: =IF(F27>0,(_xlfn.CONCAT(F27,".",G27)),H27) -> 1084.TRAV | K27: =_xlfn.CONCAT("S Gray-",(LEFT(B27,15)),"-",E27) -> S Gray-QANTAS081HQA3H4-Peninsula Downs Trip / WA Gekko Sales Trip | L27: I | M27: =IF(C27>0,C27,-D27) -> 442.5 | N27: T | R27: =LEN(K27) -> 66
A28: 45868 | B28: QANTAS081HQA3H4VM6A MASCOT AUS | C28: =885/2 -> 442.5 | E28: G1145-Peninsula Downs Trip | F28: 1060GE2 | G28: MISC | J28: =IF(F28>0,(_xlfn.CONCAT(F28,".",G28)),H28) -> 1060GE2.MISC | K28: =_xlfn.CONCAT("S Gray-",(LEFT(B28,15)),"-",E28) -> S Gray-QANTAS081HQA3H4-G1145-Peninsula Downs Trip | L28: I | M28: =IF(C28>0,C28,-D28) -> 442.5 | N28: T | R28: =LEN(K28) -> 49
A29: 45867 | B29: QANTAS0812373860663 NSW AUS | C29: =144.2/2 -> 72.1 | E29: Peninsula Downs Trip / WA Gekko Sales Trip | F29: 1084 | G29: TRAV | J29: =IF(F29>0,(_xlfn.CONCAT(F29,".",G29)),H29) -> 1084.TRAV | K29: =_xlfn.CONCAT("S Gray-",(LEFT(B29,15)),"-",E29) -> S Gray-QANTAS081237386-Peninsula Downs Trip / WA Gekko Sales Trip | L29: I | M29: =IF(C29>0,C29,-D29) -> 72.1 | N29: T | R29: =LEN(K29) -> 66
A30: 45867 | B30: QANTAS0812373860663 NSW AUS | C30: =144.2/2 -> 72.1 | E30: G1145-Peninsula Downs Trip | F30: 1060GE2 | G30: MISC | J30: =IF(F30>0,(_xlfn.CONCAT(F30,".",G30)),H30) -> 1060GE2.MISC | K30: =_xlfn.CONCAT("S Gray-",(LEFT(B30,15)),"-",E30) -> S Gray-QANTAS081237386-G1145-Peninsula Downs Trip | L30: I | M30: =IF(C30>0,C30,-D30) -> 72.1 | N30: T | R30: =LEN(K30) -> 49
A31: 45866 | B31: BUDGET RENT A CAR HOBART AUS | C31: 44.75 | F31: 1084 | G31: TRAV | J31: =IF(F31>0,(_xlfn.CONCAT(F31,".",G31)),H31) -> 1084.TRAV | K31: =_xlfn.CONCAT("S Gray-",(LEFT(B31,15)),"-",E31) -> S Gray-BUDGET RENT A C- | L31: I | M31: =IF(C31>0,C31,-D31) -> 44.75 | N31: T | R31: =LEN(K31) -> 23
A32: 45866 | B32: QANTAS VALET PARKING M MELBOURNE AUS | C32: =171.68/2 -> 85.84 | E32: Peninsula Downs Trip / WA Gekko Sales Trip | F32: 1084 | G32: TRAV | J32: =IF(F32>0,(_xlfn.CONCAT(F32,".",G32)),H32) -> 1084.TRAV | K32: =_xlfn.CONCAT("S Gray-",(LEFT(B32,15)),"-",E32) -> S Gray-QANTAS VALET PA-Peninsula Downs Trip / WA Gekko Sales Trip | L32: I | M32: =IF(C32>0,C32,-D32) -> 85.84 | N32: T | R32: =LEN(K32) -> 66
A33: 45866 | B33: QANTAS VALET PARKING M MELBOURNE AUS | C33: =171.68/2 -> 85.84 | E33: G1145-Peninsula Downs Trip | F33: 1060GE2 | G33: MISC | J33: =IF(F33>0,(_xlfn.CONCAT(F33,".",G33)),H33) -> 1060GE2.MISC | K33: =_xlfn.CONCAT("S Gray-",(LEFT(B33,15)),"-",E33) -> S Gray-QANTAS VALET PA-G1145-Peninsula Downs Trip | L33: I | M33: =IF(C33>0,C33,-D33) -> 85.84 | N33: T | R33: =LEN(K33) -> 49
A34: 45865 | B34: BEACHFRONT VOYAGER M BURNIE AUS | C34: 5 | F34: 1084 | G34: TRAV | J34: =IF(F34>0,(_xlfn.CONCAT(F34,".",G34)),H34) -> 1084.TRAV | K34: =_xlfn.CONCAT("S Gray-",(LEFT(B34,15)),"-",E34) -> S Gray-BEACHFRONT VOYA- | L34: I | M34: =IF(C34>0,C34,-D34) -> 5 | N34: T | R34: =LEN(K34) -> 23
A35: 45862 | B35: DSwiss AG Z rich CHE FRGN AMT: 59.40 U. S. DOLLAR | C35: 93.49 | F35: 1041 | G35: TRAV | J35: =IF(F35>0,(_xlfn.CONCAT(F35,".",G35)),H35) -> 1041.TRAV | K35: =_xlfn.CONCAT("S Gray-",(LEFT(B35,15)),"-",E35) -> S Gray-DSwiss AG Z ric- | L35: I | M35: =IF(C35>0,C35,-D35) -> 93.49 | N35: F | R35: =LEN(K35) -> 23
A36: 45861 | B36: SQ *LE PECHE GOURMAND Creswick AUS | C36: 112.55 | E36: Catering Pronto lunch | F36: 1084 | G36: ENON | J36: =IF(F36>0,(_xlfn.CONCAT(F36,".",G36)),H36) -> 1084.ENON | K36: =_xlfn.CONCAT("S Gray-",(LEFT(B36,15)),"-",E36) -> S Gray-SQ *LE PECHE GO-Catering Pronto lunch | L36: I | M36: =IF(C36>0,C36,-D36) -> 112.55 | N36: T | R36: =LEN(K36) -> 44
A37: 45860 | B37: WEBJET MELBOURNE AUS | C37: =923.9/2 -> 461.95 | E37: Peninsula Downs Trip / WA Gekko Sales Trip | F37: 1084 | G37: TRAV | J37: =IF(F37>0,(_xlfn.CONCAT(F37,".",G37)),H37) -> 1084.TRAV | K37: =_xlfn.CONCAT("S Gray-",(LEFT(B37,15)),"-",E37) -> S Gray-WEBJET MELBOURN-Peninsula Downs Trip / WA Gekko Sales Trip | L37: I | M37: =IF(C37>0,C37,-D37) -> 461.95 | N37: T | R37: =LEN(K37) -> 66
A38: 45860 | B38: WEBJET MELBOURNE AUS | C38: =923.9/2 -> 461.95 | E38: G1145-Peninsula Downs Trip | F38: 1060GE2 | G38: MISC | J38: =IF(F38>0,(_xlfn.CONCAT(F38,".",G38)),H38) -> 1060GE2.MISC | K38: =_xlfn.CONCAT("S Gray-",(LEFT(B38,15)),"-",E38) -> S Gray-WEBJET MELBOURN-G1145-Peninsula Downs Trip | L38: I | M38: =IF(C38>0,C38,-D38) -> 461.95 | N38: T | R38: =LEN(K38) -> 49

Sheet W Lodge
A1: Employee to code & narrate | J1: To be copied in to pronto
J2: Credit card Statement TOTAL | K2: 3472.3
J3: Subtotal | K3: =SUM(M9:M144) -> 3472.3
A4: Wayne Lodge | J4: Variance Check | K4: =K2-K3 -> 0
A5: Reference | B5: =CONCATENATE(Header!$E$4,"Lodge") -> MC-250816Lodge | J5: EMPLOYEES DO NOT CHANGE
A6: Document Date | B6: =Header!$E$5 -> 45885 | E6: Credit card holder to add details
A8: Date | B8: Narrative | C8: Debit Amount | D8: Credit Amount | E8: Description | F8: Project No | G8: Cost Category | H8: GL account | J8: Account | K8: Reference | L8: Tax | M8: Amount | N8: Tax CODE | O8: TAX Amount (leave blank) | P8: CBS - Only if required | R8: limit 56charaters
A9: 45860 | B9: CBSA-ASFC OTTAWA CAN FRGN AMT: 3000.00 CANADIAN DOLLAR | C9: 3472.3 | E9: Import bond for Canada under the CARM regulations | H9: 199999991130 | J9: =IF(F9>0,(_xlfn.CONCAT(F9,".",G9)),H9) -> 199999991130 | K9: =_xlfn.CONCAT("W Lodge-",(LEFT(B9,15)),"-",E9) -> W Lodge-CBSA-ASFC OTTAW-Import bond for Canada under the CARM regulations | L9: I | M9: =IF(C9>0,C9,-D9) -> 3472.3 | N9: F | Q9: CBS - needs to be pasted seperately | R9: =LEN(K9) -> 73
R10: =LEN(K10) -> 0
R11: =LEN(K11) -> 0
R12: =LEN(K12) -> 0
R13: =LEN(K13) -> 0
R14: =LEN(K14) -> 0
R15: =LEN(K15) -> 0
R16: =LEN(K16) -> 0
R17: =LEN(K17) -> 0
R18: =LEN(K18) -> 0
R19: =LEN(K19) -> 0
R20: =LEN(K20) -> 0
R21: =LEN(K21) -> 0
... R30: =LEN(K30) -> 0

Sheet S McLaughlin
A1: Employee to code & narrate | J1: To be copied in to pronto
J2: Credit card Statement TOTAL | K2: 427.96
J3: Subtotal | K3: =SUM(M9:M144) -> 427.96
A4: Shane McLaughlin | J4: Variance Check | K4: =K2-K3 -> 0
A5: Reference | B5: =CONCATENATE(Header!$E$4,"McLaughlin") -> MC-250816McLaughlin | J5: EMPLOYEES DO NOT CHANGE
A6: Document Date | B6: =Header!$E$5 -> 45885 | E6: Credit card holder to add details
A8: Date | B8: Narrative | C8: Debit Amount | D8: Credit Amount | E8: Description | F8: Project No | G8: Cost Category | H8: GL account | J8: Account | K8: Reference | L8: Tax | M8: Amount | N8: Tax CODE | O8: TAX Amount (leave blank) | P8: CBS - Only if required | R8: limit 56charaters
A9: 45882 | B9: METRO PETROLEUM GOLDEN Golden Poin AUS | C9: 17.41 | E9: Petrol CN pump | F9: 1051 | G9: CONS | J9: =IF(F9>0,(_xlfn.CONCAT(F9,".",G9)),H9) -> 1051.CONS | K9: =_xlfn.CONCAT("S McLaughlin-",(LEFT(B9,15)),"-",E9) -> S McLaughlin-METRO PETROLEUM-Petrol CN pump | L9: I | M9: =IF(C9>0,C9,-D9) -> 17.41 | N9: T | Q9: CBS - needs to be pasted seperately | R9: =LEN(K9) -> 43
A10: 45881 | B10: COLES 7798 BALLARAT AUS | C10: 21.3 | E10: Wed lunch drinks | F10: 1051 | G10: STAF | J10: =IF(F10>0,(_xlfn.CONCAT(F10,".",G10)),H10) -> 1051.STAF | K10: =_xlfn.CONCAT("S McLaughlin-",(LEFT(B10,15)),"-",E10) -> S McLaughlin-COLES 7798 BALL-Wed lunch drinks | L10: I | M10: =IF(C10>0,C10,-D10) -> 21.3 | N10: T | R10: =LEN(K10) -> 45
A11: 45878 | B11: METRO PETROLEUM GOLDEN Golden Poin AUS | C11: 60.4 | E11: Petrol Personal Car use | F11: 1051 | G11: MVPF | J11: =IF(F11>0,(_xlfn.CONCAT(F11,".",G11)),H11) -> 1051.MVPF | K11: =_xlfn.CONCAT("S McLaughlin-",(LEFT(B11,15)),"-",E11) -> S McLaughlin-METRO PETROLEUM-Petrol Personal Car use | L11: I | M11: =IF(C11>0,C11,-D11) -> 60.4 | N11: T | R11: =LEN(K11) -> 52
A12: 45876 | B12: BUNNINGS 730000 BALLARAT AUS | C12: 79.41 | E12: Safety gloves, cable ties | F12: 1051 | G12: SPPE | J12: =IF(F12>0,(_xlfn.CONCAT(F12,".",G12)),H12) -> 1051.SPPE | K12: =_xlfn.CONCAT("S McLaughlin-",(LEFT(B12,15)),"-",E12) -> S McLaughlin-BUNNINGS 730000-Safety gloves, cable ties | L12: I | M12: =IF(C12>0,C12,-D12) -> 79.41 | N12: T | R12: =LEN(K12) -> 54
A13: 45870 | B13: Ballarat Materials Ha MITCHELL PA AUS | C13: 85.18 | E13: Bottle Roll containers | F13: 1051 | G13: CONS | J13: =IF(F13>0,(_xlfn.CONCAT(F13,".",G13)),H13) -> 1051.CONS | K13: =_xlfn.CONCAT("S McLaughlin-",(LEFT(B13,15)),"-",E13) -> S McLaughlin-Ballarat Materi-Bottle Roll containers | L13: I | M13: =IF(C13>0,C13,-D13) -> 85.18 | N13: T | R13: =LEN(K13) -> 51
A14: 45867 | B14: METRO PETROLEUM GOLDEN Golden Poin AUS | C14: 15.65 | E14: Petrol CN pump | F14: 1051 | G14: CONS | J14: =IF(F14>0,(_xlfn.CONCAT(F14,".",G14)),H14) -> 1051.CONS | K14: =_xlfn.CONCAT("S McLaughlin-",(LEFT(B14,15)),"-",E14) -> S McLaughlin-METRO PETROLEUM-Petrol CN pump | L14: I | M14: =IF(C14>0,C14,-D14) -> 15.65 | N14: T | R14: =LEN(K14) -> 43
A15: 45862 | B15: FIFTEEN NEEDLES GROUP WENDOUREE AUS | C15: 52 | E15: Hip Pocket Safety Gear | F15: 1051 | G15: SPPE | J15: =IF(F15>0,(_xlfn.CONCAT(F15,".",G15)),H15) -> 1051.SPPE | K15: =_xlfn.CONCAT("S McLaughlin-",(LEFT(B15,15)),"-",E15) -> S McLaughlin-FIFTEEN NEEDLES-Hip Pocket Safety Gear | L15: I | M15: =IF(C15>0,C15,-D15) -> 52 | N15: T | R15: =LEN(K15) -> 51
A16: 45862 | B16: BUNNINGS 730000 BALLARAT AUS | C16: 9 | E16: Safety Gloves | F16: 1051 | G16: SPPE | J16: =IF(F16>0,(_xlfn.CONCAT(F16,".",G16)),H16) -> 1051.SPPE | K16: =_xlfn.CONCAT("S McLaughlin-",(LEFT(B16,15)),"-",E16) -> S McLaughlin-BUNNINGS 730000-Safety Gloves | L16: I | M16: =IF(C16>0,C16,-D16) -> 9 | N16: T | R16: =LEN(K16) -> 42
A17: 45861 | B17: WOOLWORTHS 3309 WENDOUREE AUS | C17: 27.6 | E17: Wed lunch drinks | F17: 1051 | G17: STAF | J17: =IF(F17>0,(_xlfn.CONCAT(F17,".",G17)),H17) -> 1051.STAF | K17: =_xlfn.CONCAT("S McLaughlin-",(LEFT(B17,15)),"-",E17) -> S McLaughlin-WOOLWORTHS -Wed lunch drinks | L17: I | M17: =IF(C17>0,C17,-D17) -> 27.6 | N17: T | R17: =LEN(K17) -> 45
A18: 45854 | B18: APCO MAIN RD BALLARA BALLARAT AUS | C18: 60.01 | E18: Petrol Personal Car use | F18: 1051 | G18: MVPF | J18: =IF(F18>0,(_xlfn.CONCAT(F18,".",G18)),H18) -> 1051.MVPF | K18: =_xlfn.CONCAT("S McLaughlin-",(LEFT(B18,15)),"-",E18) -> S McLaughlin-APCO MAIN RD BA-Petrol Personal Car use | L18: I | M18: =IF(C18>0,C18,-D18) -> 60.01 | N18: T | R18: =LEN(K18) -> 52
R19: =LEN(K19) -> 0
R20: =LEN(K20) -> 0
R21: =LEN(K21) -> 0
R22: =LEN(K22) -> 0
R23: =LEN(K23) -> 0
R24: =LEN(K24) -> 0
R25: =LEN(K25) -> 0
R26: =LEN(K26) -> 0
R27: =LEN(K27) -> 0
R28: =LEN(K28) -> 0
R29: =LEN(K29) -> 0
R30: =LEN(K30) -> 0

Sheet M Ntombela
A1: Employee to code & narrate | J1: To be copied in to pronto
J2: Credit card Statement TOTAL | K2: 570
J3: Subtotal | K3: =SUM(M9:M144) -> 570
A4: Mx Ntombela | J4: Variance Check | K4: =K2-K3 -> 0
A5: Reference | B5: =CONCATENATE(Header!$E$4,"Ntombela") -> MC-250816Ntombela | J5: EMPLOYEES DO NOT CHANGE
A6: Document Date | B6: =Header!$E$5 -> 45885 | E6: Credit card holder to add details
A8: Date | B8: Narrative | C8: Debit Amount | D8: Credit Amount | E8: Description | F8: Project No | G8: Cost Category | H8: GL account | J8: Account | K8: Reference | L8: Tax | M8: Amount | N8: Tax CODE | O8: TAX Amount (leave blank) | P8: CBS - Only if required | R8: limit 56charaters
A9: 45876 | B9: MYKI | C9: 20 | E9: Train Fare to/from MelbMining Club Lunch | F9: 1041 | G9: TRAV | J9: =IF(F9>0,(_xlfn.CONCAT(F9,".",G9)),H9) -> 1041.TRAV | K9: =_xlfn.CONCAT("M Ntombela-",(LEFT(B9,15)),"-",E9) -> M Ntombela-MYKI-Train Fare to/from MelbMining Club Lunch | L9: I | M9: =IF(C9>0,C9,-D9) -> 20 | N9: T | Q9: CBS - needs to be pasted seperately | R9: =LEN(K9) -> 56
A10: 45868 | B10: AusIMM | C10: 550 | E10: 12mth Subs 1041/MEMB | H10: 199999991502 | J10: =IF(F10>0,(_xlfn.CONCAT(F10,".",G10)),H10) -> 199999991502 | K10: =_xlfn.CONCAT("M Ntombela-",(LEFT(B10,15)),"-",E10) -> M Ntombela-AusIMM-12mth Subs 1041/MEMB | L10: I | M10: =IF(C10>0,C10,-D10) -> 550 | N10: T | R10: =LEN(K10) -> 38 | U10: 1041 | V10: MEMB
R11: =LEN(K11) -> 0
R12: =LEN(K12) -> 0
R13: =LEN(K13) -> 0
R14: =LEN(K14) -> 0
R15: =LEN(K15) -> 0
R16: =LEN(K16) -> 0
R17: =LEN(K17) -> 0
R18: =LEN(K18) -> 0
R19: =LEN(K19) -> 0
R20: =LEN(K20) -> 0
R21: =LEN(K21) -> 0
R22: =LEN(K22) -> 0
... R30: =LEN(K30) -> 0

Sheet M Prendergast
A1: Employee to code & narrate | J1: To be copied in to pronto
J2: Credit card Statement TOTAL | K2: 32.79
J3: Subtotal | K3: =SUM(M9:M144) -> 32.79
A4: Melinda Pendergast | J4: Variance Check | K4: =K2-K3 -> 0
A5: Reference | B5: =CONCATENATE(Header!$E$4,"Pendergast") -> MC-250816Pendergast | J5: EMPLOYEES DO NOT CHANGE
A6: Document Date | B6: =Header!$E$5 -> 45885 | E6: Credit card holder to add details
A8: Date | B8: Narrative | C8: Debit Amount | D8: Credit Amount | E8: Description - Please limit to short 30 character limit | F8: Project No | G8: Cost Category | H8: GL account | J8: Account | K8: Reference | L8: Tax | M8: Amount | N8: Tax CODE | O8: TAX Amount (leave blank) | P8: CBS - Only if required | R8: limit 56charaters
A9: 45867 | B9: ALIEXPRESS | C9: 15.88 | E9: replac the Orange Pi with Ethernet apt-USB type A 90° adpt | F9: X195 | G9: ASPU | J9: =IF(F9>0,(_xlfn.CONCAT(F9,".",G9)),H9) -> X195.ASPU | K9: =_xlfn.CONCAT("M Pendergast-",(LEFT(B9,15)),"-",E9) -> M Pendergast-ALIEXPRESS-replac the Orange Pi with Ethernet apt-USB type A 90° adpt | L9: I | M9: =IF(C9>0,C9,-D9) -> 15.88 | N9: F | Q9: CBS - needs to be pasted seperately | R9: =LEN(K9) -> 83
A10: 45856 | B10: aliexpress | C10: 16.91 | E10: 2xHDMIDummyPlug 4K@60Hz forPMeyer for testing | F10: X129-04 | G10: ASPU | J10: =IF(F10>0,(_xlfn.CONCAT(F10,".",G10)),H10) -> X129-04.ASPU | K10: =_xlfn.CONCAT("M Pendergast-",(LEFT(B10,15)),"-",E10) -> M Pendergast-aliexpress-2xHDMIDummyPlug 4K@60Hz forPMeyer for testing | L10: I | M10: =IF(C10>0,C10,-D10) -> 16.91 | N10: T | R10: =LEN(K10) -> 69
R11: =LEN(K11) -> 0
R12: =LEN(K12) -> 0
R13: =LEN(K13) -> 0
R14: =LEN(K14) -> 0
R15: =LEN(K15) -> 0
R16: =LEN(K16) -> 0

Sheet C Torney
A1: Employee to code & narrate | J1: To be copied in to pronto
J2: Credit card Statement TOTAL | K2: 618.3
J3: Subtotal | K3: =SUM(M9:M144) -> 618.3
A4: Clint Torney | J4: Variance Check | K4: =K2-K3 -> 0
A5: Reference | B5: =CONCATENATE(Header!$E$4,"Torney") -> MC-250816Torney | J5: EMPLOYEES DO NOT CHANGE
A6: Document Date | B6: =Header!$E$5 -> 45885 | E6: Credit card holder to add details
A8: Date | B8: Narrative | C8: Debit Amount | D8: Credit Amount | E8: Description | F8: Project No | G8: Cost Category | H8: GL account | J8: Account | K8: Reference | L8: Tax | M8: Amount | N8: Tax CODE | O8: TAX Amount (leave blank) | P8: CBS - Only if required | R8: limit 56charaters
A9: 45880 | B9: SPRINGFIELDS | C9: 135 | E9: Accommodation for Weld Aust | F9: 1073 | G9: TRAI | J9: =IF(F9>0,(_xlfn.CONCAT(F9,".",G9)),H9) -> 1073.TRAI | K9: =_xlfn.CONCAT("C Torney-",(LEFT(B9,15)),"-",E9) -> C Torney-SPRINGFIELDS -Accommodation for Weld Aust | L9: I | M9: =IF(C9>0,C9,-D9) -> 135 | N9: T | Q9: CBS - needs to be pasted seperately | R9: =LEN(K9) -> 50
A10: 45876 | B10: TOTAL TOOLS BALLARAT BALLARAT AUS | C10: 483.3 | E10: tools for worshop | F10: 1073 | G10: TOOL | J10: =IF(F10>0,(_xlfn.CONCAT(F10,".",G10)),H10) -> 1073.TOOL | K10: =_xlfn.CONCAT("C Torney-",(LEFT(B10,15)),"-",E10) -> C Torney-TOTAL TOOLS BAL-tools for worshop | L10: I | M10: =IF(C10>0,C10,-D10) -> 483.3 | N10: T | R10: =LEN(K10) -> 42
R11: =LEN(K11) -> 0
R12: =LEN(K12) -> 0
R13: =LEN(K13) -> 0
R14: =LEN(K14) -> 0
R15: =LEN(K15) -> 0
R16: =LEN(K16) -> 0
R17: =LEN(K17) -> 0
R18: =LEN(K18) -> 0
R19: =LEN(K19) -> 0
R20: =LEN(K20) -> 0
R21: =LEN(K21) -> 0
R22: =LEN(K22) -> 0
... R30: =LEN(K30) -> 0

Sheet B Tuncks
A1: Employee to code & narrate | J1: To be copied in to pronto
J2: Credit card Statement TOTAL | K2: 3356.85
J3: Subtotal | K3: =SUM(M9:M144) -> 3356.85
A4: Barry Tuncks | J4: Variance Check | K4: =K2-K3 -> 0
A5: Reference | B5: =CONCATENATE(Header!$E$4,"Tuncks") -> MC-250816Tuncks | J5: EMPLOYEES DO NOT CHANGE
A6: Document Date | B6: =Header!$E$5 -> 45885 | E6: Credit card holder to add details
A8: Date | B8: Narrative | C8: Debit Amount | D8: Credit Amount | E8: Description | F8: Project No | G8: Cost Category | H8: GL account | J8: Account | K8: Reference | L8: Tax | M8: Amount | N8: Tax CODE | O8: TAX Amount (leave blank) | P8: CBS - Only if required | R8: limit 56charaters
A9: 45881 | B9: PAYPAL *CLOUDFLARE 4029357733 USA | C9: 82.49 | E9: Website Domain and security | F9: 1084 | G9: ITSW | J9: =IF(F9>0,(_xlfn.CONCAT(F9,".",G9)),H9) -> 1084.ITSW | K9: =_xlfn.CONCAT("B Tuncks-",(LEFT(B9,15)),"-",E9) -> B Tuncks-PAYPAL *CLOUDFL-Website Domain and security | L9: I | M9: =IF(C9>0,C9,-D9) -> 82.49 | N9: F | Q9: CBS - needs to be pasted seperately | R9: =LEN(K9) -> 52
A10: 45881 | B10: INTRUDER.IO PRO LONDON GBR FRGN AMT: 263.67 U. S. DOLLAR | C10: 419.16 | E10: Cyber Security scanner | F10: 1084 | G10: ITSW | J10: =IF(F10>0,(_xlfn.CONCAT(F10,".",G10)),H10) -> 1084.ITSW | K10: =_xlfn.CONCAT("B Tuncks-",(LEFT(B10,15)),"-",E10) -> B Tuncks-INTRUDER.IO PRO-Cyber Security scanner | L10: I | M10: =IF(C10>0,C10,-D10) -> 419.16 | N10: F | R10: =LEN(K10) -> 47
A11: 45879 | B11: ONESIMCARD.COM BELMONT USA FRGN AMT: 103.90 U. S. DOLLAR | C11: 164.82 | E11: Machine Data Ops | F11: CS007-D | G11: MISC | J11: =IF(F11>0,(_xlfn.CONCAT(F11,".",G11)),H11) -> CS007-D.MISC | K11: =_xlfn.CONCAT("B Tuncks-",(LEFT(B11,15)),"-",E11) -> B Tuncks-ONESIMCARD.COM -Machine Data Ops | L11: I | M11: =IF(C11>0,C11,-D11) -> 164.82 | N11: F | R11: =LEN(K11) -> 41
A12: 45879 | B12: DATACHANT HIGHLAND PA USA FRGN AMT: 100.00 U. S. DOLLAR | C12: 158.63 | E12: Projects Tool | F12: 1084 | G12: ITSW | J12: =IF(F12>0,(_xlfn.CONCAT(F12,".",G12)),H12) -> 1084.ITSW | K12: =_xlfn.CONCAT("B Tuncks-",(LEFT(B12,15)),"-",E12) -> B Tuncks-DATACHANT HIGHL-Projects Tool | L12: I | M12: =IF(C12>0,C12,-D12) -> 158.63 | N12: F | R12: =LEN(K12) -> 38
A13: 45879 | B13: AMAZON AU MARKETPLACE SYDNEY AUS | C13: 246.97 | E13: Laptop Docks | F13: 1084 | G13: ITHA | J13: =IF(F13>0,(_xlfn.CONCAT(F13,".",G13)),H13) -> 1084.ITHA | K13: =_xlfn.CONCAT("B Tuncks-",(LEFT(B13,15)),"-",E13) -> B Tuncks-AMAZON AU MARKE-Laptop Docks | L13: I | M13: =IF(C13>0,C13,-D13) -> 246.97 | N13: T | R13: =LEN(K13) -> 37
A14: 45873 | B14: ONESIMCARD.COM BELMONT USA FRGN AMT: 207.80 U. S. DOLLAR | C14: 331.42 | E14: Machine Data Ops | F14: CS007-D | G14: MISC | J14: =IF(F14>0,(_xlfn.CONCAT(F14,".",G14)),H14) -> CS007-D.MISC | K14: =_xlfn.CONCAT("B Tuncks-",(LEFT(B14,15)),"-",E14) -> B Tuncks-ONESIMCARD.COM -Machine Data Ops | L14: I | M14: =IF(C14>0,C14,-D14) -> 331.42 | N14: F | R14: =LEN(K14) -> 41
A15: 45869 | B15: TAILSCALE US INC. SAN FRANCIS USA FRGN AMT: 12.00 U. S. DOLLAR | C15: 19.23 | E15: VPN Solution subscription. | F15: 1084 | G15: ITSW | J15: =IF(F15>0,(_xlfn.CONCAT(F15,".",G15)),H15) -> 1084.ITSW | K15: =_xlfn.CONCAT("B Tuncks-",(LEFT(B15,15)),"-",E15) -> B Tuncks-TAILSCALE US IN-VPN Solution subscription. | L15: I | M15: =IF(C15>0,C15,-D15) -> 19.23 | N15: F | R15: =LEN(K15) -> 51
A16: 45865 | B16: SMTP2GO, I* SMTP2GO EM KELLER USA FRGN AMT: 15.00 U. S. DOLLAR | C16: 23.58 | E16: Email Relay service. | F16: 1084 | G16: ITSW | J16: =IF(F16>0,(_xlfn.CONCAT(F16,".",G16)),H16) -> 1084.ITSW | K16: =_xlfn.CONCAT("B Tuncks-",(LEFT(B16,15)),"-",E16) -> B Tuncks-SMTP2GO, I* SMT-Email Relay service. | L16: I | M16: =IF(C16>0,C16,-D16) -> 23.58 | N16: F | R16: =LEN(K16) -> 45
A17: 45865 | B17: MSFT * E0400WROZO SYDNEY AUS | C17: 46.2 | E17: Gaia M365 subscriptions | F17: 1060GE2 | G17: MISC | J17: =IF(F17>0,(_xlfn.CONCAT(F17,".",G17)),H17) -> 1060GE2.MISC | K17: =_xlfn.CONCAT("B Tuncks-",(LEFT(B17,15)),"-",E17) -> B Tuncks-MSFT * E0400WRO-Gaia M365 subscriptions | L17: I | M17: =IF(C17>0,C17,-D17) -> 46.2 | N17: T | R17: =LEN(K17) -> 48
A18: 45865 | B18: MSFT+*+E0400WRQWX Sydney AUS | C18: 14.85 | E18: Gaia M365 subscriptions | F18: 1060GE2 | G18: MISC | J18: =IF(F18>0,(_xlfn.CONCAT(F18,".",G18)),H18) -> 1060GE2.MISC | K18: =_xlfn.CONCAT("B Tuncks-",(LEFT(B18,15)),"-",E18) -> B Tuncks-MSFT+*+E0400WRQ-Gaia M365 subscriptions | L18: I | M18: =IF(C18>0,C18,-D18) -> 14.85 | N18: T | R18: =LEN(K18) -> 48
A19: 45865 | B19: MSFT * E0400WRTG0 Sydney AUS | C19: 506.66 | E19: Gaia M365 subscriptions | F19: 1060GE2 | G19: MISC | J19: =IF(F19>0,(_xlfn.CONCAT(F19,".",G19)),H19) -> 1060GE2.MISC | K19: =_xlfn.CONCAT("B Tuncks-",(LEFT(B19,15)),"-",E19) -> B Tuncks-MSFT * E0400WRT-Gaia M365 subscriptions | L19: I | M19: =IF(C19>0,C19,-D19) -> 506.66 | N19: T | R19: =LEN(K19) -> 48
A20: 45865 | B20: MSFT * E0400WRQWY Sydney AUS | C20: 13.2 | E20: Gaia M365 subscriptions | F20: 1060GE2 | G20: MISC | J20: =IF(F20>0,(_xlfn.CONCAT(F20,".",G20)),H20) -> 1060GE2.MISC | K20: =_xlfn.CONCAT("B Tuncks-",(LEFT(B20,15)),"-",E20) -> B Tuncks-MSFT * E0400WRQ-Gaia M365 subscriptions | L20: I | M20: =IF(C20>0,C20,-D20) -> 13.2 | N20: T | R20: =LEN(K20) -> 48
A21: 45865 | B21: MSFT * E0400WRQWW Sydney AUS | C21: 29.7 | E21: Gaia M365 subscriptions | F21: 1060GE2 | G21: MISC | J21: =IF(F21>0,(_xlfn.CONCAT(F21,".",G21)),H21) -> 1060GE2.MISC | K21: =_xlfn.CONCAT("B Tuncks-",(LEFT(B21,15)),"-",E21) -> B Tuncks-MSFT * E0400WRQ-Gaia M365 subscriptions | L21: I | M21: =IF(C21>0,C21,-D21) -> 29.7 | N21: T | R21: =LEN(K21) -> 48
A22: 45864 | B22: PAYPAL *ADOBESYSTEM 4029357733 AUS | C22: 75.99 | E22: Adobe Acrobat PDF Editor x2 | F22: 1084 | G22: ITSW | J22: =IF(F22>0,(_xlfn.CONCAT(F22,".",G22)),H22) -> 1084.ITSW | K22: =_xlfn.CONCAT("B Tuncks-",(LEFT(B22,15)),"-",E22) -> B Tuncks-PAYPAL *ADOBESY-Adobe Acrobat PDF Editor x2 | L22: I | M22: =IF(C22>0,C22,-D22) -> 75.99 | N22: T | R22: =LEN(K22) -> 52
A23: 45860 | B23: ONESIMCARD.COM BELMONT USA FRGN AMT: 103.90 U. S. DOLLAR | C23: 164.59 | E23: Machine Data Ops | H23: 11053SVC4300 | J23: =IF(F23>0,(_xlfn.CONCAT(F23,".",G23)),H23) -> 11053SVC4300 | K23: =_xlfn.CONCAT("B Tuncks-",(LEFT(B23,15)),"-",E23) -> B Tuncks-ONESIMCARD.COM -Machine Data Ops | L23: I | M23: =IF(C23>0,C23,-D23) -> 164.59 | N23: F | R23: =LEN(K23) -> 41
A24: 45860 | B24: 1PASSWORD TORONTO CAN FRGN AMT: 21.95 U. S. DOLLAR | C24: 34.77 | E24: Password manager subscription | F24: 1084 | G24: ITSW | J24: =IF(F24>0,(_xlfn.CONCAT(F24,".",G24)),H24) -> 1084.ITSW | K24: =_xlfn.CONCAT("B Tuncks-",(LEFT(B24,15)),"-",E24) -> B Tuncks-1PASSWORD TORON-Password manager subscription | L24: I | M24: =IF(C24>0,C24,-D24) -> 34.77 | N24: F | R24: =LEN(K24) -> 54
A25: 45857 | B25: INTRUDER.IO PRO LONDON GBR FRGN AMT: 263.67 U. S. DOLLAR | C25: 419.3 | E25: Cyber Security scanner | F25: 1084 | G25: ITSW | J25: =IF(F25>0,(_xlfn.CONCAT(F25,".",G25)),H25) -> 1084.ITSW | K25: =_xlfn.CONCAT("B Tuncks-",(LEFT(B25,15)),"-",E25) -> B Tuncks-INTRUDER.IO PRO-Cyber Security scanner | L25: I | M25: =IF(C25>0,C25,-D25) -> 419.3 | N25: F | R25: =LEN(K25) -> 47
A26: 45855 | B26: DATACHANT HIGHLAND PA USA FRGN AMT: 100.00 U. S. DOLLAR | C26: 158.63 | E26: Projects Tool | F26: 1084 | G26: ITSW | J26: =IF(F26>0,(_xlfn.CONCAT(F26,".",G26)),H26) -> 1084.ITSW | K26: =_xlfn.CONCAT("B Tuncks-",(LEFT(B26,15)),"-",E26) -> B Tuncks-DATACHANT HIGHL-Projects Tool | L26: I | M26: =IF(C26>0,C26,-D26) -> 158.63 | N26: F | R26: =LEN(K26) -> 38
A27: 45854 | B27: 4CABLING* 4CABLING HOMEBUSH WE AUS | C27: 435.72 | E27: Fiber cables and optics - Site networking | F27: 1084 | G27: ITHA | J27: =IF(F27>0,(_xlfn.CONCAT(F27,".",G27)),H27) -> 1084.ITHA | K27: =_xlfn.CONCAT("B Tuncks-",(LEFT(B27,15)),"-",E27) -> B Tuncks-4CABLING* 4CABL-Fiber cables and optics - Site networking | L27: I | M27: =IF(C27>0,C27,-D27) -> 435.72 | N27: T | R27: =LEN(K27) -> 66
A28: 45853 | B28: WWW.ALIEXPRESS.COM LONDON GBR | C28: 10.94 | E28: Charge back to BT accidental purchase. | F28: 1084 | G28: PERS | J28: =IF(F28>0,(_xlfn.CONCAT(F28,".",G28)),H28) -> 1084.PERS | K28: =_xlfn.CONCAT("B Tuncks-",(LEFT(B28,15)),"-",E28) -> B Tuncks-WWW.ALIEXPRESS.-Charge back to BT accidental purchase. | L28: I | M28: =IF(C28>0,C28,-D28) -> 10.94 | N28: F | R28: =LEN(K28) -> 63
R29: =LEN(K29) -> 0
R30: =LEN(K30) -> 0

Sheet K Rouhan
A1: Employee to code & narrate | J1: To be copied in to pronto
J2: Credit card Statement TOTAL | K2: 3842.74
J3: Subtotal | K3: =SUM(M9:M144) -> 3842.74
A4: Kate Rouhan | J4: Variance Check | K4: =K2-K3 -> 0
A5: Reference | B5: =CONCATENATE(Header!$E$4,"Rouhan") -> MC-250816Rouhan | J5: EMPLOYEES DO NOT CHANGE
A6: Document Date | B6: =Header!$E$5 -> 45885 | E6: Credit card holder to add details
A8: Date | B8: Narrative | C8: Debit Amount | D8: Credit Amount | E8: Description | F8: Project No | G8: Cost Category | H8: GL account | J8: Account | K8: Reference | L8: Tax | M8: Amount | N8: Tax CODE | O8: TAX Amount (leave blank) | P8: CBS - Only if required | R8: limit 56charaters
A9: 45882 | B9: WOOLWORTHS 3066 ALFREDTON AUS | C9: 72.2 | E9: Drinks, Fruit etc | F9: 1084 | G9: STAF | J9: =IF(F9>0,(_xlfn.CONCAT(F9,".",G9)),H9) -> 1084.STAF | K9: =_xlfn.CONCAT("K Rouhan-",(LEFT(B9,15)),"-",E9) -> K Rouhan-WOOLWORTHS -Drinks, Fruit etc | L9: I | M9: =IF(C9>0,C9,-D9) -> 72.2 | N9: T | Q9: CBS - needs to be pasted seperately | R9: =LEN(K9) -> 42
A10: 45881 | B10: HTTPS://SCRIBE.HOW/B SAN FRANCIS USA FRGN AMT: 251.54 U. S. DOLLAR | C10: 399.88 | E10: Prepaid sofware - Scorm Files | F10: 1084 | G10: ITSW | J10: =IF(F10>0,(_xlfn.CONCAT(F10,".",G10)),H10) -> 1084.ITSW | K10: =_xlfn.CONCAT("K Rouhan-",(LEFT(B10,15)),"-",E10) -> K Rouhan-HTTPS://SCRIBE.-Prepaid sofware - Scorm Files | L10: I | M10: =IF(C10>0,C10,-D10) -> 399.88 | N10: F | R10: =LEN(K10) -> 55
A11: 45881 | B11: POST LUCAS LPO LUCAS AUS | C11: 11.15 | E11: Postage to Perth Office | F11: 1084 | G11: POST | J11: =IF(F11>0,(_xlfn.CONCAT(F11,".",G11)),H11) -> 1084.POST | K11: =_xlfn.CONCAT("K Rouhan-",(LEFT(B11,15)),"-",E11) -> K Rouhan-POST LUCAS LPO -Postage to Perth Office | L11: I | M11: =IF(C11>0,C11,-D11) -> 11.15 | N11: T | R11: =LEN(K11) -> 48
A12: 45880 | B12: BALLARATS SANCTUARY DA BALLARAT AUS | C12: 202.2 | E12: Gift for O'Halloran Family Baby | F12: 1084 | G12: STAF | J12: =IF(F12>0,(_xlfn.CONCAT(F12,".",G12)),H12) -> 1084.STAF | K12: =_xlfn.CONCAT("K Rouhan-",(LEFT(B12,15)),"-",E12) -> K Rouhan-BALLARATS SANCT-Gift for O'Halloran Family Baby | L12: I | M12: =IF(C12>0,C12,-D12) -> 202.2 | N12: T | R12: =LEN(K12) -> 56
A13: 45880 | B13: Golden Nugget Bakery Ballarat Ce AUS | C13: 212.68 | E13: Catering for Pronto team - Onsite | F13: 1084 | G13: ENON | J13: =IF(F13>0,(_xlfn.CONCAT(F13,".",G13)),H13) -> 1084.ENON | K13: =_xlfn.CONCAT("K Rouhan-",(LEFT(B13,15)),"-",E13) -> K Rouhan-Golden Nugget B-Catering for Pronto team - Onsite | L13: I | M13: =IF(C13>0,C13,-D13) -> 212.68 | N13: T | R13: =LEN(K13) -> 58
A14: 45875 | B14: SMP*Major Roasts Ballarat No AUS | C14: 663.77 | E14: Wednesday lunch - Onsite | F14: 1084 | G14: ENON | J14: =IF(F14>0,(_xlfn.CONCAT(F14,".",G14)),H14) -> 1084.ENON | K14: =_xlfn.CONCAT("K Rouhan-",(LEFT(B14,15)),"-",E14) -> K Rouhan-SMP*Major Roast-Wednesday lunch - Onsite | L14: I | M14: =IF(C14>0,C14,-D14) -> 663.77 | N14: T | R14: =LEN(K14) -> 49
A15: 45875 | B15: WOOLWORTHS 3066 ALFREDTON AUS | C15: 209.21 | E15: Food for Wednesday lunch | F15: 1084 | G15: ENON | J15: =IF(F15>0,(_xlfn.CONCAT(F15,".",G15)),H15) -> 1084.ENON | K15: =_xlfn.CONCAT("K Rouhan-",(LEFT(B15,15)),"-",E15) -> K Rouhan-WOOLWORTHS -Food for Wednesday lunch | L15: I | M15: =IF(C15>0,C15,-D15) -> 209.21 | N15: T | R15: =LEN(K15) -> 49
A16: 45875 | B16: Bakers Delight | C16: 62.8 | E16: Rolls for Wednesday lunch - Onsite | F16: 1084 | G16: ENON | J16: =IF(F16>0,(_xlfn.CONCAT(F16,".",G16)),H16) -> 1084.ENON | K16: =_xlfn.CONCAT("K Rouhan-",(LEFT(B16,15)),"-",E16) -> K Rouhan-Bakers Delight-Rolls for Wednesday lunch - Onsite | L16: I | M16: =IF(C16>0,C16,-D16) -> 62.8 | N16: T | R16: =LEN(K16) -> 58
A17: 45872 | B17: Subway Wendouree Lake Wendou AUS | C17: 219.9 | E17: Pronto Team lunch - Onsite | F17: 1084 | G17: ENON | J17: =IF(F17>0,(_xlfn.CONCAT(F17,".",G17)),H17) -> 1084.ENON | K17: =_xlfn.CONCAT("K Rouhan-",(LEFT(B17,15)),"-",E17) -> K Rouhan-Subway Wendoure-Pronto Team lunch - Onsite | L17: I | M17: =IF(C17>0,C17,-D17) -> 219.9 | N17: T | R17: =LEN(K17) -> 51
A18: 45872 | B18: EG GROUP 3873 LUCAS AUS | C18: 7.5 | E18: Purchase of Milk | F18: 1084 | G18: STAF | J18: =IF(F18>0,(_xlfn.CONCAT(F18,".",G18)),H18) -> 1084.STAF | K18: =_xlfn.CONCAT("K Rouhan-",(LEFT(B18,15)),"-",E18) -> K Rouhan-EG GROUP -Purchase of Milk | L18: I | M18: =IF(C18>0,C18,-D18) -> 7.5 | N18: T | R18: =LEN(K18) -> 41
A19: 45870 | B19: POST LUCAS LPO LUCAS AUS | C19: 4.7 | E19: Postage to Perth Office | F19: 1084 | G19: POST | J19: =IF(F19>0,(_xlfn.CONCAT(F19,".",G19)),H19) -> 1084.POST | K19: =_xlfn.CONCAT("K Rouhan-",(LEFT(B19,15)),"-",E19) -> K Rouhan-POST LUCAS LPO -Postage to Perth Office | L19: I | M19: =IF(C19>0,C19,-D19) -> 4.7 | N19: T | R19: =LEN(K19) -> 48
A20: 45868 | B20: BABY BUNTING WENDEOUREE AUS | C20: 400 | E20: Gift for O'Halloran Baby | F20: 1084 | G20: STAF | J20: =IF(F20>0,(_xlfn.CONCAT(F20,".",G20)),H20) -> 1084.STAF | K20: =_xlfn.CONCAT("K Rouhan-",(LEFT(B20,15)),"-",E20) -> K Rouhan-BABY BUNTING WE-Gift for O'Halloran Baby | L20: I | M20: =IF(C20>0,C20,-D20) -> 400 | N20: T | R20: =LEN(K20) -> 49
A21: 45868 | B21: Nextra Wendouree Wendouree AUS | C21: 23.19 | E21: Purchase of cards to staff | F21: 1084 | G21: STAF | J21: =IF(F21>0,(_xlfn.CONCAT(F21,".",G21)),H21) -> 1084.STAF | K21: =_xlfn.CONCAT("K Rouhan-",(LEFT(B21,15)),"-",E21) -> K Rouhan-Nextra Wendoure-Purchase of cards to staff | L21: I | M21: =IF(C21>0,C21,-D21) -> 23.19 | N21: T | R21: =LEN(K21) -> 51
... A25: 45862 | B25: DAN MURPHY'S 3905 DELACOMBE AUS | C25: 307.93 | E25: Drinks for Friday night drinks - Onsite | F25: 1084 | G25: STAF | J25: =IF(F25>0,(_xlfn.CONCAT(F25,".",G25)),H25) -> 1084.STAF | K25: =_xlfn.CONCAT("K Rouhan-",(LEFT(B25,15)),"-",E25) -> K Rouhan-DAN MURPHY'S -Drinks for Friday night drinks - Onsite | L25: I | M25: =IF(C25>0,C25,-D25) -> 307.93 | N25: T | R25: =LEN(K25) -> 64
R26: =LEN(K26) -> 0
R27: =LEN(K27) -> 0
R28: =LEN(K28) -> 0
R29: =LEN(K29) -> 0
R30: =LEN(K30) -> 0

Sheet M Trenorden
A1: Employee to code & narrate | J1: To be copied in to pronto
J2: Credit card Statement TOTAL | K2: 1139.3
J3: Subtotal | K3: =SUM(M9:M144) -> 1139.3
A4: Michael Trenorden | J4: Variance Check | K4: =K2-K3 -> 0
A5: Reference | B5: =CONCATENATE(Header!$E$4,"Trenorden") -> MC-250816Trenorden | J5: EMPLOYEES DO NOT CHANGE
A6: Document Date | B6: =Header!$E$5 -> 45885 | E6: Credit card holder to add details
A8: Date | B8: Narrative | C8: Debit Amount | D8: Credit Amount | E8: Description | F8: Project No | G8: Cost Category | H8: GL account | J8: Account | K8: Reference | L8: Tax | M8: Amount | N8: Tax CODE | O8: TAX Amount (leave blank) | P8: CBS - Only if required | R8: limit 56charaters
A9: 45876 | B9: CONSUMER AFFAIRS VIC MELBOURNE AUS | C9: 627.3 | E9: Professional Engineer Reg-Vic | F9: 1074 | G9: PERM | J9: =IF(F9>0,(_xlfn.CONCAT(F9,".",G9)),H9) -> 1074.PERM | K9: =_xlfn.CONCAT("MTrenorden-",(LEFT(B9,15)),"-",E9) -> MTrenorden-CONSUMER AFFAIR-Professional Engineer Reg-Vic | L9: I | M9: =IF(C9>0,C9,-D9) -> 627.3 | N9: T | Q9: CBS - needs to be pasted seperately | R9: =LEN(K9) -> 56
A10: 45874 | B10: FUTURE ENERGY SKILLS L CLAYTON AUS | C10: 256 | E10: REL Class 2 Assmt - Max J | F10: 1074 | G10: PERM | J10: =IF(F10>0,(_xlfn.CONCAT(F10,".",G10)),H10) -> 1074.PERM | K10: =_xlfn.CONCAT("MTrenorden-",(LEFT(B10,15)),"-",E10) -> MTrenorden-FUTURE ENERGY S-REL Class 2 Assmt - Max J | L10: I | M10: =IF(C10>0,C10,-D10) -> 256 | N10: T | R10: =LEN(K10) -> 53
A11: 45860 | B11: FUTURE ENERGY SKILLS L CLAYTON AUS | C11: 256 | E11: REL Class 2 Assmt - Harry L | F11: 1058 | G11: PERM | J11: =IF(F11>0,(_xlfn.CONCAT(F11,".",G11)),H11) -> 1058.PERM | K11: =_xlfn.CONCAT("MTrenorden-",(LEFT(B11,15)),"-",E11) -> MTrenorden-FUTURE ENERGY S-REL Class 2 Assmt - Harry L | L11: I | M11: =IF(C11>0,C11,-D11) -> 256 | N11: T | R11: =LEN(K11) -> 55
R12: =LEN(K12) -> 0
R13: =LEN(K13) -> 0
R14: =LEN(K14) -> 0
R15: =LEN(K15) -> 0
R16: =LEN(K16) -> 0
R17: =LEN(K17) -> 0
R18: =LEN(K18) -> 0
R19: =LEN(K19) -> 0
R20: =LEN(K20) -> 0
R21: =LEN(K21) -> 0
R22: =LEN(K22) -> 0
R23: =LEN(K23) -> 0
... R30: =LEN(K30) -> 0

Sheet L VanKollenburg
A1: Employee to code & narrate | J1: To be copied in to pronto
J2: Credit card Statement TOTAL | K2: 1307.78
J3: Subtotal | K3: =SUM(M9:M144) -> 1307.78
A4: Leon VanKollenburg | J4: Variance Check | K4: =K2-K3 -> 0
A5: Reference | B5: =CONCATENATE(Header!$E$4,"VanKollenburg") -> MC-250816VanKollenburg | J5: EMPLOYEES DO NOT CHANGE
A6: Document Date | B6: =Header!$E$5 -> 45885 | E6: Credit card holder to add details
A8: Date | B8: Narrative | C8: Debit Amount | D8: Credit Amount | E8: Description | F8: Project No | G8: Cost Category | H8: GL account | J8: Account | K8: Reference | L8: Tax | M8: Amount | N8: Tax CODE | O8: TAX Amount (leave blank) | P8: CBS - Only if required | R8: limit 56charaters
A9: 45881 | B9: GB FASTENERS ALFREDTON AUS | C9: 27.6 | E9: touch up paint | F9: 1073 | G9: CONS | J9: =IF(F9>0,(_xlfn.CONCAT(F9,".",G9)),H9) -> 1073.CONS | K9: =_xlfn.CONCAT("L VKburg-",(LEFT(B9,15)),"-",E9) -> L VKburg-GB FASTENERS AL-touch up paint | L9: I | M9: =IF(C9>0,C9,-D9) -> 27.6 | N9: T | Q9: CBS - needs to be pasted seperately | R9: =LEN(K9) -> 39
A10: 45868 | B10: GB FASTENERS ALFREDTON AUS | C10: 51.98 | E10: dyna bolts for workshop | F10: 1073 | G10: CONS | J10: =IF(F10>0,(_xlfn.CONCAT(F10,".",G10)),H10) -> 1073.CONS | K10: =_xlfn.CONCAT("L VKburg-",(LEFT(B10,15)),"-",E10) -> L VKburg-GB FASTENERS AL-dyna bolts for workshop | L10: I | M10: =IF(C10>0,C10,-D10) -> 51.98 | N10: T | R10: =LEN(K10) -> 48
A11: 45856 | B11: TOTAL TOOLS BALLARAT BALLARAT AUS | C11: 119.45 | E11: tools for the workshop | F11: 1073 | G11: TOOL | J11: =IF(F11>0,(_xlfn.CONCAT(F11,".",G11)),H11) -> 1073.TOOL | K11: =_xlfn.CONCAT("L VKburg-",(LEFT(B11,15)),"-",E11) -> L VKburg-TOTAL TOOLS BAL-tools for the workshop | L11: I | M11: =IF(C11>0,C11,-D11) -> 119.45 | N11: T | R11: =LEN(K11) -> 47
A12: 45855 | B12: POST BALLARAT WEST LPO BALLARAT AUS | C12: 98.64 | E12: work safe licence fee | F12: 1073 | G12: PERM | J12: =IF(F12>0,(_xlfn.CONCAT(F12,".",G12)),H12) -> 1073.PERM | K12: =_xlfn.CONCAT("L VKburg-",(LEFT(B12,15)),"-",E12) -> L VKburg-POST BALLARAT W-work safe licence fee | L12: I | M12: =IF(C12>0,C12,-D12) -> 98.64 | N12: T | R12: =LEN(K12) -> 46
A13: 45855 | B13: POST BALLARAT WEST LPO BALLARAT AUS | C13: 98.64 | E13: work safe licence fee | F13: 1073 | G13: PERM | J13: =IF(F13>0,(_xlfn.CONCAT(F13,".",G13)),H13) -> 1073.PERM | K13: =_xlfn.CONCAT("L VKburg-",(LEFT(B13,15)),"-",E13) -> L VKburg-POST BALLARAT W-work safe licence fee | L13: I | M13: =IF(C13>0,C13,-D13) -> 98.64 | N13: T | R13: =LEN(K13) -> 46
A14: 45855 | B14: CRED VOUCHER SPIRIT OF TASMANIA DEVONPORT AUS | D14: 316 | E14: credit for Jonty no longer | F14: s12392-b | G14: TRVP | J14: =IF(F14>0,(_xlfn.CONCAT(F14,".",G14)),H14) -> s12392-b.TRVP | K14: =_xlfn.CONCAT("L VKburg-",(LEFT(B14,15)),"-",E14) -> L VKburg-CRED VOUCHER SP-credit for Jonty no longer | L14: I | M14: =IF(C14>0,C14,-D14) -> -316 | N14: T | P14: 1.6.01 | R14: =LEN(K14) -> 52
A15: 45854 | B15: SPIRIT OF TASMANIA DEVONPORT AUS | C15: 1227.47 | E15: Travel to Rosebery | F15: s12392-b | G15: TRVP | J15: =IF(F15>0,(_xlfn.CONCAT(F15,".",G15)),H15) -> s12392-b.TRVP | K15: =_xlfn.CONCAT("L VKburg-",(LEFT(B15,15)),"-",E15) -> L VKburg-SPIRIT OF TASMA-Travel to Rosebery | L15: I | M15: =IF(C15>0,C15,-D15) -> 1227.47 | N15: T | P15: 1.6.01 | R15: =LEN(K15) -> 43
R16: =LEN(K16) -> 0
R17: =LEN(K17) -> 0
R18: =LEN(K18) -> 0
R19: =LEN(K19) -> 0
R20: =LEN(K20) -> 0
R21: =LEN(K21) -> 0
R22: =LEN(K22) -> 0
R23: =LEN(K23) -> 0
R24: =LEN(K24) -> 0
R25: =LEN(K25) -> 0
R26: =LEN(K26) -> 0
R27: =LEN(K27) -> 0
... R30: =LEN(K30) -> 0

Sheet B Wraith
A1: Employee to code & narrate | J1: To be copied in to pronto
J2: Credit card Statement TOTAL | K2: 2095.52
J3: Subtotal | K3: =SUM(M9:M144) -> 2095.52
J4: Variance Check | K4: =K2-K3 -> 0
A5: Ben Wraith
A6: Reference | B6: =CONCATENATE([1]Header!$E$4,"Wraith") -> MC-250816Wraith | J6: EMPLOYEES DO NOT CHANGE
A7: Document Date | B7: =[1]Header!$E$5 -> 45885 | E7: Credit card holder to add details
A9: Date | B9: Narrative | C9: Debit Amount | D9: Credit Amount | E9: Description | F9: Project No | G9: Cost Category | H9: GL account | J9: Account | K9: Reference | L9: Tax | M9: Amount | N9: Tax CODE | O9: TAX Amount (leave blank) | P9: CBS - Only if required | R9: limit 56charaters
A10: 45854 | B10: austmine | C10: 44 | E10: Registration for industry event | F10: 1041 | G10: CONF | J10: =IF(F10>0,(_xlfn.CONCAT(F10,".",G10)),H10) -> 1041.CONF | K10: =_xlfn.CONCAT("BWraith-",(LEFT(B10,15)),"-",E10) -> BWraith-austmine-Registration for industry event | L10: I | M10: =IF(C10>0,C10,-D10) -> 44 | N10: T | Q10: CBS - needs to be pasted seperately | R10: =LEN(K10) -> 48
A11: 45860 | B11: melbourne taxi | C11: 83.33 | E11: Travel home from industry event | F11: G077 | G11: SALP | J11: =IF(F11>0,(_xlfn.CONCAT(F11,".",G11)),H11) -> G077.SALP | K11: =_xlfn.CONCAT("BWraith-",(LEFT(B11,15)),"-",E11) -> BWraith-melbourne taxi-Travel home from industry event | L11: I | M11: =IF(C11>0,C11,-D11) -> 83.33 | N11: T | R11: =LEN(K11) -> 54
A12: 45870 | B12: didi mobility | C12: 70.06 | E12: Travel to airport for Diggers and Dealers Conference | F12: G077 | G12: SALP | J12: =IF(F12>0,(_xlfn.CONCAT(F12,".",G12)),H12) -> G077.SALP | K12: =_xlfn.CONCAT("BWraith-",(LEFT(B12,15)),"-",E12) -> BWraith-didi mobility-Travel to airport for Diggers and Dealers Conference | L12: I | M12: =IF(C12>0,C12,-D12) -> 70.06 | N12: T | R12: =LEN(K12) -> 74
A13: 45870 | B13: perth soccer | C13: 94 | E13: Entertain Lycopodium Jeans for Genes Event | F13: G077 | G13: SALP | J13: =IF(F13>0,(_xlfn.CONCAT(F13,".",G13)),H13) -> G077.SALP | K13: =_xlfn.CONCAT("BWraith-",(LEFT(B13,15)),"-",E13) -> BWraith-perth soccer-Entertain Lycopodium Jeans for Genes Event | L13: I | M13: =IF(C13>0,C13,-D13) -> 94 | N13: T | R13: =LEN(K13) -> 63
A14: 45870 | B14: perth soccer | C14: 42 | E14: Entertain Lycopodium Jeans for Genes Event | F14: G077 | G14: SALP | J14: =IF(F14>0,(_xlfn.CONCAT(F14,".",G14)),H14) -> G077.SALP | K14: =_xlfn.CONCAT("BWraith-",(LEFT(B14,15)),"-",E14) -> BWraith-perth soccer-Entertain Lycopodium Jeans for Genes Event | L14: I | M14: =IF(C14>0,C14,-D14) -> 42 | N14: T | R14: =LEN(K14) -> 63
A15: 45871 | B15: murray mews | C15: 53.8 | E15: Breakfast on Diggers and Dealers trip | F15: G077 | G15: SALP | J15: =IF(F15>0,(_xlfn.CONCAT(F15,".",G15)),H15) -> G077.SALP | K15: =_xlfn.CONCAT("BWraith-",(LEFT(B15,15)),"-",E15) -> BWraith-murray mews-Breakfast on Diggers and Dealers trip | L15: I | M15: =IF(C15>0,C15,-D15) -> 53.8 | N15: T | R15: =LEN(K15) -> 57
A16: 45871 | B16: didi mobility | C16: 18.84 | E16: Travel to event with WA Metallurgists | F16: G077 | G16: SALP | J16: =IF(F16>0,(_xlfn.CONCAT(F16,".",G16)),H16) -> G077.SALP | K16: =_xlfn.CONCAT("BWraith-",(LEFT(B16,15)),"-",E16) -> BWraith-didi mobility-Travel to event with WA Metallurgists | L16: I | M16: =IF(C16>0,C16,-D16) -> 18.84 | N16: T | R16: =LEN(K16) -> 59
A17: 45871 | B17: alh venues | C17: 37 | E17: event drinks with WA Metallurgists | F17: G077 | G17: SALP | J17: =IF(F17>0,(_xlfn.CONCAT(F17,".",G17)),H17) -> G077.SALP | K17: =_xlfn.CONCAT("BWraith-",(LEFT(B17,15)),"-",E17) -> BWraith-alh venues-event drinks with WA Metallurgists | L17: I | M17: =IF(C17>0,C17,-D17) -> 37 | N17: T | R17: =LEN(K17) -> 53
A18: 45871 | B18: didi mobility | C18: 21.15 | E18: Travel to event with WA Metallurgists | F18: G077 | G18: SALP | J18: =IF(F18>0,(_xlfn.CONCAT(F18,".",G18)),H18) -> G077.SALP | K18: =_xlfn.CONCAT("BWraith-",(LEFT(B18,15)),"-",E18) -> BWraith-didi mobility-Travel to event with WA Metallurgists | L18: I | M18: =IF(C18>0,C18,-D18) -> 21.15 | N18: T | R18: =LEN(K18) -> 59
A19: 45871 | B19: alh venues | C19: 25.4 | E19: event drinks with WA Metallurgists | F19: G077 | G19: SALP | J19: =IF(F19>0,(_xlfn.CONCAT(F19,".",G19)),H19) -> G077.SALP | K19: =_xlfn.CONCAT("BWraith-",(LEFT(B19,15)),"-",E19) -> BWraith-alh venues-event drinks with WA Metallurgists | L19: I | M19: =IF(C19>0,C19,-D19) -> 25.4 | N19: T | R19: =LEN(K19) -> 53
A20: 45871 | B20: alh venues | C20: 35.9 | E20: event drinks with WA Metallurgists | F20: G077 | G20: SALP | J20: =IF(F20>0,(_xlfn.CONCAT(F20,".",G20)),H20) -> G077.SALP | K20: =_xlfn.CONCAT("BWraith-",(LEFT(B20,15)),"-",E20) -> BWraith-alh venues-event drinks with WA Metallurgists | L20: I | M20: =IF(C20>0,C20,-D20) -> 35.9 | N20: T | R20: =LEN(K20) -> 53
A21: 45872 | B21: ls the wolf espresso perth | C21: 19.93 | E21: Coffee's on the way to Kalgoorlie for Diggers and Dealers | F21: G077 | G21: SALP | J21: =IF(F21>0,(_xlfn.CONCAT(F21,".",G21)),H21) -> G077.SALP | K21: =_xlfn.CONCAT("BWraith-",(LEFT(B21,15)),"-",E21) -> BWraith-ls the wolf esp-Coffee's on the way to Kalgoorlie for Diggers and Dealers | L21: I | M21: =IF(C21>0,C21,-D21) -> 19.93 | N21: T | R21: =LEN(K21) -> 81
A22: 45872 | B22: star & garter hotel | C22: 8 | E22: D&D meals and drinks | F22: G077 | G22: SALP | J22: =IF(F22>0,(_xlfn.CONCAT(F22,".",G22)),H22) -> G077.SALP | K22: =_xlfn.CONCAT("BWraith-",(LEFT(B22,15)),"-",E22) -> BWraith-star & garter h-D&D meals and drinks | L22: I | M22: =IF(C22>0,C22,-D22) -> 8 | N22: T | R22: =LEN(K22) -> 44
... A34: 45876 | B34: delaware north redcliffe | C34: 39 | E34: Dinner whilst traveling home from D&D | F34: G077 | G34: SALP | J34: =IF(F34>0,(_xlfn.CONCAT(F34,".",G34)),H34) -> G077.SALP | K34: =_xlfn.CONCAT("BWraith-",(LEFT(B34,15)),"-",E34) -> BWraith-delaware north -Dinner whilst traveling home from D&D | L34: I | M34: =IF(C34>0,C34,-D34) -> 39 | N34: T | R34: =LEN(K34) -> 61
A35: 45880 | B35: ausimm carlton | C35: 20 | E35: Student Meets IndustryNightReg | F35: 1041 | G35: CONF | J35: =IF(F35>0,(_xlfn.CONCAT(F35,".",G35)),H35) -> 1041.CONF | K35: =_xlfn.CONCAT("BWraith-",(LEFT(B35,15)),"-",E35) -> BWraith-ausimm carlton-Student Meets IndustryNightReg | L35: I | M35: =IF(C35>0,C35,-D35) -> 20 | N35: T | R35: =LEN(K35) -> 53
A36: 45881 | B36: best choice ballarat | C36: 229.88 | E36: Sales Conference Accomodation | F36: G068 | G36: SALP | J36: =IF(F36>0,(_xlfn.CONCAT(F36,".",G36)),H36) -> G068.SALP | K36: =_xlfn.CONCAT("BWraith-",(LEFT(B36,15)),"-",E36) -> BWraith-best choice bal-Sales Conference Accomodation | L36: I | M36: =IF(C36>0,C36,-D36) -> 229.88 | N36: T | R36: =LEN(K36) -> 53
A37: 45881 | B37: sq 3350 coffee bar ballarat | C37: 19.81 | E37: Breakfast Sales Conference | F37: G068 | G37: SALP | J37: =IF(F37>0,(_xlfn.CONCAT(F37,".",G37)),H37) -> G068.SALP | K37: =_xlfn.CONCAT("BWraith-",(LEFT(B37,15)),"-",E37) -> BWraith-sq 3350 coffee -Breakfast Sales Conference | L37: I | M37: =IF(C37>0,C37,-D37) -> 19.81 | N37: T | R37: =LEN(K37) -> 50
A38: 45882 | B38: north star | C38: 677.58 | E38: Dinner: AE, NK, NZ, TB, BW, TH, SM | F38: G068 | G38: SALP | J38: =IF(F38>0,(_xlfn.CONCAT(F38,".",G38)),H38) -> G068.SALP | K38: =_xlfn.CONCAT("BWraith-",(LEFT(B38,15)),"-",E38) -> BWraith-north star-Dinner: AE, NK, NZ, TB, BW, TH, SM | L38: I | M38: =IF(C38>0,C38,-D38) -> 677.58 | N38: T | R38: =LEN(K38) -> 53

Sheet N Zhang
A1: Employee to code & narrate | J1: To be copied in to pronto
J2: Credit card Statement TOTAL | K2: 315.62
J3: Subtotal | K3: =SUM(M9:M144) -> 315.62
A4: Nick Zhang | J4: Variance Check | K4: =K2-K3 -> 0
A5: Reference | B5: =CONCATENATE(Header!$E$4,"Zhang") -> MC-250816Zhang | J5: EMPLOYEES DO NOT CHANGE
A6: Document Date | B6: =Header!$E$5 -> 45885 | E6: Credit card holder to add details
A8: Date | B8: Narrative | C8: Debit Amount | D8: Credit Amount | E8: Description | F8: Project No | G8: Cost Category | H8: GL account | J8: Account | K8: Reference | L8: Tax | M8: Amount | N8: Tax CODE | O8: TAX Amount (leave blank) | P8: CBS - Only if required | R8: limit 56charaters
A9: 45883 | B9: SQ *LILY DANG Ballarat Ce AUS | C9: 37.4 | E9: Dinner | F9: 1053 | G9: TRAV | J9: =IF(F9>0,(_xlfn.CONCAT(F9,".",G9)),H9) -> 1053.TRAV | K9: =_xlfn.CONCAT("N Zhang-",(LEFT(B9,15)),"-",E9) -> N Zhang-SQ *LILY DANG B-Dinner | L9: I | M9: =IF(C9>0,C9,-D9) -> 37.4 | N9: T | Q9: CBS - needs to be pasted seperately | R9: =LEN(K9) -> 30
A10: 45879 | B10: Watermark Mascot AUS | C10: 18.71 | E10: Food | F10: 1053 | G10: TRAV | J10: =IF(F10>0,(_xlfn.CONCAT(F10,".",G10)),H10) -> 1053.TRAV | K10: =_xlfn.CONCAT("N Zhang-",(LEFT(B10,15)),"-",E10) -> N Zhang-Watermark Masco-Food | L10: I | M10: =IF(C10>0,C10,-D10) -> 18.71 | N10: T | R10: =LEN(K10) -> 28
A11: 45867 | B11: SYD APRT EPARK ONL28 SYDNEY INTE AUS | C11: 169.51 | E11: Airport Parking | F11: 1053 | G11: TRAV | J11: =IF(F11>0,(_xlfn.CONCAT(F11,".",G11)),H11) -> 1053.TRAV | K11: =_xlfn.CONCAT("N Zhang-",(LEFT(B11,15)),"-",E11) -> N Zhang-SYD APRT EPARK -Airport Parking | L11: I | M11: =IF(C11>0,C11,-D11) -> 169.51 | N11: T | R11: =LEN(K11) -> 39
A12: 45867 | B12: Airport Shuttle Bus BAKERY HILL AUS | C12: 90 | E12: Bus to Ballarat | F12: 1053 | G12: TRAV | J12: =IF(F12>0,(_xlfn.CONCAT(F12,".",G12)),H12) -> 1053.TRAV | K12: =_xlfn.CONCAT("N Zhang-",(LEFT(B12,15)),"-",E12) -> N Zhang-Airport Shuttle-Bus to Ballarat | L12: I | M12: =IF(C12>0,C12,-D12) -> 90 | N12: T | R12: =LEN(K12) -> 39
R13: =LEN(K13) -> 0
R14: =LEN(K14) -> 0
R15: =LEN(K15) -> 0
R16: =LEN(K16) -> 0

Sheet Full Data
B1: Bank Account | C1: Date | D1: Narrative | F1: Debit Amount | G1: Credit Amount | K1: Card Number | L1: Name
A2: =VLOOKUP(B2,$K$2:$L$29,2,FALSE) -> Baker | B2: 6547 | C2: 45862 | D2: BUNNINGS 329000 DELACOMBE AUS | E2: =LEFT(D2,15) -> BUNNINGS 329000 | F2: 98.96 | K2: 6547 | L2: Baker
A3: =VLOOKUP(B3,$K$2:$L$29,2,FALSE) -> Barclay | B3: 6341 | C3: 45884 | D3: WOOLWORTHS 3066 ALFREDTON AUS | E3: =LEFT(D3,15) -> WOOLWORTHS | F3: 216.27 | K3: 6341 | L3: Barclay
A4: =VLOOKUP(B4,$K$2:$L$29,2,FALSE) -> Barclay | B4: 6341 | C4: 45876 | D4: WOOLWORTHS 3066 ALFREDTON AUS | E4: =LEFT(D4,15) -> WOOLWORTHS | F4: 93.93 | K4: 4137 | L4: Bell
A5: =VLOOKUP(B5,$K$2:$L$29,2,FALSE) -> Barclay | B5: 6341 | C5: 45871 | D5: LINKT MELBOURNE MELBOURNE AUS | E5: =LEFT(D5,15) -> LINKT MELBOURNE | F5: 33.92 | K5: 7173 | L5: Brown
A6: =VLOOKUP(B6,$K$2:$L$29,2,FALSE) -> Barclay | B6: 6341 | C6: 45869 | D6: OFFICEWORKS 0364OFFICE BALLARAT AUS | E6: =LEFT(D6,15) -> OFFICEWORKS 036 | F6: 58 | K6: 4265 | L6: Conroy
A7: =VLOOKUP(B7,$K$2:$L$29,2,FALSE) -> Barclay | B7: 6341 | C7: 45868 | D7: J AND M CATERING SERVI WENDOUREE AUS | E7: =LEFT(D7,15) -> J AND M CATERIN | F7: 77.5 | K7: 7718 | L7: Delemontex
A8: =VLOOKUP(B8,$K$2:$L$29,2,FALSE) -> Barclay | B8: 6341 | C8: 45866 | D8: BUNNINGS 329000 DELACOMBE AUS | E8: =LEFT(D8,15) -> BUNNINGS 329000 | F8: 53.35 | K8: 2571 | L8: Donadio
A9: =VLOOKUP(B9,$K$2:$L$29,2,FALSE) -> Bell | B9: 4137 | C9: 45884 | D9: UBER *TRIP HELP.UBER.C 14518236738 AUS | E9: =LEFT(D9,15) -> UBER *TRIP HELP | F9: 33.67 | K9: 3601 | L9: DUva
A10: =VLOOKUP(B10,$K$2:$L$29,2,FALSE) -> Bell | B10: 4137 | C10: 45883 | D10: MCDONALDS WENDOUREE WENDOUREE AUS | E10: =LEFT(D10,15) -> MCDONALDS WENDO | F10: 9.7 | K10: 1694 | L10: Edmondston
A11: =VLOOKUP(B11,$K$2:$L$29,2,FALSE) -> Bell | B11: 4137 | C11: 45882 | D11: MCDONALDS WENDOUREE WENDOUREE AUS | E11: =LEFT(D11,15) -> MCDONALDS WENDO | F11: 9.7 | K11: 3540 | L11: Gort
A12: =VLOOKUP(B12,$K$2:$L$29,2,FALSE) -> Bell | B12: 4137 | C12: 45881 | D12: MCDONALDS WENDOUREE WENDOUREE AUS | E12: =LEFT(D12,15) -> MCDONALDS WENDO | F12: 15.8 | K12: 8338 | L12: Grigg
A13: =VLOOKUP(B13,$K$2:$L$29,2,FALSE) -> Bell | B13: 4137 | C13: 45881 | D13: North Star Hotel SOLDIERS HI AUS | E13: =LEFT(D13,15) -> North Star Hote | F13: 156.88 | K13: 7601 | L13: Hughes
... A29: =VLOOKUP(B29,$K$2:$L$29,2,FALSE) -> Bell | B29: 4137 | C29: 45874 | D29: PALACE HOTEL KALGOORL Kalgoorlie AUS | E29: =LEFT(D29,15) -> PALACE HOTEL KA | F29: 13.95 | K29: 4130 | L29: Wraith
A30: =VLOOKUP(B30,$K$2:$L$29,2,FALSE) -> Bell | B30: 4137 | C30: 45874 | D30: PALACE HOTEL KALGOORL Kalgoorlie AUS | E30: =LEFT(D30,15) -> PALACE HOTEL KA | F30: 51.16
A31: =VLOOKUP(B31,$K$2:$L$29,2,FALSE) -> Bell | B31: 4137 | C31: 45873 | D31: WIZ PHY KALGOORLIE KALGOORLIE AUS | E31: =LEFT(D31,15) -> WIZ PHY KALGOOR | F31: 8.99
A32: =VLOOKUP(B32,$K$2:$L$29,2,FALSE) -> Bell | B32: 4137 | C32: 45873 | D32: Exchange Hotel Kalgoorlie AUS | E32: =LEFT(D32,15) -> Exchange Hotel | F32: 211.63
A33: =VLOOKUP(B33,$K$2:$L$29,2,FALSE) -> Bell | B33: 4137 | C33: 45871 | D33: UBER *TRIP HELP.UBER.C 14518236738 AUS | E33: =LEFT(D33,15) -> UBER *TRIP HELP | F33: 44.11
A34: =VLOOKUP(B34,$K$2:$L$29,2,FALSE) -> Bell | B34: 4137 | C34: 45871 | D34: UBER *TRIP HELP.UBER.C 14518236738 AUS | E34: =LEFT(D34,15) -> UBER *TRIP HELP | F34: 35.98
A35: =VLOOKUP(B35,$K$2:$L$29,2,FALSE) -> Bell | B35: 4137 | C35: 45870 | D35: UBER* TRIP SYDNEY AUS | E35: =LEFT(D35,15) -> UBER* TRIP SYDN | F35: 9.38
A36: =VLOOKUP(B36,$K$2:$L$29,2,FALSE) -> Bell | B36: 4137 | C36: 45869 | D36: Kwik Kopy Canning Vale Canning Val AUS | E36: =LEFT(D36,15) -> Kwik Kopy Canni | F36: 165.33
A37: =VLOOKUP(B37,$K$2:$L$29,2,FALSE) -> Bell | B37: 4137 | C37: 45869 | D37: CHILDRENS MEDICAL RESE WESTMEAD AUS | E37: =LEFT(D37,15) -> CHILDRENS MEDIC | F37: 27.81
A38: =VLOOKUP(B38,$K$2:$L$29,2,FALSE) -> Bell | B38: 4137 | C38: 45869 | D38: UBER *TRIP HELP.UBER.C 14518236738 AUS | E38: =LEFT(D38,15) -> UBER *TRIP HELP | F38: 8.94
A39: =VLOOKUP(B39,$K$2:$L$29,2,FALSE) -> Bell | B39: 4137 | C39: 45869 | D39: LENA'S BAR Perth AUS | E39: =LEFT(D39,15) -> LENA'S BAR Pert | F39: 64.96
A40: =VLOOKUP(B40,$K$2:$L$29,2,FALSE) -> Bell | B40: 4137 | C40: 45868 | D40: UBER *TRIP HELP.UBER.C 14518236738 AUS | E40: =LEFT(D40,15) -> UBER *TRIP HELP | F40: 9.09
A41: =VLOOKUP(B41,$K$2:$L$29,2,FALSE) -> Bell | B41: 4137 | C41: 45867 | D41: UBER *TRIP HELP.UBER.C 14518236738 AUS | E41: =LEFT(D41,15) -> UBER *TRIP HELP | F41: 8.94
... A60: =VLOOKUP(B60,$K$2:$L$29,2,FALSE) -> Brown | B60: 7173 | C60: 45874 | D60: AWM WENDOUREE WENDOUREE AUS | E60: =LEFT(D60,15) -> AWM WENDOUREE W | F60: 184.67
A61: =VLOOKUP(B61,$K$2:$L$29,2,FALSE) -> Brown | B61: 7173 | C61: 45874 | D61: CRED VOUCHER AWM WENDOUREE WENDOUREE AUS | E61: =LEFT(D61,15) -> CRED VOUCHER AW | G61: 71.98
A62: =VLOOKUP(B62,$K$2:$L$29,2,FALSE) -> Brown | B62: 7173 | C62: 45874 | D62: L&H WENDOUREE WENDOUREE AUS | E62: =LEFT(D62,15) -> L&H WENDOUREE W | F62: 241.66
A63: =VLOOKUP(B63,$K$2:$L$29,2,FALSE) -> Brown | B63: 7173 | C63: 45869 | D63: Ballarat Materials Ha MITCHELL PA AUS | E63: =LEFT(D63,15) -> Ballarat Materi | F63: 250.97
A64: =VLOOKUP(B64,$K$2:$L$29,2,FALSE) -> Brown | B64: 7173 | C64: 45868 | D64: AVENUTUM BALLARAT BALLARAT AUS | E64: =LEFT(D64,15) -> AVENUTUM BALLAR | F64: 486.57
A65: =VLOOKUP(B65,$K$2:$L$29,2,FALSE) -> Brown | B65: 7173 | C65: 45868 | D65: UNITED BALLARAT EURE WENDOUREE AUS | E65: =LEFT(D65,15) -> UNITED BALLARAT | F65: 118.34
A66: =VLOOKUP(B66,$K$2:$L$29,2,FALSE) -> Brown | B66: 7173 | C66: 45866 | D66: Ballarat Bolts & Fast DELACOMBE AUS | E66: =LEFT(D66,15) -> Ballarat Bolts | F66: 4.06
A67: =VLOOKUP(B67,$K$2:$L$29,2,FALSE) -> Brown | B67: 7173 | C67: 45863 | D67: BUNNINGS 329000 DELACOMBE AUS | E67: =LEFT(D67,15) -> BUNNINGS 329000 | F67: 33
A68: =VLOOKUP(B68,$K$2:$L$29,2,FALSE) -> Brown | B68: 7173 | C68: 45860 | D68: STERIDIUM PTY LTD CLEAR ISLAN AUS | E68: =LEFT(D68,15) -> STERIDIUM PTY L | F68: 483.87
A69: =VLOOKUP(B69,$K$2:$L$29,2,FALSE) -> Brown | B69: 7173 | C69: 45859 | D69: BUNNINGS 329000 DELACOMBE AUS | E69: =LEFT(D69,15) -> BUNNINGS 329000 | F69: 59.45
A70: =VLOOKUP(B70,$K$2:$L$29,2,FALSE) -> Brown | B70: 7173 | C70: 45859 | D70: UNITED BALLARAT EURE WENDOUREE AUS | E70: =LEFT(D70,15) -> UNITED BALLARAT | F70: 118.45
A71: =VLOOKUP(B71,$K$2:$L$29,2,FALSE) -> Brown | B71: 7173 | C71: 45856 | D71: L&H WENDOUREE WENDOUREE AUS | E71: =LEFT(D71,15) -> L&H WENDOUREE W | F71: 73.61
A72: =VLOOKUP(B72,$K$2:$L$29,2,FALSE) -> Brown | B72: 7173 | C72: 45855 | D72: COLES 0628COLES 0628 BALLARAT AUS | E72: =LEFT(D72,15) -> COLES 0628COLES | F72: 12
A73: =VLOOKUP(B73,$K$2:$L$29,2,FALSE) -> Brown | B73: 7173 | C73: 45854 | D73: BUNNINGS 329000 DELACOMBE AUS | E73: =LEFT(D73,15) -> BUNNINGS 329000 | F73: 21.99
... A301: =VLOOKUP(B301,$K$2:$L$29,2,FALSE) -> VanKollenburg | B301: 9991 | C301: 45855 | D301: POST BALLARAT WEST LPO BALLARAT AUS | E301: =LEFT(D301,15) -> POST BALLARAT W | F301: 98.64
A302: =VLOOKUP(B302,$K$2:$L$29,2,FALSE) -> VanKollenburg | B302: 9991 | C302: 45855 | D302: CRED VOUCHER SPIRIT OF TASMANIA DEVONPORT AUS | E302: =LEFT(D302,15) -> CRED VOUCHER SP | G302: 316
A303: =VLOOKUP(B303,$K$2:$L$29,2,FALSE) -> VanKollenburg | B303: 9991 | C303: 45854 | D303: SPIRIT OF TASMANIA DEVONPORT AUS | E303: =LEFT(D303,15) -> SPIRIT OF TASMA | F303: 1227.47
A304: =VLOOKUP(B304,$K$2:$L$29,2,FALSE) -> Zhang | B304: 6594 | C304: 45883 | D304: SQ *LILY DANG Ballarat Ce AUS | E304: =LEFT(D304,15) -> SQ *LILY DANG B | F304: 37.4
A305: =VLOOKUP(B305,$K$2:$L$29,2,FALSE) -> Zhang | B305: 6594 | C305: 45879 | D305: Watermark Mascot AUS | E305: =LEFT(D305,15) -> Watermark Masco | F305: 18.71
A306: =VLOOKUP(B306,$K$2:$L$29,2,FALSE) -> Zhang | B306: 6594 | C306: 45867 | D306: SYD APRT EPARK ONL28 SYDNEY INTE AUS | E306: =LEFT(D306,15) -> SYD APRT EPARK | F306: 169.51
A307: =VLOOKUP(B307,$K$2:$L$29,2,FALSE) -> Zhang | B307: 6594 | C307: 45867 | D307: Airport Shuttle Bus BAKERY HILL AUS | E307: =LEFT(D307,15) -> Airport Shuttle | F307: 90
E308: =LEFT(D308,15)

Sheet Pronto layout
A1: Format for copy & paste of invoice
A3: Account | B3: Reference | C3: Tax | D3: Amount | E3: Tax CODE | F3: TAX Amount (leave blank) | G3: CBS
A4: 1051.CONS | B4: credit card import test | C4: I | D4: 900 | E4: T | G4: 1.3 | H4: CBS - needs to be pasted seperately
A5: 1084.PHON | B5: credit card import test | C5: I | D5: 450 | E5: F
A6: 110849995900 | B6: credit card import test | C6: I | D6: 600 | E6: T
A7: 199999991140 | B7: credit card import test | C7: I | D7: 50 | E7: F
A38: To find your job number & cost code category
A40: Log in to Pronto
A41: Select Reporting Portal
A42: Select Gekko Reporting
A43: Select GEK_Credit Card Code Lookup
A44: Find the relevant project code
A45: Select OK at the bottom of the screen
A46: Enter the Project number & the Cost Category into the relevant cells.
A47: If you cannot find the information you are after then leave it blank & let me know.
